Workbook

Sheet Cockpit
A1: IT | B1: IT Process Portfolio – Cockpit
B2: Datenstand Draft April 2026 · Quelle: Process_Portfolio_Timeline.xlsx · Mappe erzeugt am 01.09.2026
B3: Auswahlfelder ändern – Kennzahlen, Diagramme und Liste rechnen sofort neu.
B5: PROZESSGRUPPE | C5: INITIATIVE | D5: L1-PROZESS | E5: EBENE | F5: STATUS | G5: PROCESS MANAGER | H5: STICHTAG
B6: (Alle) | C6: (Alle) | D6: (Alle) | E6: (Alle) | F6: (Alle) | G6: (Alle) | H6: 46266
B8: PROZESSE IM FILTER | C8: Ø FORTSCHRITT | D8: VERZÖGERT | E8: ÜBERFÄLLIG | F8: ELABORATION FERTIG | G8: IN IMPLEMENTIERUNG | H8: TERMINE IN 90 TAGEN
B9: =SUM(Prozesse!$S$2:$S$125) -> 124 | C9: =IFERROR(SUMPRODUCT(Prozesse!$S$2:$S$125,Prozesse!$I$2:$I$125)/SUM(Prozesse!$S$2:$S$125),0) -> 0.40395161 | D9: =SUMPRODUCT(Prozesse!$S$2:$S$125,--(Prozesse!$H$2:$H$125="Verzögert")) -> 29 | E9: =SUMPRODUCT(Prozesse!$S$2:$S$125,Prozesse!$Q$2:$Q$125) -> 52 | F9: =SUMPRODUCT(Prozesse!$S$2:$S$125,--(Prozesse!$M$2:$M$125="Abgeschlossen")) -> 30 | G9: =SUMPRODUCT(Prozesse!$S$2:$S$125,Prozesse!$R$2:$R$125) -> 20 | H9: =SUMPRODUCT(Phasen!$I$2:$I$497,--(Phasen!$G$2:$G$497>=$H$6),--(Phasen!$G$2:$G$497<=$H$6+90)) -> 8
B58: PROZESSE IM FILTER – VERZÖGERTE ZUERST, ERSTE 15
B59: Prozess | C59: Gruppe | D59: Status | E59: % fertig | F59: Ende | G59: Process Manager
B60: =IFERROR(INDEX(Prozesse!$B$2:$B$125,MATCH(1,Prozesse!$T$2:$T$125,0)),"") -> Analyse architecture impact | C60: =IFERROR(INDEX(Prozesse!$D$2:$D$125,MATCH(1,Prozesse!$T$2:$T$125,0)),"") -> CP | D60: =IFERROR(INDEX(Prozesse!$H$2:$H$125,MATCH(1,Prozesse!$T$2:$T$125,0)),"") -> Verzögert | E60: =IFERROR(INDEX(Prozesse!$I$2:$I$125,MATCH(1,Prozesse!$T$2:$T$125,0)),"") -> 1 | F60: =IFERROR(INDEX(Prozesse!$K$2:$K$125,MATCH(1,Prozesse!$T$2:$T$125,0)),"") -> 46142 | G60: =IFERROR(INDEX(Prozesse!$O$2:$O$125,MATCH(1,Prozesse!$T$2:$T$125,0)),"") -> Mielenz Thomas (LMT)
B61: =IFERROR(INDEX(Prozesse!$B$2:$B$125,MATCH(2,Prozesse!$T$2:$T$125,0)),"") -> Approve IT demand | C61: =IFERROR(INDEX(Prozesse!$D$2:$D$125,MATCH(2,Prozesse!$T$2:$T$125,0)),"") -> CP | D61: =IFERROR(INDEX(Prozesse!$H$2:$H$125,MATCH(2,Prozesse!$T$2:$T$125,0)),"") -> Verzögert | E61: =IFERROR(INDEX(Prozesse!$I$2:$I$125,MATCH(2,Prozesse!$T$2:$T$125,0)),"") -> 1 | F61: =IFERROR(INDEX(Prozesse!$K$2:$K$125,MATCH(2,Prozesse!$T$2:$T$125,0)),"") -> 46112 | G61: =IFERROR(INDEX(Prozesse!$O$2:$O$125,MATCH(2,Prozesse!$T$2:$T$125,0)),"") -> Mielenz Thomas (LMT)
B62: =IFERROR(INDEX(Prozesse!$B$2:$B$125,MATCH(3,Prozesse!$T$2:$T$125,0)),"") -> Attract and hire employees | C62: =IFERROR(INDEX(Prozesse!$D$2:$D$125,MATCH(3,Prozesse!$T$2:$T$125,0)),"") -> SP | D62: =IFERROR(INDEX(Prozesse!$H$2:$H$125,MATCH(3,Prozesse!$T$2:$T$125,0)),"") -> Verzögert | E62: =IFERROR(INDEX(Prozesse!$I$2:$I$125,MATCH(3,Prozesse!$T$2:$T$125,0)),"") -> 0.18 | F62: =IFERROR(INDEX(Prozesse!$K$2:$K$125,MATCH(3,Prozesse!$T$2:$T$125,0)),"") -> 46387 | G62: =IFERROR(INDEX(Prozesse!$O$2:$O$125,MATCH(3,Prozesse!$T$2:$T$125,0)),"") -> Mielenz Thomas (LMT)
B63: =IFERROR(INDEX(Prozesse!$B$2:$B$125,MATCH(4,Prozesse!$T$2:$T$125,0)),"") -> Define solution target architecture | C63: =IFERROR(INDEX(Prozesse!$D$2:$D$125,MATCH(4,Prozesse!$T$2:$T$125,0)),"") -> CP | D63: =IFERROR(INDEX(Prozesse!$H$2:$H$125,MATCH(4,Prozesse!$T$2:$T$125,0)),"") -> Verzögert | E63: =IFERROR(INDEX(Prozesse!$I$2:$I$125,MATCH(4,Prozesse!$T$2:$T$125,0)),"") -> 0.5 | F63: =IFERROR(INDEX(Prozesse!$K$2:$K$125,MATCH(4,Prozesse!$T$2:$T$125,0)),"") -> 46195 | G63: =IFERROR(INDEX(Prozesse!$O$2:$O$125,MATCH(4,Prozesse!$T$2:$T$125,0)),"") -> Nussbaumer Florian (LBC)
B64: =IFERROR(INDEX(Prozesse!$B$2:$B$125,MATCH(5,Prozesse!$T$2:$T$125,0)),"") -> Ensure performance and conformance of IT services | C64: =IFERROR(INDEX(Prozesse!$D$2:$D$125,MATCH(5,Prozesse!$T$2:$T$125,0)),"") -> SP | D64: =IFERROR(INDEX(Prozesse!$H$2:$H$125,MATCH(5,Prozesse!$T$2:$T$125,0)),"") -> Verzögert | E64: =IFERROR(INDEX(Prozesse!$I$2:$I$125,MATCH(5,Prozesse!$T$2:$T$125,0)),"") -> 0 | F64: =IFERROR(INDEX(Prozesse!$K$2:$K$125,MATCH(5,Prozesse!$T$2:$T$125,0)),"") -> 0 | G64: =IFERROR(INDEX(Prozesse!$O$2:$O$125,MATCH(5,Prozesse!$T$2:$T$125,0)),"") -> Sint Rachel (LBH)
B65: =IFERROR(INDEX(Prozesse!$B$2:$B$125,MATCH(6,Prozesse!$T$2:$T$125,0)),"") -> Evaluate and qualify IT demand | C65: =IFERROR(INDEX(Prozesse!$D$2:$D$125,MATCH(6,Prozesse!$T$2:$T$125,0)),"") -> CP | D65: =IFERROR(INDEX(Prozesse!$H$2:$H$125,MATCH(6,Prozesse!$T$2:$T$125,0)),"") -> Verzögert | E65: =IFERROR(INDEX(Prozesse!$I$2:$I$125,MATCH(6,Prozesse!$T$2:$T$125,0)),"") -> 1 | F65: =IFERROR(INDEX(Prozesse!$K$2:$K$125,MATCH(6,Prozesse!$T$2:$T$125,0)),"") -> 46142 | G65: =IFERROR(INDEX(Prozesse!$O$2:$O$125,MATCH(6,Prozesse!$T$2:$T$125,0)),"") -> Mielenz Thomas (LMT)
B66: =IFERROR(INDEX(Prozesse!$B$2:$B$125,MATCH(7,Prozesse!$T$2:$T$125,0)),"") -> Handle IT service order | C66: =IFERROR(INDEX(Prozesse!$D$2:$D$125,MATCH(7,Prozesse!$T$2:$T$125,0)),"") -> CP | D66: =IFERROR(INDEX(Prozesse!$H$2:$H$125,MATCH(7,Prozesse!$T$2:$T$125,0)),"") -> Verzögert | E66: =IFERROR(INDEX(Prozesse!$I$2:$I$125,MATCH(7,Prozesse!$T$2:$T$125,0)),"") -> 0 | F66: =IFERROR(INDEX(Prozesse!$K$2:$K$125,MATCH(7,Prozesse!$T$2:$T$125,0)),"") -> 46190 | G66: =IFERROR(INDEX(Prozesse!$O$2:$O$125,MATCH(7,Prozesse!$T$2:$T$125,0)),"") -> Schnurrenberger Christoph (LIS-LIN)
B67: =IFERROR(INDEX(Prozesse!$B$2:$B$125,MATCH(8,Prozesse!$T$2:$T$125,0)),"") -> Implement and maintain IT job architecture | C67: =IFERROR(INDEX(Prozesse!$D$2:$D$125,MATCH(8,Prozesse!$T$2:$T$125,0)),"") -> SP | D67: =IFERROR(INDEX(Prozesse!$H$2:$H$125,MATCH(8,Prozesse!$T$2:$T$125,0)),"") -> Verzögert | E67: =IFERROR(INDEX(Prozesse!$I$2:$I$125,MATCH(8,Prozesse!$T$2:$T$125,0)),"") -> 0 | F67: =IFERROR(INDEX(Prozesse!$K$2:$K$125,MATCH(8,Prozesse!$T$2:$T$125,0)),"") -> 46173 | G67: =IFERROR(INDEX(Prozesse!$O$2:$O$125,MATCH(8,Prozesse!$T$2:$T$125,0)),"") -> Rollinger Alexander (LIS)
B68: =IFERROR(INDEX(Prozesse!$B$2:$B$125,MATCH(9,Prozesse!$T$2:$T$125,0)),"") -> Maintain IT glossary | C68: =IFERROR(INDEX(Prozesse!$D$2:$D$125,MATCH(9,Prozesse!$T$2:$T$125,0)),"") -> MP | D68: =IFERROR(INDEX(Prozesse!$H$2:$H$125,MATCH(9,Prozesse!$T$2:$T$125,0)),"") -> Verzögert | E68: =IFERROR(INDEX(Prozesse!$I$2:$I$125,MATCH(9,Prozesse!$T$2:$T$125,0)),"") -> 0.25 | F68: =IFERROR(INDEX(Prozesse!$K$2:$K$125,MATCH(9,Prozesse!$T$2:$T$125,0)),"") -> 46039 | G68: =IFERROR(INDEX(Prozesse!$O$2:$O$125,MATCH(9,Prozesse!$T$2:$T$125,0)),"") -> Mielenz Thomas (LMT)
B69: =IFERROR(INDEX(Prozesse!$B$2:$B$125,MATCH(10,Prozesse!$T$2:$T$125,0)),"") -> Manage HR4IT service demand | C69: =IFERROR(INDEX(Prozesse!$D$2:$D$125,MATCH(10,Prozesse!$T$2:$T$125,0)),"") -> SP | D69: =IFERROR(INDEX(Prozesse!$H$2:$H$125,MATCH(10,Prozesse!$T$2:$T$125,0)),"") -> Verzögert | E69: =IFERROR(INDEX(Prozesse!$I$2:$I$125,MATCH(10,Prozesse!$T$2:$T$125,0)),"") -> 0 | F69: =IFERROR(INDEX(Prozesse!$K$2:$K$125,MATCH(10,Prozesse!$T$2:$T$125,0)),"") -> 46203 | G69: =IFERROR(INDEX(Prozesse!$O$2:$O$125,MATCH(10,Prozesse!$T$2:$T$125,0)),"") -> Rollinger Alexander (LIS)
B70: =IFERROR(INDEX(Prozesse!$B$2:$B$125,MATCH(11,Prozesse!$T$2:$T$125,0)),"") -> Manage IT global orientation programme incl. job shadowing | C70: =IFERROR(INDEX(Prozesse!$D$2:$D$125,MATCH(11,Prozesse!$T$2:$T$125,0)),"") -> SP | D70: =IFERROR(INDEX(Prozesse!$H$2:$H$125,MATCH(11,Prozesse!$T$2:$T$125,0)),"") -> Verzögert | E70: =IFERROR(INDEX(Prozesse!$I$2:$I$125,MATCH(11,Prozesse!$T$2:$T$125,0)),"") -> 0 | F70: =IFERROR(INDEX(Prozesse!$K$2:$K$125,MATCH(11,Prozesse!$T$2:$T$125,0)),"") -> 46204 | G70: =IFERROR(INDEX(Prozesse!$O$2:$O$125,MATCH(11,Prozesse!$T$2:$T$125,0)),"") -> Mielenz Thomas (LMT)
B71: =IFERROR(INDEX(Prozesse!$B$2:$B$125,MATCH(12,Prozesse!$T$2:$T$125,0)),"") -> Manage IT knowledge | C71: =IFERROR(INDEX(Prozesse!$D$2:$D$125,MATCH(12,Prozesse!$T$2:$T$125,0)),"") -> SP | D71: =IFERROR(INDEX(Prozesse!$H$2:$H$125,MATCH(12,Prozesse!$T$2:$T$125,0)),"") -> Verzögert | E71: =IFERROR(INDEX(Prozesse!$I$2:$I$125,MATCH(12,Prozesse!$T$2:$T$125,0)),"") -> 1 | F71: =IFERROR(INDEX(Prozesse!$K$2:$K$125,MATCH(12,Prozesse!$T$2:$T$125,0)),"") -> 46203 | G71: =IFERROR(INDEX(Prozesse!$O$2:$O$125,MATCH(12,Prozesse!$T$2:$T$125,0)),"") -> Sint Rachel (LBH)
B72: =IFERROR(INDEX(Prozesse!$B$2:$B$125,MATCH(13,Prozesse!$T$2:$T$125,0)),"") -> Manage IT project portfolio | C72: =IFERROR(INDEX(Prozesse!$D$2:$D$125,MATCH(13,Prozesse!$T$2:$T$125,0)),"") -> MP | D72: =IFERROR(INDEX(Prozesse!$H$2:$H$125,MATCH(13,Prozesse!$T$2:$T$125,0)),"") -> Verzögert | E72: =IFERROR(INDEX(Prozesse!$I$2:$I$125,MATCH(13,Prozesse!$T$2:$T$125,0)),"") -> 1 | F72: =IFERROR(INDEX(Prozesse!$K$2:$K$125,MATCH(13,Prozesse!$T$2:$T$125,0)),"") -> 46173 | G72: =IFERROR(INDEX(Prozesse!$O$2:$O$125,MATCH(13,Prozesse!$T$2:$T$125,0)),"") -> Rollinger Alexander (LIS)
B73: =IFERROR(INDEX(Prozesse!$B$2:$B$125,MATCH(14,Prozesse!$T$2:$T$125,0)),"") -> Manage IT service provision request | C73: =IFERROR(INDEX(Prozesse!$D$2:$D$125,MATCH(14,Prozesse!$T$2:$T$125,0)),"") -> CP | D73: =IFERROR(INDEX(Prozesse!$H$2:$H$125,MATCH(14,Prozesse!$T$2:$T$125,0)),"") -> Verzögert | E73: =IFERROR(INDEX(Prozesse!$I$2:$I$125,MATCH(14,Prozesse!$T$2:$T$125,0)),"") -> 0 | F73: =IFERROR(INDEX(Prozesse!$K$2:$K$125,MATCH(14,Prozesse!$T$2:$T$125,0)),"") -> 46190 | G73: =IFERROR(INDEX(Prozesse!$O$2:$O$125,MATCH(14,Prozesse!$T$2:$T$125,0)),"") -> Schnurrenberger Christoph (LIS-LIN)
B74: =IFERROR(INDEX(Prozesse!$B$2:$B$125,MATCH(15,Prozesse!$T$2:$T$125,0)),"") -> Manage IT skills | C74: =IFERROR(INDEX(Prozesse!$D$2:$D$125,MATCH(15,Prozesse!$T$2:$T$125,0)),"") -> SP | D74: =IFERROR(INDEX(Prozesse!$H$2:$H$125,MATCH(15,Prozesse!$T$2:$T$125,0)),"") -> Verzögert | E74: =IFERROR(INDEX(Prozesse!$I$2:$I$125,MATCH(15,Prozesse!$T$2:$T$125,0)),"") -> 0 | F74: =IFERROR(INDEX(Prozesse!$K$2:$K$125,MATCH(15,Prozesse!$T$2:$T$125,0)),"") -> 46568 | G74: =IFERROR(INDEX(Prozesse!$O$2:$O$125,MATCH(15,Prozesse!$T$2:$T$125,0)),"") -> Mielenz Thomas (LMT)

Sheet Prozesse
A1: Nr | B1: Prozess | C1: Pfad | D1: Gruppe | E1: Initiative | F1: L1-Prozess | G1: Ebene | H1: Status | I1: Fortschritt | J1: Start | K1: Ende | L1: Dauer (T) | M1: Elaboration | N1: Initiative Lead | O1: Process Manager | P1: Consultant | Q1: Überfällig | R1: In Implementierung | S1: Treffer | T1: Rang
A2: 1 | B2: Analyse architecture impact | C2: Plan IT service › Evaluate and qualify IT demand › Analyse architecture impact | D2: CP | E2: Corporate IT body | F2: Plan IT service | G2: L3 | H2: Verzögert | I2: 1 | J2: 45870 | K2: 46142 | L2: 195 | M2: Abgeschlossen | N2: Pernet Benoit (LEC)) | O2: Mielenz Thomas (LMT) | P2: Kunz Christina (LIS-MHP) | Q2: =IF(AND(K2<>"",K2<Cockpit!$H$6,H2<>"Abgeschlossen"),1,0) -> 1 | R2: 1 | S2: =IF(AND(OR(Cockpit!$B$6="(Alle)",D2=Cockpit!$B$6),OR(Cockpit!$C$6="(Alle)",E2=Cockpit!$C$6),OR(Cockpit!$D$6="(Alle)",F2=Cockpit!$D$6),OR(Cockpit!$E$6="(Alle)",G2=Cockpit!$E$6),OR(Cockpit!$F$6="(Alle)",H2=Cockpit!$F$6),OR(Cockpit!$G$6="(Alle)",O2=Cockpit!$G$6)),1,0) -> 1 | T2: =IF(S2=1,SUM($S$2:S2),"") -> 1
A3: 2 | B3: Approve IT demand | C3: Plan IT service › Approve IT demand | D3: CP | E3: Corporate IT body | F3: Plan IT service | G3: L2 | H3: Verzögert | I3: 1 | J3: 45870 | K3: 46112 | L3: 1 | M3: Abgeschlossen | N3: Spieth Tina (LIS) | O3: Mielenz Thomas (LMT) | P3: Kunz Christina (LIS-MHP) | Q3: =IF(AND(K3<>"",K3<Cockpit!$H$6,H3<>"Abgeschlossen"),1,0) -> 1 | R3: 1 | S3: =IF(AND(OR(Cockpit!$B$6="(Alle)",D3=Cockpit!$B$6),OR(Cockpit!$C$6="(Alle)",E3=Cockpit!$C$6),OR(Cockpit!$D$6="(Alle)",F3=Cockpit!$D$6),OR(Cockpit!$E$6="(Alle)",G3=Cockpit!$E$6),OR(Cockpit!$F$6="(Alle)",H3=Cockpit!$F$6),OR(Cockpit!$G$6="(Alle)",O3=Cockpit!$G$6)),1,0) -> 1 | T3: =IF(S3=1,SUM($S$2:S3),"") -> 2
A4: 3 | B4: Attract and hire employees | C4: Provide and develop IT workforce › Attract and hire employees | D4: SP | E4: HR initiatives for IT | F4: Provide and develop IT workforce | G4: L2 | H4: Verzögert | I4: 0.18 | J4: 45931 | K4: 46387 | L4: 327 | M4: In Arbeit | N4: Kiesewetter Ivana (LIS) | O4: Mielenz Thomas (LMT) | P4: Chen Leilei (LIS-BPMO), Hynek Tobias (LIS) | Q4: =IF(AND(K4<>"",K4<Cockpit!$H$6,H4<>"Abgeschlossen"),1,0) -> 0 | R4: 0 | S4: =IF(AND(OR(Cockpit!$B$6="(Alle)",D4=Cockpit!$B$6),OR(Cockpit!$C$6="(Alle)",E4=Cockpit!$C$6),OR(Cockpit!$D$6="(Alle)",F4=Cockpit!$D$6),OR(Cockpit!$E$6="(Alle)",G4=Cockpit!$E$6),OR(Cockpit!$F$6="(Alle)",H4=Cockpit!$F$6),OR(Cockpit!$G$6="(Alle)",O4=Cockpit!$G$6)),1,0) -> 1 | T4: =IF(S4=1,SUM($S$2:S4),"") -> 3
A5: 4 | B5: Define solution target architecture | C5: Build IT Service › Design IT service › Define solution target architecture | D5: CP | E5: Architecture management | F5: Build IT Service | G5: L3 | H5: Verzögert | I5: 0.5 | J5: 46036 | K5: 46195 | L5: 114 | M5: In Arbeit | N5: Hammer Marco (AER) | O5: Nussbaumer Florian (LBC) | P5: Hoermann Patrick (LLI) | Q5: =IF(AND(K5<>"",K5<Cockpit!$H$6,H5<>"Abgeschlossen"),1,0) -> 1 | R5: 0 | S5: =IF(AND(OR(Cockpit!$B$6="(Alle)",D5=Cockpit!$B$6),OR(Cockpit!$C$6="(Alle)",E5=Cockpit!$C$6),OR(Cockpit!$D$6="(Alle)",F5=Cockpit!$D$6),OR(Cockpit!$E$6="(Alle)",G5=Cockpit!$E$6),OR(Cockpit!$F$6="(Alle)",H5=Cockpit!$F$6),OR(Cockpit!$G$6="(Alle)",O5=Cockpit!$G$6)),1,0) -> 1 | T5: =IF(S5=1,SUM($S$2:S5),"") -> 4
A6: 5 | B6: Ensure performance and conformance of IT services | C6: Ensure performance and conformance of IT services | D6: SP | E6: ITSM | F6: Ensure performance and conformance of IT services | G6: L1 | H6: Verzögert | I6: 0 | M6: Verzögert | N6: – | O6: Sint Rachel (LBH) | P6: Schroeder Michael (LIS) | Q6: =IF(AND(K6<>"",K6<Cockpit!$H$6,H6<>"Abgeschlossen"),1,0) -> 0 | R6: 0 | S6: =IF(AND(OR(Cockpit!$B$6="(Alle)",D6=Cockpit!$B$6),OR(Cockpit!$C$6="(Alle)",E6=Cockpit!$C$6),OR(Cockpit!$D$6="(Alle)",F6=Cockpit!$D$6),OR(Cockpit!$E$6="(Alle)",G6=Cockpit!$E$6),OR(Cockpit!$F$6="(Alle)",H6=Cockpit!$F$6),OR(Cockpit!$G$6="(Alle)",O6=Cockpit!$G$6)),1,0) -> 1 | T6: =IF(S6=1,SUM($S$2:S6),"") -> 5
A7: 6 | B7: Evaluate and qualify IT demand | C7: Plan IT service › Evaluate and qualify IT demand | D7: CP | E7: Corporate IT body | F7: Plan IT service | G7: L2 | H7: Verzögert | I7: 1 | J7: 45870 | K7: 46142 | L7: 195 | M7: Abgeschlossen | N7: Spieth Tina (LIS) | O7: Mielenz Thomas (LMT) | P7: Kunz Christina (LIS-MHP) | Q7: =IF(AND(K7<>"",K7<Cockpit!$H$6,H7<>"Abgeschlossen"),1,0) -> 1 | R7: 1 | S7: =IF(AND(OR(Cockpit!$B$6="(Alle)",D7=Cockpit!$B$6),OR(Cockpit!$C$6="(Alle)",E7=Cockpit!$C$6),OR(Cockpit!$D$6="(Alle)",F7=Cockpit!$D$6),OR(Cockpit!$E$6="(Alle)",G7=Cockpit!$E$6),OR(Cockpit!$F$6="(Alle)",H7=Cockpit!$F$6),OR(Cockpit!$G$6="(Alle)",O7=Cockpit!$G$6)),1,0) -> 1 | T7: =IF(S7=1,SUM($S$2:S7),"") -> 6
A8: 7 | B8: Handle IT service order | C8: Deliver IT service › Handle IT service order | D8: CP | E8: ITSM | F8: Deliver IT service | G8: L2 | H8: Verzögert | I8: 0 | J8: 46113 | K8: 46190 | L8: 56 | M8: Verzögert | N8: – | O8: Schnurrenberger Christoph (LIS-LIN) | P8: – | Q8: =IF(AND(K8<>"",K8<Cockpit!$H$6,H8<>"Abgeschlossen"),1,0) -> 1 | R8: 0 | S8: =IF(AND(OR(Cockpit!$B$6="(Alle)",D8=Cockpit!$B$6),OR(Cockpit!$C$6="(Alle)",E8=Cockpit!$C$6),OR(Cockpit!$D$6="(Alle)",F8=Cockpit!$D$6),OR(Cockpit!$E$6="(Alle)",G8=Cockpit!$E$6),OR(Cockpit!$F$6="(Alle)",H8=Cockpit!$F$6),OR(Cockpit!$G$6="(Alle)",O8=Cockpit!$G$6)),1,0) -> 1 | T8: =IF(S8=1,SUM($S$2:S8),"") -> 7
A9: 8 | B9: Implement and maintain IT job architecture | C9: Provide and develop IT workforce › Manage HR4IT strategy, governane and framework › Implement and maintain IT job architecture | D9: SP | E9: HR initiatives for IT | F9: Provide and develop IT workforce | G9: L3 | H9: Verzögert | I9: 0 | J9: 45946 | K9: 46173 | L9: 162 | M9: Verzögert | N9: Amelang Nicole (LIS) | O9: Rollinger Alexander (LIS) | P9: Chen Leilei (LIS-BPMO), Hynek Tobias (LIS) | Q9: =IF(AND(K9<>"",K9<Cockpit!$H$6,H9<>"Abgeschlossen"),1,0) -> 1 | R9: 0 | S9: =IF(AND(OR(Cockpit!$B$6="(Alle)",D9=Cockpit!$B$6),OR(Cockpit!$C$6="(Alle)",E9=Cockpit!$C$6),OR(Cockpit!$D$6="(Alle)",F9=Cockpit!$D$6),OR(Cockpit!$E$6="(Alle)",G9=Cockpit!$E$6),OR(Cockpit!$F$6="(Alle)",H9=Cockpit!$F$6),OR(Cockpit!$G$6="(Alle)",O9=Cockpit!$G$6)),1,0) -> 1 | T9: =IF(S9=1,SUM($S$2:S9),"") -> 8
A10: 9 | B10: Maintain IT glossary | C10: Manage IT governance framework › Maintain IT glossary | D10: MP | E10: Corporate IT body | F10: Manage IT governance framework | G10: L2 | H10: Verzögert | I10: 0.25 | J10: 46029 | K10: 46039 | L10: 8 | M10: Ohne Angabe | N10: Felder Max (LLI) | O10: Mielenz Thomas (LMT) | P10: Kunz Christina (LIS-MHP) | Q10: =IF(AND(K10<>"",K10<Cockpit!$H$6,H10<>"Abgeschlossen"),1,0) -> 1 | R10: 0 | S10: =IF(AND(OR(Cockpit!$B$6="(Alle)",D10=Cockpit!$B$6),OR(Cockpit!$C$6="(Alle)",E10=Cockpit!$C$6),OR(Cockpit!$D$6="(Alle)",F10=Cockpit!$D$6),OR(Cockpit!$E$6="(Alle)",G10=Cockpit!$E$6),OR(Cockpit!$F$6="(Alle)",H10=Cockpit!$F$6),OR(Cockpit!$G$6="(Alle)",O10=Cockpit!$G$6)),1,0) -> 1 | T10: =IF(S10=1,SUM($S$2:S10),"") -> 9
A11: 10 | B11: Manage HR4IT service demand | C11: Provide and develop IT workforce › Manage HR4IT strategy, governane and framework › Manage HR4IT service demand | D11: SP | E11: HR initiatives for IT | F11: Provide and develop IT workforce | G11: L3 | H11: Verzögert | I11: 0 | J11: 45931 | K11: 46203 | L11: 195 | M11: Verzögert | N11: Amelang Nicole (LIS) | O11: Rollinger Alexander (LIS) | P11: Chen Leilei (LIS-BPMO), Hynek Tobias (LIS) | Q11: =IF(AND(K11<>"",K11<Cockpit!$H$6,H11<>"Abgeschlossen"),1,0) -> 1 | R11: 0 | S11: =IF(AND(OR(Cockpit!$B$6="(Alle)",D11=Cockpit!$B$6),OR(Cockpit!$C$6="(Alle)",E11=Cockpit!$C$6),OR(Cockpit!$D$6="(Alle)",F11=Cockpit!$D$6),OR(Cockpit!$E$6="(Alle)",G11=Cockpit!$E$6),OR(Cockpit!$F$6="(Alle)",H11=Cockpit!$F$6),OR(Cockpit!$G$6="(Alle)",O11=Cockpit!$G$6)),1,0) -> 1 | T11: =IF(S11=1,SUM($S$2:S11),"") -> 10
A12: 11 | B12: Manage IT global orientation programme incl. job shadowing | C12: Provide and develop IT workforce › Perform, learn and grow › Manage IT global orientation programme incl. job shadowing | D12: SP | E12: HR initiatives for IT | F12: Provide and develop IT workforce | G12: L3 | H12: Verzögert | I12: 0 | J12: 46037 | K12: 46204 | L12: 120 | M12: Verzögert | N12: Grabmair Melanie (LIS) | O12: Mielenz Thomas (LMT) | P12: Chen Leilei (LIS-BPMO), Hynek Tobias (LIS) | Q12: =IF(AND(K12<>"",K12<Cockpit!$H$6,H12<>"Abgeschlossen"),1,0) -> 1 | R12: 0 | S12: =IF(AND(OR(Cockpit!$B$6="(Alle)",D12=Cockpit!$B$6),OR(Cockpit!$C$6="(Alle)",E12=Cockpit!$C$6),OR(Cockpit!$D$6="(Alle)",F12=Cockpit!$D$6),OR(Cockpit!$E$6="(Alle)",G12=Cockpit!$E$6),OR(Cockpit!$F$6="(Alle)",H12=Cockpit!$F$6),OR(Cockpit!$G$6="(Alle)",O12=Cockpit!$G$6)),1,0) -> 1 | T12: =IF(S12=1,SUM($S$2:S12),"") -> 11
A13: 12 | B13: Manage IT knowledge | C13: Manage IT knowledge | D13: SP | E13: ITSM | F13: Manage IT knowledge | G13: L1 | H13: Verzögert | I13: 1 | J13: 46042 | K13: 46203 | L13: 116 | M13: Abgeschlossen | N13: Kuerschner Philipp (LIS) | O13: Sint Rachel (LBH) | P13: Schroeder Michael (LIS) | Q13: =IF(AND(K13<>"",K13<Cockpit!$H$6,H13<>"Abgeschlossen"),1,0) -> 1 | R13: 1 | S13: =IF(AND(OR(Cockpit!$B$6="(Alle)",D13=Cockpit!$B$6),OR(Cockpit!$C$6="(Alle)",E13=Cockpit!$C$6),OR(Cockpit!$D$6="(Alle)",F13=Cockpit!$D$6),OR(Cockpit!$E$6="(Alle)",G13=Cockpit!$E$6),OR(Cockpit!$F$6="(Alle)",H13=Cockpit!$F$6),OR(Cockpit!$G$6="(Alle)",O13=Cockpit!$G$6)),1,0) -> 1 | T13: =IF(S13=1,SUM($S$2:S13),"") -> 12
A14: 13 | B14: Manage IT project portfolio | C14: Manage IT portfolio › Manage IT project portfolio | D14: MP | E14: IT project management | F14: Manage IT portfolio | G14: L2 | H14: Verzögert | I14: 1 | J14: 45971 | K14: 46173 | L14: 145 | M14: Abgeschlossen | N14: Mühlbacher Christian (LIS) | O14: Rollinger Alexander (LIS) | P14: Frank Maren (LIS) | Q14: =IF(AND(K14<>"",K14<Cockpit!$H$6,H14<>"Abgeschlossen"),1,0) -> 1 | R14: 0 | S14: =IF(AND(OR(Cockpit!$B$6="(Alle)",D14=Cockpit!$B$6),OR(Cockpit!$C$6="(Alle)",E14=Cockpit!$C$6),OR(Cockpit!$D$6="(Alle)",F14=Cockpit!$D$6),OR(Cockpit!$E$6="(Alle)",G14=Cockpit!$E$6),OR(Cockpit!$F$6="(Alle)",H14=Cockpit!$F$6),OR(Cockpit!$G$6="(Alle)",O14=Cockpit!$G$6)),1,0) -> 1 | T14: =IF(S14=1,SUM($S$2:S14),"") -> 13
A15: 14 | B15: Manage IT service provision request | C15: Deliver IT service › Manage IT service provision request | D15: CP | E15: ITSM | F15: Deliver IT service | G15: L2 | H15: Verzögert | I15: 0 | J15: 46113 | K15: 46190 | L15: 56 | M15: Verzögert | N15: – | O15: Schnurrenberger Christoph (LIS-LIN) | P15: – | Q15: =IF(AND(K15<>"",K15<Cockpit!$H$6,H15<>"Abgeschlossen"),1,0) -> 1 | R15: 0 | S15: =IF(AND(OR(Cockpit!$B$6="(Alle)",D15=Cockpit!$B$6),OR(Cockpit!$C$6="(Alle)",E15=Cockpit!$C$6),OR(Cockpit!$D$6="(Alle)",F15=Cockpit!$D$6),OR(Cockpit!$E$6="(Alle)",G15=Cockpit!$E$6),OR(Cockpit!$F$6="(Alle)",H15=Cockpit!$F$6),OR(Cockpit!$G$6="(Alle)",O15=Cockpit!$G$6)),1,0) -> 1 | T15: =IF(S15=1,SUM($S$2:S15),"") -> 14
A16: 15 | B16: Manage IT skills | C16: Provide and develop IT workforce › Perform, learn and grow › Manage IT skills | D16: SP | E16: HR initiatives for IT | F16: Provide and develop IT workforce | G16: L3 | H16: Verzögert | I16: 0 | J16: 46023 | K16: 46568 | L16: 390 | M16: Verzögert | N16: Grabmair Melanie (LIS) | O16: Mielenz Thomas (LMT) | P16: Chen Leilei (LIS-BPMO), Hynek Tobias (LIS) | Q16: =IF(AND(K16<>"",K16<Cockpit!$H$6,H16<>"Abgeschlossen"),1,0) -> 0 | R16: 0 | S16: =IF(AND(OR(Cockpit!$B$6="(Alle)",D16=Cockpit!$B$6),OR(Cockpit!$C$6="(Alle)",E16=Cockpit!$C$6),OR(Cockpit!$D$6="(Alle)",F16=Cockpit!$D$6),OR(Cockpit!$E$6="(Alle)",G16=Cockpit!$E$6),OR(Cockpit!$F$6="(Alle)",H16=Cockpit!$F$6),OR(Cockpit!$G$6="(Alle)",O16=Cockpit!$G$6)),1,0) -> 1 | T16: =IF(S16=1,SUM($S$2:S16),"") -> 15
A17: 16 | B17: Manage IT stakeholder relationships | C17: Manage IT stakeholder relationships | D17: MP | E17: Corporate IT body | F17: Manage IT stakeholder relationships | G17: L1 | H17: Verzögert | I17: 0 | J17: 46113 | K17: 46379 | L17: 191 | M17: Verzögert | N17: Felder Max (LLI) | O17: Mielenz Thomas (LMT) | P17: Kreis Andreas (LLI) | Q17: =IF(AND(K17<>"",K17<Cockpit!$H$6,H17<>"Abgeschlossen"),1,0) -> 0 | R17: 0 | S17: =IF(AND(OR(Cockpit!$B$6="(Alle)",D17=Cockpit!$B$6),OR(Cockpit!$C$6="(Alle)",E17=Cockpit!$C$6),OR(Cockpit!$D$6="(Alle)",F17=Cockpit!$D$6),OR(Cockpit!$E$6="(Alle)",G17=Cockpit!$E$6),OR(Cockpit!$F$6="(Alle)",H17=Cockpit!$F$6),OR(Cockpit!$G$6="(Alle)",O17=Cockpit!$G$6)),1,0) -> 1 | T17: =IF(S17=1,SUM($S$2:S17),"") -> 16
A18: 17 | B18: Manage continuous improvement | C18: Manage IT processes and continuous improvement › Manage continuous improvement | D18: MP | E18: ITSM | F18: Manage IT processes and continuous improvement | G18: L2 | H18: Verzögert | I18: 0 | J18: 45931 | K18: 46052 | L18: 88 | M18: Verzögert | N18: Kuerschner Philipp (LIS) | O18: Reiner Heiko (HAU-ITSA) | P18: Boehme Matthias (LIS-BPMO), Rollinger Alexander (LIS) | Q18: =IF(AND(K18<>"",K18<Cockpit!$H$6,H18<>"Abgeschlossen"),1,0) -> 1 | R18: 0 | S18: =IF(AND(OR(Cockpit!$B$6="(Alle)",D18=Cockpit!$B$6),OR(Cockpit!$C$6="(Alle)",E18=Cockpit!$C$6),OR(Cockpit!$D$6="(Alle)",F18=Cockpit!$D$6),OR(Cockpit!$E$6="(Alle)",G18=Cockpit!$E$6),OR(Cockpit!$F$6="(Alle)",H18=Cockpit!$F$6),OR(Cockpit!$G$6="(Alle)",O18=Cockpit!$G$6)),1,0) -> 1 | T18: =IF(S18=1,SUM($S$2:S18),"") -> 17
... A29: 28 | B29: Run IT service | C29: Run IT service | D29: CP | E29: ITSM | F29: Run IT service | G29: L1 | H29: Verzögert | I29: 0.17 | J29: 45945 | K29: 46290 | L29: 248 | M29: Verzögert | N29: Oey Kai (LIS) | O29: Sint Rachel (LBH) | P29: Schroeder Michael (LIS), Boehme Matthias (LIS-BPMO) | Q29: =IF(AND(K29<>"",K29<Cockpit!$H$6,H29<>"Abgeschlossen"),1,0) -> 0 | R29: 0 | S29: =IF(AND(OR(Cockpit!$B$6="(Alle)",D29=Cockpit!$B$6),OR(Cockpit!$C$6="(Alle)",E29=Cockpit!$C$6),OR(Cockpit!$D$6="(Alle)",F29=Cockpit!$D$6),OR(Cockpit!$E$6="(Alle)",G29=Cockpit!$E$6),OR(Cockpit!$F$6="(Alle)",H29=Cockpit!$F$6),OR(Cockpit!$G$6="(Alle)",O29=Cockpit!$G$6)),1,0) -> 1 | T29: =IF(S29=1,SUM($S$2:S29),"") -> 28
A30: 29 | B30: Strategic architecture process | C30: Manage enterprise architecture › Strategic architecture process | D30: MP | E30: Corporate IT body | F30: Manage enterprise architecture | G30: L2 | H30: Verzögert | I30: 0 | J30: 45946 | K30: 46142 | M30: Verzögert | N30: – | O30: – | P30: – | Q30: =IF(AND(K30<>"",K30<Cockpit!$H$6,H30<>"Abgeschlossen"),1,0) -> 1 | R30: 0 | S30: =IF(AND(OR(Cockpit!$B$6="(Alle)",D30=Cockpit!$B$6),OR(Cockpit!$C$6="(Alle)",E30=Cockpit!$C$6),OR(Cockpit!$D$6="(Alle)",F30=Cockpit!$D$6),OR(Cockpit!$E$6="(Alle)",G30=Cockpit!$E$6),OR(Cockpit!$F$6="(Alle)",H30=Cockpit!$F$6),OR(Cockpit!$G$6="(Alle)",O30=Cockpit!$G$6)),1,0) -> 1 | T30: =IF(S30=1,SUM($S$2:S30),"") -> 29
A31: 30 | B31: Apply cost model to calculate service cost per unit | C31: Manage and control IT financials › Model and allocate IT costs › Apply cost model to calculate service cost per unit | D31: MP | E31: IT planning and steering | F31: Manage and control IT financials | G31: L3 | H31: In Arbeit | I31: 0.5 | J31: 45945 | M31: Ohne Angabe | N31: Frank Nicole (LIS) | O31: Moser Mario (LIS-LAH) | P31: Hynek Tobias (LIS), Kreis Andreas (LLI) | Q31: =IF(AND(K31<>"",K31<Cockpit!$H$6,H31<>"Abgeschlossen"),1,0) -> 0 | R31: 0 | S31: =IF(AND(OR(Cockpit!$B$6="(Alle)",D31=Cockpit!$B$6),OR(Cockpit!$C$6="(Alle)",E31=Cockpit!$C$6),OR(Cockpit!$D$6="(Alle)",F31=Cockpit!$D$6),OR(Cockpit!$E$6="(Alle)",G31=Cockpit!$E$6),OR(Cockpit!$F$6="(Alle)",H31=Cockpit!$F$6),OR(Cockpit!$G$6="(Alle)",O31=Cockpit!$G$6)),1,0) -> 1 | T31: =IF(S31=1,SUM($S$2:S31),"") -> 30
A32: 31 | B32: Approve and communicate budget plan | C32: Manage and control IT financials › Create and maintain IT budgets › Approve and communicate budget plan | D32: MP | E32: IT planning and steering | F32: Manage and control IT financials | G32: L3 | H32: In Arbeit | I32: 0.5 | J32: 45945 | M32: Ohne Angabe | N32: Frank Nicole (LIS) | O32: Mielenz Thomas (LMT) | P32: Hynek Tobias (LIS), Kreis Andreas (LLI) | Q32: =IF(AND(K32<>"",K32<Cockpit!$H$6,H32<>"Abgeschlossen"),1,0) -> 0 | R32: 0 | S32: =IF(AND(OR(Cockpit!$B$6="(Alle)",D32=Cockpit!$B$6),OR(Cockpit!$C$6="(Alle)",E32=Cockpit!$C$6),OR(Cockpit!$D$6="(Alle)",F32=Cockpit!$D$6),OR(Cockpit!$E$6="(Alle)",G32=Cockpit!$E$6),OR(Cockpit!$F$6="(Alle)",H32=Cockpit!$F$6),OR(Cockpit!$G$6="(Alle)",O32=Cockpit!$G$6)),1,0) -> 1 | T32: =IF(S32=1,SUM($S$2:S32),"") -> 31
A33: 32 | B33: Build IT Service | C33: Build IT Service | D33: CP | E33: ITSM | F33: Build IT Service | G33: L1 | H33: In Arbeit | I33: 0.41 | M33: Ohne Angabe | N33: Dalek Martin (LIS) | O33: Wiehe Alexander (COB) | P33: Kunz Christina (LIS-MHP) | Q33: =IF(AND(K33<>"",K33<Cockpit!$H$6,H33<>"Abgeschlossen"),1,0) -> 0 | R33: 0 | S33: =IF(AND(OR(Cockpit!$B$6="(Alle)",D33=Cockpit!$B$6),OR(Cockpit!$C$6="(Alle)",E33=Cockpit!$C$6),OR(Cockpit!$D$6="(Alle)",F33=Cockpit!$D$6),OR(Cockpit!$E$6="(Alle)",G33=Cockpit!$E$6),OR(Cockpit!$F$6="(Alle)",H33=Cockpit!$F$6),OR(Cockpit!$G$6="(Alle)",O33=Cockpit!$G$6)),1,0) -> 1 | T33: =IF(S33=1,SUM($S$2:S33),"") -> 32
A34: 33 | B34: Collect and consolidate budget from stakeholders | C34: Manage and control IT financials › Create and maintain IT budgets › Collect and consolidate budget from stakeholders | D34: MP | E34: IT planning and steering | F34: Manage and control IT financials | G34: L3 | H34: In Arbeit | I34: 0.5 | J34: 45945 | M34: Ohne Angabe | N34: Frank Nicole (LIS) | O34: Mielenz Thomas (LMT) | P34: Hynek Tobias (LIS), Kreis Andreas (LLI) | Q34: =IF(AND(K34<>"",K34<Cockpit!$H$6,H34<>"Abgeschlossen"),1,0) -> 0 | R34: 0 | S34: =IF(AND(OR(Cockpit!$B$6="(Alle)",D34=Cockpit!$B$6),OR(Cockpit!$C$6="(Alle)",E34=Cockpit!$C$6),OR(Cockpit!$D$6="(Alle)",F34=Cockpit!$D$6),OR(Cockpit!$E$6="(Alle)",G34=Cockpit!$E$6),OR(Cockpit!$F$6="(Alle)",H34=Cockpit!$F$6),OR(Cockpit!$G$6="(Alle)",O34=Cockpit!$G$6)),1,0) -> 1 | T34: =IF(S34=1,SUM($S$2:S34),"") -> 33
A35: 34 | B35: Compare actual cost to budget forecast | C35: Manage and control IT financials › Manage IT costs › Compare actual cost to budget forecast | D35: MP | E35: IT planning and steering | F35: Manage and control IT financials | G35: L3 | H35: In Arbeit | I35: 0.5 | J35: 45945 | M35: Ohne Angabe | N35: Frank Nicole (LIS) | O35: Moser Mario (LIS-LAH) | P35: Hynek Tobias (LIS), Kreis Andreas (LLI) | Q35: =IF(AND(K35<>"",K35<Cockpit!$H$6,H35<>"Abgeschlossen"),1,0) -> 0 | R35: 0 | S35: =IF(AND(OR(Cockpit!$B$6="(Alle)",D35=Cockpit!$B$6),OR(Cockpit!$C$6="(Alle)",E35=Cockpit!$C$6),OR(Cockpit!$D$6="(Alle)",F35=Cockpit!$D$6),OR(Cockpit!$E$6="(Alle)",G35=Cockpit!$E$6),OR(Cockpit!$F$6="(Alle)",H35=Cockpit!$F$6),OR(Cockpit!$G$6="(Alle)",O35=Cockpit!$G$6)),1,0) -> 1 | T35: =IF(S35=1,SUM($S$2:S35),"") -> 34
A36: 35 | B36: Create and maintain IT budgets | C36: Manage and control IT financials › Create and maintain IT budgets | D36: MP | E36: IT planning and steering | F36: Manage and control IT financials | G36: L2 | H36: In Arbeit | I36: 0.5 | J36: 45945 | M36: Ohne Angabe | N36: Frank Nicole (LIS) | O36: Mielenz Thomas (LMT) | P36: Hynek Tobias (LIS), Kreis Andreas (LLI) | Q36: =IF(AND(K36<>"",K36<Cockpit!$H$6,H36<>"Abgeschlossen"),1,0) -> 0 | R36: 0 | S36: =IF(AND(OR(Cockpit!$B$6="(Alle)",D36=Cockpit!$B$6),OR(Cockpit!$C$6="(Alle)",E36=Cockpit!$C$6),OR(Cockpit!$D$6="(Alle)",F36=Cockpit!$D$6),OR(Cockpit!$E$6="(Alle)",G36=Cockpit!$E$6),OR(Cockpit!$F$6="(Alle)",H36=Cockpit!$F$6),OR(Cockpit!$G$6="(Alle)",O36=Cockpit!$G$6)),1,0) -> 1 | T36: =IF(S36=1,SUM($S$2:S36),"") -> 35
A37: 36 | B37: Create, approve and publish trainings for IT workforce within IT Training Catalogue | C37: Provide and develop IT workforce › Perform, learn and grow › Create, approve and publish trainings for IT workforce within IT Training Catalogue | D37: SP | E37: HR initiatives for IT | F37: Provide and develop IT workforce | G37: L3 | H37: In Arbeit | I37: 0.5 | J37: 45931 | K37: 46142 | L37: 152 | M37: In Arbeit | N37: Grabmair Melanie (LIS) | O37: Mielenz Thomas (LMT) | P37: Chen Leilei (LIS-BPMO), Hynek Tobias (LIS) | Q37: =IF(AND(K37<>"",K37<Cockpit!$H$6,H37<>"Abgeschlossen"),1,0) -> 1 | R37: 0 | S37: =IF(AND(OR(Cockpit!$B$6="(Alle)",D37=Cockpit!$B$6),OR(Cockpit!$C$6="(Alle)",E37=Cockpit!$C$6),OR(Cockpit!$D$6="(Alle)",F37=Cockpit!$D$6),OR(Cockpit!$E$6="(Alle)",G37=Cockpit!$E$6),OR(Cockpit!$F$6="(Alle)",H37=Cockpit!$F$6),OR(Cockpit!$G$6="(Alle)",O37=Cockpit!$G$6)),1,0) -> 1 | T37: =IF(S37=1,SUM($S$2:S37),"") -> 36
A38: 37 | B38: DC/DCC/MSC IT-compliance | C38: Manage IT risks and compliance › Manage IT compliance › DC/DCC/MSC IT-compliance | D38: MP | E38: Central area (Jan Müskens) | F38: Manage IT risks and compliance | G38: L3 | H38: In Arbeit | I38: 0.25 | J38: 45931 | K38: 46295 | L38: 261 | M38: In Arbeit | N38: Mueskens Jan (LHO) | O38: Monnier Murielle (LEC) | P38: Kreis Andreas (LLI) | Q38: =IF(AND(K38<>"",K38<Cockpit!$H$6,H38<>"Abgeschlossen"),1,0) -> 0 | R38: 0 | S38: =IF(AND(OR(Cockpit!$B$6="(Alle)",D38=Cockpit!$B$6),OR(Cockpit!$C$6="(Alle)",E38=Cockpit!$C$6),OR(Cockpit!$D$6="(Alle)",F38=Cockpit!$D$6),OR(Cockpit!$E$6="(Alle)",G38=Cockpit!$E$6),OR(Cockpit!$F$6="(Alle)",H38=Cockpit!$F$6),OR(Cockpit!$G$6="(Alle)",O38=Cockpit!$G$6)),1,0) -> 1 | T38: =IF(S38=1,SUM($S$2:S38),"") -> 37
A39: 38 | B39: Define cost allocation principles | C39: Manage and control IT financials › Model and allocate IT costs › Define cost allocation principles | D39: MP | E39: IT planning and steering | F39: Manage and control IT financials | G39: L3 | H39: In Arbeit | I39: 0.5 | J39: 45945 | M39: Ohne Angabe | N39: Frank Nicole (LIS) | O39: Moser Mario (LIS-LAH) | P39: Hynek Tobias (LIS), Kreis Andreas (LLI) | Q39: =IF(AND(K39<>"",K39<Cockpit!$H$6,H39<>"Abgeschlossen"),1,0) -> 0 | R39: 0 | S39: =IF(AND(OR(Cockpit!$B$6="(Alle)",D39=Cockpit!$B$6),OR(Cockpit!$C$6="(Alle)",E39=Cockpit!$C$6),OR(Cockpit!$D$6="(Alle)",F39=Cockpit!$D$6),OR(Cockpit!$E$6="(Alle)",G39=Cockpit!$E$6),OR(Cockpit!$F$6="(Alle)",H39=Cockpit!$F$6),OR(Cockpit!$G$6="(Alle)",O39=Cockpit!$G$6)),1,0) -> 1 | T39: =IF(S39=1,SUM($S$2:S39),"") -> 38
A40: 39 | B40: Define financial management framework | C40: Manage and control IT financials › Manage finance and accounting › Define financial management framework | D40: MP | E40: IT planning and steering | F40: Manage and control IT financials | G40: L3 | H40: In Arbeit | I40: 0.5 | J40: 45945 | M40: Ohne Angabe | N40: Frank Nicole (LIS) | O40: Moser Mario (LIS-LAH) | P40: Hynek Tobias (LIS), Kreis Andreas (LLI) | Q40: =IF(AND(K40<>"",K40<Cockpit!$H$6,H40<>"Abgeschlossen"),1,0) -> 0 | R40: 0 | S40: =IF(AND(OR(Cockpit!$B$6="(Alle)",D40=Cockpit!$B$6),OR(Cockpit!$C$6="(Alle)",E40=Cockpit!$C$6),OR(Cockpit!$D$6="(Alle)",F40=Cockpit!$D$6),OR(Cockpit!$E$6="(Alle)",G40=Cockpit!$E$6),OR(Cockpit!$F$6="(Alle)",H40=Cockpit!$F$6),OR(Cockpit!$G$6="(Alle)",O40=Cockpit!$G$6)),1,0) -> 1 | T40: =IF(S40=1,SUM($S$2:S40),"") -> 39
A41: 40 | B41: Deploy IT service | C41: Build IT Service › Deploy IT service | D41: CP | E41: ITSM | F41: Build IT Service | G41: L2 | H41: In Arbeit | I41: 0 | J41: 46146 | K41: 46234 | M41: In Arbeit | N41: Dalek Martin (LIS) | O41: Wiehe Alexander (COB) | P41: Kunz Christina (LIS-MHP) | Q41: =IF(AND(K41<>"",K41<Cockpit!$H$6,H41<>"Abgeschlossen"),1,0) -> 1 | R41: 0 | S41: =IF(AND(OR(Cockpit!$B$6="(Alle)",D41=Cockpit!$B$6),OR(Cockpit!$C$6="(Alle)",E41=Cockpit!$C$6),OR(Cockpit!$D$6="(Alle)",F41=Cockpit!$D$6),OR(Cockpit!$E$6="(Alle)",G41=Cockpit!$E$6),OR(Cockpit!$F$6="(Alle)",H41=Cockpit!$F$6),OR(Cockpit!$G$6="(Alle)",O41=Cockpit!$G$6)),1,0) -> 1 | T41: =IF(S41=1,SUM($S$2:S41),"") -> 40
A42: 41 | B42: Design IT service | C42: Build IT Service › Design IT service | D42: CP | E42: ITSM | F42: Build IT Service | G42: L2 | H42: In Arbeit | I42: 0.5 | J42: 46146 | K42: 46234 | M42: In Arbeit | N42: Dalek Martin (LIS) | O42: Wiehe Alexander (COB) | P42: Kunz Christina (LIS-MHP) | Q42: =IF(AND(K42<>"",K42<Cockpit!$H$6,H42<>"Abgeschlossen"),1,0) -> 1 | R42: 0 | S42: =IF(AND(OR(Cockpit!$B$6="(Alle)",D42=Cockpit!$B$6),OR(Cockpit!$C$6="(Alle)",E42=Cockpit!$C$6),OR(Cockpit!$D$6="(Alle)",F42=Cockpit!$D$6),OR(Cockpit!$E$6="(Alle)",G42=Cockpit!$E$6),OR(Cockpit!$F$6="(Alle)",H42=Cockpit!$F$6),OR(Cockpit!$G$6="(Alle)",O42=Cockpit!$G$6)),1,0) -> 1 | T42: =IF(S42=1,SUM($S$2:S42),"") -> 41
A43: 42 | B43: Develop and customise IT service | C43: Build IT Service › Develop and customise IT service | D43: CP | E43: ITSM | F43: Build IT Service | G43: L2 | H43: In Arbeit | I43: 0 | J43: 46146 | K43: 46234 | M43: In Arbeit | N43: Dalek Martin (LIS) | O43: Wiehe Alexander (COB) | P43: Kunz Christina (LIS-MHP) | Q43: =IF(AND(K43<>"",K43<Cockpit!$H$6,H43<>"Abgeschlossen"),1,0) -> 1 | R43: 0 | S43: =IF(AND(OR(Cockpit!$B$6="(Alle)",D43=Cockpit!$B$6),OR(Cockpit!$C$6="(Alle)",E43=Cockpit!$C$6),OR(Cockpit!$D$6="(Alle)",F43=Cockpit!$D$6),OR(Cockpit!$E$6="(Alle)",G43=Cockpit!$E$6),OR(Cockpit!$F$6="(Alle)",H43=Cockpit!$F$6),OR(Cockpit!$G$6="(Alle)",O43=Cockpit!$G$6)),1,0) -> 1 | T43: =IF(S43=1,SUM($S$2:S43),"") -> 42
A44: 43 | B44: Develop preliminary budget plan | C44: Manage and control IT financials › Create and maintain IT budgets › Develop preliminary budget plan | D44: MP | E44: IT planning and steering | F44: Manage and control IT financials | G44: L3 | H44: In Arbeit | I44: 0.5 | J44: 45945 | M44: Ohne Angabe | N44: Frank Nicole (LIS) | O44: Mielenz Thomas (LMT) | P44: Hynek Tobias (LIS), Kreis Andreas (LLI) | Q44: =IF(AND(K44<>"",K44<Cockpit!$H$6,H44<>"Abgeschlossen"),1,0) -> 0 | R44: 0 | S44: =IF(AND(OR(Cockpit!$B$6="(Alle)",D44=Cockpit!$B$6),OR(Cockpit!$C$6="(Alle)",E44=Cockpit!$C$6),OR(Cockpit!$D$6="(Alle)",F44=Cockpit!$D$6),OR(Cockpit!$E$6="(Alle)",G44=Cockpit!$E$6),OR(Cockpit!$F$6="(Alle)",H44=Cockpit!$F$6),OR(Cockpit!$G$6="(Alle)",O44=Cockpit!$G$6)),1,0) -> 1 | T44: =IF(S44=1,SUM($S$2:S44),"") -> 43
A45: 44 | B45: Elaborate to-be process | C45: Manage IT processes and continuous improvement › Perform operational process management › Elaborate to-be process | D45: MP | E45: ITSM | F45: Manage IT processes and continuous improvement | G45: L3 | H45: In Arbeit | I45: 0.25 | J45: 46034 | K45: 46173 | L45: 100 | M45: In Arbeit | N45: Rollinger Alexander (LIS) | O45: Reiner Heiko (HAU-ITSA) | P45: Rollinger Alexander (LIS) | Q45: =IF(AND(K45<>"",K45<Cockpit!$H$6,H45<>"Abgeschlossen"),1,0) -> 1 | R45: 0 | S45: =IF(AND(OR(Cockpit!$B$6="(Alle)",D45=Cockpit!$B$6),OR(Cockpit!$C$6="(Alle)",E45=Cockpit!$C$6),OR(Cockpit!$D$6="(Alle)",F45=Cockpit!$D$6),OR(Cockpit!$E$6="(Alle)",G45=Cockpit!$E$6),OR(Cockpit!$F$6="(Alle)",H45=Cockpit!$F$6),OR(Cockpit!$G$6="(Alle)",O45=Cockpit!$G$6)),1,0) -> 1 | T45: =IF(S45=1,SUM($S$2:S45),"") -> 44
A46: 45 | B46: Ensure Information security | C46: Ensure Information security | D46: SP | E46: Information security | F46: Ensure Information security | G46: L1 | H46: In Arbeit | I46: 0.5 | J46: 45946 | K46: 45946 | L46: 1 | M46: Ohne Angabe | N46: Da Silva Alessandro (LIN) | O46: Monnier Murielle (LEC) | P46: Rollinger Alexander (LIS) | Q46: =IF(AND(K46<>"",K46<Cockpit!$H$6,H46<>"Abgeschlossen"),1,0) -> 1 | R46: 0 | S46: =IF(AND(OR(Cockpit!$B$6="(Alle)",D46=Cockpit!$B$6),OR(Cockpit!$C$6="(Alle)",E46=Cockpit!$C$6),OR(Cockpit!$D$6="(Alle)",F46=Cockpit!$D$6),OR(Cockpit!$E$6="(Alle)",G46=Cockpit!$E$6),OR(Cockpit!$F$6="(Alle)",H46=Cockpit!$F$6),OR(Cockpit!$G$6="(Alle)",O46=Cockpit!$G$6)),1,0) -> 1 | T46: =IF(S46=1,SUM($S$2:S46),"") -> 45
A47: 46 | B47: Establish cost allocation model | C47: Manage and control IT financials › Model and allocate IT costs › Establish cost allocation model | D47: MP | E47: IT planning and steering | F47: Manage and control IT financials | G47: L3 | H47: In Arbeit | I47: 0.5 | J47: 45945 | M47: Ohne Angabe | N47: Frank Nicole (LIS) | O47: Moser Mario (LIS-LAH) | P47: Hynek Tobias (LIS), Kreis Andreas (LLI) | Q47: =IF(AND(K47<>"",K47<Cockpit!$H$6,H47<>"Abgeschlossen"),1,0) -> 0 | R47: 0 | S47: =IF(AND(OR(Cockpit!$B$6="(Alle)",D47=Cockpit!$B$6),OR(Cockpit!$C$6="(Alle)",E47=Cockpit!$C$6),OR(Cockpit!$D$6="(Alle)",F47=Cockpit!$D$6),OR(Cockpit!$E$6="(Alle)",G47=Cockpit!$E$6),OR(Cockpit!$F$6="(Alle)",H47=Cockpit!$F$6),OR(Cockpit!$G$6="(Alle)",O47=Cockpit!$G$6)),1,0) -> 1 | T47: =IF(S47=1,SUM($S$2:S47),"") -> 46
A48: 47 | B48: Establish financial accounting structure | C48: Manage and control IT financials › Manage finance and accounting › Establish financial accounting structure | D48: MP | E48: IT planning and steering | F48: Manage and control IT financials | G48: L3 | H48: In Arbeit | I48: 0.5 | J48: 45945 | M48: Ohne Angabe | N48: Frank Nicole (LIS) | O48: Moser Mario (LIS-LAH) | P48: Hynek Tobias (LIS), Kreis Andreas (LLI) | Q48: =IF(AND(K48<>"",K48<Cockpit!$H$6,H48<>"Abgeschlossen"),1,0) -> 0 | R48: 0 | S48: =IF(AND(OR(Cockpit!$B$6="(Alle)",D48=Cockpit!$B$6),OR(Cockpit!$C$6="(Alle)",E48=Cockpit!$C$6),OR(Cockpit!$D$6="(Alle)",F48=Cockpit!$D$6),OR(Cockpit!$E$6="(Alle)",G48=Cockpit!$E$6),OR(Cockpit!$F$6="(Alle)",H48=Cockpit!$F$6),OR(Cockpit!$G$6="(Alle)",O48=Cockpit!$G$6)),1,0) -> 1 | T48: =IF(S48=1,SUM($S$2:S48),"") -> 47
A49: 48 | B49: Evaluate success of IT service rollout | C49: Build IT Service › Evaluate success of IT service rollout | D49: CP | E49: ITSM | F49: Build IT Service | G49: L2 | H49: In Arbeit | I49: 0 | J49: 46146 | K49: 46234 | M49: In Arbeit | N49: Dalek Martin (LIS) | O49: Wiehe Alexander (COB) | P49: Kunz Christina (LIS-MHP) | Q49: =IF(AND(K49<>"",K49<Cockpit!$H$6,H49<>"Abgeschlossen"),1,0) -> 1 | R49: 0 | S49: =IF(AND(OR(Cockpit!$B$6="(Alle)",D49=Cockpit!$B$6),OR(Cockpit!$C$6="(Alle)",E49=Cockpit!$C$6),OR(Cockpit!$D$6="(Alle)",F49=Cockpit!$D$6),OR(Cockpit!$E$6="(Alle)",G49=Cockpit!$E$6),OR(Cockpit!$F$6="(Alle)",H49=Cockpit!$F$6),OR(Cockpit!$G$6="(Alle)",O49=Cockpit!$G$6)),1,0) -> 1 | T49: =IF(S49=1,SUM($S$2:S49),"") -> 48
A50: 49 | B50: Gather relevant cost and consumption data | C50: Manage and control IT financials › Model and allocate IT costs › Gather relevant cost and consumption data | D50: MP | E50: IT planning and steering | F50: Manage and control IT financials | G50: L3 | H50: In Arbeit | I50: 0.5 | J50: 45945 | M50: Ohne Angabe | N50: Frank Nicole (LIS) | O50: Moser Mario (LIS-LAH) | P50: Hynek Tobias (LIS), Kreis Andreas (LLI) | Q50: =IF(AND(K50<>"",K50<Cockpit!$H$6,H50<>"Abgeschlossen"),1,0) -> 0 | R50: 0 | S50: =IF(AND(OR(Cockpit!$B$6="(Alle)",D50=Cockpit!$B$6),OR(Cockpit!$C$6="(Alle)",E50=Cockpit!$C$6),OR(Cockpit!$D$6="(Alle)",F50=Cockpit!$D$6),OR(Cockpit!$E$6="(Alle)",G50=Cockpit!$E$6),OR(Cockpit!$F$6="(Alle)",H50=Cockpit!$F$6),OR(Cockpit!$G$6="(Alle)",O50=Cockpit!$G$6)),1,0) -> 1 | T50: =IF(S50=1,SUM($S$2:S50),"") -> 49
A51: 50 | B51: Handle IT Incident | C51: Run IT service › Provide IT service support › Handle IT Incident | D51: CP | E51: ITSM | F51: Run IT service | G51: L3 | H51: In Arbeit | I51: 0.75 | J51: 46035 | K51: 46100 | L51: 48 | M51: In Arbeit | N51: Kuerschner Philipp (LIS) | O51: Sint Rachel (LBH) | P51: Schroeder Michael (LIS) | Q51: =IF(AND(K51<>"",K51<Cockpit!$H$6,H51<>"Abgeschlossen"),1,0) -> 1 | R51: 0 | S51: =IF(AND(OR(Cockpit!$B$6="(Alle)",D51=Cockpit!$B$6),OR(Cockpit!$C$6="(Alle)",E51=Cockpit!$C$6),OR(Cockpit!$D$6="(Alle)",F51=Cockpit!$D$6),OR(Cockpit!$E$6="(Alle)",G51=Cockpit!$E$6),OR(Cockpit!$F$6="(Alle)",H51=Cockpit!$F$6),OR(Cockpit!$G$6="(Alle)",O51=Cockpit!$G$6)),1,0) -> 1 | T51: =IF(S51=1,SUM($S$2:S51),"") -> 50
A52: 51 | B52: Handle IT problem | C52: Run IT service › Provide IT service support › Handle IT problem | D52: CP | E52: ITSM | F52: Run IT service | G52: L3 | H52: In Arbeit | I52: 0.75 | J52: 46035 | K52: 46100 | L52: 48 | M52: In Arbeit | N52: Kuerschner Philipp (LIS) | O52: Sint Rachel (LBH) | P52: Schroeder Michael (LIS) | Q52: =IF(AND(K52<>"",K52<Cockpit!$H$6,H52<>"Abgeschlossen"),1,0) -> 1 | R52: 0 | S52: =IF(AND(OR(Cockpit!$B$6="(Alle)",D52=Cockpit!$B$6),OR(Cockpit!$C$6="(Alle)",E52=Cockpit!$C$6),OR(Cockpit!$D$6="(Alle)",F52=Cockpit!$D$6),OR(Cockpit!$E$6="(Alle)",G52=Cockpit!$E$6),OR(Cockpit!$F$6="(Alle)",H52=Cockpit!$F$6),OR(Cockpit!$G$6="(Alle)",O52=Cockpit!$G$6)),1,0) -> 1 | T52: =IF(S52=1,SUM($S$2:S52),"") -> 51
A53: 52 | B53: Identify process and determine goals | C53: Manage IT processes and continuous improvement › Perform operational process management › Identify process and determine goals | D53: MP | E53: ITSM | F53: Manage IT processes and continuous improvement | G53: L3 | H53: In Arbeit | I53: 0.25 | J53: 46034 | K53: 46173 | L53: 100 | M53: In Arbeit | N53: Rollinger Alexander (LIS) | O53: Reiner Heiko (HAU-ITSA) | P53: Rollinger Alexander (LIS) | Q53: =IF(AND(K53<>"",K53<Cockpit!$H$6,H53<>"Abgeschlossen"),1,0) -> 1 | R53: 0 | S53: =IF(AND(OR(Cockpit!$B$6="(Alle)",D53=Cockpit!$B$6),OR(Cockpit!$C$6="(Alle)",E53=Cockpit!$C$6),OR(Cockpit!$D$6="(Alle)",F53=Cockpit!$D$6),OR(Cockpit!$E$6="(Alle)",G53=Cockpit!$E$6),OR(Cockpit!$F$6="(Alle)",H53=Cockpit!$F$6),OR(Cockpit!$G$6="(Alle)",O53=Cockpit!$G$6)),1,0) -> 1 | T53: =IF(S53=1,SUM($S$2:S53),"") -> 52
A54: 53 | B54: Implement cost allocation to stakeholders or companies | C54: Manage and control IT financials › Model and allocate IT costs › Implement cost allocation to stakeholders or companies | D54: MP | E54: IT planning and steering | F54: Manage and control IT financials | G54: L3 | H54: In Arbeit | I54: 0.5 | J54: 45945 | M54: Ohne Angabe | N54: Frank Nicole (LIS) | O54: Moser Mario (LIS-LAH) | P54: Hynek Tobias (LIS), Kreis Andreas (LLI) | Q54: =IF(AND(K54<>"",K54<Cockpit!$H$6,H54<>"Abgeschlossen"),1,0) -> 0 | R54: 0 | S54: =IF(AND(OR(Cockpit!$B$6="(Alle)",D54=Cockpit!$B$6),OR(Cockpit!$C$6="(Alle)",E54=Cockpit!$C$6),OR(Cockpit!$D$6="(Alle)",F54=Cockpit!$D$6),OR(Cockpit!$E$6="(Alle)",G54=Cockpit!$E$6),OR(Cockpit!$F$6="(Alle)",H54=Cockpit!$F$6),OR(Cockpit!$G$6="(Alle)",O54=Cockpit!$G$6)),1,0) -> 1 | T54: =IF(S54=1,SUM($S$2:S54),"") -> 53
A55: 54 | B55: Implement process | C55: Manage IT processes and continuous improvement › Perform operational process management › Implement process | D55: MP | E55: ITSM | F55: Manage IT processes and continuous improvement | G55: L3 | H55: In Arbeit | I55: 0.25 | J55: 46034 | K55: 46173 | L55: 100 | M55: In Arbeit | N55: Rollinger Alexander (LIS) | O55: Reiner Heiko (HAU-ITSA) | P55: Rollinger Alexander (LIS) | Q55: =IF(AND(K55<>"",K55<Cockpit!$H$6,H55<>"Abgeschlossen"),1,0) -> 1 | R55: 0 | S55: =IF(AND(OR(Cockpit!$B$6="(Alle)",D55=Cockpit!$B$6),OR(Cockpit!$C$6="(Alle)",E55=Cockpit!$C$6),OR(Cockpit!$D$6="(Alle)",F55=Cockpit!$D$6),OR(Cockpit!$E$6="(Alle)",G55=Cockpit!$E$6),OR(Cockpit!$F$6="(Alle)",H55=Cockpit!$F$6),OR(Cockpit!$G$6="(Alle)",O55=Cockpit!$G$6)),1,0) -> 1 | T55: =IF(S55=1,SUM($S$2:S55),"") -> 54
A56: 55 | B56: Implement to improve | C56: Manage IT risks and compliance › Manage IT compliance › Implement to improve | D56: MP | E56: Central area (Jan Müskens) | F56: Manage IT risks and compliance | G56: L3 | H56: In Arbeit | I56: 0.25 | J56: 45931 | K56: 46295 | L56: 261 | M56: In Arbeit | N56: Mueskens Jan (LHO) | O56: Monnier Murielle (LEC) | P56: – | Q56: =IF(AND(K56<>"",K56<Cockpit!$H$6,H56<>"Abgeschlossen"),1,0) -> 0 | R56: 0 | S56: =IF(AND(OR(Cockpit!$B$6="(Alle)",D56=Cockpit!$B$6),OR(Cockpit!$C$6="(Alle)",E56=Cockpit!$C$6),OR(Cockpit!$D$6="(Alle)",F56=Cockpit!$D$6),OR(Cockpit!$E$6="(Alle)",G56=Cockpit!$E$6),OR(Cockpit!$F$6="(Alle)",H56=Cockpit!$F$6),OR(Cockpit!$G$6="(Alle)",O56=Cockpit!$G$6)),1,0) -> 1 | T56: =IF(S56=1,SUM($S$2:S56),"") -> 55
A57: 56 | B57: Initiate corrective or preventive actions | C57: Manage and control IT financials › Manage IT costs › Initiate corrective or preventive actions | D57: MP | E57: IT planning and steering | F57: Manage and control IT financials | G57: L3 | H57: In Arbeit | I57: 0.5 | J57: 45945 | M57: Ohne Angabe | N57: Frank Nicole (LIS) | O57: Moser Mario (LIS-LAH) | P57: Hynek Tobias (LIS), Kreis Andreas (LLI) | Q57: =IF(AND(K57<>"",K57<Cockpit!$H$6,H57<>"Abgeschlossen"),1,0) -> 0 | R57: 0 | S57: =IF(AND(OR(Cockpit!$B$6="(Alle)",D57=Cockpit!$B$6),OR(Cockpit!$C$6="(Alle)",E57=Cockpit!$C$6),OR(Cockpit!$D$6="(Alle)",F57=Cockpit!$D$6),OR(Cockpit!$E$6="(Alle)",G57=Cockpit!$E$6),OR(Cockpit!$F$6="(Alle)",H57=Cockpit!$F$6),OR(Cockpit!$G$6="(Alle)",O57=Cockpit!$G$6)),1,0) -> 1 | T57: =IF(S57=1,SUM($S$2:S57),"") -> 56
A58: 57 | B58: Leverage IT innovation | C58: Leverage IT innovation | D58: SP | E58: ITSM | F58: Leverage IT innovation | G58: L1 | H58: In Arbeit | I58: 0.25 | J58: 46143 | K58: 46326 | L58: 55 | M58: Ohne Angabe | N58: Abbondio Viviana (LIS) | O58: Sint Rachel (LBH) | P58: Chen Leilei (LIS-BPMO) | Q58: =IF(AND(K58<>"",K58<Cockpit!$H$6,H58<>"Abgeschlossen"),1,0) -> 0 | R58: 0 | S58: =IF(AND(OR(Cockpit!$B$6="(Alle)",D58=Cockpit!$B$6),OR(Cockpit!$C$6="(Alle)",E58=Cockpit!$C$6),OR(Cockpit!$D$6="(Alle)",F58=Cockpit!$D$6),OR(Cockpit!$E$6="(Alle)",G58=Cockpit!$E$6),OR(Cockpit!$F$6="(Alle)",H58=Cockpit!$F$6),OR(Cockpit!$G$6="(Alle)",O58=Cockpit!$G$6)),1,0) -> 1 | T58: =IF(S58=1,SUM($S$2:S58),"") -> 57
A59: 58 | B59: Maintain CMDB | C59: Run IT service › Operate and maintain IT service › Maintain CMDB | D59: CP | E59: ITSM | F59: Run IT service | G59: L3 | H59: In Arbeit | I59: 0.5 | J59: 46036 | K59: 46189 | L59: 91 | M59: In Arbeit | N59: Kretz Lucas (COC-COT-IT) | O59: Sint Rachel (LBH) | P59: Schroeder Michael (LIS) | Q59: =IF(AND(K59<>"",K59<Cockpit!$H$6,H59<>"Abgeschlossen"),1,0) -> 1 | R59: 0 | S59: =IF(AND(OR(Cockpit!$B$6="(Alle)",D59=Cockpit!$B$6),OR(Cockpit!$C$6="(Alle)",E59=Cockpit!$C$6),OR(Cockpit!$D$6="(Alle)",F59=Cockpit!$D$6),OR(Cockpit!$E$6="(Alle)",G59=Cockpit!$E$6),OR(Cockpit!$F$6="(Alle)",H59=Cockpit!$F$6),OR(Cockpit!$G$6="(Alle)",O59=Cockpit!$G$6)),1,0) -> 1 | T59: =IF(S59=1,SUM($S$2:S59),"") -> 58
A60: 59 | B60: Maintan and adjust budget | C60: Manage and control IT financials › Create and maintain IT budgets › Maintan and adjust budget | D60: MP | E60: IT planning and steering | F60: Manage and control IT financials | G60: L3 | H60: In Arbeit | I60: 0.5 | J60: 45945 | M60: Ohne Angabe | N60: Frank Nicole (LIS) | O60: Mielenz Thomas (LMT) | P60: Hynek Tobias (LIS), Kreis Andreas (LLI) | Q60: =IF(AND(K60<>"",K60<Cockpit!$H$6,H60<>"Abgeschlossen"),1,0) -> 0 | R60: 0 | S60: =IF(AND(OR(Cockpit!$B$6="(Alle)",D60=Cockpit!$B$6),OR(Cockpit!$C$6="(Alle)",E60=Cockpit!$C$6),OR(Cockpit!$D$6="(Alle)",F60=Cockpit!$D$6),OR(Cockpit!$E$6="(Alle)",G60=Cockpit!$E$6),OR(Cockpit!$F$6="(Alle)",H60=Cockpit!$F$6),OR(Cockpit!$G$6="(Alle)",O60=Cockpit!$G$6)),1,0) -> 1 | T60: =IF(S60=1,SUM($S$2:S60),"") -> 59
A61: 60 | B61: Manage IT compliance | C61: Manage IT risks and compliance › Manage IT compliance | D61: MP | E61: Central area (Jan Müskens) | F61: Manage IT risks and compliance | G61: L2 | H61: In Arbeit | I61: 0.25 | J61: 45931 | K61: 46295 | L61: 261 | M61: In Arbeit | N61: Mueskens Jan (LHO) | O61: Monnier Murielle (LEC) | P61: Kreis Andreas (LLI) | Q61: =IF(AND(K61<>"",K61<Cockpit!$H$6,H61<>"Abgeschlossen"),1,0) -> 0 | R61: 0 | S61: =IF(AND(OR(Cockpit!$B$6="(Alle)",D61=Cockpit!$B$6),OR(Cockpit!$C$6="(Alle)",E61=Cockpit!$C$6),OR(Cockpit!$D$6="(Alle)",F61=Cockpit!$D$6),OR(Cockpit!$E$6="(Alle)",G61=Cockpit!$E$6),OR(Cockpit!$F$6="(Alle)",H61=Cockpit!$F$6),OR(Cockpit!$G$6="(Alle)",O61=Cockpit!$G$6)),1,0) -> 1 | T61: =IF(S61=1,SUM($S$2:S61),"") -> 60
A62: 61 | B62: Manage IT costs | C62: Manage and control IT financials › Manage IT costs | D62: MP | E62: IT planning and steering | F62: Manage and control IT financials | G62: L2 | H62: In Arbeit | I62: 0.5 | J62: 45945 | M62: Ohne Angabe | N62: Frank Nicole (LIS) | O62: Moser Mario (LIS-LAH) | P62: Hynek Tobias (LIS), Kreis Andreas (LLI) | Q62: =IF(AND(K62<>"",K62<Cockpit!$H$6,H62<>"Abgeschlossen"),1,0) -> 0 | R62: 0 | S62: =IF(AND(OR(Cockpit!$B$6="(Alle)",D62=Cockpit!$B$6),OR(Cockpit!$C$6="(Alle)",E62=Cockpit!$C$6),OR(Cockpit!$D$6="(Alle)",F62=Cockpit!$D$6),OR(Cockpit!$E$6="(Alle)",G62=Cockpit!$E$6),OR(Cockpit!$F$6="(Alle)",H62=Cockpit!$F$6),OR(Cockpit!$G$6="(Alle)",O62=Cockpit!$G$6)),1,0) -> 1 | T62: =IF(S62=1,SUM($S$2:S62),"") -> 61
A63: 62 | B63: Manage IT governance framework | C63: Manage IT governance framework | D63: MP | E63: Corporate IT body | F63: Manage IT governance framework | G63: L1 | H63: In Arbeit | I63: 0.5 | J63: 46029 | K63: 46265 | L63: 169 | M63: In Arbeit | N63: Felder Max (LLI) | O63: Mielenz Thomas (LMT) | P63: Kunz Christina (LIS-MHP), Kreis Andreas (LLI) | Q63: =IF(AND(K63<>"",K63<Cockpit!$H$6,H63<>"Abgeschlossen"),1,0) -> 1 | R63: 0 | S63: =IF(AND(OR(Cockpit!$B$6="(Alle)",D63=Cockpit!$B$6),OR(Cockpit!$C$6="(Alle)",E63=Cockpit!$C$6),OR(Cockpit!$D$6="(Alle)",F63=Cockpit!$D$6),OR(Cockpit!$E$6="(Alle)",G63=Cockpit!$E$6),OR(Cockpit!$F$6="(Alle)",H63=Cockpit!$F$6),OR(Cockpit!$G$6="(Alle)",O63=Cockpit!$G$6)),1,0) -> 1 | T63: =IF(S63=1,SUM($S$2:S63),"") -> 62
A64: 63 | B64: Manage IT portfolio | C64: Manage IT portfolio | D64: MP | E64: ITSM | F64: Manage IT portfolio | G64: L1 | H64: In Arbeit | I64: 0.78 | J64: 45971 | K64: 46157 | L64: 135 | M64: Abgeschlossen | N64: – | O64: – | P64: Frank Maren (LIS), Kunz Christina (LIS-MHP) | Q64: =IF(AND(K64<>"",K64<Cockpit!$H$6,H64<>"Abgeschlossen"),1,0) -> 1 | R64: 0 | S64: =IF(AND(OR(Cockpit!$B$6="(Alle)",D64=Cockpit!$B$6),OR(Cockpit!$C$6="(Alle)",E64=Cockpit!$C$6),OR(Cockpit!$D$6="(Alle)",F64=Cockpit!$D$6),OR(Cockpit!$E$6="(Alle)",G64=Cockpit!$E$6),OR(Cockpit!$F$6="(Alle)",H64=Cockpit!$F$6),OR(Cockpit!$G$6="(Alle)",O64=Cockpit!$G$6)),1,0) -> 1 | T64: =IF(S64=1,SUM($S$2:S64),"") -> 63
A65: 64 | B65: Manage IT processes and continuous improvement | C65: Manage IT processes and continuous improvement | D65: MP | E65: ITSM | F65: Manage IT processes and continuous improvement | G65: L1 | H65: In Arbeit | I65: 0.21 | J65: 45931 | K65: 46173 | L65: 173 | M65: Abgeschlossen | N65: Rollinger Alexander (LIS) | O65: Reiner Heiko (HAU-ITSA) | P65: Hoermann Patrick (LLI) | Q65: =IF(AND(K65<>"",K65<Cockpit!$H$6,H65<>"Abgeschlossen"),1,0) -> 1 | R65: 0 | S65: =IF(AND(OR(Cockpit!$B$6="(Alle)",D65=Cockpit!$B$6),OR(Cockpit!$C$6="(Alle)",E65=Cockpit!$C$6),OR(Cockpit!$D$6="(Alle)",F65=Cockpit!$D$6),OR(Cockpit!$E$6="(Alle)",G65=Cockpit!$E$6),OR(Cockpit!$F$6="(Alle)",H65=Cockpit!$F$6),OR(Cockpit!$G$6="(Alle)",O65=Cockpit!$G$6)),1,0) -> 1 | T65: =IF(S65=1,SUM($S$2:S65),"") -> 64
A66: 65 | B66: Manage IT risks and compliance | C66: Manage IT risks and compliance | D66: MP | E66: n/a | F66: Manage IT risks and compliance | G66: L1 | H66: In Arbeit | I66: 0.22 | J66: 45931 | K66: 46295 | M66: Abgeschlossen | N66: Mueskens Jan (LHO) | O66: Monnier Murielle (LEC) | P66: Hoermann Patrick (LLI) | Q66: =IF(AND(K66<>"",K66<Cockpit!$H$6,H66<>"Abgeschlossen"),1,0) -> 0 | R66: 0 | S66: =IF(AND(OR(Cockpit!$B$6="(Alle)",D66=Cockpit!$B$6),OR(Cockpit!$C$6="(Alle)",E66=Cockpit!$C$6),OR(Cockpit!$D$6="(Alle)",F66=Cockpit!$D$6),OR(Cockpit!$E$6="(Alle)",G66=Cockpit!$E$6),OR(Cockpit!$F$6="(Alle)",H66=Cockpit!$F$6),OR(Cockpit!$G$6="(Alle)",O66=Cockpit!$G$6)),1,0) -> 1 | T66: =IF(S66=1,SUM($S$2:S66),"") -> 65
A67: 66 | B67: Manage IT service portfolio | C67: Manage IT portfolio › Manage IT service portfolio | D67: MP | E67: ITSM | F67: Manage IT portfolio | G67: L2 | H67: In Arbeit | I67: 0.5 | J67: 46113 | K67: 46273 | L67: 115 | M67: In Arbeit | N67: Birgit Gerathewohl (LIS) | O67: Reiner Heiko (HAU-ITSA) | P67: Frank Maren (LIS), Kunz Christina (LIS-MHP) | Q67: =IF(AND(K67<>"",K67<Cockpit!$H$6,H67<>"Abgeschlossen"),1,0) -> 0 | R67: 0 | S67: =IF(AND(OR(Cockpit!$B$6="(Alle)",D67=Cockpit!$B$6),OR(Cockpit!$C$6="(Alle)",E67=Cockpit!$C$6),OR(Cockpit!$D$6="(Alle)",F67=Cockpit!$D$6),OR(Cockpit!$E$6="(Alle)",G67=Cockpit!$E$6),OR(Cockpit!$F$6="(Alle)",H67=Cockpit!$F$6),OR(Cockpit!$G$6="(Alle)",O67=Cockpit!$G$6)),1,0) -> 1 | T67: =IF(S67=1,SUM($S$2:S67),"") -> 66
A68: 67 | B68: Manage IT service release | C68: Build IT Service › Manage IT service release | D68: CP | E68: ITSM | F68: Build IT Service | G68: L2 | H68: In Arbeit | I68: 0.5 | J68: 46073 | K68: 46203 | L68: 93 | M68: In Arbeit | N68: Hoeller Martin (LBH) | O68: Wiehe Alexander (COB) | P68: Kunz Christina (LIS-MHP), Frank Maren (LIS) | Q68: =IF(AND(K68<>"",K68<Cockpit!$H$6,H68<>"Abgeschlossen"),1,0) -> 1 | R68: 0 | S68: =IF(AND(OR(Cockpit!$B$6="(Alle)",D68=Cockpit!$B$6),OR(Cockpit!$C$6="(Alle)",E68=Cockpit!$C$6),OR(Cockpit!$D$6="(Alle)",F68=Cockpit!$D$6),OR(Cockpit!$E$6="(Alle)",G68=Cockpit!$E$6),OR(Cockpit!$F$6="(Alle)",H68=Cockpit!$F$6),OR(Cockpit!$G$6="(Alle)",O68=Cockpit!$G$6)),1,0) -> 1 | T68: =IF(S68=1,SUM($S$2:S68),"") -> 67
A69: 68 | B69: Manage IT sourcing and procurement | C69: Manage IT sourcing and procurement | D69: SP | E69: ITSM | F69: Manage IT sourcing and procurement | G69: L1 | H69: In Arbeit | I69: 0.25 | J69: 46132 | K69: 46211 | L69: 118 | M69: In Arbeit | N69: Dolderer Wolfgang (LIS) | O69: Monnier Murielle (LEC) | P69: Schoeberl Lorena (LBH) | Q69: =IF(AND(K69<>"",K69<Cockpit!$H$6,H69<>"Abgeschlossen"),1,0) -> 1 | R69: 1 | S69: =IF(AND(OR(Cockpit!$B$6="(Alle)",D69=Cockpit!$B$6),OR(Cockpit!$C$6="(Alle)",E69=Cockpit!$C$6),OR(Cockpit!$D$6="(Alle)",F69=Cockpit!$D$6),OR(Cockpit!$E$6="(Alle)",G69=Cockpit!$E$6),OR(Cockpit!$F$6="(Alle)",H69=Cockpit!$F$6),OR(Cockpit!$G$6="(Alle)",O69=Cockpit!$G$6)),1,0) -> 1 | T69: =IF(S69=1,SUM($S$2:S69),"") -> 68
A70: 69 | B70: Manage IT strategy | C70: Manage IT strategy | D70: MP | E70: Corporate IT body | F70: Manage IT strategy | G70: L1 | H70: In Arbeit | I70: 0.5 | J70: 46055 | K70: 46232 | L70: 128 | M70: In Arbeit | N70: Felder Max (LLI) | O70: Mielenz Thomas (LMT) | P70: Kreis Andreas (LLI) | Q70: =IF(AND(K70<>"",K70<Cockpit!$H$6,H70<>"Abgeschlossen"),1,0) -> 1 | R70: 0 | S70: =IF(AND(OR(Cockpit!$B$6="(Alle)",D70=Cockpit!$B$6),OR(Cockpit!$C$6="(Alle)",E70=Cockpit!$C$6),OR(Cockpit!$D$6="(Alle)",F70=Cockpit!$D$6),OR(Cockpit!$E$6="(Alle)",G70=Cockpit!$E$6),OR(Cockpit!$F$6="(Alle)",H70=Cockpit!$F$6),OR(Cockpit!$G$6="(Alle)",O70=Cockpit!$G$6)),1,0) -> 1 | T70: =IF(S70=1,SUM($S$2:S70),"") -> 69
A71: 70 | B71: Manage IT-C framework | C71: Manage IT risks and compliance › Manage IT compliance › Manage IT-C framework | D71: MP | E71: Central area (Jan Müskens) | F71: Manage IT risks and compliance | G71: L3 | H71: In Arbeit | I71: 0.25 | J71: 45931 | K71: 46295 | L71: 261 | M71: In Arbeit | N71: Mueskens Jan (LHO) | O71: Monnier Murielle (LEC) | P71: Kreis Andreas (LLI) | Q71: =IF(AND(K71<>"",K71<Cockpit!$H$6,H71<>"Abgeschlossen"),1,0) -> 0 | R71: 0 | S71: =IF(AND(OR(Cockpit!$B$6="(Alle)",D71=Cockpit!$B$6),OR(Cockpit!$C$6="(Alle)",E71=Cockpit!$C$6),OR(Cockpit!$D$6="(Alle)",F71=Cockpit!$D$6),OR(Cockpit!$E$6="(Alle)",G71=Cockpit!$E$6),OR(Cockpit!$F$6="(Alle)",H71=Cockpit!$F$6),OR(Cockpit!$G$6="(Alle)",O71=Cockpit!$G$6)),1,0) -> 1 | T71: =IF(S71=1,SUM($S$2:S71),"") -> 70
A72: 71 | B72: Manage IT-C strategy | C72: Manage IT risks and compliance › Manage IT compliance › Manage IT-C strategy | D72: MP | E72: Central area (Jan Müskens) | F72: Manage IT risks and compliance | G72: L3 | H72: In Arbeit | I72: 0.25 | J72: 45931 | K72: 46295 | L72: 261 | M72: In Arbeit | N72: Mueskens Jan (LHO) | O72: Monnier Murielle (LEC) | P72: Kreis Andreas (LLI) | Q72: =IF(AND(K72<>"",K72<Cockpit!$H$6,H72<>"Abgeschlossen"),1,0) -> 0 | R72: 0 | S72: =IF(AND(OR(Cockpit!$B$6="(Alle)",D72=Cockpit!$B$6),OR(Cockpit!$C$6="(Alle)",E72=Cockpit!$C$6),OR(Cockpit!$D$6="(Alle)",F72=Cockpit!$D$6),OR(Cockpit!$E$6="(Alle)",G72=Cockpit!$E$6),OR(Cockpit!$F$6="(Alle)",H72=Cockpit!$F$6),OR(Cockpit!$G$6="(Alle)",O72=Cockpit!$G$6)),1,0) -> 1 | T72: =IF(S72=1,SUM($S$2:S72),"") -> 71
A73: 72 | B73: Manage and control IT financials | C73: Manage and control IT financials | D73: MP | E73: IT planning and steering | F73: Manage and control IT financials | G73: L1 | H73: In Arbeit | I73: 0.5 | J73: 45945 | K73: 46234 | L73: 208 | M73: In Arbeit | N73: Frank Nicole (LIS) | O73: Moser Mario (LIS-LAH) | P73: Hynek Tobias (LIS), Kreis Andreas (LLI) | Q73: =IF(AND(K73<>"",K73<Cockpit!$H$6,H73<>"Abgeschlossen"),1,0) -> 1 | R73: 0 | S73: =IF(AND(OR(Cockpit!$B$6="(Alle)",D73=Cockpit!$B$6),OR(Cockpit!$C$6="(Alle)",E73=Cockpit!$C$6),OR(Cockpit!$D$6="(Alle)",F73=Cockpit!$D$6),OR(Cockpit!$E$6="(Alle)",G73=Cockpit!$E$6),OR(Cockpit!$F$6="(Alle)",H73=Cockpit!$F$6),OR(Cockpit!$G$6="(Alle)",O73=Cockpit!$G$6)),1,0) -> 1 | T73: =IF(S73=1,SUM($S$2:S73),"") -> 72
A74: 73 | B74: Manage finance and accounting | C74: Manage and control IT financials › Manage finance and accounting | D74: MP | E74: IT planning and steering | F74: Manage and control IT financials | G74: L2 | H74: In Arbeit | I74: 0.5 | J74: 45945 | M74: Ohne Angabe | N74: Frank Nicole (LIS) | O74: Mielenz Thomas (LMT) | P74: Hynek Tobias (LIS), Kreis Andreas (LLI) | Q74: =IF(AND(K74<>"",K74<Cockpit!$H$6,H74<>"Abgeschlossen"),1,0) -> 0 | R74: 0 | S74: =IF(AND(OR(Cockpit!$B$6="(Alle)",D74=Cockpit!$B$6),OR(Cockpit!$C$6="(Alle)",E74=Cockpit!$C$6),OR(Cockpit!$D$6="(Alle)",F74=Cockpit!$D$6),OR(Cockpit!$E$6="(Alle)",G74=Cockpit!$E$6),OR(Cockpit!$F$6="(Alle)",H74=Cockpit!$F$6),OR(Cockpit!$G$6="(Alle)",O74=Cockpit!$G$6)),1,0) -> 1 | T74: =IF(S74=1,SUM($S$2:S74),"") -> 73
A75: 74 | B75: Model and allocate IT costs | C75: Manage and control IT financials › Model and allocate IT costs | D75: MP | E75: IT planning and steering | F75: Manage and control IT financials | G75: L2 | H75: In Arbeit | I75: 0.5 | J75: 45945 | M75: Ohne Angabe | N75: Frank Nicole (LIS) | O75: Moser Mario (LIS-LAH) | P75: Hynek Tobias (LIS), Kreis Andreas (LLI) | Q75: =IF(AND(K75<>"",K75<Cockpit!$H$6,H75<>"Abgeschlossen"),1,0) -> 0 | R75: 0 | S75: =IF(AND(OR(Cockpit!$B$6="(Alle)",D75=Cockpit!$B$6),OR(Cockpit!$C$6="(Alle)",E75=Cockpit!$C$6),OR(Cockpit!$D$6="(Alle)",F75=Cockpit!$D$6),OR(Cockpit!$E$6="(Alle)",G75=Cockpit!$E$6),OR(Cockpit!$F$6="(Alle)",H75=Cockpit!$F$6),OR(Cockpit!$G$6="(Alle)",O75=Cockpit!$G$6)),1,0) -> 1 | T75: =IF(S75=1,SUM($S$2:S75),"") -> 74
A76: 75 | B76: Monitor to delegate | C76: Manage IT risks and compliance › Manage IT compliance › Monitor to delegate | D76: MP | E76: Central area (Jan Müskens) | F76: Manage IT risks and compliance | G76: L3 | H76: In Arbeit | I76: 0.25 | J76: 45931 | K76: 46295 | L76: 261 | M76: In Arbeit | N76: Mueskens Jan (LHO) | O76: Monnier Murielle (LEC) | P76: – | Q76: =IF(AND(K76<>"",K76<Cockpit!$H$6,H76<>"Abgeschlossen"),1,0) -> 0 | R76: 0 | S76: =IF(AND(OR(Cockpit!$B$6="(Alle)",D76=Cockpit!$B$6),OR(Cockpit!$C$6="(Alle)",E76=Cockpit!$C$6),OR(Cockpit!$D$6="(Alle)",F76=Cockpit!$D$6),OR(Cockpit!$E$6="(Alle)",G76=Cockpit!$E$6),OR(Cockpit!$F$6="(Alle)",H76=Cockpit!$F$6),OR(Cockpit!$G$6="(Alle)",O76=Cockpit!$G$6)),1,0) -> 1 | T76: =IF(S76=1,SUM($S$2:S76),"") -> 75
A77: 76 | B77: Onboard new IT employee and manager | C77: Provide and develop IT workforce › Perform onboarding › Onboard new IT employee and manager | D77: SP | E77: HR initiatives for IT | F77: Provide and develop IT workforce | G77: L3 | H77: In Arbeit | I77: 0.5 | J77: 45946 | K77: 46142 | L77: 141 | M77: In Arbeit | N77: – | O77: Mielenz Thomas (LMT) | P77: Chen Leilei (LIS-BPMO), Hynek Tobias (LIS) | Q77: =IF(AND(K77<>"",K77<Cockpit!$H$6,H77<>"Abgeschlossen"),1,0) -> 1 | R77: 0 | S77: =IF(AND(OR(Cockpit!$B$6="(Alle)",D77=Cockpit!$B$6),OR(Cockpit!$C$6="(Alle)",E77=Cockpit!$C$6),OR(Cockpit!$D$6="(Alle)",F77=Cockpit!$D$6),OR(Cockpit!$E$6="(Alle)",G77=Cockpit!$E$6),OR(Cockpit!$F$6="(Alle)",H77=Cockpit!$F$6),OR(Cockpit!$G$6="(Alle)",O77=Cockpit!$G$6)),1,0) -> 1 | T77: =IF(S77=1,SUM($S$2:S77),"") -> 76
A78: 77 | B78: Perform SaaS Security Assessment | C78: Ensure Information security › Perform SaaS Security Assessment | D78: SP | E78: Information security | F78: Ensure Information security | G78: L2 | H78: In Arbeit | I78: 0.5 | J78: 45949 | K78: 45991 | M78: In Arbeit | N78: Hefele Michael (LIN-LIS) | O78: Reiner Heiko (HAU-ITSA) | P78: Hoermann Patrick (LLI), Rollinger Alexander (LIS) | Q78: =IF(AND(K78<>"",K78<Cockpit!$H$6,H78<>"Abgeschlossen"),1,0) -> 1 | R78: 0 | S78: =IF(AND(OR(Cockpit!$B$6="(Alle)",D78=Cockpit!$B$6),OR(Cockpit!$C$6="(Alle)",E78=Cockpit!$C$6),OR(Cockpit!$D$6="(Alle)",F78=Cockpit!$D$6),OR(Cockpit!$E$6="(Alle)",G78=Cockpit!$E$6),OR(Cockpit!$F$6="(Alle)",H78=Cockpit!$F$6),OR(Cockpit!$G$6="(Alle)",O78=Cockpit!$G$6)),1,0) -> 1 | T78: =IF(S78=1,SUM($S$2:S78),"") -> 77
A79: 78 | B79: Perform onboarding | C79: Provide and develop IT workforce › Perform onboarding | D79: SP | E79: HR initiatives for IT | F79: Provide and develop IT workforce | G79: L2 | H79: In Arbeit | I79: 0.33 | J79: 45946 | K79: 46142 | L79: 141 | M79: In Arbeit | N79: – | O79: Mielenz Thomas (LMT) | P79: Chen Leilei (LIS-BPMO), Hynek Tobias (LIS) | Q79: =IF(AND(K79<>"",K79<Cockpit!$H$6,H79<>"Abgeschlossen"),1,0) -> 1 | R79: 0 | S79: =IF(AND(OR(Cockpit!$B$6="(Alle)",D79=Cockpit!$B$6),OR(Cockpit!$C$6="(Alle)",E79=Cockpit!$C$6),OR(Cockpit!$D$6="(Alle)",F79=Cockpit!$D$6),OR(Cockpit!$E$6="(Alle)",G79=Cockpit!$E$6),OR(Cockpit!$F$6="(Alle)",H79=Cockpit!$F$6),OR(Cockpit!$G$6="(Alle)",O79=Cockpit!$G$6)),1,0) -> 1 | T79: =IF(S79=1,SUM($S$2:S79),"") -> 78
A80: 79 | B80: Perform operational process management | C80: Manage IT processes and continuous improvement › Perform operational process management | D80: MP | E80: ITSM | F80: Manage IT processes and continuous improvement | G80: L2 | H80: In Arbeit | I80: 0.25 | J80: 45931 | K80: 46173 | L80: 173 | M80: In Arbeit | N80: Rollinger Alexander (LIS) | O80: Reiner Heiko (HAU-ITSA) | P80: Rollinger Alexander (LIS) | Q80: =IF(AND(K80<>"",K80<Cockpit!$H$6,H80<>"Abgeschlossen"),1,0) -> 1 | R80: 0 | S80: =IF(AND(OR(Cockpit!$B$6="(Alle)",D80=Cockpit!$B$6),OR(Cockpit!$C$6="(Alle)",E80=Cockpit!$C$6),OR(Cockpit!$D$6="(Alle)",F80=Cockpit!$D$6),OR(Cockpit!$E$6="(Alle)",G80=Cockpit!$E$6),OR(Cockpit!$F$6="(Alle)",H80=Cockpit!$F$6),OR(Cockpit!$G$6="(Alle)",O80=Cockpit!$G$6)),1,0) -> 1 | T80: =IF(S80=1,SUM($S$2:S80),"") -> 79
A81: 80 | B81: Perform, learn and grow | C81: Provide and develop IT workforce › Perform, learn and grow | D81: SP | E81: HR initiatives for IT | F81: Provide and develop IT workforce | G81: L2 | H81: In Arbeit | I81: 0.11 | J81: 45931 | K81: 46568 | L81: 456 | M81: Ohne Angabe | N81: Grabmair Melanie (LIS) | O81: Mielenz Thomas (LMT) | P81: Chen Leilei (LIS-BPMO), Hynek Tobias (LIS) | Q81: =IF(AND(K81<>"",K81<Cockpit!$H$6,H81<>"Abgeschlossen"),1,0) -> 0 | R81: 0 | S81: =IF(AND(OR(Cockpit!$B$6="(Alle)",D81=Cockpit!$B$6),OR(Cockpit!$C$6="(Alle)",E81=Cockpit!$C$6),OR(Cockpit!$D$6="(Alle)",F81=Cockpit!$D$6),OR(Cockpit!$E$6="(Alle)",G81=Cockpit!$E$6),OR(Cockpit!$F$6="(Alle)",H81=Cockpit!$F$6),OR(Cockpit!$G$6="(Alle)",O81=Cockpit!$G$6)),1,0) -> 1 | T81: =IF(S81=1,SUM($S$2:S81),"") -> 80
A82: 81 | B82: Plan process execution | C82: Manage IT processes and continuous improvement › Perform operational process management › Plan process execution | D82: MP | E82: ITSM | F82: Manage IT processes and continuous improvement | G82: L3 | H82: In Arbeit | I82: 0.25 | J82: 46034 | K82: 46173 | L82: 100 | M82: In Arbeit | N82: Rollinger Alexander (LIS) | O82: Reiner Heiko (HAU-ITSA) | P82: Rollinger Alexander (LIS) | Q82: =IF(AND(K82<>"",K82<Cockpit!$H$6,H82<>"Abgeschlossen"),1,0) -> 1 | R82: 0 | S82: =IF(AND(OR(Cockpit!$B$6="(Alle)",D82=Cockpit!$B$6),OR(Cockpit!$C$6="(Alle)",E82=Cockpit!$C$6),OR(Cockpit!$D$6="(Alle)",F82=Cockpit!$D$6),OR(Cockpit!$E$6="(Alle)",G82=Cockpit!$E$6),OR(Cockpit!$F$6="(Alle)",H82=Cockpit!$F$6),OR(Cockpit!$G$6="(Alle)",O82=Cockpit!$G$6)),1,0) -> 1 | T82: =IF(S82=1,SUM($S$2:S82),"") -> 81
A83: 82 | B83: Pre-board new IT employee and manager | C83: Provide and develop IT workforce › Perform onboarding › Pre-board new IT employee and manager | D83: SP | E83: HR initiatives for IT | F83: Provide and develop IT workforce | G83: L3 | H83: In Arbeit | I83: 0.25 | J83: 45946 | K83: 46142 | L83: 141 | M83: In Arbeit | N83: – | O83: Mielenz Thomas (LMT) | P83: Chen Leilei (LIS-BPMO), Hynek Tobias (LIS) | Q83: =IF(AND(K83<>"",K83<Cockpit!$H$6,H83<>"Abgeschlossen"),1,0) -> 1 | R83: 0 | S83: =IF(AND(OR(Cockpit!$B$6="(Alle)",D83=Cockpit!$B$6),OR(Cockpit!$C$6="(Alle)",E83=Cockpit!$C$6),OR(Cockpit!$D$6="(Alle)",F83=Cockpit!$D$6),OR(Cockpit!$E$6="(Alle)",G83=Cockpit!$E$6),OR(Cockpit!$F$6="(Alle)",H83=Cockpit!$F$6),OR(Cockpit!$G$6="(Alle)",O83=Cockpit!$G$6)),1,0) -> 1 | T83: =IF(S83=1,SUM($S$2:S83),"") -> 82
A84: 83 | B84: Provide and develop IT workforce | C84: Provide and develop IT workforce | D84: SP | E84: HR initiatives for IT | F84: Provide and develop IT workforce | G84: L1 | H84: In Arbeit | I84: 0.15 | J84: 45931 | K84: 46568 | L84: 456 | M84: Abgeschlossen | N84: Amelang Nicole (LIS) | O84: Rollinger Alexander (LIS) | P84: Chen Leilei (LIS-BPMO), Hynek Tobias (LIS) | Q84: =IF(AND(K84<>"",K84<Cockpit!$H$6,H84<>"Abgeschlossen"),1,0) -> 0 | R84: 0 | S84: =IF(AND(OR(Cockpit!$B$6="(Alle)",D84=Cockpit!$B$6),OR(Cockpit!$C$6="(Alle)",E84=Cockpit!$C$6),OR(Cockpit!$D$6="(Alle)",F84=Cockpit!$D$6),OR(Cockpit!$E$6="(Alle)",G84=Cockpit!$E$6),OR(Cockpit!$F$6="(Alle)",H84=Cockpit!$F$6),OR(Cockpit!$G$6="(Alle)",O84=Cockpit!$G$6)),1,0) -> 1 | T84: =IF(S84=1,SUM($S$2:S84),"") -> 83
A85: 84 | B85: Report actual IT costs | C85: Manage and control IT financials › Manage IT costs › Report actual IT costs | D85: MP | E85: IT planning and steering | F85: Manage and control IT financials | G85: L3 | H85: In Arbeit | I85: 0.5 | J85: 45945 | M85: Ohne Angabe | N85: Frank Nicole (LIS) | O85: Moser Mario (LIS-LAH) | P85: Hynek Tobias (LIS), Kreis Andreas (LLI) | Q85: =IF(AND(K85<>"",K85<Cockpit!$H$6,H85<>"Abgeschlossen"),1,0) -> 0 | R85: 0 | S85: =IF(AND(OR(Cockpit!$B$6="(Alle)",D85=Cockpit!$B$6),OR(Cockpit!$C$6="(Alle)",E85=Cockpit!$C$6),OR(Cockpit!$D$6="(Alle)",F85=Cockpit!$D$6),OR(Cockpit!$E$6="(Alle)",G85=Cockpit!$E$6),OR(Cockpit!$F$6="(Alle)",H85=Cockpit!$F$6),OR(Cockpit!$G$6="(Alle)",O85=Cockpit!$G$6)),1,0) -> 1 | T85: =IF(S85=1,SUM($S$2:S85),"") -> 84
A86: 85 | B86: Requirements to measures | C86: Manage IT risks and compliance › Manage IT compliance › Requirements to measures | D86: MP | E86: Central area (Jan Müskens) | F86: Manage IT risks and compliance | G86: L3 | H86: In Arbeit | I86: 0.25 | J86: 45931 | K86: 46295 | L86: 261 | M86: In Arbeit | N86: Mueskens Jan (LHO) | O86: Monnier Murielle (LEC) | P86: – | Q86: =IF(AND(K86<>"",K86<Cockpit!$H$6,H86<>"Abgeschlossen"),1,0) -> 0 | R86: 0 | S86: =IF(AND(OR(Cockpit!$B$6="(Alle)",D86=Cockpit!$B$6),OR(Cockpit!$C$6="(Alle)",E86=Cockpit!$C$6),OR(Cockpit!$D$6="(Alle)",F86=Cockpit!$D$6),OR(Cockpit!$E$6="(Alle)",G86=Cockpit!$E$6),OR(Cockpit!$F$6="(Alle)",H86=Cockpit!$F$6),OR(Cockpit!$G$6="(Alle)",O86=Cockpit!$G$6)),1,0) -> 1 | T86: =IF(S86=1,SUM($S$2:S86),"") -> 85
A87: 86 | B87: Review budget plan | C87: Manage and control IT financials › Create and maintain IT budgets › Review budget plan | D87: MP | E87: IT planning and steering | F87: Manage and control IT financials | G87: L3 | H87: In Arbeit | I87: 0.5 | J87: 45945 | M87: Ohne Angabe | N87: Frank Nicole (LIS) | O87: Mielenz Thomas (LMT) | P87: Hynek Tobias (LIS), Kreis Andreas (LLI) | Q87: =IF(AND(K87<>"",K87<Cockpit!$H$6,H87<>"Abgeschlossen"),1,0) -> 0 | R87: 0 | S87: =IF(AND(OR(Cockpit!$B$6="(Alle)",D87=Cockpit!$B$6),OR(Cockpit!$C$6="(Alle)",E87=Cockpit!$C$6),OR(Cockpit!$D$6="(Alle)",F87=Cockpit!$D$6),OR(Cockpit!$E$6="(Alle)",G87=Cockpit!$E$6),OR(Cockpit!$F$6="(Alle)",H87=Cockpit!$F$6),OR(Cockpit!$G$6="(Alle)",O87=Cockpit!$G$6)),1,0) -> 1 | T87: =IF(S87=1,SUM($S$2:S87),"") -> 86
A88: 87 | B88: Revise and optimize budget plan | C88: Manage and control IT financials › Create and maintain IT budgets › Revise and optimize budget plan | D88: MP | E88: IT planning and steering | F88: Manage and control IT financials | G88: L3 | H88: In Arbeit | I88: 0.5 | J88: 45945 | M88: Ohne Angabe | N88: Frank Nicole (LIS) | O88: Mielenz Thomas (LMT) | P88: Hynek Tobias (LIS), Kreis Andreas (LLI) | Q88: =IF(AND(K88<>"",K88<Cockpit!$H$6,H88<>"Abgeschlossen"),1,0) -> 0 | R88: 0 | S88: =IF(AND(OR(Cockpit!$B$6="(Alle)",D88=Cockpit!$B$6),OR(Cockpit!$C$6="(Alle)",E88=Cockpit!$C$6),OR(Cockpit!$D$6="(Alle)",F88=Cockpit!$D$6),OR(Cockpit!$E$6="(Alle)",G88=Cockpit!$E$6),OR(Cockpit!$F$6="(Alle)",H88=Cockpit!$F$6),OR(Cockpit!$G$6="(Alle)",O88=Cockpit!$G$6)),1,0) -> 1 | T88: =IF(S88=1,SUM($S$2:S88),"") -> 87
A89: 88 | B89: Test and validate IT service | C89: Build IT Service › Test and validate IT service | D89: CP | E89: ITSM | F89: Build IT Service | G89: L2 | H89: In Arbeit | I89: 0 | J89: 46146 | K89: 46234 | M89: In Arbeit | N89: Dalek Martin (LIS) | O89: Wiehe Alexander (COB) | P89: Kunz Christina (LIS-MHP) | Q89: =IF(AND(K89<>"",K89<Cockpit!$H$6,H89<>"Abgeschlossen"),1,0) -> 1 | R89: 0 | S89: =IF(AND(OR(Cockpit!$B$6="(Alle)",D89=Cockpit!$B$6),OR(Cockpit!$C$6="(Alle)",E89=Cockpit!$C$6),OR(Cockpit!$D$6="(Alle)",F89=Cockpit!$D$6),OR(Cockpit!$E$6="(Alle)",G89=Cockpit!$E$6),OR(Cockpit!$F$6="(Alle)",H89=Cockpit!$F$6),OR(Cockpit!$G$6="(Alle)",O89=Cockpit!$G$6)),1,0) -> 1 | T89: =IF(S89=1,SUM($S$2:S89),"") -> 88
A90: 89 | B90: Deliver IT service | C90: Deliver IT service | D90: CP | E90: ITSM | F90: Deliver IT service | G90: L1 | H90: Terminiert | I90: 0 | J90: 46113 | K90: 46190 | L90: 56 | M90: Ohne Angabe | N90: – | O90: Schnurrenberger Christoph (LIS-LIN) | P90: – | Q90: =IF(AND(K90<>"",K90<Cockpit!$H$6,H90<>"Abgeschlossen"),1,0) -> 1 | R90: 0 | S90: =IF(AND(OR(Cockpit!$B$6="(Alle)",D90=Cockpit!$B$6),OR(Cockpit!$C$6="(Alle)",E90=Cockpit!$C$6),OR(Cockpit!$D$6="(Alle)",F90=Cockpit!$D$6),OR(Cockpit!$E$6="(Alle)",G90=Cockpit!$E$6),OR(Cockpit!$F$6="(Alle)",H90=Cockpit!$F$6),OR(Cockpit!$G$6="(Alle)",O90=Cockpit!$G$6)),1,0) -> 1 | T90: =IF(S90=1,SUM($S$2:S90),"") -> 89
A91: 90 | B91: Manage HR4IT strategy, governane and framework | C91: Provide and develop IT workforce › Manage HR4IT strategy, governane and framework | D91: SP | E91: HR initiatives for IT | F91: Provide and develop IT workforce | G91: L2 | H91: Terminiert | I91: 0 | J91: 45931 | K91: 46387 | M91: Abgeschlossen | N91: Amelang Nicole (LIS) | O91: Rollinger Alexander (LIS) | P91: Chen Leilei (LIS-BPMO), Hynek Tobias (LIS) | Q91: =IF(AND(K91<>"",K91<Cockpit!$H$6,H91<>"Abgeschlossen"),1,0) -> 0 | R91: 0 | S91: =IF(AND(OR(Cockpit!$B$6="(Alle)",D91=Cockpit!$B$6),OR(Cockpit!$C$6="(Alle)",E91=Cockpit!$C$6),OR(Cockpit!$D$6="(Alle)",F91=Cockpit!$D$6),OR(Cockpit!$E$6="(Alle)",G91=Cockpit!$E$6),OR(Cockpit!$F$6="(Alle)",H91=Cockpit!$F$6),OR(Cockpit!$G$6="(Alle)",O91=Cockpit!$G$6)),1,0) -> 1 | T91: =IF(S91=1,SUM($S$2:S91),"") -> 90
A92: 91 | B92: Manage IT development programme | C92: Provide and develop IT workforce › Perform, learn and grow › Manage IT development programme | D92: SP | E92: HR initiatives for IT | F92: Provide and develop IT workforce | G92: L3 | H92: Terminiert | I92: 0 | J92: 45946 | K92: 45946 | L92: 0 | M92: Ohne Angabe | N92: Grabmair Melanie (LIS) | O92: Mielenz Thomas (LMT) | P92: Chen Leilei (LIS-BPMO), Hynek Tobias (LIS) | Q92: =IF(AND(K92<>"",K92<Cockpit!$H$6,H92<>"Abgeschlossen"),1,0) -> 1 | R92: 0 | S92: =IF(AND(OR(Cockpit!$B$6="(Alle)",D92=Cockpit!$B$6),OR(Cockpit!$C$6="(Alle)",E92=Cockpit!$C$6),OR(Cockpit!$D$6="(Alle)",F92=Cockpit!$D$6),OR(Cockpit!$E$6="(Alle)",G92=Cockpit!$E$6),OR(Cockpit!$F$6="(Alle)",H92=Cockpit!$F$6),OR(Cockpit!$G$6="(Alle)",O92=Cockpit!$G$6)),1,0) -> 1 | T92: =IF(S92=1,SUM($S$2:S92),"") -> 91
A93: 92 | B93: Manage IT risks | C93: Manage IT risks and compliance › Manage IT risks | D93: MP | E93: Central area (Jan Müskens) | F93: Manage IT risks and compliance | G93: L2 | H93: Terminiert | I93: 0 | J93: 45931 | K93: 46295 | L93: 261 | M93: Ohne Angabe | N93: – | O93: Monnier Murielle (LEC) | P93: – | Q93: =IF(AND(K93<>"",K93<Cockpit!$H$6,H93<>"Abgeschlossen"),1,0) -> 0 | R93: 0 | S93: =IF(AND(OR(Cockpit!$B$6="(Alle)",D93=Cockpit!$B$6),OR(Cockpit!$C$6="(Alle)",E93=Cockpit!$C$6),OR(Cockpit!$D$6="(Alle)",F93=Cockpit!$D$6),OR(Cockpit!$E$6="(Alle)",G93=Cockpit!$E$6),OR(Cockpit!$F$6="(Alle)",H93=Cockpit!$F$6),OR(Cockpit!$G$6="(Alle)",O93=Cockpit!$G$6)),1,0) -> 1 | T93: =IF(S93=1,SUM($S$2:S93),"") -> 92
A94: 93 | B94: Manage IT talent pool and identify potential | C94: Provide and develop IT workforce › Perform, learn and grow › Manage IT talent pool and identify potential | D94: SP | E94: HR initiatives for IT | F94: Provide and develop IT workforce | G94: L3 | H94: Terminiert | I94: 0 | J94: 45946 | K94: 45946 | L94: 0 | M94: Ohne Angabe | N94: Grabmair Melanie (LIS) | O94: Mielenz Thomas (LMT) | P94: Chen Leilei (LIS-BPMO), Hynek Tobias (LIS) | Q94: =IF(AND(K94<>"",K94<Cockpit!$H$6,H94<>"Abgeschlossen"),1,0) -> 1 | R94: 0 | S94: =IF(AND(OR(Cockpit!$B$6="(Alle)",D94=Cockpit!$B$6),OR(Cockpit!$C$6="(Alle)",E94=Cockpit!$C$6),OR(Cockpit!$D$6="(Alle)",F94=Cockpit!$D$6),OR(Cockpit!$E$6="(Alle)",G94=Cockpit!$E$6),OR(Cockpit!$F$6="(Alle)",H94=Cockpit!$F$6),OR(Cockpit!$G$6="(Alle)",O94=Cockpit!$G$6)),1,0) -> 1 | T94: =IF(S94=1,SUM($S$2:S94),"") -> 93
A95: 94 | B95: Monitor and report IT service level | C95: Run IT service › Monitor and report IT service performance › Monitor and report IT service level | D95: CP | E95: ITSM | F95: Run IT service | G95: L3 | H95: Terminiert | I95: 0 | J95: 46127 | K95: 46234 | L95: 0 | M95: Ohne Angabe | N95: Kuerschner Philipp (LIS) | O95: Sint Rachel (LBH) | P95: Schroeder Michael (LIS) | Q95: =IF(AND(K95<>"",K95<Cockpit!$H$6,H95<>"Abgeschlossen"),1,0) -> 1 | R95: 0 | S95: =IF(AND(OR(Cockpit!$B$6="(Alle)",D95=Cockpit!$B$6),OR(Cockpit!$C$6="(Alle)",E95=Cockpit!$C$6),OR(Cockpit!$D$6="(Alle)",F95=Cockpit!$D$6),OR(Cockpit!$E$6="(Alle)",G95=Cockpit!$E$6),OR(Cockpit!$F$6="(Alle)",H95=Cockpit!$F$6),OR(Cockpit!$G$6="(Alle)",O95=Cockpit!$G$6)),1,0) -> 1 | T95: =IF(S95=1,SUM($S$2:S95),"") -> 94
A96: 95 | B96: Monitor and report IT service performance | C96: Run IT service › Monitor and report IT service performance | D96: CP | E96: ITSM | F96: Run IT service | G96: L2 | H96: Terminiert | I96: 0 | J96: 46127 | M96: Ohne Angabe | N96: Kuerschner Philipp (LIS) | O96: Sint Rachel (LBH) | P96: Schroeder Michael (LIS) | Q96: =IF(AND(K96<>"",K96<Cockpit!$H$6,H96<>"Abgeschlossen"),1,0) -> 0 | R96: 0 | S96: =IF(AND(OR(Cockpit!$B$6="(Alle)",D96=Cockpit!$B$6),OR(Cockpit!$C$6="(Alle)",E96=Cockpit!$C$6),OR(Cockpit!$D$6="(Alle)",F96=Cockpit!$D$6),OR(Cockpit!$E$6="(Alle)",G96=Cockpit!$E$6),OR(Cockpit!$F$6="(Alle)",H96=Cockpit!$F$6),OR(Cockpit!$G$6="(Alle)",O96=Cockpit!$G$6)),1,0) -> 1 | T96: =IF(S96=1,SUM($S$2:S96),"") -> 95
A97: 96 | B97: Ensure IT service continuity | C97: Run IT service › Ensure IT service continuity | D97: CP | E97: ITSM | F97: Run IT service | G97: L2 | H97: Nicht geplant | I97: 0 | M97: Ohne Angabe | N97: – | O97: Sint Rachel (LBH) | P97: Schroeder Michael (LIS), Boehme Matthias (LIS-BPMO) | Q97: =IF(AND(K97<>"",K97<Cockpit!$H$6,H97<>"Abgeschlossen"),1,0) -> 0 | R97: 0 | S97: =IF(AND(OR(Cockpit!$B$6="(Alle)",D97=Cockpit!$B$6),OR(Cockpit!$C$6="(Alle)",E97=Cockpit!$C$6),OR(Cockpit!$D$6="(Alle)",F97=Cockpit!$D$6),OR(Cockpit!$E$6="(Alle)",G97=Cockpit!$E$6),OR(Cockpit!$F$6="(Alle)",H97=Cockpit!$F$6),OR(Cockpit!$G$6="(Alle)",O97=Cockpit!$G$6)),1,0) -> 1 | T97: =IF(S97=1,SUM($S$2:S97),"") -> 96
A98: 97 | B98: Maintain IT asset database | C98: Run IT service › Operate and maintain IT service › Maintain IT asset database | D98: CP | E98: ITSM | F98: Run IT service | G98: L3 | H98: Nicht geplant | I98: 0 | M98: Ohne Angabe | N98: – | O98: Sint Rachel (LBH) | P98: Schroeder Michael (LIS) | Q98: =IF(AND(K98<>"",K98<Cockpit!$H$6,H98<>"Abgeschlossen"),1,0) -> 0 | R98: 0 | S98: =IF(AND(OR(Cockpit!$B$6="(Alle)",D98=Cockpit!$B$6),OR(Cockpit!$C$6="(Alle)",E98=Cockpit!$C$6),OR(Cockpit!$D$6="(Alle)",F98=Cockpit!$D$6),OR(Cockpit!$E$6="(Alle)",G98=Cockpit!$E$6),OR(Cockpit!$F$6="(Alle)",H98=Cockpit!$F$6),OR(Cockpit!$G$6="(Alle)",O98=Cockpit!$G$6)),1,0) -> 1 | T98: =IF(S98=1,SUM($S$2:S98),"") -> 97
A99: 98 | B99: Maintain standard change catalogue for IT service | C99: Run IT service › Operate and maintain IT service › Maintain standard change catalogue for IT service | D99: CP | E99: ITSM | F99: Run IT service | G99: L3 | H99: Nicht geplant | I99: 0 | M99: Ohne Angabe | N99: – | O99: Sint Rachel (LBH) | P99: Schroeder Michael (LIS) | Q99: =IF(AND(K99<>"",K99<Cockpit!$H$6,H99<>"Abgeschlossen"),1,0) -> 0 | R99: 0 | S99: =IF(AND(OR(Cockpit!$B$6="(Alle)",D99=Cockpit!$B$6),OR(Cockpit!$C$6="(Alle)",E99=Cockpit!$C$6),OR(Cockpit!$D$6="(Alle)",F99=Cockpit!$D$6),OR(Cockpit!$E$6="(Alle)",G99=Cockpit!$E$6),OR(Cockpit!$F$6="(Alle)",H99=Cockpit!$F$6),OR(Cockpit!$G$6="(Alle)",O99=Cockpit!$G$6)),1,0) -> 1 | T99: =IF(S99=1,SUM($S$2:S99),"") -> 98
A100: 99 | B100: Manage IT service capacity | C100: Run IT service › Ensure IT service continuity › Manage IT service capacity | D100: CP | E100: ITSM | F100: Run IT service | G100: L3 | H100: Nicht geplant | I100: 0 | M100: Ohne Angabe | N100: – | O100: Sint Rachel (LBH) | P100: Schroeder Michael (LIS), Boehme Matthias (LIS-BPMO) | Q100: =IF(AND(K100<>"",K100<Cockpit!$H$6,H100<>"Abgeschlossen"),1,0) -> 0 | R100: 0 | S100: =IF(AND(OR(Cockpit!$B$6="(Alle)",D100=Cockpit!$B$6),OR(Cockpit!$C$6="(Alle)",E100=Cockpit!$C$6),OR(Cockpit!$D$6="(Alle)",F100=Cockpit!$D$6),OR(Cockpit!$E$6="(Alle)",G100=Cockpit!$E$6),OR(Cockpit!$F$6="(Alle)",H100=Cockpit!$F$6),OR(Cockpit!$G$6="(Alle)",O100=Cockpit!$G$6)),1,0) -> 1 | T100: =IF(S100=1,SUM($S$2:S100),"") -> 99
A101: 100 | B101: Manage IT service desk | C101: Run IT service › Provide IT service support › Manage IT service desk | D101: CP | E101: ITSM | F101: Run IT service | G101: L3 | H101: Nicht geplant | I101: 0 | M101: Ohne Angabe | N101: – | O101: Sint Rachel (LBH) | P101: Schroeder Michael (LIS) | Q101: =IF(AND(K101<>"",K101<Cockpit!$H$6,H101<>"Abgeschlossen"),1,0) -> 0 | R101: 0 | S101: =IF(AND(OR(Cockpit!$B$6="(Alle)",D101=Cockpit!$B$6),OR(Cockpit!$C$6="(Alle)",E101=Cockpit!$C$6),OR(Cockpit!$D$6="(Alle)",F101=Cockpit!$D$6),OR(Cockpit!$E$6="(Alle)",G101=Cockpit!$E$6),OR(Cockpit!$F$6="(Alle)",H101=Cockpit!$F$6),OR(Cockpit!$G$6="(Alle)",O101=Cockpit!$G$6)),1,0) -> 1 | T101: =IF(S101=1,SUM($S$2:S101),"") -> 100
A102: 101 | B102: Manage a common approach to contiual improvement | C102: Manage IT processes and continuous improvement › Manage continuous improvement › Manage a common approach to contiual improvement | D102: MP | E102: ITSM | F102: Manage IT processes and continuous improvement | G102: L3 | H102: Nicht geplant | I102: 0 | K102: 45946 | M102: Ohne Angabe | N102: Kuerschner Philipp (LIS) | O102: Reiner Heiko (HAU-ITSA) | P102: Boehme Matthias (LIS-BPMO), Rollinger Alexander (LIS) | Q102: =IF(AND(K102<>"",K102<Cockpit!$H$6,H102<>"Abgeschlossen"),1,0) -> 1 | R102: 0 | S102: =IF(AND(OR(Cockpit!$B$6="(Alle)",D102=Cockpit!$B$6),OR(Cockpit!$C$6="(Alle)",E102=Cockpit!$C$6),OR(Cockpit!$D$6="(Alle)",F102=Cockpit!$D$6),OR(Cockpit!$E$6="(Alle)",G102=Cockpit!$E$6),OR(Cockpit!$F$6="(Alle)",H102=Cockpit!$F$6),OR(Cockpit!$G$6="(Alle)",O102=Cockpit!$G$6)),1,0) -> 1 | T102: =IF(S102=1,SUM($S$2:S102),"") -> 101
A103: 102 | B103: Manage continual improvement initiative | C103: Manage IT processes and continuous improvement › Manage continuous improvement › Manage continual improvement initiative | D103: MP | E103: ITSM | F103: Manage IT processes and continuous improvement | G103: L3 | H103: Nicht geplant | I103: 0 | K103: 45946 | M103: Ohne Angabe | N103: Kuerschner Philipp (LIS) | O103: Reiner Heiko (HAU-ITSA) | P103: Boehme Matthias (LIS-BPMO), Rollinger Alexander (LIS) | Q103: =IF(AND(K103<>"",K103<Cockpit!$H$6,H103<>"Abgeschlossen"),1,0) -> 1 | R103: 0 | S103: =IF(AND(OR(Cockpit!$B$6="(Alle)",D103=Cockpit!$B$6),OR(Cockpit!$C$6="(Alle)",E103=Cockpit!$C$6),OR(Cockpit!$D$6="(Alle)",F103=Cockpit!$D$6),OR(Cockpit!$E$6="(Alle)",G103=Cockpit!$E$6),OR(Cockpit!$F$6="(Alle)",H103=Cockpit!$F$6),OR(Cockpit!$G$6="(Alle)",O103=Cockpit!$G$6)),1,0) -> 1 | T103: =IF(S103=1,SUM($S$2:S103),"") -> 102
A104: 103 | B104: Monitor IT service risk and compliance | C104: Run IT service › Monitor and report IT service performance › Monitor IT service risk and compliance | D104: CP | E104: ITSM | F104: Run IT service | G104: L3 | H104: Nicht geplant | I104: 0 | M104: Ohne Angabe | N104: Kuerschner Philipp (LIS) | O104: Sint Rachel (LBH) | P104: Schroeder Michael (LIS) | Q104: =IF(AND(K104<>"",K104<Cockpit!$H$6,H104<>"Abgeschlossen"),1,0) -> 0 | R104: 0 | S104: =IF(AND(OR(Cockpit!$B$6="(Alle)",D104=Cockpit!$B$6),OR(Cockpit!$C$6="(Alle)",E104=Cockpit!$C$6),OR(Cockpit!$D$6="(Alle)",F104=Cockpit!$D$6),OR(Cockpit!$E$6="(Alle)",G104=Cockpit!$E$6),OR(Cockpit!$F$6="(Alle)",H104=Cockpit!$F$6),OR(Cockpit!$G$6="(Alle)",O104=Cockpit!$G$6)),1,0) -> 1 | T104: =IF(S104=1,SUM($S$2:S104),"") -> 103
A105: 104 | B105: Monitor and analyse events | C105: Run IT service › Monitor and report IT service performance › Monitor and analyse events | D105: CP | E105: ITSM | F105: Run IT service | G105: L3 | H105: Nicht geplant | I105: 0 | M105: Ohne Angabe | N105: Kuerschner Philipp (LIS) | O105: Sint Rachel (LBH) | P105: Schroeder Michael (LIS) | Q105: =IF(AND(K105<>"",K105<Cockpit!$H$6,H105<>"Abgeschlossen"),1,0) -> 0 | R105: 0 | S105: =IF(AND(OR(Cockpit!$B$6="(Alle)",D105=Cockpit!$B$6),OR(Cockpit!$C$6="(Alle)",E105=Cockpit!$C$6),OR(Cockpit!$D$6="(Alle)",F105=Cockpit!$D$6),OR(Cockpit!$E$6="(Alle)",G105=Cockpit!$E$6),OR(Cockpit!$F$6="(Alle)",H105=Cockpit!$F$6),OR(Cockpit!$G$6="(Alle)",O105=Cockpit!$G$6)),1,0) -> 1 | T105: =IF(S105=1,SUM($S$2:S105),"") -> 104
A106: 105 | B106: Monitor and report IT service financials | C106: Run IT service › Monitor and report IT service performance › Monitor and report IT service financials | D106: CP | E106: ITSM | F106: Run IT service | G106: L3 | H106: Nicht geplant | I106: 0 | M106: Ohne Angabe | N106: Kuerschner Philipp (LIS) | O106: Sint Rachel (LBH) | P106: Schroeder Michael (LIS) | Q106: =IF(AND(K106<>"",K106<Cockpit!$H$6,H106<>"Abgeschlossen"),1,0) -> 0 | R106: 0 | S106: =IF(AND(OR(Cockpit!$B$6="(Alle)",D106=Cockpit!$B$6),OR(Cockpit!$C$6="(Alle)",E106=Cockpit!$C$6),OR(Cockpit!$D$6="(Alle)",F106=Cockpit!$D$6),OR(Cockpit!$E$6="(Alle)",G106=Cockpit!$E$6),OR(Cockpit!$F$6="(Alle)",H106=Cockpit!$F$6),OR(Cockpit!$G$6="(Alle)",O106=Cockpit!$G$6)),1,0) -> 1 | T106: =IF(S106=1,SUM($S$2:S106),"") -> 105
A107: 106 | B107: Monitor user experience | C107: Run IT service › Monitor and report IT service performance › Monitor user experience | D107: CP | E107: ITSM | F107: Run IT service | G107: L3 | H107: Nicht geplant | I107: 0 | M107: Ohne Angabe | N107: Kuerschner Philipp (LIS) | O107: Sint Rachel (LBH) | P107: Schroeder Michael (LIS) | Q107: =IF(AND(K107<>"",K107<Cockpit!$H$6,H107<>"Abgeschlossen"),1,0) -> 0 | R107: 0 | S107: =IF(AND(OR(Cockpit!$B$6="(Alle)",D107=Cockpit!$B$6),OR(Cockpit!$C$6="(Alle)",E107=Cockpit!$C$6),OR(Cockpit!$D$6="(Alle)",F107=Cockpit!$D$6),OR(Cockpit!$E$6="(Alle)",G107=Cockpit!$E$6),OR(Cockpit!$F$6="(Alle)",H107=Cockpit!$F$6),OR(Cockpit!$G$6="(Alle)",O107=Cockpit!$G$6)),1,0) -> 1 | T107: =IF(S107=1,SUM($S$2:S107),"") -> 106
A108: 107 | B108: Review and maintain IT service continuity plan | C108: Run IT service › Ensure IT service continuity › Review and maintain IT service continuity plan | D108: CP | E108: ITSM | F108: Run IT service | G108: L3 | H108: Nicht geplant | I108: 0 | M108: Ohne Angabe | N108: – | O108: Sint Rachel (LBH) | P108: Schroeder Michael (LIS), Boehme Matthias (LIS-BPMO) | Q108: =IF(AND(K108<>"",K108<Cockpit!$H$6,H108<>"Abgeschlossen"),1,0) -> 0 | R108: 0 | S108: =IF(AND(OR(Cockpit!$B$6="(Alle)",D108=Cockpit!$B$6),OR(Cockpit!$C$6="(Alle)",E108=Cockpit!$C$6),OR(Cockpit!$D$6="(Alle)",F108=Cockpit!$D$6),OR(Cockpit!$E$6="(Alle)",G108=Cockpit!$E$6),OR(Cockpit!$F$6="(Alle)",H108=Cockpit!$F$6),OR(Cockpit!$G$6="(Alle)",O108=Cockpit!$G$6)),1,0) -> 1 | T108: =IF(S108=1,SUM($S$2:S108),"") -> 107
A109: 108 | B109: Analyse process | C109: Manage IT processes and continuous improvement › Perform operational process management › Analyse process | D109: MP | E109: ITSM | F109: Manage IT processes and continuous improvement | G109: L3 | H109: Abgeschlossen | I109: 1 | J109: 45931 | K109: 45931 | L109: 1 | M109: Abgeschlossen | N109: Rollinger Alexander (LIS) | O109: Reiner Heiko (HAU-ITSA) | P109: Hoermann Patrick (LLI) | Q109: =IF(AND(K109<>"",K109<Cockpit!$H$6,H109<>"Abgeschlossen"),1,0) -> 0 | R109: 0 | S109: =IF(AND(OR(Cockpit!$B$6="(Alle)",D109=Cockpit!$B$6),OR(Cockpit!$C$6="(Alle)",E109=Cockpit!$C$6),OR(Cockpit!$D$6="(Alle)",F109=Cockpit!$D$6),OR(Cockpit!$E$6="(Alle)",G109=Cockpit!$E$6),OR(Cockpit!$F$6="(Alle)",H109=Cockpit!$F$6),OR(Cockpit!$G$6="(Alle)",O109=Cockpit!$G$6)),1,0) -> 1 | T109: =IF(S109=1,SUM($S$2:S109),"") -> 108
A110: 109 | B110: Assign personnel resources to IT project | C110: Manage IT project › Assign personnel resources to IT project | D110: SP | E110: IT project management | F110: Manage IT project | G110: L2 | H110: Abgeschlossen | I110: 1 | J110: 45852 | K110: 46001 | L110: 1 | M110: Abgeschlossen | N110: Mühlbacher Christian (LIS) | O110: Rollinger Alexander (LIS) | P110: Frank Maren (LIS) | Q110: =IF(AND(K110<>"",K110<Cockpit!$H$6,H110<>"Abgeschlossen"),1,0) -> 0 | R110: 1 | S110: =IF(AND(OR(Cockpit!$B$6="(Alle)",D110=Cockpit!$B$6),OR(Cockpit!$C$6="(Alle)",E110=Cockpit!$C$6),OR(Cockpit!$D$6="(Alle)",F110=Cockpit!$D$6),OR(Cockpit!$E$6="(Alle)",G110=Cockpit!$E$6),OR(Cockpit!$F$6="(Alle)",H110=Cockpit!$F$6),OR(Cockpit!$G$6="(Alle)",O110=Cockpit!$G$6)),1,0) -> 1 | T110: =IF(S110=1,SUM($S$2:S110),"") -> 109
...

Sheet Phasen
A1: Nr | B1: Prozess | C1: Gruppe | D1: Phase | E1: Status | F1: Start | G1: Ende | H1: Dauer (T) | I1: Treffer
A2: 1 | B2: Analyse architecture impact | C2: CP | D2: Elaboration | E2: Abgeschlossen | F2: 45870 | G2: 45945 | H2: 54 | I2: =INDEX(Prozesse!$S$2:$S$125,MATCH(A2,Prozesse!$A$2:$A$125,0)) -> 1
A3: 1 | B3: Analyse architecture impact | C3: CP | D3: Implementation LIS | E3: Ohne Angabe | F3: 46327 | G3: 46081 | H3: 0 | I3: =INDEX(Prozesse!$S$2:$S$125,MATCH(A3,Prozesse!$A$2:$A$125,0)) -> 1
A4: 1 | B4: Analyse architecture impact | C4: CP | D4: Implementation LUS | E4: Ohne Angabe | I4: =INDEX(Prozesse!$S$2:$S$125,MATCH(A4,Prozesse!$A$2:$A$125,0)) -> 1
A5: 1 | B5: Analyse architecture impact | C5: CP | D5: Implementation COT | E5: Verzögert | F5: 45946 | G5: 46142 | H5: 141 | I5: =INDEX(Prozesse!$S$2:$S$125,MATCH(A5,Prozesse!$A$2:$A$125,0)) -> 1
A6: 2 | B6: Approve IT demand | C6: CP | D6: Elaboration | E6: Abgeschlossen | F6: 45870 | G6: 45870 | H6: 1 | I6: =INDEX(Prozesse!$S$2:$S$125,MATCH(A6,Prozesse!$A$2:$A$125,0)) -> 1
A7: 2 | B7: Approve IT demand | C7: CP | D7: Implementation LIS | E7: Verzögert | F7: 45962 | G7: 46081 | H7: 85 | I7: =INDEX(Prozesse!$S$2:$S$125,MATCH(A7,Prozesse!$A$2:$A$125,0)) -> 1
A8: 2 | B8: Approve IT demand | C8: CP | D8: Implementation LUS | E8: Ohne Angabe | I8: =INDEX(Prozesse!$S$2:$S$125,MATCH(A8,Prozesse!$A$2:$A$125,0)) -> 1
A9: 2 | B9: Approve IT demand | C9: CP | D9: Implementation COT | E9: Verzögert | F9: 45964 | G9: 46112 | H9: 107 | I9: =INDEX(Prozesse!$S$2:$S$125,MATCH(A9,Prozesse!$A$2:$A$125,0)) -> 1
A10: 3 | B10: Attract and hire employees | C10: SP | D10: Elaboration | E10: In Arbeit | F10: 46029 | G10: 46097 | H10: 49 | I10: =INDEX(Prozesse!$S$2:$S$125,MATCH(A10,Prozesse!$A$2:$A$125,0)) -> 1
A11: 3 | B11: Attract and hire employees | C11: SP | D11: Implementation LIS | E11: Verzögert | F11: 46113 | G11: 46188 | H11: 54 | I11: =INDEX(Prozesse!$S$2:$S$125,MATCH(A11,Prozesse!$A$2:$A$125,0)) -> 1
A12: 3 | B12: Attract and hire employees | C12: SP | D12: Implementation LUS | E12: Ohne Angabe | I12: =INDEX(Prozesse!$S$2:$S$125,MATCH(A12,Prozesse!$A$2:$A$125,0)) -> 1
A13: 3 | B13: Attract and hire employees | C13: SP | D13: Implementation COT | E13: Verzögert | F13: 46113 | G13: 46188 | H13: 54 | I13: =INDEX(Prozesse!$S$2:$S$125,MATCH(A13,Prozesse!$A$2:$A$125,0)) -> 1
A14: 4 | B14: Define solution target architecture | C14: CP | D14: Elaboration | E14: In Arbeit | F14: 46058 | G14: 46188 | H14: 54 | I14: =INDEX(Prozesse!$S$2:$S$125,MATCH(A14,Prozesse!$A$2:$A$125,0)) -> 1
A15: 4 | B15: Define solution target architecture | C15: CP | D15: Implementation LIS | E15: Verzögert | I15: =INDEX(Prozesse!$S$2:$S$125,MATCH(A15,Prozesse!$A$2:$A$125,0)) -> 1
A16: 4 | B16: Define solution target architecture | C16: CP | D16: Implementation LUS | E16: Verzögert | I16: =INDEX(Prozesse!$S$2:$S$125,MATCH(A16,Prozesse!$A$2:$A$125,0)) -> 1
A17: 4 | B17: Define solution target architecture | C17: CP | D17: Implementation COT | E17: Verzögert | I17: =INDEX(Prozesse!$S$2:$S$125,MATCH(A17,Prozesse!$A$2:$A$125,0)) -> 1
A18: 5 | B18: Ensure performance and conformance of IT services | C18: SP | D18: Elaboration | E18: Verzögert | I18: =INDEX(Prozesse!$S$2:$S$125,MATCH(A18,Prozesse!$A$2:$A$125,0)) -> 1
A19: 5 | B19: Ensure performance and conformance of IT services | C19: SP | D19: Implementation LIS | E19: Ohne Angabe | I19: =INDEX(Prozesse!$S$2:$S$125,MATCH(A19,Prozesse!$A$2:$A$125,0)) -> 1
A20: 5 | B20: Ensure performance and conformance of IT services | C20: SP | D20: Implementation LUS | E20: Ohne Angabe | I20: =INDEX(Prozesse!$S$2:$S$125,MATCH(A20,Prozesse!$A$2:$A$125,0)) -> 1
A21: 5 | B21: Ensure performance and conformance of IT services | C21: SP | D21: Implementation COT | E21: Ohne Angabe | I21: =INDEX(Prozesse!$S$2:$S$125,MATCH(A21,Prozesse!$A$2:$A$125,0)) -> 1
A22: 6 | B22: Evaluate and qualify IT demand | C22: CP | D22: Elaboration | E22: Abgeschlossen | F22: 45870 | G22: 45870 | H22: 1 | I22: =INDEX(Prozesse!$S$2:$S$125,MATCH(A22,Prozesse!$A$2:$A$125,0)) -> 1
A23: 6 | B23: Evaluate and qualify IT demand | C23: CP | D23: Implementation LIS | E23: Verzögert | F23: 45962 | G23: 46081 | H23: 85 | I23: =INDEX(Prozesse!$S$2:$S$125,MATCH(A23,Prozesse!$A$2:$A$125,0)) -> 1
A24: 6 | B24: Evaluate and qualify IT demand | C24: CP | D24: Implementation LUS | E24: Ohne Angabe | I24: =INDEX(Prozesse!$S$2:$S$125,MATCH(A24,Prozesse!$A$2:$A$125,0)) -> 1
A25: 6 | B25: Evaluate and qualify IT demand | C25: CP | D25: Implementation COT | E25: Verzögert | F25: 45964 | G25: 46112 | H25: 107 | I25: =INDEX(Prozesse!$S$2:$S$125,MATCH(A25,Prozesse!$A$2:$A$125,0)) -> 1
A26: 7 | B26: Handle IT service order | C26: CP | D26: Elaboration | E26: Verzögert | F26: 46113 | G26: 46190 | H26: 56 | I26: =INDEX(Prozesse!$S$2:$S$125,MATCH(A26,Prozesse!$A$2:$A$125,0)) -> 1
A27: 7 | B27: Handle IT service order | C27: CP | D27: Implementation LIS | E27: Verzögert | F27: 46113 | G27: 46188 | H27: 54 | I27: =INDEX(Prozesse!$S$2:$S$125,MATCH(A27,Prozesse!$A$2:$A$125,0)) -> 1
A28: 7 | B28: Handle IT service order | C28: CP | D28: Implementation LUS | E28: Ohne Angabe | I28: =INDEX(Prozesse!$S$2:$S$125,MATCH(A28,Prozesse!$A$2:$A$125,0)) -> 1
A29: 7 | B29: Handle IT service order | C29: CP | D29: Implementation COT | E29: Ohne Angabe | I29: =INDEX(Prozesse!$S$2:$S$125,MATCH(A29,Prozesse!$A$2:$A$125,0)) -> 1
A30: 8 | B30: Implement and maintain IT job architecture | C30: SP | D30: Elaboration | E30: Verzögert | F30: 45946 | G30: 46173 | H30: 162 | I30: =INDEX(Prozesse!$S$2:$S$125,MATCH(A30,Prozesse!$A$2:$A$125,0)) -> 1
A31: 8 | B31: Implement and maintain IT job architecture | C31: SP | D31: Implementation LIS | E31: Ohne Angabe | I31: =INDEX(Prozesse!$S$2:$S$125,MATCH(A31,Prozesse!$A$2:$A$125,0)) -> 1
A32: 8 | B32: Implement and maintain IT job architecture | C32: SP | D32: Implementation LUS | E32: Ohne Angabe | I32: =INDEX(Prozesse!$S$2:$S$125,MATCH(A32,Prozesse!$A$2:$A$125,0)) -> 1
A33: 8 | B33: Implement and maintain IT job architecture | C33: SP | D33: Implementation COT | E33: Ohne Angabe | I33: =INDEX(Prozesse!$S$2:$S$125,MATCH(A33,Prozesse!$A$2:$A$125,0)) -> 1
A34: 9 | B34: Maintain IT glossary | C34: MP | D34: Elaboration | E34: Ohne Angabe | F34: 46029 | I34: =INDEX(Prozesse!$S$2:$S$125,MATCH(A34,Prozesse!$A$2:$A$125,0)) -> 1
A35: 9 | B35: Maintain IT glossary | C35: MP | D35: Implementation LIS | E35: Verzögert | F35: 46029 | G35: 46039 | H35: 7 | I35: =INDEX(Prozesse!$S$2:$S$125,MATCH(A35,Prozesse!$A$2:$A$125,0)) -> 1
A36: 9 | B36: Maintain IT glossary | C36: MP | D36: Implementation LUS | E36: Ohne Angabe | I36: =INDEX(Prozesse!$S$2:$S$125,MATCH(A36,Prozesse!$A$2:$A$125,0)) -> 1
A37: 9 | B37: Maintain IT glossary | C37: MP | D37: Implementation COT | E37: Ohne Angabe | F37: 46029 | I37: =INDEX(Prozesse!$S$2:$S$125,MATCH(A37,Prozesse!$A$2:$A$125,0)) -> 1
A38: 10 | B38: Manage HR4IT service demand | C38: SP | D38: Elaboration | E38: Verzögert | F38: 45931 | G38: 46173 | H38: 173 | I38: =INDEX(Prozesse!$S$2:$S$125,MATCH(A38,Prozesse!$A$2:$A$125,0)) -> 1
A39: 10 | B39: Manage HR4IT service demand | C39: SP | D39: Implementation LIS | E39: Terminiert | F39: 46174 | G39: 46203 | H39: 22 | I39: =INDEX(Prozesse!$S$2:$S$125,MATCH(A39,Prozesse!$A$2:$A$125,0)) -> 1
A40: 10 | B40: Manage HR4IT service demand | C40: SP | D40: Implementation LUS | E40: Terminiert | F40: 46174 | G40: 46203 | H40: 22 | I40: =INDEX(Prozesse!$S$2:$S$125,MATCH(A40,Prozesse!$A$2:$A$125,0)) -> 1
A41: 10 | B41: Manage HR4IT service demand | C41: SP | D41: Implementation COT | E41: Terminiert | F41: 46174 | G41: 46203 | H41: 22 | I41: =INDEX(Prozesse!$S$2:$S$125,MATCH(A41,Prozesse!$A$2:$A$125,0)) -> 1
A42: 11 | B42: Manage IT global orientation programme incl. job shadowing | C42: SP | D42: Elaboration | E42: Verzögert | F42: 46037 | G42: 46112 | H42: 54 | I42: =INDEX(Prozesse!$S$2:$S$125,MATCH(A42,Prozesse!$A$2:$A$125,0)) -> 1
A43: 11 | B43: Manage IT global orientation programme incl. job shadowing | C43: SP | D43: Implementation LIS | E43: Verzögert | F43: 46113 | G43: 46204 | H43: 66 | I43: =INDEX(Prozesse!$S$2:$S$125,MATCH(A43,Prozesse!$A$2:$A$125,0)) -> 1
A44: 11 | B44: Manage IT global orientation programme incl. job shadowing | C44: SP | D44: Implementation LUS | E44: Verzögert | F44: 46113 | G44: 46204 | H44: 66 | I44: =INDEX(Prozesse!$S$2:$S$125,MATCH(A44,Prozesse!$A$2:$A$125,0)) -> 1
A45: 11 | B45: Manage IT global orientation programme incl. job shadowing | C45: SP | D45: Implementation COT | E45: Verzögert | F45: 46113 | G45: 46204 | H45: 66 | I45: =INDEX(Prozesse!$S$2:$S$125,MATCH(A45,Prozesse!$A$2:$A$125,0)) -> 1
A46: 12 | B46: Manage IT knowledge | C46: SP | D46: Elaboration | E46: Abgeschlossen | F46: 46042 | G46: 46078 | H46: 27 | I46: =INDEX(Prozesse!$S$2:$S$125,MATCH(A46,Prozesse!$A$2:$A$125,0)) -> 1
A47: 12 | B47: Manage IT knowledge | C47: SP | D47: Implementation LIS | E47: Verzögert | F47: 46127 | G47: 46203 | H47: 55 | I47: =INDEX(Prozesse!$S$2:$S$125,MATCH(A47,Prozesse!$A$2:$A$125,0)) -> 1
A48: 12 | B48: Manage IT knowledge | C48: SP | D48: Implementation LUS | E48: Ohne Angabe | I48: =INDEX(Prozesse!$S$2:$S$125,MATCH(A48,Prozesse!$A$2:$A$125,0)) -> 1
A49: 12 | B49: Manage IT knowledge | C49: SP | D49: Implementation COT | E49: Ohne Angabe | I49: =INDEX(Prozesse!$S$2:$S$125,MATCH(A49,Prozesse!$A$2:$A$125,0)) -> 1
A50: 13 | B50: Manage IT project portfolio | C50: MP | D50: Elaboration | E50: Abgeschlossen | F50: 45971 | G50: 46001 | H50: 23 | I50: =INDEX(Prozesse!$S$2:$S$125,MATCH(A50,Prozesse!$A$2:$A$125,0)) -> 1
A51: 13 | B51: Manage IT project portfolio | C51: MP | D51: Implementation LIS | E51: Verzögert | F51: 46054 | G51: 46173 | H51: 85 | I51: =INDEX(Prozesse!$S$2:$S$125,MATCH(A51,Prozesse!$A$2:$A$125,0)) -> 1
A52: 13 | B52: Manage IT project portfolio | C52: MP | D52: Implementation LUS | E52: Ohne Angabe | I52: =INDEX(Prozesse!$S$2:$S$125,MATCH(A52,Prozesse!$A$2:$A$125,0)) -> 1
A53: 13 | B53: Manage IT project portfolio | C53: MP | D53: Implementation COT | E53: Ohne Angabe | I53: =INDEX(Prozesse!$S$2:$S$125,MATCH(A53,Prozesse!$A$2:$A$125,0)) -> 1
A54: 14 | B54: Manage IT service provision request | C54: CP | D54: Elaboration | E54: Verzögert | F54: 46113 | G54: 46190 | H54: 56 | I54: =INDEX(Prozesse!$S$2:$S$125,MATCH(A54,Prozesse!$A$2:$A$125,0)) -> 1
A55: 14 | B55: Manage IT service provision request | C55: CP | D55: Implementation LIS | E55: Verzögert | F55: 46113 | G55: 46188 | H55: 54 | I55: =INDEX(Prozesse!$S$2:$S$125,MATCH(A55,Prozesse!$A$2:$A$125,0)) -> 1
A56: 14 | B56: Manage IT service provision request | C56: CP | D56: Implementation LUS | E56: Ohne Angabe | I56: =INDEX(Prozesse!$S$2:$S$125,MATCH(A56,Prozesse!$A$2:$A$125,0)) -> 1
A57: 14 | B57: Manage IT service provision request | C57: CP | D57: Implementation COT | E57: Ohne Angabe | I57: =INDEX(Prozesse!$S$2:$S$125,MATCH(A57,Prozesse!$A$2:$A$125,0)) -> 1
A58: 15 | B58: Manage IT skills | C58: SP | D58: Elaboration | E58: Verzögert | F58: 46023 | G58: 46387 | H58: 261 | I58: =INDEX(Prozesse!$S$2:$S$125,MATCH(A58,Prozesse!$A$2:$A$125,0)) -> 1
A59: 15 | B59: Manage IT skills | C59: SP | D59: Implementation LIS | E59: Terminiert | F59: 46388 | G59: 46568 | H59: 129 | I59: =INDEX(Prozesse!$S$2:$S$125,MATCH(A59,Prozesse!$A$2:$A$125,0)) -> 1
A60: 15 | B60: Manage IT skills | C60: SP | D60: Implementation LUS | E60: Terminiert | F60: 46388 | G60: 46568 | H60: 129 | I60: =INDEX(Prozesse!$S$2:$S$125,MATCH(A60,Prozesse!$A$2:$A$125,0)) -> 1
A61: 15 | B61: Manage IT skills | C61: SP | D61: Implementation COT | E61: Terminiert | F61: 46388 | G61: 46568 | H61: 129 | I61: =INDEX(Prozesse!$S$2:$S$125,MATCH(A61,Prozesse!$A$2:$A$125,0)) -> 1
A62: 16 | B62: Manage IT stakeholder relationships | C62: MP | D62: Elaboration | E62: Verzögert | F62: 46113 | G62: 46188 | H62: 54 | I62: =INDEX(Prozesse!$S$2:$S$125,MATCH(A62,Prozesse!$A$2:$A$125,0)) -> 1
A63: 16 | B63: Manage IT stakeholder relationships | C63: MP | D63: Implementation LIS | E63: Terminiert | F63: 46310 | G63: 46379 | H63: 50 | I63: =INDEX(Prozesse!$S$2:$S$125,MATCH(A63,Prozesse!$A$2:$A$125,0)) -> 1
A64: 16 | B64: Manage IT stakeholder relationships | C64: MP | D64: Implementation LUS | E64: Ohne Angabe | I64: =INDEX(Prozesse!$S$2:$S$125,MATCH(A64,Prozesse!$A$2:$A$125,0)) -> 1
A65: 16 | B65: Manage IT stakeholder relationships | C65: MP | D65: Implementation COT | E65: Ohne Angabe | I65: =INDEX(Prozesse!$S$2:$S$125,MATCH(A65,Prozesse!$A$2:$A$125,0)) -> 1
A66: 17 | B66: Manage continuous improvement | C66: MP | D66: Elaboration | E66: Verzögert | F66: 45931 | G66: 46052 | H66: 88 | I66: =INDEX(Prozesse!$S$2:$S$125,MATCH(A66,Prozesse!$A$2:$A$125,0)) -> 1
A67: 17 | B67: Manage continuous improvement | C67: MP | D67: Implementation LIS | E67: Ohne Angabe | I67: =INDEX(Prozesse!$S$2:$S$125,MATCH(A67,Prozesse!$A$2:$A$125,0)) -> 1
A68: 17 | B68: Manage continuous improvement | C68: MP | D68: Implementation LUS | E68: Ohne Angabe | I68: =INDEX(Prozesse!$S$2:$S$125,MATCH(A68,Prozesse!$A$2:$A$125,0)) -> 1
A69: 17 | B69: Manage continuous improvement | C69: MP | D69: Implementation COT | E69: Ohne Angabe | I69: =INDEX(Prozesse!$S$2:$S$125,MATCH(A69,Prozesse!$A$2:$A$125,0)) -> 1
A70: 18 | B70: Manage enterprise architecture | C70: MP | D70: Elaboration | E70: Verzögert | F70: 46076 | G70: 46150 | I70: =INDEX(Prozesse!$S$2:$S$125,MATCH(A70,Prozesse!$A$2:$A$125,0)) -> 1
A71: 18 | B71: Manage enterprise architecture | C71: MP | D71: Implementation LIS | E71: Terminiert | F71: 46150 | G71: 46219 | I71: =INDEX(Prozesse!$S$2:$S$125,MATCH(A71,Prozesse!$A$2:$A$125,0)) -> 1
A72: 18 | B72: Manage enterprise architecture | C72: MP | D72: Implementation LUS | E72: Terminiert | F72: 46150 | G72: 46153 | I72: =INDEX(Prozesse!$S$2:$S$125,MATCH(A72,Prozesse!$A$2:$A$125,0)) -> 1
A73: 18 | B73: Manage enterprise architecture | C73: MP | D73: Implementation COT | E73: Terminiert | F73: 46150 | G73: 46153 | I73: =INDEX(Prozesse!$S$2:$S$125,MATCH(A73,Prozesse!$A$2:$A$125,0)) -> 1
A74: 19 | B74: Mapping and evaluate IT career level | C74: SP | D74: Elaboration | E74: Verzögert | F74: 46113 | G74: 46388 | H74: 198 | I74: =INDEX(Prozesse!$S$2:$S$125,MATCH(A74,Prozesse!$A$2:$A$125,0)) -> 1
A75: 19 | B75: Mapping and evaluate IT career level | C75: SP | D75: Implementation LIS | E75: Ohne Angabe | I75: =INDEX(Prozesse!$S$2:$S$125,MATCH(A75,Prozesse!$A$2:$A$125,0)) -> 1
A76: 19 | B76: Mapping and evaluate IT career level | C76: SP | D76: Implementation LUS | E76: Ohne Angabe | I76: =INDEX(Prozesse!$S$2:$S$125,MATCH(A76,Prozesse!$A$2:$A$125,0)) -> 1
A77: 19 | B77: Mapping and evaluate IT career level | C77: SP | D77: Implementation COT | E77: Ohne Angabe | I77: =INDEX(Prozesse!$S$2:$S$125,MATCH(A77,Prozesse!$A$2:$A$125,0)) -> 1
A78: 20 | B78: Operate and maintain IT service | C78: CP | D78: Elaboration | E78: Verzögert | F78: 46034 | G78: 46203 | H78: 122 | I78: =INDEX(Prozesse!$S$2:$S$125,MATCH(A78,Prozesse!$A$2:$A$125,0)) -> 1
A79: 20 | B79: Operate and maintain IT service | C79: CP | D79: Implementation LIS | E79: Verzögert | F79: 46127 | G79: 46203 | H79: 55 | I79: =INDEX(Prozesse!$S$2:$S$125,MATCH(A79,Prozesse!$A$2:$A$125,0)) -> 1
A80: 20 | B80: Operate and maintain IT service | C80: CP | D80: Implementation LUS | E80: Ohne Angabe | I80: =INDEX(Prozesse!$S$2:$S$125,MATCH(A80,Prozesse!$A$2:$A$125,0)) -> 1
A81: 20 | B81: Operate and maintain IT service | C81: CP | D81: Implementation COT | E81: Ohne Angabe | I81: =INDEX(Prozesse!$S$2:$S$125,MATCH(A81,Prozesse!$A$2:$A$125,0)) -> 1
A82: 21 | B82: Perform active sourcing | C82: SP | D82: Elaboration | E82: Verzögert | F82: 45931 | G82: 46142 | H82: 152 | I82: =INDEX(Prozesse!$S$2:$S$125,MATCH(A82,Prozesse!$A$2:$A$125,0)) -> 1
A83: 21 | B83: Perform active sourcing | C83: SP | D83: Implementation LIS | E83: Verzögert | F83: 46082 | G83: 46387 | H83: 219 | I83: =INDEX(Prozesse!$S$2:$S$125,MATCH(A83,Prozesse!$A$2:$A$125,0)) -> 1
A84: 21 | B84: Perform active sourcing | C84: SP | D84: Implementation LUS | E84: Ohne Angabe | I84: =INDEX(Prozesse!$S$2:$S$125,MATCH(A84,Prozesse!$A$2:$A$125,0)) -> 1
A85: 21 | B85: Perform active sourcing | C85: SP | D85: Implementation COT | E85: Ohne Angabe | I85: =INDEX(Prozesse!$S$2:$S$125,MATCH(A85,Prozesse!$A$2:$A$125,0)) -> 1
A86: 22 | B86: Perform initial assessment of customer need | C86: CP | D86: Elaboration | E86: Abgeschlossen | F86: 45870 | G86: 45870 | H86: 1 | I86: =INDEX(Prozesse!$S$2:$S$125,MATCH(A86,Prozesse!$A$2:$A$125,0)) -> 1
A87: 22 | B87: Perform initial assessment of customer need | C87: CP | D87: Implementation LIS | E87: Verzögert | F87: 45962 | G87: 46081 | H87: 85 | I87: =INDEX(Prozesse!$S$2:$S$125,MATCH(A87,Prozesse!$A$2:$A$125,0)) -> 1
A88: 22 | B88: Perform initial assessment of customer need | C88: CP | D88: Implementation LUS | E88: Ohne Angabe | I88: =INDEX(Prozesse!$S$2:$S$125,MATCH(A88,Prozesse!$A$2:$A$125,0)) -> 1
A89: 22 | B89: Perform initial assessment of customer need | C89: CP | D89: Implementation COT | E89: Verzögert | F89: 45964 | G89: 46112 | H89: 107 | I89: =INDEX(Prozesse!$S$2:$S$125,MATCH(A89,Prozesse!$A$2:$A$125,0)) -> 1
A90: 23 | B90: Perform software selection | C90: CP | D90: Elaboration | E90: Abgeschlossen | F90: 45931 | G90: 46014 | H90: 60 | I90: =INDEX(Prozesse!$S$2:$S$125,MATCH(A90,Prozesse!$A$2:$A$125,0)) -> 1
A91: 23 | B91: Perform software selection | C91: CP | D91: Implementation LIS | E91: Verzögert | F91: 46069 | G91: 46142 | H91: 54 | I91: =INDEX(Prozesse!$S$2:$S$125,MATCH(A91,Prozesse!$A$2:$A$125,0)) -> 1
A92: 23 | B92: Perform software selection | C92: CP | D92: Implementation LUS | E92: Ohne Angabe | I92: =INDEX(Prozesse!$S$2:$S$125,MATCH(A92,Prozesse!$A$2:$A$125,0)) -> 1
A93: 23 | B93: Perform software selection | C93: CP | D93: Implementation COT | E93: Verzögert | F93: 45946 | G93: 46022 | H93: 55 | I93: =INDEX(Prozesse!$S$2:$S$125,MATCH(A93,Prozesse!$A$2:$A$125,0)) -> 1
A94: 24 | B94: Plan IT service | C94: CP | D94: Elaboration | E94: Abgeschlossen | F94: 45946 | G94: 45961 | H94: 12 | I94: =INDEX(Prozesse!$S$2:$S$125,MATCH(A94,Prozesse!$A$2:$A$125,0)) -> 1
A95: 24 | B95: Plan IT service | C95: CP | D95: Implementation LIS | E95: Verzögert | F95: 45962 | G95: 46081 | H95: 85 | I95: =INDEX(Prozesse!$S$2:$S$125,MATCH(A95,Prozesse!$A$2:$A$125,0)) -> 1
A96: 24 | B96: Plan IT service | C96: CP | D96: Implementation LUS | E96: Ohne Angabe | I96: =INDEX(Prozesse!$S$2:$S$125,MATCH(A96,Prozesse!$A$2:$A$125,0)) -> 1
A97: 24 | B97: Plan IT service | C97: CP | D97: Implementation COT | E97: Verzögert | F97: 45964 | G97: 46112 | H97: 107 | I97: =INDEX(Prozesse!$S$2:$S$125,MATCH(A97,Prozesse!$A$2:$A$125,0)) -> 1
A98: 25 | B98: Plan IT workforce | C98: SP | D98: Elaboration | E98: Verzögert | F98: 45946 | G98: 46022 | H98: 55 | I98: =INDEX(Prozesse!$S$2:$S$125,MATCH(A98,Prozesse!$A$2:$A$125,0)) -> 1
A99: 25 | B99: Plan IT workforce | C99: SP | D99: Implementation LIS | E99: Verzögert | F99: 46023 | G99: 46387 | H99: 261 | I99: =INDEX(Prozesse!$S$2:$S$125,MATCH(A99,Prozesse!$A$2:$A$125,0)) -> 1
A100: 25 | B100: Plan IT workforce | C100: SP | D100: Implementation LUS | E100: Ohne Angabe | I100: =INDEX(Prozesse!$S$2:$S$125,MATCH(A100,Prozesse!$A$2:$A$125,0)) -> 1
...

Sheet Listen
A1: Auswahllisten für die Felder im Cockpit
A2: Prozessgruppe | B2: Initiative | C2: L1-Prozess | D2: Ebene | E2: Status | F2: Process Manager
A3: (Alle) | B3: (Alle) | C3: (Alle) | D3: (Alle) | E3: (Alle) | F3: (Alle)
A4: CP | B4: Architecture management | C4: Build IT Service | D4: L1 | E4: Verzögert | F4: Mielenz Thomas (LMT)
A5: MP | B5: Central area (Jan Müskens) | C5: Deliver IT service | D5: L2 | E5: In Arbeit | F5: Monnier Murielle (LEC)
A6: SP | B6: Corporate IT body | C6: Ensure Information security | D6: L3 | E6: Terminiert | F6: Moser Mario (LIS-LAH)
B7: HR initiatives for IT | C7: Ensure performance and conformance of IT services | D7: L4 | E7: Abgeschlossen | F7: Nussbaumer Florian (LBC)
B8: IT planning and steering | C8: Leverage IT innovation | E8: Nicht geplant | F8: Reiner Heiko (HAU-ITSA)
B9: IT project management | C9: Manage IT governance framework | F9: Rollinger Alexander (LIS)
B10: ITSM | C10: Manage IT knowledge | F10: Schnurrenberger Christoph (LIS-LIN)
B11: Information security | C11: Manage IT portfolio | F11: Sint Rachel (LBH)
B12: n/a | C12: Manage IT processes and continuous improvement | F12: Wiehe Alexander (COB)
C13: Manage IT project | F13: –
C14: Manage IT risks and compliance
C15: Manage IT sourcing and procurement
C16: Manage IT stakeholder relationships
C17: Manage IT strategy
C18: Manage and control IT financials
C19: Manage enterprise architecture
C20: Plan IT service
C21: Provide and develop IT workforce
C22: Run IT service

Sheet Auswertung
A1: Auswertung – speist die Diagramme im Cockpit. Alle Werte sind Formeln über die Trefferspalte.
A3: Status | B3: Anzahl | D3: Prozessgruppe | E3: Verzögert | F3: In Arbeit | G3: Terminiert | H3: Abgeschlossen | I3: Nicht geplant
A4: Verzögert | B4: =SUMPRODUCT(Prozesse!$S$2:$S$125,--(Prozesse!$H$2:$H$125=$A4)) -> 29 | C4: MP | D4: MP · Management | E4: =SUMPRODUCT(Prozesse!$S$2:$S$125,--(Prozesse!$D$2:$D$125=$C4),--(Prozesse!$H$2:$H$125=E$3)) -> 6 | F4: =SUMPRODUCT(Prozesse!$S$2:$S$125,--(Prozesse!$D$2:$D$125=$C4),--(Prozesse!$H$2:$H$125=F$3)) -> 39 | G4: =SUMPRODUCT(Prozesse!$S$2:$S$125,--(Prozesse!$D$2:$D$125=$C4),--(Prozesse!$H$2:$H$125=G$3)) -> 1 | H4: =SUMPRODUCT(Prozesse!$S$2:$S$125,--(Prozesse!$D$2:$D$125=$C4),--(Prozesse!$H$2:$H$125=H$3)) -> 3 | I4: =SUMPRODUCT(Prozesse!$S$2:$S$125,--(Prozesse!$D$2:$D$125=$C4),--(Prozesse!$H$2:$H$125=I$3)) -> 2
A5: In Arbeit | B5: =SUMPRODUCT(Prozesse!$S$2:$S$125,--(Prozesse!$H$2:$H$125=$A5)) -> 59 | C5: CP | D5: CP · Core | E5: =SUMPRODUCT(Prozesse!$S$2:$S$125,--(Prozesse!$D$2:$D$125=$C5),--(Prozesse!$H$2:$H$125=E$3)) -> 12 | F5: =SUMPRODUCT(Prozesse!$S$2:$S$125,--(Prozesse!$D$2:$D$125=$C5),--(Prozesse!$H$2:$H$125=F$3)) -> 10 | G5: =SUMPRODUCT(Prozesse!$S$2:$S$125,--(Prozesse!$D$2:$D$125=$C5),--(Prozesse!$H$2:$H$125=G$3)) -> 3 | H5: =SUMPRODUCT(Prozesse!$S$2:$S$125,--(Prozesse!$D$2:$D$125=$C5),--(Prozesse!$H$2:$H$125=H$3)) -> 7 | I5: =SUMPRODUCT(Prozesse!$S$2:$S$125,--(Prozesse!$D$2:$D$125=$C5),--(Prozesse!$H$2:$H$125=I$3)) -> 10
A6: Terminiert | B6: =SUMPRODUCT(Prozesse!$S$2:$S$125,--(Prozesse!$H$2:$H$125=$A6)) -> 7 | C6: SP | D6: SP · Support | E6: =SUMPRODUCT(Prozesse!$S$2:$S$125,--(Prozesse!$D$2:$D$125=$C6),--(Prozesse!$H$2:$H$125=E$3)) -> 11 | F6: =SUMPRODUCT(Prozesse!$S$2:$S$125,--(Prozesse!$D$2:$D$125=$C6),--(Prozesse!$H$2:$H$125=F$3)) -> 10 | G6: =SUMPRODUCT(Prozesse!$S$2:$S$125,--(Prozesse!$D$2:$D$125=$C6),--(Prozesse!$H$2:$H$125=G$3)) -> 3 | H6: =SUMPRODUCT(Prozesse!$S$2:$S$125,--(Prozesse!$D$2:$D$125=$C6),--(Prozesse!$H$2:$H$125=H$3)) -> 7 | I6: =SUMPRODUCT(Prozesse!$S$2:$S$125,--(Prozesse!$D$2:$D$125=$C6),--(Prozesse!$H$2:$H$125=I$3)) -> 0
A7: Abgeschlossen | B7: =SUMPRODUCT(Prozesse!$S$2:$S$125,--(Prozesse!$H$2:$H$125=$A7)) -> 17
A8: Nicht geplant | B8: =SUMPRODUCT(Prozesse!$S$2:$S$125,--(Prozesse!$H$2:$H$125=$A8)) -> 12
A10: Initiative | B10: Ø Fortschritt | C10: Prozesse | E10: L1-Prozessbereich | F10: davon verzögert
A11: Architecture management | B11: =IFERROR(SUMPRODUCT(Prozesse!$S$2:$S$125,--(Prozesse!$E$2:$E$125=$A11),Prozesse!$I$2:$I$125)/SUMPRODUCT(Prozesse!$S$2:$S$125,--(Prozesse!$E$2:$E$125=$A11)),0) -> 0.92857143 | C11: =SUMPRODUCT(Prozesse!$S$2:$S$125,--(Prozesse!$E$2:$E$125=$A11)) -> 7 | E11: Provide and develop IT workforce | F11: =SUMPRODUCT(Prozesse!$S$2:$S$125,--(Prozesse!$F$2:$F$125=$E11),--(Prozesse!$H$2:$H$125="Verzögert")) -> 9
A12: Central area (Jan Müskens) | B12: =IFERROR(SUMPRODUCT(Prozesse!$S$2:$S$125,--(Prozesse!$E$2:$E$125=$A12),Prozesse!$I$2:$I$125)/SUMPRODUCT(Prozesse!$S$2:$S$125,--(Prozesse!$E$2:$E$125=$A12)),0) -> 0.21875 | C12: =SUMPRODUCT(Prozesse!$S$2:$S$125,--(Prozesse!$E$2:$E$125=$A12)) -> 8 | E12: Plan IT service | F12: =SUMPRODUCT(Prozesse!$S$2:$S$125,--(Prozesse!$F$2:$F$125=$E12),--(Prozesse!$H$2:$H$125="Verzögert")) -> 5
A13: Corporate IT body | B13: =IFERROR(SUMPRODUCT(Prozesse!$S$2:$S$125,--(Prozesse!$E$2:$E$125=$A13),Prozesse!$I$2:$I$125)/SUMPRODUCT(Prozesse!$S$2:$S$125,--(Prozesse!$E$2:$E$125=$A13)),0) -> 0.56818182 | C13: =SUMPRODUCT(Prozesse!$S$2:$S$125,--(Prozesse!$E$2:$E$125=$A13)) -> 11 | E13: Run IT service | F13: =SUMPRODUCT(Prozesse!$S$2:$S$125,--(Prozesse!$F$2:$F$125=$E13),--(Prozesse!$H$2:$H$125="Verzögert")) -> 3
A14: HR initiatives for IT | B14: =IFERROR(SUMPRODUCT(Prozesse!$S$2:$S$125,--(Prozesse!$E$2:$E$125=$A14),Prozesse!$I$2:$I$125)/SUMPRODUCT(Prozesse!$S$2:$S$125,--(Prozesse!$E$2:$E$125=$A14)),0) -> 0.12611111 | C14: =SUMPRODUCT(Prozesse!$S$2:$S$125,--(Prozesse!$E$2:$E$125=$A14)) -> 18 | E14: Deliver IT service | F14: =SUMPRODUCT(Prozesse!$S$2:$S$125,--(Prozesse!$F$2:$F$125=$E14),--(Prozesse!$H$2:$H$125="Verzögert")) -> 2
A15: IT planning and steering | B15: =IFERROR(SUMPRODUCT(Prozesse!$S$2:$S$125,--(Prozesse!$E$2:$E$125=$A15),Prozesse!$I$2:$I$125)/SUMPRODUCT(Prozesse!$S$2:$S$125,--(Prozesse!$E$2:$E$125=$A15)),0) -> 0.5 | C15: =SUMPRODUCT(Prozesse!$S$2:$S$125,--(Prozesse!$E$2:$E$125=$A15)) -> 21 | E15: Build IT Service | F15: =SUMPRODUCT(Prozesse!$S$2:$S$125,--(Prozesse!$F$2:$F$125=$E15),--(Prozesse!$H$2:$H$125="Verzögert")) -> 2
A16: IT project management | B16: =IFERROR(SUMPRODUCT(Prozesse!$S$2:$S$125,--(Prozesse!$E$2:$E$125=$A16),Prozesse!$I$2:$I$125)/SUMPRODUCT(Prozesse!$S$2:$S$125,--(Prozesse!$E$2:$E$125=$A16)),0) -> 1 | C16: =SUMPRODUCT(Prozesse!$S$2:$S$125,--(Prozesse!$E$2:$E$125=$A16)) -> 8 | E16: Manage enterprise architecture | F16: =SUMPRODUCT(Prozesse!$S$2:$S$125,--(Prozesse!$F$2:$F$125=$E16),--(Prozesse!$H$2:$H$125="Verzögert")) -> 2
A17: ITSM | B17: =IFERROR(SUMPRODUCT(Prozesse!$S$2:$S$125,--(Prozesse!$E$2:$E$125=$A17),Prozesse!$I$2:$I$125)/SUMPRODUCT(Prozesse!$S$2:$S$125,--(Prozesse!$E$2:$E$125=$A17)),0) -> 0.28333333 | C17: =SUMPRODUCT(Prozesse!$S$2:$S$125,--(Prozesse!$E$2:$E$125=$A17)) -> 48 | E17: Ensure performance and conformance of IT services | F17: =SUMPRODUCT(Prozesse!$S$2:$S$125,--(Prozesse!$F$2:$F$125=$E17),--(Prozesse!$H$2:$H$125="Verzögert")) -> 1
A18: Information security | B18: =IFERROR(SUMPRODUCT(Prozesse!$S$2:$S$125,--(Prozesse!$E$2:$E$125=$A18),Prozesse!$I$2:$I$125)/SUMPRODUCT(Prozesse!$S$2:$S$125,--(Prozesse!$E$2:$E$125=$A18)),0) -> 0.5 | C18: =SUMPRODUCT(Prozesse!$S$2:$S$125,--(Prozesse!$E$2:$E$125=$A18)) -> 2 | E18: Manage IT processes and continuous improvement | F18: =SUMPRODUCT(Prozesse!$S$2:$S$125,--(Prozesse!$F$2:$F$125=$E18),--(Prozesse!$H$2:$H$125="Verzögert")) -> 1
A19: n/a | B19: =IFERROR(SUMPRODUCT(Prozesse!$S$2:$S$125,--(Prozesse!$E$2:$E$125=$A19),Prozesse!$I$2:$I$125)/SUMPRODUCT(Prozesse!$S$2:$S$125,--(Prozesse!$E$2:$E$125=$A19)),0) -> 0.22 | C19: =SUMPRODUCT(Prozesse!$S$2:$S$125,--(Prozesse!$E$2:$E$125=$A19)) -> 1 | E19: Manage IT knowledge | F19: =SUMPRODUCT(Prozesse!$S$2:$S$125,--(Prozesse!$F$2:$F$125=$E19),--(Prozesse!$H$2:$H$125="Verzögert")) -> 1
E20: Manage IT portfolio | F20: =SUMPRODUCT(Prozesse!$S$2:$S$125,--(Prozesse!$F$2:$F$125=$E20),--(Prozesse!$H$2:$H$125="Verzögert")) -> 1
A23: Phase | B23: terminiert | C23: abgeschlossen
A24: Elaboration | B24: =SUMPRODUCT(Phasen!$I$2:$I$497,--(Phasen!$D$2:$D$497=$A24),--(Phasen!$F$2:$F$497<>"")) -> 104 | C24: =SUMPRODUCT(Phasen!$I$2:$I$497,--(Phasen!$D$2:$D$497=$A24),--(Phasen!$E$2:$E$497="Abgeschlossen")) -> 30
A25: Implementation LIS | B25: =SUMPRODUCT(Phasen!$I$2:$I$497,--(Phasen!$D$2:$D$497=$A25),--(Phasen!$F$2:$F$497<>"")) -> 30 | C25: =SUMPRODUCT(Phasen!$I$2:$I$497,--(Phasen!$D$2:$D$497=$A25),--(Phasen!$E$2:$E$497="Abgeschlossen")) -> 0
A26: Implementation LUS | B26: =SUMPRODUCT(Phasen!$I$2:$I$497,--(Phasen!$D$2:$D$497=$A26),--(Phasen!$F$2:$F$497<>"")) -> 4 | C26: =SUMPRODUCT(Phasen!$I$2:$I$497,--(Phasen!$D$2:$D$497=$A26),--(Phasen!$E$2:$E$497="Abgeschlossen")) -> 0
A27: Implementation COT | B27: =SUMPRODUCT(Phasen!$I$2:$I$497,--(Phasen!$D$2:$D$497=$A27),--(Phasen!$F$2:$F$497<>"")) -> 12 | C27: =SUMPRODUCT(Phasen!$I$2:$I$497,--(Phasen!$D$2:$D$497=$A27),--(Phasen!$E$2:$E$497="Abgeschlossen")) -> 0

Sheet Hinweise
B2: IT Process Portfolio – Cockpit
B4: Bedienung
B5: Im Blatt Cockpit die gelb hinterlegten Auswahlfelder ändern. Kennzahlen, Diagramme und
B6: die Trefferliste rechnen sofort neu. Alle übrigen Zellen sind gesperrt, damit nichts
B7: versehentlich überschrieben wird; ein Kennwort wird dafür nicht benötigt.
B8: Die Blätter Prozesse und Phasen tragen echte Excel-Tabellen: dort lässt sich zusätzlich
B9: über die Spaltenköpfe filtern und sortieren.
B11: Gemeinsames Arbeiten
B12: Die Auswahlfelder sind Zellen der Mappe. Ändert sie jemand, sehen alle anderen dieselbe
B13: Auswahl. Wer für sich allein filtern möchte, nutzt in Excel für das Web auf den Blättern
B14: Prozesse oder Phasen die Blattansicht (Ansicht > Blattansicht > Neu).
B16: Wie der Status entsteht
... B34: Neu erzeugen nach einer aktualisierten Planung: python3 build/excel.py
