Workbook
Name Task_Table1: Task_Table1!$A$1:$P$1

Sheet Task_Table1
A1: Initative | B1: Process | C1: Phase | D1: Process level | E1: Process group | F1: Percent complete | G1: IT process Consultant | H1: Responsible | I1: Care taker | J1: Start | K1: End | L1: Duration | M1: Approval date | N1: Actual phase | O1: Planned phase | P1: Associated process on L1
A2: Corporate IT body | B2: Manage IT strategy | C2: Total | D2: L1 | E2: MP | F2: 0.07 | J2: 46029 | K2: 46203 | L2: =NETWORKDAYS(J2,K2) -> 125 | O2: 1 | P2: Manage IT strategy
A3: Corporate IT body | B3: Manage IT strategy | C3: Elaboration | D3: L1 | E3: MP | F3: 0.15 | G3: Kunz Christina (LIS-MHP Management- und IT Beratung GmbH) | H3: Felder Max (LLI) | I3: Mielenz Thomas (LMT) | J3: 46029 | K3: 46097 | L3: =NETWORKDAYS(J3,K3) -> 49 | N3: Elaboration in progress | O3: Scheduled | P3: Manage IT strategy
A4: Corporate IT body | B4: Manage IT strategy | C4: Implementation LIS | D4: L1 | E4: MP | F4: 0 | J4: 46127 | K4: 46203 | L4: =NETWORKDAYS(J4,K4) -> 55 | O4: Scheduled | P4: Manage IT strategy
A5: Corporate IT body | B5: Manage IT strategy | C5: Implementation COT | D5: L1 | E5: MP | F5: 0 | L5: =NETWORKDAYS(J5,K5) -> 0 | P5: Manage IT strategy
A6: Corporate IT body | B6: Manage IT strategy | C6: Implementation LUS | D6: L1 | E6: MP | F6: 0 | L6: =NETWORKDAYS(J6,K6) -> 0 | P6: Manage IT strategy
A7: Corporate IT body | B7: Manage IT governance framework | C7: Total | D7: L1 | E7: MP | F7: 0 | J7: 46029 | K7: 46203 | L7: =NETWORKDAYS(J7,K7) -> 125 | P7: Manage IT governance framework
A8: Corporate IT body | B8: Manage IT governance framework | C8: Elaboration | D8: L1 | E8: MP | F8: 0 | G8: Kunz Christina (LIS-MHP Management- und IT Beratung GmbH) | H8: Felder Max (LLI) | I8: Mielenz Thomas (LMT) | J8: 46029 | K8: 46097 | L8: =NETWORKDAYS(J8,K8) -> 49 | O8: Scheduled | P8: Manage IT governance framework
A9: Corporate IT body | B9: Manage IT governance framework | C9: Implementation LIS | D9: L1 | E9: MP | F9: 0 | J9: 46127 | K9: 46203 | L9: =NETWORKDAYS(J9,K9) -> 55 | O9: Scheduled | P9: Manage IT governance framework
A10: Corporate IT body | B10: Manage IT governance framework | C10: Implementation COT | D10: L1 | E10: MP | F10: 0 | L10: =NETWORKDAYS(J10,K10) -> 0 | P10: Manage IT governance framework
A11: Corporate IT body | B11: Manage IT governance framework | C11: Implementation LUS | D11: L1 | E11: MP | F11: 0 | L11: =NETWORKDAYS(J11,K11) -> 0 | P11: Manage IT governance framework
A12: Corporate IT body | B12: Maintain IT glossary | C12: Total | D12: L2 | E12: MP | F12: 0 | L12: =NETWORKDAYS(J12,K12) -> 0 | P12: Manage IT governance framework
A13: Corporate IT body | B13: Maintain IT glossary | C13: Elaboration | D13: L2 | E13: MP | F13: 0 | G13: Kunz Christina (LIS-MHP Management- und IT Beratung GmbH) | H13: Felder Max (LLI) | I13: Mielenz Thomas (LMT) | L13: =NETWORKDAYS(J13,K13) -> 0 | P13: Manage IT governance framework
A14: Corporate IT body | B14: Maintain IT glossary | C14: Implementation LIS | D14: L2 | E14: MP | F14: 0 | J14: 46029 | K14: 46039 | L14: =NETWORKDAYS(J14,K14) -> 8 | O14: Scheduled | P14: Manage IT governance framework
A15: Corporate IT body | B15: Maintain IT glossary | C15: Implementation COT | D15: L2 | E15: MP | F15: 0 | L15: =NETWORKDAYS(J15,K15) -> 0 | P15: Manage IT governance framework
A16: Corporate IT body | B16: Maintain IT glossary | C16: Implementation LUS | D16: L2 | E16: MP | F16: 0 | L16: =NETWORKDAYS(J16,K16) -> 0 | P16: Manage IT governance framework
A17: Corporate IT body | B17: Manage enterprise architecture | C17: Total | D17: L1 | E17: MP | F17: 0 | J17: 46029 | K17: 46195 | L17: =NETWORKDAYS(J17,K17) -> 119 | P17: Manage enterprise architecture
A18: Corporate IT body | B18: Manage enterprise architecture | C18: Elaboration | D18: L1 | E18: MP | F18: 0 | G18: Hoermann Patrick (LLI) | H18: Gujral Parth (COB-COT-IT) | I18: Nussbaumer Florian (LBC) | J18: 46029 | K18: 46097 | L18: =NETWORKDAYS(J18,K18) -> 49 | O18: Scheduled | P18: Manage enterprise architecture
A19: Corporate IT body | B19: Manage enterprise architecture | C19: Implementation LIS | D19: L1 | E19: MP | F19: 0 | J19: 46127 | K19: 46195 | L19: =NETWORKDAYS(J19,K19) -> 49 | O19: Scheduled | P19: Manage enterprise architecture
A20: Corporate IT body | B20: Manage enterprise architecture | C20: Implementation COT | D20: L1 | E20: MP | F20: 0 | L20: =NETWORKDAYS(J20,K20) -> 0 | P20: Manage enterprise architecture
A21: Corporate IT body | B21: Manage enterprise architecture | C21: Implementation LUS | D21: L1 | E21: MP | F21: 0 | J21: 46142 | K21: 46142 | L21: =NETWORKDAYS(J21,K21) -> 1 | O21: Scheduled | P21: Manage enterprise architecture
A22: Corporate IT body | B22: Strategic architecture process | C22: Total | D22: L2 | E22: MP | F22: 0 | J22: 46142 | K22: 46142 | L22: =NETWORKDAYS(J22,K22) -> 1 | P22: Manage enterprise architecture
A23: Corporate IT body | B23: Strategic architecture process | C23: Elaboration | D23: L2 | E23: MP | F23: 0 | G23: Hoermann Patrick (LLI) | H23: Gujral Parth (COB-COT-IT) | I23: Nussbaumer Florian (LBC) | L23: =NETWORKDAYS(J23,K23) -> 0 | P23: Manage enterprise architecture
A24: Corporate IT body | B24: Strategic architecture process | C24: Implementation LIS | D24: L2 | E24: MP | F24: 0 | K24: 46142 | L24: =NETWORKDAYS(J24,K24) -> 32959 | P24: Manage enterprise architecture
A25: Corporate IT body | B25: Strategic architecture process | C25: Implementation COT | D25: L2 | E25: MP | F25: 0 | L25: =NETWORKDAYS(J25,K25) -> 0 | P25: Manage enterprise architecture
A26: Corporate IT body | B26: Strategic architecture process | C26: Implementation LUS | D26: L2 | E26: MP | F26: 0 | L26: =NETWORKDAYS(J26,K26) -> 0 | P26: Manage enterprise architecture
A27: ITSM | B27: Manage IT portfolio | C27: Total | D27: L1 | E27: MP | F27: 0 | J27: 45971 | K27: 46157 | L27: =NETWORKDAYS(J27,K27) -> 135 | P27: Manage IT portfolio
A28: ITSM | B28: Manage IT portfolio | C28: Elaboration | D28: L1 | E28: MP | F28: 0 | G28: Frank Maren (LIS);Kunz Christina (LIS-MHP Management- und IT Beratung GmbH) | H28: Rantou Anna (LIS) | J28: 45877 | K28: 46053 | L28: =NETWORKDAYS(J28,K28) -> 126 | N28: Delayed | O28: Elaboration in progress | P28: Manage IT portfolio
A29: ITSM | B29: Manage IT portfolio | C29: Implementation LIS | D29: L1 | E29: MP | F29: 0 | L29: =NETWORKDAYS(J29,K29) -> 0 | P29: Manage IT portfolio
A30: ITSM | B30: Manage IT portfolio | C30: Implementation COT | D30: L1 | E30: MP | F30: 0 | L30: =NETWORKDAYS(J30,K30) -> 0 | P30: Manage IT portfolio
A31: ITSM | B31: Manage IT portfolio | C31: Implementation LUS | D31: L1 | E31: MP | F31: 0 | J31: 46013 | K31: 46025 | L31: =NETWORKDAYS(J31,K31) -> 10 | O31: Scheduled | P31: Manage IT portfolio
A32: IT project management | B32: Manage IT project portfolio | C32: Total | D32: L2 | E32: MP | F32: 0 | J32: 45971 | K32: 46014 | L32: =NETWORKDAYS(J32,K32) -> 32 | P32: Manage IT portfolio
A33: IT project management | B33: Manage IT project portfolio | C33: Elaboration | D33: L2 | E33: MP | F33: 0 | G33: Frank Maren (LIS) | H33: Mühlbacher Christian (LIS) | I33: Rollinger Alexander (LIS) | J33: 45971 | K33: 46014 | L33: =NETWORKDAYS(J33,K33) -> 32 | N33: Delayed | O33: Elaboration in progress | P33: Manage IT portfolio
A34: IT project management | B34: Manage IT project portfolio | C34: Implementation LIS | D34: L2 | E34: MP | F34: 0 | L34: =NETWORKDAYS(J34,K34) -> 0 | P34: Manage IT portfolio
A35: IT project management | B35: Manage IT project portfolio | C35: Implementation COT | D35: L2 | E35: MP | F35: 0 | L35: =NETWORKDAYS(J35,K35) -> 0 | P35: Manage IT portfolio
A36: IT project management | B36: Manage IT project portfolio | C36: Implementation LUS | D36: L2 | E36: MP | F36: 0 | L36: =NETWORKDAYS(J36,K36) -> 0 | P36: Manage IT portfolio
A37: ITSM | B37: Manage IT service portfolio | C37: Total | D37: L2 | E37: MP | F37: 0 | J37: 46027 | K37: 46203 | L37: =NETWORKDAYS(J37,K37) -> 127 | P37: Manage IT portfolio
A38: ITSM | B38: Manage IT service portfolio | C38: Elaboration | D38: L2 | E38: MP | F38: 0 | G38: Frank Maren (LIS);Kunz Christina (LIS-MHP Management- und IT Beratung GmbH) | H38: Rantou Anna (LIS) | I38: Reiner Heiko (HAU-ITSA) | J38: 46027 | K38: 46111 | L38: =NETWORKDAYS(J38,K38) -> 61 | O38: Scheduled | P38: Manage IT portfolio
A39: ITSM | B39: Manage IT service portfolio | C39: Implementation LIS | D39: L2 | E39: MP | F39: 0 | J39: 46118 | K39: 46203 | L39: =NETWORKDAYS(J39,K39) -> 62 | O39: Scheduled | P39: Manage IT portfolio
A40: ITSM | B40: Manage IT service portfolio | C40: Implementation COT | D40: L2 | E40: MP | F40: 0 | L40: =NETWORKDAYS(J40,K40) -> 0 | P40: Manage IT portfolio
A41: ITSM | B41: Manage IT service portfolio | C41: Implementation LUS | D41: L2 | E41: MP | F41: 0 | L41: =NETWORKDAYS(J41,K41) -> 0 | P41: Manage IT portfolio
A42: IT planning and steering | B42: Manage and control IT financials | C42: Total | D42: L1 | E42: MP | F42: 0 | J42: 45945 | K42: 46295 | L42: =NETWORKDAYS(J42,K42) -> 251 | P42: Manage and control IT financials
A43: IT planning and steering | B43: Manage and control IT financials | C43: Elaboration | D43: L1 | E43: MP | F43: 0 | G43: Hynek Tobias (LIS) | H43: Frank Nicole (LIS) | I43: Moser Mario (LIS-LAH) | L43: =NETWORKDAYS(J43,K43) -> 0 | P43: Manage and control IT financials
A44: IT planning and steering | B44: Manage and control IT financials | C44: Implementation LIS | D44: L1 | E44: MP | F44: 0 | L44: =NETWORKDAYS(J44,K44) -> 0 | P44: Manage and control IT financials
A45: IT planning and steering | B45: Manage and control IT financials | C45: Implementation COT | D45: L2 | E45: MP | F45: 0 | L45: =NETWORKDAYS(J45,K45) -> 0 | P45: Manage and control IT financials
A46: IT planning and steering | B46: Manage and control IT financials | C46: Implementation LUS | D46: L1 | E46: MP | F46: 0 | L46: =NETWORKDAYS(J46,K46) -> 0 | P46: Manage and control IT financials
A47: IT planning and steering | B47: Create and maintain IT budgets | C47: Total | D47: L2 | E47: MP | F47: 0 | J47: 46029 | K47: 46202 | L47: =NETWORKDAYS(J47,K47) -> 124 | P47: Manage and control IT financials
A48: IT planning and steering | B48: Create and maintain IT budgets | C48: Elaboration | D48: L2 | E48: MP | F48: 0 | G48: Hynek Tobias (LIS) | H48: Frank Nicole (LIS) | I48: Mielenz Thomas (LMT) | J48: 46029 | K48: 46104 | L48: =NETWORKDAYS(J48,K48) -> 54 | O48: Scheduled | P48: Manage and control IT financials
A49: IT planning and steering | B49: Create and maintain IT budgets | C49: Implementation LIS | D49: L2 | E49: MP | F49: 0 | J49: 46118 | K49: 46202 | L49: =NETWORKDAYS(J49,K49) -> 61 | O49: Scheduled | P49: Manage and control IT financials
A50: IT planning and steering | B50: Create and maintain IT budgets | C50: Implementation COT | D50: L2 | E50: MP | F50: 0 | L50: =NETWORKDAYS(J50,K50) -> 0 | P50: Manage and control IT financials
A51: IT planning and steering | B51: Create and maintain IT budgets | C51: Implementation LUS | D51: L2 | E51: MP | F51: 0 | L51: =NETWORKDAYS(J51,K51) -> 0 | P51: Manage and control IT financials
A52: IT planning and steering | B52: Approve and communicate budget plan | C52: Total | D52: L3 | E52: MP | F52: 0 | L52: =NETWORKDAYS(J52,K52) -> 0 | P52: Manage and control IT financials
A53: IT planning and steering | B53: Approve and communicate budget plan | C53: Elaboration | D53: L3 | E53: MP | F53: 0 | G53: Hynek Tobias (LIS) | H53: Frank Nicole (LIS) | I53: Mielenz Thomas (LMT) | L53: =NETWORKDAYS(J53,K53) -> 0 | P53: Manage and control IT financials
A54: IT planning and steering | B54: Approve and communicate budget plan | C54: Implementation LIS | D54: L3 | E54: MP | F54: 0 | L54: =NETWORKDAYS(J54,K54) -> 0 | P54: Manage and control IT financials
A55: IT planning and steering | B55: Approve and communicate budget plan | C55: Implementation COT | D55: L3 | E55: MP | F55: 0 | L55: =NETWORKDAYS(J55,K55) -> 0 | P55: Manage and control IT financials
A56: IT planning and steering | B56: Approve and communicate budget plan | C56: Implementation LUS | D56: L3 | E56: MP | F56: 0 | L56: =NETWORKDAYS(J56,K56) -> 0 | P56: Manage and control IT financials
A57: IT planning and steering | B57: Collect and consolidate budget from stakeholders | C57: Total | D57: L3 | E57: MP | F57: 0 | L57: =NETWORKDAYS(J57,K57) -> 0 | P57: Manage and control IT financials
A58: IT planning and steering | B58: Collect and consolidate budget from stakeholders | C58: Elaboration | D58: L3 | E58: MP | F58: 0 | G58: Hynek Tobias (LIS) | H58: Frank Nicole (LIS) | I58: Mielenz Thomas (LMT) | L58: =NETWORKDAYS(J58,K58) -> 0 | P58: Manage and control IT financials
A59: IT planning and steering | B59: Collect and consolidate budget from stakeholders | C59: Implementation LIS | D59: L3 | E59: MP | F59: 0 | L59: =NETWORKDAYS(J59,K59) -> 0 | P59: Manage and control IT financials
A60: IT planning and steering | B60: Collect and consolidate budget from stakeholders | C60: Implementation COT | D60: L3 | E60: MP | F60: 0 | L60: =NETWORKDAYS(J60,K60) -> 0 | P60: Manage and control IT financials
A61: IT planning and steering | B61: Collect and consolidate budget from stakeholders | C61: Implementation LUS | D61: L3 | E61: MP | F61: 0 | L61: =NETWORKDAYS(J61,K61) -> 0 | P61: Manage and control IT financials
A62: IT planning and steering | B62: Develop preliminary budget plan | C62: Total | D62: L3 | E62: MP | F62: 0 | L62: =NETWORKDAYS(J62,K62) -> 0 | P62: Manage and control IT financials
A63: IT planning and steering | B63: Develop preliminary budget plan | C63: Elaboration | D63: L3 | E63: MP | F63: 0 | G63: Hynek Tobias (LIS) | H63: Frank Nicole (LIS) | I63: Mielenz Thomas (LMT) | L63: =NETWORKDAYS(J63,K63) -> 0 | P63: Manage and control IT financials
A64: IT planning and steering | B64: Develop preliminary budget plan | C64: Implementation LIS | D64: L3 | E64: MP | F64: 0 | L64: =NETWORKDAYS(J64,K64) -> 0 | P64: Manage and control IT financials
A65: IT planning and steering | B65: Develop preliminary budget plan | C65: Implementation COT | D65: L3 | E65: MP | F65: 0 | L65: =NETWORKDAYS(J65,K65) -> 0 | P65: Manage and control IT financials
A66: IT planning and steering | B66: Develop preliminary budget plan | C66: Implementation LUS | D66: L3 | E66: MP | F66: 0 | L66: =NETWORKDAYS(J66,K66) -> 0 | P66: Manage and control IT financials
A67: IT planning and steering | B67: Maintan and adjust budget | C67: Total | D67: L3 | E67: MP | F67: 0 | L67: =NETWORKDAYS(J67,K67) -> 0 | P67: Manage and control IT financials
A68: IT planning and steering | B68: Maintan and adjust budget | C68: Elaboration | D68: L3 | E68: MP | F68: 0 | G68: Hynek Tobias (LIS) | H68: Frank Nicole (LIS) | I68: Mielenz Thomas (LMT) | L68: =NETWORKDAYS(J68,K68) -> 0 | P68: Manage and control IT financials
A69: IT planning and steering | B69: Maintan and adjust budget | C69: Implementation LIS | D69: L3 | E69: MP | F69: 0 | L69: =NETWORKDAYS(J69,K69) -> 0 | P69: Manage and control IT financials
A70: IT planning and steering | B70: Maintan and adjust budget | C70: Implementation COT | D70: L3 | E70: MP | F70: 0 | L70: =NETWORKDAYS(J70,K70) -> 0 | P70: Manage and control IT financials
A71: IT planning and steering | B71: Maintan and adjust budget | C71: Implementation LUS | D71: L3 | E71: MP | F71: 0 | L71: =NETWORKDAYS(J71,K71) -> 0 | P71: Manage and control IT financials
A72: IT planning and steering | B72: Review budget plan | C72: Total | D72: L3 | E72: MP | F72: 0 | L72: =NETWORKDAYS(J72,K72) -> 0 | P72: Manage and control IT financials
A73: IT planning and steering | B73: Review budget plan | C73: Elaboration | D73: L3 | E73: MP | F73: 0 | G73: Hynek Tobias (LIS) | H73: Frank Nicole (LIS) | I73: Mielenz Thomas (LMT) | L73: =NETWORKDAYS(J73,K73) -> 0 | P73: Manage and control IT financials
A74: IT planning and steering | B74: Review budget plan | C74: Implementation LIS | D74: L3 | E74: MP | F74: 0 | L74: =NETWORKDAYS(J74,K74) -> 0 | P74: Manage and control IT financials
A75: IT planning and steering | B75: Review budget plan | C75: Implementation COT | D75: L3 | E75: MP | F75: 0 | L75: =NETWORKDAYS(J75,K75) -> 0 | P75: Manage and control IT financials
A76: IT planning and steering | B76: Review budget plan | C76: Implementation LUS | D76: L3 | E76: MP | F76: 0 | L76: =NETWORKDAYS(J76,K76) -> 0 | P76: Manage and control IT financials
A77: IT planning and steering | B77: Revise and optimize budget plan | C77: Total | D77: L3 | E77: MP | F77: 0 | L77: =NETWORKDAYS(J77,K77) -> 0 | P77: Manage and control IT financials
A78: IT planning and steering | B78: Revise and optimize budget plan | C78: Elaboration | D78: L3 | E78: MP | F78: 0 | G78: Hynek Tobias (LIS) | H78: Frank Nicole (LIS) | I78: Mielenz Thomas (LMT) | L78: =NETWORKDAYS(J78,K78) -> 0 | P78: Manage and control IT financials
A79: IT planning and steering | B79: Revise and optimize budget plan | C79: Implementation LIS | D79: L3 | E79: MP | F79: 0 | L79: =NETWORKDAYS(J79,K79) -> 0 | P79: Manage and control IT financials
A80: IT planning and steering | B80: Revise and optimize budget plan | C80: Implementation COT | D80: L3 | E80: MP | F80: 0 | L80: =NETWORKDAYS(J80,K80) -> 0 | P80: Manage and control IT financials
A81: IT planning and steering | B81: Revise and optimize budget plan | C81: Implementation LUS | D81: L3 | E81: MP | F81: 0 | L81: =NETWORKDAYS(J81,K81) -> 0 | P81: Manage and control IT financials
A82: IT planning and steering | B82: Manage finance and accounting | C82: Total | D82: L2 | E82: MP | F82: 0 | J82: 45945 | K82: 46104 | L82: =NETWORKDAYS(J82,K82) -> 114 | P82: Manage and control IT financials
A83: IT planning and steering | B83: Manage finance and accounting | C83: Elaboration | D83: L2 | E83: MP | F83: 0 | G83: Hynek Tobias (LIS) | H83: Frank Nicole (LIS) | I83: Moser Mario (LIS-LAH) | J83: 46029 | K83: 46104 | L83: =NETWORKDAYS(J83,K83) -> 54 | O83: Scheduled | P83: Manage and control IT financials
A84: IT planning and steering | B84: Manage finance and accounting | C84: Implementation LIS | D84: L2 | E84: MP | F84: 0 | L84: =NETWORKDAYS(J84,K84) -> 0 | P84: Manage and control IT financials
A85: IT planning and steering | B85: Manage finance and accounting | C85: Implementation COT | D85: L2 | E85: MP | F85: 0 | L85: =NETWORKDAYS(J85,K85) -> 0 | P85: Manage and control IT financials
A86: IT planning and steering | B86: Manage finance and accounting | C86: Implementation LUS | D86: L2 | E86: MP | F86: 0 | L86: =NETWORKDAYS(J86,K86) -> 0 | P86: Manage and control IT financials
A87: IT planning and steering | B87: Define financial management framework | C87: Total | D87: L3 | E87: MP | F87: 0 | L87: =NETWORKDAYS(J87,K87) -> 0 | P87: Manage and control IT financials
A88: IT planning and steering | B88: Define financial management framework | C88: Elaboration | D88: L3 | E88: MP | F88: 0 | G88: Hynek Tobias (LIS) | H88: Frank Nicole (LIS) | I88: Moser Mario (LIS-LAH) | L88: =NETWORKDAYS(J88,K88) -> 0 | P88: Manage and control IT financials
A89: IT planning and steering | B89: Define financial management framework | C89: Implementation LIS | D89: L3 | E89: MP | F89: 0 | L89: =NETWORKDAYS(J89,K89) -> 0 | P89: Manage and control IT financials
A90: IT planning and steering | B90: Define financial management framework | C90: Implementation COT | D90: L3 | E90: MP | F90: 0 | L90: =NETWORKDAYS(J90,K90) -> 0 | P90: Manage and control IT financials
A91: IT planning and steering | B91: Define financial management framework | C91: Implementation LUS | D91: L3 | E91: MP | F91: 0 | L91: =NETWORKDAYS(J91,K91) -> 0 | P91: Manage and control IT financials
A92: IT planning and steering | B92: Establish financial accounting structure | C92: Total | D92: L3 | E92: MP | F92: 0 | P92: Manage and control IT financials
A93: IT planning and steering | B93: Establish financial accounting structure | C93: Elaboration | D93: L3 | E93: MP | F93: 0 | G93: Hynek Tobias (LIS) | H93: Frank Nicole (LIS) | I93: Moser Mario (LIS-LAH) | L93: =NETWORKDAYS(J93,K93) -> 0 | P93: Manage and control IT financials
A94: IT planning and steering | B94: Establish financial accounting structure | C94: Implementation LIS | D94: L3 | E94: MP | F94: 0 | L94: =NETWORKDAYS(J94,K94) -> 0 | P94: Manage and control IT financials
A95: IT planning and steering | B95: Establish financial accounting structure | C95: Implementation COT | D95: L3 | E95: MP | F95: 0 | L95: =NETWORKDAYS(J95,K95) -> 0 | P95: Manage and control IT financials
A96: IT planning and steering | B96: Establish financial accounting structure | C96: Implementation LUS | D96: L3 | E96: MP | F96: 0 | L96: =NETWORKDAYS(J96,K96) -> 0 | P96: Manage and control IT financials
A97: IT planning and steering | B97: Manage IT costs | C97: Total | D97: L2 | E97: MP | F97: 0 | J97: 46034 | K97: 46195 | L97: =NETWORKDAYS(J97,K97) -> 116 | P97: Manage and control IT financials
A98: IT planning and steering | B98: Manage IT costs | C98: Elaboration | D98: L2 | E98: MP | F98: 0 | G98: Hynek Tobias (LIS) | H98: Frank Nicole (LIS) | I98: Moser Mario (LIS-LAH) | J98: 46034 | K98: 46112 | L98: =NETWORKDAYS(J98,K98) -> 57 | O98: Scheduled | P98: Manage and control IT financials
A99: IT planning and steering | B99: Manage IT costs | C99: Implementation LIS | D99: L2 | E99: MP | F99: 0 | J99: 46119 | K99: 46195 | L99: =NETWORKDAYS(J99,K99) -> 55 | O99: Scheduled | P99: Manage and control IT financials
A100: IT planning and steering | B100: Manage IT costs | C100: Implementation COT | E100: MP | F100: 0 | L100: =NETWORKDAYS(J100,K100) -> 0 | P100: Manage and control IT financials
...

Sheet Tabelle1
A1: Datum | B1: Elaboration | C1: Implementation LIS | D1: Implementation LUS | E1: Implementation COT
A2: 45870 | B2: {=SUMPRODUCT((Task_Table1!$C$2:$C$571=$B$1)*(A2>Task_Table1!$J$2:$J$571)*(A2<Task_Table1!$K$2:$K$571))} -> 1 | C2: {=SUMPRODUCT((Task_Table1!$C$2:$C$571=$C$1)*(A2>Task_Table1!$J$2:$J$571)*(A2<Task_Table1!$K$2:$K$571))} -> 2 | D2: {=SUMPRODUCT((Task_Table1!$C$2:$C$571=$D$1)*(A2>Task_Table1!$J$2:$J$571)*(A2<Task_Table1!$K$2:$K$571))} -> 0 | E2: {=SUMPRODUCT((Task_Table1!$C$2:$C$571=$E$1)*(A2>Task_Table1!$J$2:$J$571)*(A2<Task_Table1!$K$2:$K$571))} -> 1
A3: 45871 | B3: {=SUMPRODUCT((Task_Table1!$C$2:$C$571=$B$1)*(A3>Task_Table1!$J$2:$J$571)*(A3<Task_Table1!$K$2:$K$571))} -> 2 | C3: {=SUMPRODUCT((Task_Table1!$C$2:$C$568=$C$1)*(A3>Task_Table1!$J$2:$J$568)*(A3<Task_Table1!$K$2:$K$568))} -> 2 | D3: {=SUMPRODUCT((Task_Table1!$C$2:$C$571=$D$1)*(A3>Task_Table1!$J$2:$J$571)*(A3<Task_Table1!$K$2:$K$571))} -> 0 | E3: {=SUMPRODUCT((Task_Table1!$C$2:$C$571=$E$1)*(A3>Task_Table1!$J$2:$J$571)*(A3<Task_Table1!$K$2:$K$571))} -> 1
A4: 45872 | B4: {=SUMPRODUCT((Task_Table1!$C$2:$C$571=$B$1)*(A4>Task_Table1!$J$2:$J$571)*(A4<Task_Table1!$K$2:$K$571))} -> 2 | C4: {=SUMPRODUCT((Task_Table1!$C$2:$C$568=$C$1)*(A4>Task_Table1!$J$2:$J$568)*(A4<Task_Table1!$K$2:$K$568))} -> 2 | D4: {=SUMPRODUCT((Task_Table1!$C$2:$C$571=$D$1)*(A4>Task_Table1!$J$2:$J$571)*(A4<Task_Table1!$K$2:$K$571))} -> 0 | E4: {=SUMPRODUCT((Task_Table1!$C$2:$C$571=$E$1)*(A4>Task_Table1!$J$2:$J$571)*(A4<Task_Table1!$K$2:$K$571))} -> 1
A5: 45873 | B5: {=SUMPRODUCT((Task_Table1!$C$2:$C$571=$B$1)*(A5>Task_Table1!$J$2:$J$571)*(A5<Task_Table1!$K$2:$K$571))} -> 2 | C5: {=SUMPRODUCT((Task_Table1!$C$2:$C$568=$C$1)*(A5>Task_Table1!$J$2:$J$568)*(A5<Task_Table1!$K$2:$K$568))} -> 2 | D5: {=SUMPRODUCT((Task_Table1!$C$2:$C$571=$D$1)*(A5>Task_Table1!$J$2:$J$571)*(A5<Task_Table1!$K$2:$K$571))} -> 0 | E5: {=SUMPRODUCT((Task_Table1!$C$2:$C$571=$E$1)*(A5>Task_Table1!$J$2:$J$571)*(A5<Task_Table1!$K$2:$K$571))} -> 1
A6: 45874 | B6: {=SUMPRODUCT((Task_Table1!$C$2:$C$571=$B$1)*(A6>Task_Table1!$J$2:$J$571)*(A6<Task_Table1!$K$2:$K$571))} -> 2 | C6: {=SUMPRODUCT((Task_Table1!$C$2:$C$568=$C$1)*(A6>Task_Table1!$J$2:$J$568)*(A6<Task_Table1!$K$2:$K$568))} -> 2 | D6: {=SUMPRODUCT((Task_Table1!$C$2:$C$571=$D$1)*(A6>Task_Table1!$J$2:$J$571)*(A6<Task_Table1!$K$2:$K$571))} -> 0 | E6: {=SUMPRODUCT((Task_Table1!$C$2:$C$571=$E$1)*(A6>Task_Table1!$J$2:$J$571)*(A6<Task_Table1!$K$2:$K$571))} -> 1
A7: 45875 | B7: {=SUMPRODUCT((Task_Table1!$C$2:$C$571=$B$1)*(A7>Task_Table1!$J$2:$J$571)*(A7<Task_Table1!$K$2:$K$571))} -> 2 | C7: {=SUMPRODUCT((Task_Table1!$C$2:$C$568=$C$1)*(A7>Task_Table1!$J$2:$J$568)*(A7<Task_Table1!$K$2:$K$568))} -> 2 | D7: {=SUMPRODUCT((Task_Table1!$C$2:$C$571=$D$1)*(A7>Task_Table1!$J$2:$J$571)*(A7<Task_Table1!$K$2:$K$571))} -> 0 | E7: {=SUMPRODUCT((Task_Table1!$C$2:$C$571=$E$1)*(A7>Task_Table1!$J$2:$J$571)*(A7<Task_Table1!$K$2:$K$571))} -> 1
A8: 45876 | B8: {=SUMPRODUCT((Task_Table1!$C$2:$C$571=$B$1)*(A8>Task_Table1!$J$2:$J$571)*(A8<Task_Table1!$K$2:$K$571))} -> 2 | C8: {=SUMPRODUCT((Task_Table1!$C$2:$C$568=$C$1)*(A8>Task_Table1!$J$2:$J$568)*(A8<Task_Table1!$K$2:$K$568))} -> 2 | D8: {=SUMPRODUCT((Task_Table1!$C$2:$C$571=$D$1)*(A8>Task_Table1!$J$2:$J$571)*(A8<Task_Table1!$K$2:$K$571))} -> 0 | E8: {=SUMPRODUCT((Task_Table1!$C$2:$C$571=$E$1)*(A8>Task_Table1!$J$2:$J$571)*(A8<Task_Table1!$K$2:$K$571))} -> 1
A9: 45877 | B9: {=SUMPRODUCT((Task_Table1!$C$2:$C$571=$B$1)*(A9>Task_Table1!$J$2:$J$571)*(A9<Task_Table1!$K$2:$K$571))} -> 2 | C9: {=SUMPRODUCT((Task_Table1!$C$2:$C$568=$C$1)*(A9>Task_Table1!$J$2:$J$568)*(A9<Task_Table1!$K$2:$K$568))} -> 2 | D9: {=SUMPRODUCT((Task_Table1!$C$2:$C$571=$D$1)*(A9>Task_Table1!$J$2:$J$571)*(A9<Task_Table1!$K$2:$K$571))} -> 0 | E9: {=SUMPRODUCT((Task_Table1!$C$2:$C$571=$E$1)*(A9>Task_Table1!$J$2:$J$571)*(A9<Task_Table1!$K$2:$K$571))} -> 1
A10: 45878 | B10: {=SUMPRODUCT((Task_Table1!$C$2:$C$571=$B$1)*(A10>Task_Table1!$J$2:$J$571)*(A10<Task_Table1!$K$2:$K$571))} -> 3 | C10: {=SUMPRODUCT((Task_Table1!$C$2:$C$568=$C$1)*(A10>Task_Table1!$J$2:$J$568)*(A10<Task_Table1!$K$2:$K$568))} -> 2 | D10: {=SUMPRODUCT((Task_Table1!$C$2:$C$571=$D$1)*(A10>Task_Table1!$J$2:$J$571)*(A10<Task_Table1!$K$2:$K$571))} -> 0 | E10: {=SUMPRODUCT((Task_Table1!$C$2:$C$571=$E$1)*(A10>Task_Table1!$J$2:$J$571)*(A10<Task_Table1!$K$2:$K$571))} -> 1
A11: 45879 | B11: {=SUMPRODUCT((Task_Table1!$C$2:$C$571=$B$1)*(A11>Task_Table1!$J$2:$J$571)*(A11<Task_Table1!$K$2:$K$571))} -> 3 | C11: {=SUMPRODUCT((Task_Table1!$C$2:$C$568=$C$1)*(A11>Task_Table1!$J$2:$J$568)*(A11<Task_Table1!$K$2:$K$568))} -> 2 | D11: {=SUMPRODUCT((Task_Table1!$C$2:$C$571=$D$1)*(A11>Task_Table1!$J$2:$J$571)*(A11<Task_Table1!$K$2:$K$571))} -> 0 | E11: {=SUMPRODUCT((Task_Table1!$C$2:$C$571=$E$1)*(A11>Task_Table1!$J$2:$J$571)*(A11<Task_Table1!$K$2:$K$571))} -> 1
A12: 45880 | B12: {=SUMPRODUCT((Task_Table1!$C$2:$C$571=$B$1)*(A12>Task_Table1!$J$2:$J$571)*(A12<Task_Table1!$K$2:$K$571))} -> 3 | C12: {=SUMPRODUCT((Task_Table1!$C$2:$C$568=$C$1)*(A12>Task_Table1!$J$2:$J$568)*(A12<Task_Table1!$K$2:$K$568))} -> 2 | D12: {=SUMPRODUCT((Task_Table1!$C$2:$C$571=$D$1)*(A12>Task_Table1!$J$2:$J$571)*(A12<Task_Table1!$K$2:$K$571))} -> 0 | E12: {=SUMPRODUCT((Task_Table1!$C$2:$C$571=$E$1)*(A12>Task_Table1!$J$2:$J$571)*(A12<Task_Table1!$K$2:$K$571))} -> 1
A13: 45881 | B13: {=SUMPRODUCT((Task_Table1!$C$2:$C$571=$B$1)*(A13>Task_Table1!$J$2:$J$571)*(A13<Task_Table1!$K$2:$K$571))} -> 3 | C13: {=SUMPRODUCT((Task_Table1!$C$2:$C$568=$C$1)*(A13>Task_Table1!$J$2:$J$568)*(A13<Task_Table1!$K$2:$K$568))} -> 2 | D13: {=SUMPRODUCT((Task_Table1!$C$2:$C$571=$D$1)*(A13>Task_Table1!$J$2:$J$571)*(A13<Task_Table1!$K$2:$K$571))} -> 0 | E13: {=SUMPRODUCT((Task_Table1!$C$2:$C$571=$E$1)*(A13>Task_Table1!$J$2:$J$571)*(A13<Task_Table1!$K$2:$K$571))} -> 1
A14: 45882 | B14: {=SUMPRODUCT((Task_Table1!$C$2:$C$571=$B$1)*(A14>Task_Table1!$J$2:$J$571)*(A14<Task_Table1!$K$2:$K$571))} -> 3 | C14: {=SUMPRODUCT((Task_Table1!$C$2:$C$568=$C$1)*(A14>Task_Table1!$J$2:$J$568)*(A14<Task_Table1!$K$2:$K$568))} -> 2 | D14: {=SUMPRODUCT((Task_Table1!$C$2:$C$571=$D$1)*(A14>Task_Table1!$J$2:$J$571)*(A14<Task_Table1!$K$2:$K$571))} -> 0 | E14: {=SUMPRODUCT((Task_Table1!$C$2:$C$571=$E$1)*(A14>Task_Table1!$J$2:$J$571)*(A14<Task_Table1!$K$2:$K$571))} -> 1
... A520: 46388 | B520: {=SUMPRODUCT((Task_Table1!$C$2:$C$571=$B$1)*(A520>Task_Table1!$J$2:$J$571)*(A520<Task_Table1!$K$2:$K$571))} -> 1 | C520: {=SUMPRODUCT((Task_Table1!$C$2:$C$568=$C$1)*(A520>Task_Table1!$J$2:$J$568)*(A520<Task_Table1!$K$2:$K$568))} -> 0 | D520: {=SUMPRODUCT((Task_Table1!$C$2:$C$571=$D$1)*(A520>Task_Table1!$J$2:$J$571)*(A520<Task_Table1!$K$2:$K$571))} -> 0 | E520: {=SUMPRODUCT((Task_Table1!$C$2:$C$571=$E$1)*(A520>Task_Table1!$J$2:$J$571)*(A520<Task_Table1!$K$2:$K$571))} -> 0

Sheet Task_Table_02_26
A1: Initiative | B1: Process | C1: Phase | D1: Process level | E1: Process Group | F1: % Work Complete | G1: IT Process Consultant | H1: Responsible | I1: IT Process Manager | L1: Duration2 | M1: Process approval date | N1: Actual Phase | O1: Planned phase | P1: Associated Process on L1
A2: Corporate IT body | B2: Manage IT strategy | C2: Total | D2: L1 | E2: MP | F2: 0.15 | J2: 46029 | K2: 46203 | L2: =NETWORKDAYS(J2,K2) -> 125 | M2: 45953 | P2: Manage IT strategy
A3: Corporate IT body | B3: Manage IT strategy | C3: Elaboration | D3: L1 | E3: MP | F3: 0.15 | G3: Kunz Christina (LIS-MHP Management- und IT Beratung GmbH) | H3: Felder Max (LLI) | I3: Mielenz Thomas (LMT) | J3: 46029 | K3: 46097 | L3: =NETWORKDAYS(J3,K3) -> 49 | N3: Elaboration in progress | O3: Elaboration in progress | P3: Manage IT strategy
A4: Corporate IT body | B4: Manage IT strategy | C4: Implementation LIS | D4: L1 | E4: MP | F4: 0 | J4: 46127 | K4: 46203 | L4: =NETWORKDAYS(J4,K4) -> 55 | O4: Scheduled | P4: Manage IT strategy
A5: Corporate IT body | B5: Manage IT strategy | C5: Implementation COT | D5: L1 | E5: MP | F5: 0 | L5: =NETWORKDAYS(J5,K5) -> 0 | P5: Manage IT strategy
A6: Corporate IT body | B6: Manage IT strategy | C6: Implementation LUS | D6: L1 | E6: MP | F6: 0 | L6: =NETWORKDAYS(J6,K6) -> 0 | P6: Manage IT strategy
A7: Corporate IT body | B7: Manage IT governance framework | C7: Total | D7: L1 | E7: MP | F7: 0 | J7: 46029 | K7: 46203 | L7: =NETWORKDAYS(J7,K7) -> 125 | P7: Manage IT governance framework
A8: Corporate IT body | B8: Manage IT governance framework | C8: Elaboration | D8: L1 | E8: MP | F8: 0 | G8: Kunz Christina (LIS-MHP Management- und IT Beratung GmbH) | H8: Felder Max (LLI) | I8: Mielenz Thomas (LMT) | J8: 46029 | K8: 46097 | L8: =NETWORKDAYS(J8,K8) -> 49 | N8: Delayed | O8: Elaboration in progress | P8: Manage IT governance framework
A9: Corporate IT body | B9: Manage IT governance framework | C9: Implementation LIS | D9: L1 | E9: MP | F9: 0 | J9: 46127 | K9: 46203 | L9: =NETWORKDAYS(J9,K9) -> 55 | O9: Scheduled | P9: Manage IT governance framework
A10: Corporate IT body | B10: Manage IT governance framework | C10: Implementation COT | D10: L1 | E10: MP | F10: 0 | L10: =NETWORKDAYS(J10,K10) -> 0 | P10: Manage IT governance framework
A11: Corporate IT body | B11: Manage IT governance framework | C11: Implementation LUS | D11: L1 | E11: MP | F11: 0 | L11: =NETWORKDAYS(J11,K11) -> 0 | P11: Manage IT governance framework
A12: Corporate IT body | B12: Maintain IT glossary | C12: Total | D12: L2 | E12: MP | F12: 0 | L12: =NETWORKDAYS(J12,K12) -> 0 | P12: Manage IT governance framework
A13: Corporate IT body | B13: Maintain IT glossary | C13: Elaboration | D13: L2 | E13: MP | F13: 0 | G13: Kunz Christina (LIS-MHP Management- und IT Beratung GmbH) | H13: Felder Max (LLI) | I13: Mielenz Thomas (LMT) | J13: 46029 | P13: Manage IT governance framework
A14: Corporate IT body | B14: Maintain IT glossary | C14: Implementation LIS | D14: L2 | E14: MP | F14: 0 | J14: 46029 | K14: 46039 | L14: =NETWORKDAYS(J14,K14) -> 8 | N14: Delayed | O14: Implementation LIS Done | P14: Manage IT governance framework
A15: Corporate IT body | B15: Maintain IT glossary | C15: Implementation COT | D15: L2 | E15: MP | F15: 0 | J15: 46029 | P15: Manage IT governance framework
A16: Corporate IT body | B16: Maintain IT glossary | C16: Implementation LUS | D16: L2 | E16: MP | F16: 0 | L16: =NETWORKDAYS(J16,K16) -> 0 | P16: Manage IT governance framework
A17: Corporate IT body | B17: Manage enterprise architecture | C17: Total | D17: L1 | E17: MP | F17: 0 | J17: 45946 | K17: 46205 | L17: =NETWORKDAYS(J17,K17) -> 186 | P17: Manage enterprise architecture
A18: Corporate IT body | B18: Manage enterprise architecture | C18: Elaboration | D18: L1 | E18: MP | F18: 0 | G18: Hoermann Patrick (LLI) | H18: Gujral Parth (COB-COT-IT) | I18: Nussbaumer Florian (LBC) | J18: 46062 | K18: 46136 | L18: =NETWORKDAYS(J18,K18) -> 55 | N18: Delayed | O18: Elaboration in progress | P18: Manage enterprise architecture
A19: Corporate IT body | B19: Manage enterprise architecture | C19: Implementation LIS | D19: L1 | E19: MP | F19: 0 | J19: 46136 | K19: 46205 | L19: =NETWORKDAYS(J19,K19) -> 50 | O19: Scheduled | P19: Manage enterprise architecture
A20: Corporate IT body | B20: Manage enterprise architecture | C20: Implementation COT | D20: L1 | E20: MP | F20: 0 | J20: 46062 | K20: 46062 | L20: =NETWORKDAYS(J20,K20) -> 1 | N20: Delayed | O20: Implementation COT Done | P20: Manage enterprise architecture
A21: Corporate IT body | B21: Manage enterprise architecture | C21: Implementation LUS | D21: L1 | E21: MP | F21: 0 | J21: 46142 | K21: 46142 | L21: =NETWORKDAYS(J21,K21) -> 1 | O21: Scheduled | P21: Manage enterprise architecture
A22: Corporate IT body | B22: Strategic architecture process | C22: Total | D22: L2 | E22: MP | F22: 0 | J22: 45946 | K22: 46142 | L22: =NETWORKDAYS(J22,K22) -> 141 | P22: Manage enterprise architecture
A23: Corporate IT body | B23: Strategic architecture process | C23: Elaboration | D23: L2 | E23: MP | F23: 0 | G23: Hoermann Patrick (LLI) | H23: Gujral Parth (COB-COT-IT) | I23: Nussbaumer Florian (LBC) | J23: 45946 | K23: 45946 | L23: =NETWORKDAYS(J23,K23) -> 1 | N23: Delayed | O23: Elaboration Done | P23: Manage enterprise architecture
A24: Corporate IT body | B24: Strategic architecture process | C24: Implementation LIS | D24: L2 | E24: MP | F24: 0 | K24: 46142 | P24: Manage enterprise architecture
A25: Corporate IT body | B25: Strategic architecture process | C25: Implementation COT | D25: L2 | E25: MP | F25: 0 | J25: 45946 | K25: 45946 | L25: =NETWORKDAYS(J25,K25) -> 1 | N25: Delayed | O25: Implementation COT Done | P25: Manage enterprise architecture
A26: Corporate IT body | B26: Strategic architecture process | C26: Implementation LUS | D26: L2 | E26: MP | F26: 0 | J26: 45946 | K26: 45946 | L26: =NETWORKDAYS(J26,K26) -> 1 | N26: Delayed | O26: Implementation LUS Done | P26: Manage enterprise architecture
A27: ITSM | B27: Manage IT portfolio | C27: Total | D27: L1 | E27: MP | F27: 0.11 | J27: 45971 | K27: 46157 | L27: =NETWORKDAYS(J27,K27) -> 135 | P27: Manage IT portfolio
A28: ITSM | B28: Manage IT portfolio | C28: Elaboration | D28: L1 | E28: MP | F28: 0 | G28: Frank Maren (LIS);Kunz Christina (LIS-MHP Management- und IT Beratung GmbH) | H28: ? | J28: 45972 | K28: 46051 | L28: =NETWORKDAYS(J28,K28) -> 58 | N28: Delayed | O28: Elaboration Done | P28: Manage IT portfolio
A29: ITSM | B29: Manage IT portfolio | C29: Implementation LIS | D29: L1 | E29: MP | F29: 0 | L29: =NETWORKDAYS(J29,K29) -> 0 | P29: Manage IT portfolio
A30: ITSM | B30: Manage IT portfolio | C30: Implementation COT | D30: L1 | E30: MP | F30: 0 | J30: 45971 | P30: Manage IT portfolio
A31: ITSM | B31: Manage IT portfolio | C31: Implementation LUS | D31: L1 | E31: MP | F31: 0 | L31: =NETWORKDAYS(J31,K31) -> 0 | P31: Manage IT portfolio
A32: IT project management | B32: Manage IT project portfolio | C32: Total | D32: L2 | E32: MP | F32: 1 | J32: 45939 | K32: 46001 | L32: =NETWORKDAYS(J32,K32) -> 45 | P32: Manage IT portfolio
A33: IT project management | B33: Manage IT project portfolio | C33: Elaboration | D33: L2 | E33: MP | F33: 1 | G33: Frank Maren (LIS) | H33: Mühlbacher Christian (LIS) | I33: Rollinger Alexander (LIS) | J33: 45971 | K33: 46001 | L33: =NETWORKDAYS(J33,K33) -> 23 | M33: 46050 | N33: Elaboration Done | O33: Elaboration Done | P33: Manage IT portfolio
A34: IT project management | B34: Manage IT project portfolio | C34: Implementation LIS | D34: L2 | E34: MP | F34: 0 | J34: 45939 | P34: Manage IT portfolio
A35: IT project management | B35: Manage IT project portfolio | C35: Implementation COT | D35: L2 | E35: MP | F35: 0 | L35: =NETWORKDAYS(J35,K35) -> 0 | P35: Manage IT portfolio
A36: IT project management | B36: Manage IT project portfolio | C36: Implementation LUS | D36: L2 | E36: MP | F36: 0 | L36: =NETWORKDAYS(J36,K36) -> 0 | P36: Manage IT portfolio
A37: ITSM | B37: Manage IT service portfolio | C37: Total | D37: L2 | E37: MP | F37: 0 | J37: 46076 | K37: 46203 | L37: =NETWORKDAYS(J37,K37) -> 92 | P37: Manage IT portfolio
A38: ITSM | B38: Manage IT service portfolio | C38: Elaboration | D38: L2 | E38: MP | F38: 0 | G38: Frank Maren (LIS);Kunz Christina (LIS-MHP Management- und IT Beratung GmbH) | H38: ? | I38: Reiner Heiko (HAU-ITSA) | J38: 46076 | K38: 46118 | L38: =NETWORKDAYS(J38,K38) -> 31 | O38: Scheduled | P38: Manage IT portfolio
A39: ITSM | B39: Manage IT service portfolio | C39: Implementation LIS | D39: L2 | E39: MP | F39: 0 | J39: 46118 | K39: 46203 | L39: =NETWORKDAYS(J39,K39) -> 62 | O39: Scheduled | P39: Manage IT portfolio
A40: ITSM | B40: Manage IT service portfolio | C40: Implementation COT | D40: L2 | E40: MP | F40: 0 | L40: =NETWORKDAYS(J40,K40) -> 0 | P40: Manage IT portfolio
A41: ITSM | B41: Manage IT service portfolio | C41: Implementation LUS | D41: L2 | E41: MP | F41: 0 | L41: =NETWORKDAYS(J41,K41) -> 0 | P41: Manage IT portfolio
A42: IT planning and steering | B42: Manage and control IT financials | C42: Total | D42: L1 | E42: MP | F42: 0 | I42: Moser Mario (LIS-LAH) | J42: 45945 | K42: 46295 | L42: =NETWORKDAYS(J42,K42) -> 251 | P42: Manage and control IT financials
A43: IT planning and steering | B43: Manage and control IT financials | C43: Elaboration | D43: L1 | E43: MP | F43: 0 | G43: Hynek Tobias (LIS);Kreis Andreas (LLI) | H43: Frank Nicole (LIS) | I43: Moser Mario (LIS-LAH) | L43: =NETWORKDAYS(J43,K43) -> 0 | P43: Manage and control IT financials
A44: IT planning and steering | B44: Manage and control IT financials | C44: Implementation LIS | D44: L1 | E44: MP | F44: 0 | L44: =NETWORKDAYS(J44,K44) -> 0 | P44: Manage and control IT financials
A45: IT planning and steering | B45: Manage and control IT financials | C45: Implementation COT | D45: L2 | E45: MP | F45: 0 | L45: =NETWORKDAYS(J45,K45) -> 0 | P45: Manage and control IT financials
A46: IT planning and steering | B46: Manage and control IT financials | C46: Implementation LUS | D46: L1 | E46: MP | F46: 0 | L46: =NETWORKDAYS(J46,K46) -> 0 | P46: Manage and control IT financials
A47: IT planning and steering | B47: Create and maintain IT budgets | C47: Total | D47: L2 | E47: MP | F47: 0 | J47: 46029 | K47: 46202 | L47: =NETWORKDAYS(J47,K47) -> 124 | P47: Manage and control IT financials
A48: IT planning and steering | B48: Create and maintain IT budgets | C48: Elaboration | D48: L2 | E48: MP | F48: 0 | G48: Hynek Tobias (LIS);Kreis Andreas (LLI) | H48: Frank Nicole (LIS) | I48: Mielenz Thomas (LMT) | J48: 46029 | K48: 46104 | L48: =NETWORKDAYS(J48,K48) -> 54 | N48: Delayed | O48: Elaboration in progress | P48: Manage and control IT financials
A49: IT planning and steering | B49: Create and maintain IT budgets | C49: Implementation LIS | D49: L2 | E49: MP | F49: 0 | J49: 46118 | K49: 46202 | L49: =NETWORKDAYS(J49,K49) -> 61 | O49: Scheduled | P49: Manage and control IT financials
A50: IT planning and steering | B50: Create and maintain IT budgets | C50: Implementation COT | D50: L2 | E50: MP | F50: 0 | L50: =NETWORKDAYS(J50,K50) -> 0 | P50: Manage and control IT financials
A51: IT planning and steering | B51: Create and maintain IT budgets | C51: Implementation LUS | D51: L2 | E51: MP | F51: 0 | L51: =NETWORKDAYS(J51,K51) -> 0 | P51: Manage and control IT financials
A52: IT planning and steering | B52: Approve and communicate budget plan | C52: Total | D52: L3 | E52: MP | F52: 0 | L52: =NETWORKDAYS(J52,K52) -> 0 | P52: Manage and control IT financials
A53: IT planning and steering | B53: Approve and communicate budget plan | C53: Elaboration | D53: L3 | E53: MP | F53: 0 | G53: Hynek Tobias (LIS);Kreis Andreas (LLI) | H53: Frank Nicole (LIS) | I53: Mielenz Thomas (LMT) | L53: =NETWORKDAYS(J53,K53) -> 0 | P53: Manage and control IT financials
A54: IT planning and steering | B54: Approve and communicate budget plan | C54: Implementation LIS | D54: L3 | E54: MP | F54: 0 | L54: =NETWORKDAYS(J54,K54) -> 0 | P54: Manage and control IT financials
A55: IT planning and steering | B55: Approve and communicate budget plan | C55: Implementation COT | D55: L3 | E55: MP | F55: 0 | L55: =NETWORKDAYS(J55,K55) -> 0 | P55: Manage and control IT financials
A56: IT planning and steering | B56: Approve and communicate budget plan | C56: Implementation LUS | D56: L3 | E56: MP | F56: 0 | L56: =NETWORKDAYS(J56,K56) -> 0 | P56: Manage and control IT financials
A57: IT planning and steering | B57: Collect and consolidate budget from stakeholders | C57: Total | D57: L3 | E57: MP | F57: 0 | L57: =NETWORKDAYS(J57,K57) -> 0 | P57: Manage and control IT financials
A58: IT planning and steering | B58: Collect and consolidate budget from stakeholders | C58: Elaboration | D58: L3 | E58: MP | F58: 0 | G58: Hynek Tobias (LIS);Kreis Andreas (LLI) | H58: Frank Nicole (LIS) | I58: Mielenz Thomas (LMT) | L58: =NETWORKDAYS(J58,K58) -> 0 | P58: Manage and control IT financials
A59: IT planning and steering | B59: Collect and consolidate budget from stakeholders | C59: Implementation LIS | D59: L3 | E59: MP | F59: 0 | L59: =NETWORKDAYS(J59,K59) -> 0 | P59: Manage and control IT financials
A60: IT planning and steering | B60: Collect and consolidate budget from stakeholders | C60: Implementation COT | D60: L3 | E60: MP | F60: 0 | L60: =NETWORKDAYS(J60,K60) -> 0 | P60: Manage and control IT financials
A61: IT planning and steering | B61: Collect and consolidate budget from stakeholders | C61: Implementation LUS | D61: L3 | E61: MP | F61: 0 | L61: =NETWORKDAYS(J61,K61) -> 0 | P61: Manage and control IT financials
A62: IT planning and steering | B62: Develop preliminary budget plan | C62: Total | D62: L3 | E62: MP | F62: 0 | L62: =NETWORKDAYS(J62,K62) -> 0 | P62: Manage and control IT financials
A63: IT planning and steering | B63: Develop preliminary budget plan | C63: Elaboration | D63: L3 | E63: MP | F63: 0 | G63: Hynek Tobias (LIS);Kreis Andreas (LLI) | H63: Frank Nicole (LIS) | I63: Mielenz Thomas (LMT) | L63: =NETWORKDAYS(J63,K63) -> 0 | P63: Manage and control IT financials
A64: IT planning and steering | B64: Develop preliminary budget plan | C64: Implementation LIS | D64: L3 | E64: MP | F64: 0 | L64: =NETWORKDAYS(J64,K64) -> 0 | P64: Manage and control IT financials
A65: IT planning and steering | B65: Develop preliminary budget plan | C65: Implementation COT | D65: L3 | E65: MP | F65: 0 | L65: =NETWORKDAYS(J65,K65) -> 0 | P65: Manage and control IT financials
A66: IT planning and steering | B66: Develop preliminary budget plan | C66: Implementation LUS | D66: L3 | E66: MP | F66: 0 | L66: =NETWORKDAYS(J66,K66) -> 0 | P66: Manage and control IT financials
A67: IT planning and steering | B67: Maintan and adjust budget | C67: Total | D67: L3 | E67: MP | F67: 0 | L67: =NETWORKDAYS(J67,K67) -> 0 | P67: Manage and control IT financials
A68: IT planning and steering | B68: Maintan and adjust budget | C68: Elaboration | D68: L3 | E68: MP | F68: 0 | G68: Hynek Tobias (LIS);Kreis Andreas (LLI) | H68: Frank Nicole (LIS) | I68: Mielenz Thomas (LMT) | L68: =NETWORKDAYS(J68,K68) -> 0 | P68: Manage and control IT financials
A69: IT planning and steering | B69: Maintan and adjust budget | C69: Implementation LIS | D69: L3 | E69: MP | F69: 0 | L69: =NETWORKDAYS(J69,K69) -> 0 | P69: Manage and control IT financials
A70: IT planning and steering | B70: Maintan and adjust budget | C70: Implementation COT | D70: L3 | E70: MP | F70: 0 | L70: =NETWORKDAYS(J70,K70) -> 0 | P70: Manage and control IT financials
A71: IT planning and steering | B71: Maintan and adjust budget | C71: Implementation LUS | D71: L3 | E71: MP | F71: 0 | L71: =NETWORKDAYS(J71,K71) -> 0 | P71: Manage and control IT financials
A72: IT planning and steering | B72: Review budget plan | C72: Total | D72: L3 | E72: MP | F72: 0 | L72: =NETWORKDAYS(J72,K72) -> 0 | O72: 18 | P72: Manage and control IT financials
A73: IT planning and steering | B73: Review budget plan | C73: Elaboration | D73: L3 | E73: MP | F73: 0 | G73: Hynek Tobias (LIS);Kreis Andreas (LLI) | H73: Frank Nicole (LIS) | I73: Mielenz Thomas (LMT) | L73: =NETWORKDAYS(J73,K73) -> 0 | P73: Manage and control IT financials
A74: IT planning and steering | B74: Review budget plan | C74: Implementation LIS | D74: L3 | E74: MP | F74: 0 | L74: =NETWORKDAYS(J74,K74) -> 0 | P74: Manage and control IT financials
A75: IT planning and steering | B75: Review budget plan | C75: Implementation COT | D75: L3 | E75: MP | F75: 0 | L75: =NETWORKDAYS(J75,K75) -> 0 | P75: Manage and control IT financials
A76: IT planning and steering | B76: Review budget plan | C76: Implementation LUS | D76: L3 | E76: MP | F76: 0 | L76: =NETWORKDAYS(J76,K76) -> 0 | P76: Manage and control IT financials
A77: IT planning and steering | B77: Revise and optimize budget plan | C77: Total | D77: L3 | E77: MP | F77: 0 | L77: =NETWORKDAYS(J77,K77) -> 0 | P77: Manage and control IT financials
A78: IT planning and steering | B78: Revise and optimize budget plan | C78: Elaboration | D78: L3 | E78: MP | F78: 0 | G78: Hynek Tobias (LIS);Kreis Andreas (LLI) | H78: Frank Nicole (LIS) | I78: Mielenz Thomas (LMT) | L78: =NETWORKDAYS(J78,K78) -> 0 | P78: Manage and control IT financials
A79: IT planning and steering | B79: Revise and optimize budget plan | C79: Implementation LIS | D79: L3 | E79: MP | F79: 0 | L79: =NETWORKDAYS(J79,K79) -> 0 | P79: Manage and control IT financials
A80: IT planning and steering | B80: Revise and optimize budget plan | C80: Implementation COT | D80: L3 | E80: MP | F80: 0 | L80: =NETWORKDAYS(J80,K80) -> 0 | P80: Manage and control IT financials
A81: IT planning and steering | B81: Revise and optimize budget plan | C81: Implementation LUS | D81: L3 | E81: MP | F81: 0 | L81: =NETWORKDAYS(J81,K81) -> 0 | P81: Manage and control IT financials
A82: IT planning and steering | B82: Manage finance and accounting | C82: Total | D82: L2 | E82: MP | F82: 0 | J82: 45945 | K82: 46104 | L82: =NETWORKDAYS(J82,K82) -> 114 | P82: Manage and control IT financials
A83: IT planning and steering | B83: Manage finance and accounting | C83: Elaboration | D83: L2 | E83: MP | F83: 0 | G83: Hynek Tobias (LIS);Kreis Andreas (LLI) | H83: Frank Nicole (LIS) | I83: Moser Mario (LIS-LAH) | J83: 46029 | K83: 46104 | L83: =NETWORKDAYS(J83,K83) -> 54 | N83: Delayed | O83: Elaboration in progress | P83: Manage and control IT financials
A84: IT planning and steering | B84: Manage finance and accounting | C84: Implementation LIS | D84: L2 | E84: MP | F84: 0 | L84: =NETWORKDAYS(J84,K84) -> 0 | P84: Manage and control IT financials
A85: IT planning and steering | B85: Manage finance and accounting | C85: Implementation COT | D85: L2 | E85: MP | F85: 0 | L85: =NETWORKDAYS(J85,K85) -> 0 | P85: Manage and control IT financials
A86: IT planning and steering | B86: Manage finance and accounting | C86: Implementation LUS | D86: L2 | E86: MP | F86: 0 | L86: =NETWORKDAYS(J86,K86) -> 0 | P86: Manage and control IT financials
A87: IT planning and steering | B87: Define financial management framework | C87: Total | D87: L3 | E87: MP | F87: 0 | L87: =NETWORKDAYS(J87,K87) -> 0 | P87: Manage and control IT financials
A88: IT planning and steering | B88: Define financial management framework | C88: Elaboration | D88: L3 | E88: MP | F88: 0 | G88: Hynek Tobias (LIS);Kreis Andreas (LLI) | H88: Frank Nicole (LIS) | I88: Moser Mario (LIS-LAH) | L88: =NETWORKDAYS(J88,K88) -> 0 | P88: Manage and control IT financials
A89: IT planning and steering | B89: Define financial management framework | C89: Implementation LIS | D89: L3 | E89: MP | F89: 0 | L89: =NETWORKDAYS(J89,K89) -> 0 | P89: Manage and control IT financials
A90: IT planning and steering | B90: Define financial management framework | C90: Implementation COT | D90: L3 | E90: MP | F90: 0 | L90: =NETWORKDAYS(J90,K90) -> 0 | P90: Manage and control IT financials
A91: IT planning and steering | B91: Define financial management framework | C91: Implementation LUS | D91: L3 | E91: MP | F91: 0 | L91: =NETWORKDAYS(J91,K91) -> 0 | P91: Manage and control IT financials
A92: IT planning and steering | B92: Establish financial accounting structure | C92: Total | D92: L3 | E92: MP | F92: 0 | L92: =NETWORKDAYS(J92,K92) -> 0 | P92: Manage and control IT financials
A93: IT planning and steering | B93: Establish financial accounting structure | C93: Elaboration | D93: L3 | E93: MP | F93: 0 | G93: Hynek Tobias (LIS);Kreis Andreas (LLI) | H93: Frank Nicole (LIS) | I93: Moser Mario (LIS-LAH) | L93: =NETWORKDAYS(J93,K93) -> 0 | P93: Manage and control IT financials
A94: IT planning and steering | B94: Establish financial accounting structure | C94: Implementation LIS | D94: L3 | E94: MP | F94: 0 | L94: =NETWORKDAYS(J94,K94) -> 0 | P94: Manage and control IT financials
A95: IT planning and steering | B95: Establish financial accounting structure | C95: Implementation COT | D95: L3 | E95: MP | F95: 0 | L95: =NETWORKDAYS(J95,K95) -> 0 | P95: Manage and control IT financials
A96: IT planning and steering | B96: Establish financial accounting structure | C96: Implementation LUS | D96: L3 | E96: MP | F96: 0 | L96: =NETWORKDAYS(J96,K96) -> 0 | P96: Manage and control IT financials
A97: IT planning and steering | B97: Manage IT costs | C97: Total | D97: L2 | E97: MP | F97: 0 | J97: 46034 | K97: 46195 | L97: =NETWORKDAYS(J97,K97) -> 116 | P97: Manage and control IT financials
A98: IT planning and steering | B98: Manage IT costs | C98: Elaboration | D98: L2 | E98: MP | F98: 0 | G98: Hynek Tobias (LIS);Kreis Andreas (LLI) | H98: Frank Nicole (LIS) | I98: Moser Mario (LIS-LAH) | J98: 46034 | K98: 46112 | L98: =NETWORKDAYS(J98,K98) -> 57 | N98: Delayed | O98: Elaboration in progress | P98: Manage and control IT financials
A99: IT planning and steering | B99: Manage IT costs | C99: Implementation LIS | D99: L2 | E99: MP | F99: 0 | J99: 46119 | K99: 46195 | L99: =NETWORKDAYS(J99,K99) -> 55 | O99: Scheduled | P99: Manage and control IT financials
A100: IT planning and steering | B100: Manage IT costs | C100: Implementation COT | E100: MP | F100: 0 | L100: =NETWORKDAYS(J100,K100) -> 0 | P100: Manage and control IT financials
...

Sheet Date_table_02_26
A1: Datum | B1: Elaboration | C1: Implementation LIS | D1: Implementation LUS | E1: Implementation COT
A2: 45870 | B2: {=SUMPRODUCT((Task_Table_02_26!$C$2:$C$571=$B$1)*(A2>Task_Table_02_26!$J$2:$J$571)*(A2<Task_Table_02_26!$K$2:$K$571))} -> 0 | C2: {=SUMPRODUCT((Task_Table_02_26!$C$2:$C$571=$C$1)*(A2>Task_Table_02_26!$J$2:$J$571)*(A2<Task_Table_02_26!$K$2:$K$571))} -> 2 | D2: {=SUMPRODUCT((Task_Table_02_26!$C$2:$C$571=$D$1)*(A2>Task_Table_02_26!$J$2:$J$571)*(A2<Task_Table_02_26!$K$2:$K$571))} -> 0 | E2: {=SUMPRODUCT((Task_Table_02_26!$C$2:$C$571=$E$1)*(A2>Task_Table_02_26!$J$2:$J$571)*(A2<Task_Table_02_26!$K$2:$K$571))} -> 0
A3: 45871 | B3: {=SUMPRODUCT((Task_Table_02_26!$C$2:$C$571=$B$1)*(A3>Task_Table_02_26!$J$2:$J$571)*(A3<Task_Table_02_26!$K$2:$K$571))} -> 1 | C3: {=SUMPRODUCT((Task_Table_02_26!$C$2:$C$571=$C$1)*(A3>Task_Table_02_26!$J$2:$J$571)*(A3<Task_Table_02_26!$K$2:$K$571))} -> 2 | D3: {=SUMPRODUCT((Task_Table_02_26!$C$2:$C$571=$D$1)*(A3>Task_Table_02_26!$J$2:$J$571)*(A3<Task_Table_02_26!$K$2:$K$571))} -> 0 | E3: {=SUMPRODUCT((Task_Table_02_26!$C$2:$C$571=$E$1)*(A3>Task_Table_02_26!$J$2:$J$571)*(A3<Task_Table_02_26!$K$2:$K$571))} -> 0
A4: 45872 | B4: {=SUMPRODUCT((Task_Table_02_26!$C$2:$C$571=$B$1)*(A4>Task_Table_02_26!$J$2:$J$571)*(A4<Task_Table_02_26!$K$2:$K$571))} -> 1 | C4: {=SUMPRODUCT((Task_Table_02_26!$C$2:$C$571=$C$1)*(A4>Task_Table_02_26!$J$2:$J$571)*(A4<Task_Table_02_26!$K$2:$K$571))} -> 2 | D4: {=SUMPRODUCT((Task_Table_02_26!$C$2:$C$571=$D$1)*(A4>Task_Table_02_26!$J$2:$J$571)*(A4<Task_Table_02_26!$K$2:$K$571))} -> 0 | E4: {=SUMPRODUCT((Task_Table_02_26!$C$2:$C$571=$E$1)*(A4>Task_Table_02_26!$J$2:$J$571)*(A4<Task_Table_02_26!$K$2:$K$571))} -> 0
A5: 45873 | B5: {=SUMPRODUCT((Task_Table_02_26!$C$2:$C$571=$B$1)*(A5>Task_Table_02_26!$J$2:$J$571)*(A5<Task_Table_02_26!$K$2:$K$571))} -> 1 | C5: {=SUMPRODUCT((Task_Table_02_26!$C$2:$C$571=$C$1)*(A5>Task_Table_02_26!$J$2:$J$571)*(A5<Task_Table_02_26!$K$2:$K$571))} -> 2 | D5: {=SUMPRODUCT((Task_Table_02_26!$C$2:$C$571=$D$1)*(A5>Task_Table_02_26!$J$2:$J$571)*(A5<Task_Table_02_26!$K$2:$K$571))} -> 0 | E5: {=SUMPRODUCT((Task_Table_02_26!$C$2:$C$571=$E$1)*(A5>Task_Table_02_26!$J$2:$J$571)*(A5<Task_Table_02_26!$K$2:$K$571))} -> 0
A6: 45874 | B6: {=SUMPRODUCT((Task_Table_02_26!$C$2:$C$571=$B$1)*(A6>Task_Table_02_26!$J$2:$J$571)*(A6<Task_Table_02_26!$K$2:$K$571))} -> 1 | C6: {=SUMPRODUCT((Task_Table_02_26!$C$2:$C$571=$C$1)*(A6>Task_Table_02_26!$J$2:$J$571)*(A6<Task_Table_02_26!$K$2:$K$571))} -> 2 | D6: {=SUMPRODUCT((Task_Table_02_26!$C$2:$C$571=$D$1)*(A6>Task_Table_02_26!$J$2:$J$571)*(A6<Task_Table_02_26!$K$2:$K$571))} -> 0 | E6: {=SUMPRODUCT((Task_Table_02_26!$C$2:$C$571=$E$1)*(A6>Task_Table_02_26!$J$2:$J$571)*(A6<Task_Table_02_26!$K$2:$K$571))} -> 0
A7: 45875 | B7: {=SUMPRODUCT((Task_Table_02_26!$C$2:$C$571=$B$1)*(A7>Task_Table_02_26!$J$2:$J$571)*(A7<Task_Table_02_26!$K$2:$K$571))} -> 1 | C7: {=SUMPRODUCT((Task_Table_02_26!$C$2:$C$571=$C$1)*(A7>Task_Table_02_26!$J$2:$J$571)*(A7<Task_Table_02_26!$K$2:$K$571))} -> 2 | D7: {=SUMPRODUCT((Task_Table_02_26!$C$2:$C$571=$D$1)*(A7>Task_Table_02_26!$J$2:$J$571)*(A7<Task_Table_02_26!$K$2:$K$571))} -> 0 | E7: {=SUMPRODUCT((Task_Table_02_26!$C$2:$C$571=$E$1)*(A7>Task_Table_02_26!$J$2:$J$571)*(A7<Task_Table_02_26!$K$2:$K$571))} -> 0
A8: 45876 | B8: {=SUMPRODUCT((Task_Table_02_26!$C$2:$C$571=$B$1)*(A8>Task_Table_02_26!$J$2:$J$571)*(A8<Task_Table_02_26!$K$2:$K$571))} -> 1 | C8: {=SUMPRODUCT((Task_Table_02_26!$C$2:$C$571=$C$1)*(A8>Task_Table_02_26!$J$2:$J$571)*(A8<Task_Table_02_26!$K$2:$K$571))} -> 2 | D8: {=SUMPRODUCT((Task_Table_02_26!$C$2:$C$571=$D$1)*(A8>Task_Table_02_26!$J$2:$J$571)*(A8<Task_Table_02_26!$K$2:$K$571))} -> 0 | E8: {=SUMPRODUCT((Task_Table_02_26!$C$2:$C$571=$E$1)*(A8>Task_Table_02_26!$J$2:$J$571)*(A8<Task_Table_02_26!$K$2:$K$571))} -> 0
A9: 45877 | B9: {=SUMPRODUCT((Task_Table_02_26!$C$2:$C$571=$B$1)*(A9>Task_Table_02_26!$J$2:$J$571)*(A9<Task_Table_02_26!$K$2:$K$571))} -> 1 | C9: {=SUMPRODUCT((Task_Table_02_26!$C$2:$C$571=$C$1)*(A9>Task_Table_02_26!$J$2:$J$571)*(A9<Task_Table_02_26!$K$2:$K$571))} -> 2 | D9: {=SUMPRODUCT((Task_Table_02_26!$C$2:$C$571=$D$1)*(A9>Task_Table_02_26!$J$2:$J$571)*(A9<Task_Table_02_26!$K$2:$K$571))} -> 0 | E9: {=SUMPRODUCT((Task_Table_02_26!$C$2:$C$571=$E$1)*(A9>Task_Table_02_26!$J$2:$J$571)*(A9<Task_Table_02_26!$K$2:$K$571))} -> 0
A10: 45878 | B10: {=SUMPRODUCT((Task_Table_02_26!$C$2:$C$571=$B$1)*(A10>Task_Table_02_26!$J$2:$J$571)*(A10<Task_Table_02_26!$K$2:$K$571))} -> 1 | C10: {=SUMPRODUCT((Task_Table_02_26!$C$2:$C$571=$C$1)*(A10>Task_Table_02_26!$J$2:$J$571)*(A10<Task_Table_02_26!$K$2:$K$571))} -> 2 | D10: {=SUMPRODUCT((Task_Table_02_26!$C$2:$C$571=$D$1)*(A10>Task_Table_02_26!$J$2:$J$571)*(A10<Task_Table_02_26!$K$2:$K$571))} -> 0 | E10: {=SUMPRODUCT((Task_Table_02_26!$C$2:$C$571=$E$1)*(A10>Task_Table_02_26!$J$2:$J$571)*(A10<Task_Table_02_26!$K$2:$K$571))} -> 0
A11: 45879 | B11: {=SUMPRODUCT((Task_Table_02_26!$C$2:$C$571=$B$1)*(A11>Task_Table_02_26!$J$2:$J$571)*(A11<Task_Table_02_26!$K$2:$K$571))} -> 1 | C11: {=SUMPRODUCT((Task_Table_02_26!$C$2:$C$571=$C$1)*(A11>Task_Table_02_26!$J$2:$J$571)*(A11<Task_Table_02_26!$K$2:$K$571))} -> 2 | D11: {=SUMPRODUCT((Task_Table_02_26!$C$2:$C$571=$D$1)*(A11>Task_Table_02_26!$J$2:$J$571)*(A11<Task_Table_02_26!$K$2:$K$571))} -> 0 | E11: {=SUMPRODUCT((Task_Table_02_26!$C$2:$C$571=$E$1)*(A11>Task_Table_02_26!$J$2:$J$571)*(A11<Task_Table_02_26!$K$2:$K$571))} -> 0
A12: 45880 | B12: {=SUMPRODUCT((Task_Table_02_26!$C$2:$C$571=$B$1)*(A12>Task_Table_02_26!$J$2:$J$571)*(A12<Task_Table_02_26!$K$2:$K$571))} -> 1 | C12: {=SUMPRODUCT((Task_Table_02_26!$C$2:$C$571=$C$1)*(A12>Task_Table_02_26!$J$2:$J$571)*(A12<Task_Table_02_26!$K$2:$K$571))} -> 2 | D12: {=SUMPRODUCT((Task_Table_02_26!$C$2:$C$571=$D$1)*(A12>Task_Table_02_26!$J$2:$J$571)*(A12<Task_Table_02_26!$K$2:$K$571))} -> 0 | E12: {=SUMPRODUCT((Task_Table_02_26!$C$2:$C$571=$E$1)*(A12>Task_Table_02_26!$J$2:$J$571)*(A12<Task_Table_02_26!$K$2:$K$571))} -> 0
A13: 45881 | B13: {=SUMPRODUCT((Task_Table_02_26!$C$2:$C$571=$B$1)*(A13>Task_Table_02_26!$J$2:$J$571)*(A13<Task_Table_02_26!$K$2:$K$571))} -> 1 | C13: {=SUMPRODUCT((Task_Table_02_26!$C$2:$C$571=$C$1)*(A13>Task_Table_02_26!$J$2:$J$571)*(A13<Task_Table_02_26!$K$2:$K$571))} -> 2 | D13: {=SUMPRODUCT((Task_Table_02_26!$C$2:$C$571=$D$1)*(A13>Task_Table_02_26!$J$2:$J$571)*(A13<Task_Table_02_26!$K$2:$K$571))} -> 0 | E13: {=SUMPRODUCT((Task_Table_02_26!$C$2:$C$571=$E$1)*(A13>Task_Table_02_26!$J$2:$J$571)*(A13<Task_Table_02_26!$K$2:$K$571))} -> 0
... A520: 46388 | B520: {=SUMPRODUCT((Task_Table_02_26!$C$2:$C$571=$B$1)*(A520>Task_Table_02_26!$J$2:$J$571)*(A520<Task_Table_02_26!$K$2:$K$571))} -> 1 | C520: {=SUMPRODUCT((Task_Table_02_26!$C$2:$C$571=$C$1)*(A520>Task_Table_02_26!$J$2:$J$571)*(A520<Task_Table_02_26!$K$2:$K$571))} -> 0 | D520: {=SUMPRODUCT((Task_Table_02_26!$C$2:$C$571=$D$1)*(A520>Task_Table_02_26!$J$2:$J$571)*(A520<Task_Table_02_26!$K$2:$K$571))} -> 0 | E520: {=SUMPRODUCT((Task_Table_02_26!$C$2:$C$571=$E$1)*(A520>Task_Table_02_26!$J$2:$J$571)*(A520<Task_Table_02_26!$K$2:$K$571))} -> 0

Sheet Task_table_03_26
A1: Initiative | B1: Process | C1: Phase | D1: Process level | E1: Process Group | F1: % Arbeit abgeschlossen | G1: IT Process Consultant | H1: IT Process Initiative Lead | I1: IT Process Manager | J1: Anfang | K1: Ende | L1: Dauer2 | M1: Process Approval Date | N1: Actual Phase | O1: Planned phase | P1: Associated Process on L1 | R1: 📌 Analyse
A2: Corporate IT body | B2: Manage IT strategy | C2: Total | D2: L1 | E2: MP | F2: 0.5 | J2: 46055 | K2: 46232 | L2: 128 | M2: Mit 06.05.26 | O2: 1 | P2: Manage IT strategy | R2: Prozesse in Elaboration | S2: 39
A3: Corporate IT body | B3: Manage IT strategy | C3: Elaboration | D3: L1 | E3: MP | F3: 0.5 | G3: Kreis Andreas (LLI) | H3: Felder Max (LLI) | I3: Mielenz Thomas (LMT) | J3: 46055 | K3: 46142 | L3: 64 | M3: NV | N3: Elaboration in progress | O3: Elaboration in progress | P3: Manage IT strategy
A4: Corporate IT body | B4: Manage IT strategy | C4: Implementation LIS | D4: L1 | E4: MP | F4: 0 | J4: 46156 | K4: 46232 | L4: 55 | M4: NV | O4: Scheduled | P4: Manage IT strategy
A5: Corporate IT body | B5: Manage IT strategy | C5: Implementation COT | D5: L1 | E5: MP | F5: 0 | J5: ? | K5: ? | L5: 0 | M5: NV | P5: Manage IT strategy
A6: Corporate IT body | B6: Manage IT strategy | C6: Implementation LUS | D6: L1 | E6: MP | F6: 0 | J6: ? | K6: ? | L6: 0 | M6: NV | P6: Manage IT strategy
A7: Corporate IT body | B7: Manage IT governance framework | C7: Total | D7: L1 | E7: MP | F7: 0.5 | J7: 46029 | K7: 46265 | L7: 169 | M7: NV | P7: Manage IT governance framework
A8: Corporate IT body | B8: Manage IT governance framework | C8: Elaboration | D8: L1 | E8: MP | F8: 0.5 | G8: Kunz Christina (LIS-MHP Management- und IT Beratung GmbH);Kreis Andreas (LLI) | H8: Felder Max (LLI) | I8: Mielenz Thomas (LMT) | J8: 46097 | K8: 46163 | L8: 49 | M8: NV | N8: Elaboration in progress | O8: Elaboration in progress | P8: Manage IT governance framework
A9: Corporate IT body | B9: Manage IT governance framework | C9: Implementation LIS | D9: L1 | E9: MP | F9: 0 | J9: 46167 | K9: 46265 | L9: 71 | M9: NV | O9: Scheduled | P9: Manage IT governance framework
A10: Corporate IT body | B10: Manage IT governance framework | C10: Implementation COT | D10: L1 | E10: MP | F10: 0 | J10: ? | K10: ? | L10: 0 | M10: NV | P10: Manage IT governance framework
A11: Corporate IT body | B11: Manage IT governance framework | C11: Implementation LUS | D11: L1 | E11: MP | F11: 0 | J11: ? | K11: ? | L11: 0 | M11: NV | P11: Manage IT governance framework
A12: Corporate IT body | B12: Maintain IT glossary | C12: Total | D12: L2 | E12: MP | F12: 0.25 | J12: 46029 | K12: 46039 | L12: 8 | M12: NV | P12: Manage IT governance framework
A13: Corporate IT body | B13: Maintain IT glossary | C13: Elaboration | D13: L2 | E13: MP | F13: 0.25 | G13: Kunz Christina (LIS-MHP Management- und IT Beratung GmbH) | H13: Felder Max (LLI) | I13: Mielenz Thomas (LMT) | J13: 46029 | K13: ? | L13: 0 | M13: NV | P13: Manage IT governance framework
A14: Corporate IT body | B14: Maintain IT glossary | C14: Implementation LIS | D14: L2 | E14: MP | F14: 0 | J14: 46029 | K14: 46039 | L14: 7 | M14: NV | N14: Delayed | O14: Implementation LIS Done | P14: Manage IT governance framework
A15: Corporate IT body | B15: Maintain IT glossary | C15: Implementation COT | D15: L2 | E15: MP | F15: 0 | J15: 46029 | K15: ? | L15: 0 | M15: NV | P15: Manage IT governance framework
A16: Corporate IT body | B16: Maintain IT glossary | C16: Implementation LUS | D16: L2 | E16: MP | F16: 0 | J16: ? | K16: ? | L16: 0 | M16: NV | P16: Manage IT governance framework
A17: Corporate IT body | B17: Manage enterprise architecture | C17: Total | D17: L1 | E17: MP | F17: 0.24 | J17: 45946 | K17: 46219 | L17: 195.85 | M17: NV | P17: Manage enterprise architecture
A18: Corporate IT body | B18: Manage enterprise architecture | C18: Elaboration | D18: L1 | E18: MP | F18: 0 | G18: Hoermann Patrick (LLI) | H18: Gujral Parth (COB-COT-IT) | I18: Nussbaumer Florian (LBC) | J18: 46076 | K18: 46150 | L18: 54.85 | M18: NV | N18: Delayed | O18: Elaboration in progress | P18: Manage enterprise architecture
A19: Corporate IT body | B19: Manage enterprise architecture | C19: Implementation LIS | D19: L1 | E19: MP | F19: 0 | J19: 46150 | K19: 46219 | L19: 49 | M19: NV | O19: Scheduled | P19: Manage enterprise architecture
A20: Corporate IT body | B20: Manage enterprise architecture | C20: Implementation COT | D20: L1 | E20: MP | F20: 0 | J20: 46150 | K20: 46153 | L20: 1 | M20: NV | O20: Scheduled | P20: Manage enterprise architecture
A21: Corporate IT body | B21: Manage enterprise architecture | C21: Implementation LUS | D21: L1 | E21: MP | F21: 0 | J21: 46150 | K21: 46153 | L21: 1 | M21: NV | O21: Scheduled | P21: Manage enterprise architecture
A22: Corporate IT body | B22: Strategic architecture process | C22: Total | D22: L2 | E22: MP | F22: 0.5 | J22: 45946 | K22: 46142 | L22: 141 | M22: NV | P22: Manage enterprise architecture
A23: Corporate IT body | B23: Strategic architecture process | C23: Elaboration | D23: L2 | E23: MP | F23: 0.5 | G23: Hoermann Patrick (LLI) | H23: Gujral Parth (COB-COT-IT) | I23: Nussbaumer Florian (LBC) | J23: 46076 | K23: 46142 | L23: 49 | M23: NV | N23: Elaboration in progress | O23: Elaboration in progress | P23: Manage enterprise architecture
A24: Corporate IT body | B24: Strategic architecture process | C24: Implementation LIS | D24: L2 | E24: MP | F24: 0 | J24: ? | K24: ? | L24: 0 | M24: NV | P24: Manage enterprise architecture
A25: Corporate IT body | B25: Strategic architecture process | C25: Implementation COT | D25: L2 | E25: MP | F25: 0 | J25: ? | K25: ? | L25: 0 | M25: NV | P25: Manage enterprise architecture
A26: Corporate IT body | B26: Strategic architecture process | C26: Implementation LUS | D26: L2 | E26: MP | F26: 0 | J26: ? | K26: ? | L26: 0 | M26: NV | P26: Manage enterprise architecture
A27: ITSM | B27: Manage IT portfolio | C27: Total | D27: L1 | E27: MP | F27: 0.69 | J27: 45971 | K27: 46157 | L27: 135 | M27: NV | P27: Manage IT portfolio
A28: ITSM | B28: Manage IT portfolio | C28: Elaboration | D28: L1 | E28: MP | F28: 1 | G28: Frank Maren (LIS);Kunz Christina (LIS-MHP Management- und IT Beratung GmbH) | J28: 45972 | K28: 46051 | L28: 58 | M28: NV | N28: Elaboration Done | O28: Elaboration Done | P28: Manage IT portfolio
A29: ITSM | B29: Manage IT portfolio | C29: Implementation LIS | D29: L1 | E29: MP | F29: 0 | J29: ? | K29: ? | L29: 0 | M29: NV | P29: Manage IT portfolio
A30: ITSM | B30: Manage IT portfolio | C30: Implementation COT | D30: L1 | E30: MP | F30: 0 | J30: ? | K30: ? | L30: 0 | M30: NV | P30: Manage IT portfolio
A31: ITSM | B31: Manage IT portfolio | C31: Implementation LUS | D31: L1 | E31: MP | F31: 0 | J31: ? | K31: ? | L31: 0 | M31: NV | P31: Manage IT portfolio
A32: IT project management | B32: Manage IT project portfolio | C32: Total | D32: L2 | E32: MP | F32: 1 | J32: 45971 | K32: 46173 | L32: 145 | M32: NV | P32: Manage IT portfolio
A33: IT project management | B33: Manage IT project portfolio | C33: Elaboration | D33: L2 | E33: MP | F33: 1 | G33: Frank Maren (LIS) | H33: Mühlbacher Christian (LIS) | I33: Rollinger Alexander (LIS) | J33: 45971 | K33: 46001 | L33: 23 | M33: Mit 28.01.26 | N33: Elaboration Done | O33: Elaboration Done | P33: Manage IT portfolio
A34: IT project management | B34: Manage IT project portfolio | C34: Implementation LIS | D34: L2 | E34: MP | F34: 0 | J34: 46054 | K34: 46173 | L34: 85 | M34: NV | N34: Delayed | O34: Implementation LIS | P34: Manage IT portfolio
A35: IT project management | B35: Manage IT project portfolio | C35: Implementation COT | D35: L2 | E35: MP | F35: 0 | J35: ? | K35: ? | L35: 0 | M35: NV | P35: Manage IT portfolio
A36: IT project management | B36: Manage IT project portfolio | C36: Implementation LUS | D36: L2 | E36: MP | F36: 0 | J36: ? | K36: ? | L36: 0 | M36: NV | P36: Manage IT portfolio
A37: ITSM | B37: Manage IT service portfolio | C37: Total | D37: L2 | E37: MP | F37: 0 | J37: 46113 | K37: 46273 | L37: 115 | M37: NV | P37: Manage IT portfolio
A38: ITSM | B38: Manage IT service portfolio | C38: Elaboration | D38: L2 | E38: MP | F38: 0 | G38: Frank Maren (LIS);Kunz Christina (LIS-MHP Management- und IT Beratung GmbH) | H38: Ceilia Roser (LIS) | I38: Reiner Heiko (HAU-ITSA) | J38: 46113 | K38: 46155 | L38: 31 | M38: NV | O38: Scheduled | P38: Manage IT portfolio
A39: ITSM | B39: Manage IT service portfolio | C39: Implementation LIS | D39: L2 | E39: MP | F39: 0 | J39: 46188 | K39: 46273 | L39: 62 | M39: NV | O39: Scheduled | P39: Manage IT portfolio
A40: ITSM | B40: Manage IT service portfolio | C40: Implementation COT | D40: L2 | E40: MP | F40: 0 | J40: ? | K40: ? | L40: 0 | M40: NV | P40: Manage IT portfolio
A41: ITSM | B41: Manage IT service portfolio | C41: Implementation LUS | D41: L2 | E41: MP | F41: 0 | J41: ? | K41: ? | L41: 0 | M41: NV | P41: Manage IT portfolio
A42: IT planning and steering | B42: Manage and control IT financials | C42: Total | D42: L1 | E42: MP | F42: 0.5 | I42: Moser Mario (LIS-LAH) | J42: 45945 | K42: 46234 | L42: 208 | M42: NV | P42: Manage and control IT financials
A43: IT planning and steering | B43: Manage and control IT financials | C43: Elaboration | D43: L1 | E43: MP | F43: 0.5 | G43: Hynek Tobias (LIS);Kreis Andreas (LLI) | H43: Frank Nicole (LIS) | I43: Moser Mario (LIS-LAH) | J43: 45945 | K43: 46142 | L43: 142 | M43: NV | N43: Elaboration in progress | O43: Elaboration in progress | P43: Manage and control IT financials
A44: IT planning and steering | B44: Manage and control IT financials | C44: Implementation LIS | D44: L1 | E44: MP | F44: 0 | J44: 46143 | K44: 46234 | L44: 66 | M44: NV | O44: Scheduled | P44: Manage and control IT financials
A45: IT planning and steering | B45: Manage and control IT financials | C45: Implementation COT | D45: L2 | E45: MP | F45: 0 | J45: ? | K45: ? | L45: 0 | M45: NV | P45: Manage and control IT financials
A46: IT planning and steering | B46: Manage and control IT financials | C46: Implementation LUS | D46: L1 | E46: MP | F46: 0 | J46: ? | K46: ? | L46: 0 | M46: NV | P46: Manage and control IT financials
A47: IT planning and steering | B47: Create and maintain IT budgets | C47: Total | D47: L2 | E47: MP | F47: 0.5 | J47: 45945 | K47: ? | L47: 0 | M47: NV | P47: Manage and control IT financials
A48: IT planning and steering | B48: Create and maintain IT budgets | C48: Elaboration | D48: L2 | E48: MP | F48: 0.5 | G48: Hynek Tobias (LIS);Kreis Andreas (LLI) | H48: Frank Nicole (LIS) | I48: Mielenz Thomas (LMT) | J48: 45945 | K48: ? | L48: 0 | M48: NV | P48: Manage and control IT financials
A49: IT planning and steering | B49: Create and maintain IT budgets | C49: Implementation LIS | D49: L2 | E49: MP | F49: 0 | J49: ? | K49: ? | L49: 0 | M49: NV | P49: Manage and control IT financials
A50: IT planning and steering | B50: Create and maintain IT budgets | C50: Implementation COT | D50: L2 | E50: MP | F50: 0 | J50: ? | K50: ? | L50: 0 | M50: NV | P50: Manage and control IT financials
A51: IT planning and steering | B51: Create and maintain IT budgets | C51: Implementation LUS | D51: L2 | E51: MP | F51: 0 | J51: ? | K51: ? | L51: 0 | M51: NV | P51: Manage and control IT financials
A52: IT planning and steering | B52: Approve and communicate budget plan | C52: Total | D52: L3 | E52: MP | F52: 0.5 | J52: 45945 | K52: ? | L52: 0 | M52: NV | P52: Manage and control IT financials
A53: IT planning and steering | B53: Approve and communicate budget plan | C53: Elaboration | D53: L3 | E53: MP | F53: 0.5 | G53: Hynek Tobias (LIS);Kreis Andreas (LLI) | H53: Frank Nicole (LIS) | I53: Mielenz Thomas (LMT) | J53: 45945 | K53: ? | L53: 0 | M53: NV | P53: Manage and control IT financials
A54: IT planning and steering | B54: Approve and communicate budget plan | C54: Implementation LIS | D54: L3 | E54: MP | F54: 0 | J54: ? | K54: ? | L54: 0 | M54: NV | P54: Manage and control IT financials
A55: IT planning and steering | B55: Approve and communicate budget plan | C55: Implementation COT | D55: L3 | E55: MP | F55: 0 | J55: ? | K55: ? | L55: 0 | M55: NV | P55: Manage and control IT financials
A56: IT planning and steering | B56: Approve and communicate budget plan | C56: Implementation LUS | D56: L3 | E56: MP | F56: 0 | J56: ? | K56: ? | L56: 0 | M56: NV | P56: Manage and control IT financials
A57: IT planning and steering | B57: Collect and consolidate budget from stakeholders | C57: Total | D57: L3 | E57: MP | F57: 0.5 | J57: 45945 | K57: ? | L57: 0 | M57: NV | P57: Manage and control IT financials
A58: IT planning and steering | B58: Collect and consolidate budget from stakeholders | C58: Elaboration | D58: L3 | E58: MP | F58: 0.5 | G58: Hynek Tobias (LIS);Kreis Andreas (LLI) | H58: Frank Nicole (LIS) | I58: Mielenz Thomas (LMT) | J58: 45945 | K58: ? | L58: 0 | M58: NV | P58: Manage and control IT financials
A59: IT planning and steering | B59: Collect and consolidate budget from stakeholders | C59: Implementation LIS | D59: L3 | E59: MP | F59: 0 | J59: ? | K59: ? | L59: 0 | M59: NV | P59: Manage and control IT financials
A60: IT planning and steering | B60: Collect and consolidate budget from stakeholders | C60: Implementation COT | D60: L3 | E60: MP | F60: 0 | J60: ? | K60: ? | L60: 0 | M60: NV | P60: Manage and control IT financials
A61: IT planning and steering | B61: Collect and consolidate budget from stakeholders | C61: Implementation LUS | D61: L3 | E61: MP | F61: 0 | J61: ? | K61: ? | L61: 0 | M61: NV | P61: Manage and control IT financials
A62: IT planning and steering | B62: Develop preliminary budget plan | C62: Total | D62: L3 | E62: MP | F62: 0.5 | J62: 45945 | K62: ? | L62: 0 | M62: NV | P62: Manage and control IT financials
A63: IT planning and steering | B63: Develop preliminary budget plan | C63: Elaboration | D63: L3 | E63: MP | F63: 0.5 | G63: Hynek Tobias (LIS);Kreis Andreas (LLI) | H63: Frank Nicole (LIS) | I63: Mielenz Thomas (LMT) | J63: 45945 | K63: ? | L63: 0 | M63: NV | P63: Manage and control IT financials
A64: IT planning and steering | B64: Develop preliminary budget plan | C64: Implementation LIS | D64: L3 | E64: MP | F64: 0 | J64: ? | K64: ? | L64: 0 | M64: NV | P64: Manage and control IT financials
A65: IT planning and steering | B65: Develop preliminary budget plan | C65: Implementation COT | D65: L3 | E65: MP | F65: 0 | J65: ? | K65: ? | L65: 0 | M65: NV | P65: Manage and control IT financials
A66: IT planning and steering | B66: Develop preliminary budget plan | C66: Implementation LUS | D66: L3 | E66: MP | F66: 0 | J66: ? | K66: ? | L66: 0 | M66: NV | P66: Manage and control IT financials
A67: IT planning and steering | B67: Maintan and adjust budget | C67: Total | D67: L3 | E67: MP | F67: 0.5 | J67: 45945 | K67: ? | L67: 0 | M67: NV | P67: Manage and control IT financials
A68: IT planning and steering | B68: Maintan and adjust budget | C68: Elaboration | D68: L3 | E68: MP | F68: 0.5 | G68: Hynek Tobias (LIS);Kreis Andreas (LLI) | H68: Frank Nicole (LIS) | I68: Mielenz Thomas (LMT) | J68: 45945 | K68: ? | L68: 0 | M68: NV | P68: Manage and control IT financials
A69: IT planning and steering | B69: Maintan and adjust budget | C69: Implementation LIS | D69: L3 | E69: MP | F69: 0 | J69: ? | K69: ? | L69: 0 | M69: NV | P69: Manage and control IT financials
A70: IT planning and steering | B70: Maintan and adjust budget | C70: Implementation COT | D70: L3 | E70: MP | F70: 0 | J70: ? | K70: ? | L70: 0 | M70: NV | P70: Manage and control IT financials
A71: IT planning and steering | B71: Maintan and adjust budget | C71: Implementation LUS | D71: L3 | E71: MP | F71: 0 | J71: ? | K71: ? | L71: 0 | M71: NV | P71: Manage and control IT financials
A72: IT planning and steering | B72: Review budget plan | C72: Total | D72: L3 | E72: MP | F72: 0.5 | J72: 45945 | K72: ? | L72: 0 | M72: NV | O72: 18 | P72: Manage and control IT financials
A73: IT planning and steering | B73: Review budget plan | C73: Elaboration | D73: L3 | E73: MP | F73: 0.5 | G73: Hynek Tobias (LIS);Kreis Andreas (LLI) | H73: Frank Nicole (LIS) | I73: Mielenz Thomas (LMT) | J73: 45945 | K73: ? | L73: 0 | M73: NV | P73: Manage and control IT financials
A74: IT planning and steering | B74: Review budget plan | C74: Implementation LIS | D74: L3 | E74: MP | F74: 0 | J74: ? | K74: ? | L74: 0 | M74: NV | P74: Manage and control IT financials
A75: IT planning and steering | B75: Review budget plan | C75: Implementation COT | D75: L3 | E75: MP | F75: 0 | J75: ? | K75: ? | L75: 0 | M75: NV | P75: Manage and control IT financials
A76: IT planning and steering | B76: Review budget plan | C76: Implementation LUS | D76: L3 | E76: MP | F76: 0 | J76: ? | K76: ? | L76: 0 | M76: NV | P76: Manage and control IT financials
A77: IT planning and steering | B77: Revise and optimize budget plan | C77: Total | D77: L3 | E77: MP | F77: 0.5 | J77: 45945 | K77: ? | L77: 0 | M77: NV | P77: Manage and control IT financials
A78: IT planning and steering | B78: Revise and optimize budget plan | C78: Elaboration | D78: L3 | E78: MP | F78: 0.5 | G78: Hynek Tobias (LIS);Kreis Andreas (LLI) | H78: Frank Nicole (LIS) | I78: Mielenz Thomas (LMT) | J78: 45945 | K78: ? | L78: 0 | M78: NV | P78: Manage and control IT financials
A79: IT planning and steering | B79: Revise and optimize budget plan | C79: Implementation LIS | D79: L3 | E79: MP | F79: 0 | J79: ? | K79: ? | L79: 0 | M79: NV | P79: Manage and control IT financials
A80: IT planning and steering | B80: Revise and optimize budget plan | C80: Implementation COT | D80: L3 | E80: MP | F80: 0 | J80: ? | K80: ? | L80: 0 | M80: NV | P80: Manage and control IT financials
A81: IT planning and steering | B81: Revise and optimize budget plan | C81: Implementation LUS | D81: L3 | E81: MP | F81: 0 | J81: ? | K81: ? | L81: 0 | M81: NV | P81: Manage and control IT financials
A82: IT planning and steering | B82: Manage finance and accounting | C82: Total | D82: L2 | E82: MP | F82: 0.5 | J82: 45945 | K82: ? | L82: 0 | M82: NV | P82: Manage and control IT financials
A83: IT planning and steering | B83: Manage finance and accounting | C83: Elaboration | D83: L2 | E83: MP | F83: 0.5 | G83: Hynek Tobias (LIS);Kreis Andreas (LLI) | H83: Frank Nicole (LIS) | I83: Moser Mario (LIS-LAH) | J83: 45945 | K83: ? | L83: 0 | M83: NV | P83: Manage and control IT financials
A84: IT planning and steering | B84: Manage finance and accounting | C84: Implementation LIS | D84: L2 | E84: MP | F84: 0 | J84: ? | K84: ? | L84: 0 | M84: NV | P84: Manage and control IT financials
A85: IT planning and steering | B85: Manage finance and accounting | C85: Implementation COT | D85: L2 | E85: MP | F85: 0 | J85: ? | K85: ? | L85: 0 | M85: NV | P85: Manage and control IT financials
A86: IT planning and steering | B86: Manage finance and accounting | C86: Implementation LUS | D86: L2 | E86: MP | F86: 0 | J86: ? | K86: ? | L86: 0 | M86: NV | P86: Manage and control IT financials
A87: IT planning and steering | B87: Define financial management framework | C87: Total | D87: L3 | E87: MP | F87: 0.5 | J87: 45945 | K87: ? | L87: 0 | M87: NV | P87: Manage and control IT financials
A88: IT planning and steering | B88: Define financial management framework | C88: Elaboration | D88: L3 | E88: MP | F88: 0.5 | G88: Hynek Tobias (LIS);Kreis Andreas (LLI) | H88: Frank Nicole (LIS) | I88: Moser Mario (LIS-LAH) | J88: 45945 | K88: ? | L88: 0 | M88: NV | P88: Manage and control IT financials
A89: IT planning and steering | B89: Define financial management framework | C89: Implementation LIS | D89: L3 | E89: MP | F89: 0 | J89: ? | K89: ? | L89: 0 | M89: NV | P89: Manage and control IT financials
A90: IT planning and steering | B90: Define financial management framework | C90: Implementation COT | D90: L3 | E90: MP | F90: 0 | J90: ? | K90: ? | L90: 0 | M90: NV | P90: Manage and control IT financials
A91: IT planning and steering | B91: Define financial management framework | C91: Implementation LUS | D91: L3 | E91: MP | F91: 0 | J91: ? | K91: ? | L91: 0 | M91: NV | P91: Manage and control IT financials
A92: IT planning and steering | B92: Establish financial accounting structure | C92: Total | D92: L3 | E92: MP | F92: 0.5 | J92: 45945 | K92: ? | L92: 0 | M92: NV | P92: Manage and control IT financials
A93: IT planning and steering | B93: Establish financial accounting structure | C93: Elaboration | D93: L3 | E93: MP | F93: 0.5 | G93: Hynek Tobias (LIS);Kreis Andreas (LLI) | H93: Frank Nicole (LIS) | I93: Moser Mario (LIS-LAH) | J93: 45945 | K93: ? | L93: 0 | M93: NV | P93: Manage and control IT financials
A94: IT planning and steering | B94: Establish financial accounting structure | C94: Implementation LIS | D94: L3 | E94: MP | F94: 0 | J94: ? | K94: ? | L94: 0 | M94: NV | P94: Manage and control IT financials
A95: IT planning and steering | B95: Establish financial accounting structure | C95: Implementation COT | D95: L3 | E95: MP | F95: 0 | J95: ? | K95: ? | L95: 0 | M95: NV | P95: Manage and control IT financials
A96: IT planning and steering | B96: Establish financial accounting structure | C96: Implementation LUS | D96: L3 | E96: MP | F96: 0 | J96: ? | K96: ? | L96: 0 | M96: NV | P96: Manage and control IT financials
A97: IT planning and steering | B97: Manage IT costs | C97: Total | D97: L2 | E97: MP | F97: 0.5 | J97: 45945 | K97: ? | L97: 0 | M97: NV | P97: Manage and control IT financials
A98: IT planning and steering | B98: Manage IT costs | C98: Elaboration | D98: L2 | E98: MP | F98: 0.5 | G98: Hynek Tobias (LIS);Kreis Andreas (LLI) | H98: Frank Nicole (LIS) | I98: Moser Mario (LIS-LAH) | J98: 45945 | K98: ? | L98: 0 | M98: NV | P98: Manage and control IT financials
A99: IT planning and steering | B99: Manage IT costs | C99: Implementation LIS | D99: L2 | E99: MP | F99: 0 | J99: ? | K99: ? | L99: 0 | M99: NV | P99: Manage and control IT financials
A100: IT planning and steering | B100: Manage IT costs | C100: Implementation COT | E100: MP | F100: 0 | J100: ? | K100: ? | L100: 0 | M100: NV | P100: Manage and control IT financials
...

Sheet Date_table_03_26
A1: Datum | B1: Elaboration | C1: Implementation LIS | D1: Implementation LUS | E1: Implementation COT
A2: 45870 | B2: {=SUMPRODUCT((Task_table_03_2_26!$C$2:$C$596=$B$1)*(A2>Task_table_03_2_26!$J$2:$J$596)*(A2<Task_table_03_2_26!$K$2:$K$596))} -> 0 | C2: {=SUMPRODUCT((Task_table_03_2_26!$C$2:$C$596=$C$1)*(A2>Task_table_03_2_26!$J$2:$J$596)*(A2<Task_table_03_2_26!$K$2:$K$596))} -> 1 | D2: {=SUMPRODUCT((Task_table_03_2_26!$C$2:$C$596=$D$1)*(A2>Task_table_03_2_26!$J$2:$J$596)*(A2<Task_table_03_2_26!$K$2:$K$596))} -> 0 | E2: {=SUMPRODUCT((Task_table_03_2_26!$C$2:$C$596=$E$1)*(A2>Task_table_03_2_26!$J$2:$J$596)*(A2<Task_table_03_2_26!$K$2:$K$596))} -> 0
A3: 45871 | B3: {=SUMPRODUCT((Task_table_03_2_26!$C$2:$C$596=$B$1)*(A3>Task_table_03_2_26!$J$2:$J$596)*(A3<Task_table_03_2_26!$K$2:$K$596))} -> 1 | C3: {=SUMPRODUCT((Task_table_03_2_26!$C$2:$C$596=$C$1)*(A3>Task_table_03_2_26!$J$2:$J$596)*(A3<Task_table_03_2_26!$K$2:$K$596))} -> 1 | D3: {=SUMPRODUCT((Task_table_03_2_26!$C$2:$C$596=$D$1)*(A3>Task_table_03_2_26!$J$2:$J$596)*(A3<Task_table_03_2_26!$K$2:$K$596))} -> 0 | E3: {=SUMPRODUCT((Task_table_03_2_26!$C$2:$C$596=$E$1)*(A3>Task_table_03_2_26!$J$2:$J$596)*(A3<Task_table_03_2_26!$K$2:$K$596))} -> 0
A4: 45872 | B4: {=SUMPRODUCT((Task_table_03_2_26!$C$2:$C$596=$B$1)*(A4>Task_table_03_2_26!$J$2:$J$596)*(A4<Task_table_03_2_26!$K$2:$K$596))} -> 1 | C4: {=SUMPRODUCT((Task_table_03_2_26!$C$2:$C$596=$C$1)*(A4>Task_table_03_2_26!$J$2:$J$596)*(A4<Task_table_03_2_26!$K$2:$K$596))} -> 1 | D4: {=SUMPRODUCT((Task_table_03_2_26!$C$2:$C$596=$D$1)*(A4>Task_table_03_2_26!$J$2:$J$596)*(A4<Task_table_03_2_26!$K$2:$K$596))} -> 0 | E4: {=SUMPRODUCT((Task_table_03_2_26!$C$2:$C$596=$E$1)*(A4>Task_table_03_2_26!$J$2:$J$596)*(A4<Task_table_03_2_26!$K$2:$K$596))} -> 0
A5: 45873 | B5: {=SUMPRODUCT((Task_table_03_2_26!$C$2:$C$596=$B$1)*(A5>Task_table_03_2_26!$J$2:$J$596)*(A5<Task_table_03_2_26!$K$2:$K$596))} -> 1 | C5: {=SUMPRODUCT((Task_table_03_2_26!$C$2:$C$596=$C$1)*(A5>Task_table_03_2_26!$J$2:$J$596)*(A5<Task_table_03_2_26!$K$2:$K$596))} -> 1 | D5: {=SUMPRODUCT((Task_table_03_2_26!$C$2:$C$596=$D$1)*(A5>Task_table_03_2_26!$J$2:$J$596)*(A5<Task_table_03_2_26!$K$2:$K$596))} -> 0 | E5: {=SUMPRODUCT((Task_table_03_2_26!$C$2:$C$596=$E$1)*(A5>Task_table_03_2_26!$J$2:$J$596)*(A5<Task_table_03_2_26!$K$2:$K$596))} -> 0
A6: 45874 | B6: {=SUMPRODUCT((Task_table_03_2_26!$C$2:$C$596=$B$1)*(A6>Task_table_03_2_26!$J$2:$J$596)*(A6<Task_table_03_2_26!$K$2:$K$596))} -> 2 | C6: {=SUMPRODUCT((Task_table_03_2_26!$C$2:$C$596=$C$1)*(A6>Task_table_03_2_26!$J$2:$J$596)*(A6<Task_table_03_2_26!$K$2:$K$596))} -> 1 | D6: {=SUMPRODUCT((Task_table_03_2_26!$C$2:$C$596=$D$1)*(A6>Task_table_03_2_26!$J$2:$J$596)*(A6<Task_table_03_2_26!$K$2:$K$596))} -> 0 | E6: {=SUMPRODUCT((Task_table_03_2_26!$C$2:$C$596=$E$1)*(A6>Task_table_03_2_26!$J$2:$J$596)*(A6<Task_table_03_2_26!$K$2:$K$596))} -> 0
A7: 45875 | B7: {=SUMPRODUCT((Task_table_03_2_26!$C$2:$C$596=$B$1)*(A7>Task_table_03_2_26!$J$2:$J$596)*(A7<Task_table_03_2_26!$K$2:$K$596))} -> 2 | C7: {=SUMPRODUCT((Task_table_03_2_26!$C$2:$C$596=$C$1)*(A7>Task_table_03_2_26!$J$2:$J$596)*(A7<Task_table_03_2_26!$K$2:$K$596))} -> 1 | D7: {=SUMPRODUCT((Task_table_03_2_26!$C$2:$C$596=$D$1)*(A7>Task_table_03_2_26!$J$2:$J$596)*(A7<Task_table_03_2_26!$K$2:$K$596))} -> 0 | E7: {=SUMPRODUCT((Task_table_03_2_26!$C$2:$C$596=$E$1)*(A7>Task_table_03_2_26!$J$2:$J$596)*(A7<Task_table_03_2_26!$K$2:$K$596))} -> 0
A8: 45876 | B8: {=SUMPRODUCT((Task_table_03_2_26!$C$2:$C$596=$B$1)*(A8>Task_table_03_2_26!$J$2:$J$596)*(A8<Task_table_03_2_26!$K$2:$K$596))} -> 2 | C8: {=SUMPRODUCT((Task_table_03_2_26!$C$2:$C$596=$C$1)*(A8>Task_table_03_2_26!$J$2:$J$596)*(A8<Task_table_03_2_26!$K$2:$K$596))} -> 1 | D8: {=SUMPRODUCT((Task_table_03_2_26!$C$2:$C$596=$D$1)*(A8>Task_table_03_2_26!$J$2:$J$596)*(A8<Task_table_03_2_26!$K$2:$K$596))} -> 0 | E8: {=SUMPRODUCT((Task_table_03_2_26!$C$2:$C$596=$E$1)*(A8>Task_table_03_2_26!$J$2:$J$596)*(A8<Task_table_03_2_26!$K$2:$K$596))} -> 0
A9: 45877 | B9: {=SUMPRODUCT((Task_table_03_2_26!$C$2:$C$596=$B$1)*(A9>Task_table_03_2_26!$J$2:$J$596)*(A9<Task_table_03_2_26!$K$2:$K$596))} -> 2 | C9: {=SUMPRODUCT((Task_table_03_2_26!$C$2:$C$596=$C$1)*(A9>Task_table_03_2_26!$J$2:$J$596)*(A9<Task_table_03_2_26!$K$2:$K$596))} -> 1 | D9: {=SUMPRODUCT((Task_table_03_2_26!$C$2:$C$596=$D$1)*(A9>Task_table_03_2_26!$J$2:$J$596)*(A9<Task_table_03_2_26!$K$2:$K$596))} -> 0 | E9: {=SUMPRODUCT((Task_table_03_2_26!$C$2:$C$596=$E$1)*(A9>Task_table_03_2_26!$J$2:$J$596)*(A9<Task_table_03_2_26!$K$2:$K$596))} -> 0
A10: 45878 | B10: {=SUMPRODUCT((Task_table_03_2_26!$C$2:$C$596=$B$1)*(A10>Task_table_03_2_26!$J$2:$J$596)*(A10<Task_table_03_2_26!$K$2:$K$596))} -> 2 | C10: {=SUMPRODUCT((Task_table_03_2_26!$C$2:$C$596=$C$1)*(A10>Task_table_03_2_26!$J$2:$J$596)*(A10<Task_table_03_2_26!$K$2:$K$596))} -> 1 | D10: {=SUMPRODUCT((Task_table_03_2_26!$C$2:$C$596=$D$1)*(A10>Task_table_03_2_26!$J$2:$J$596)*(A10<Task_table_03_2_26!$K$2:$K$596))} -> 0 | E10: {=SUMPRODUCT((Task_table_03_2_26!$C$2:$C$596=$E$1)*(A10>Task_table_03_2_26!$J$2:$J$596)*(A10<Task_table_03_2_26!$K$2:$K$596))} -> 0
A11: 45879 | B11: {=SUMPRODUCT((Task_table_03_2_26!$C$2:$C$596=$B$1)*(A11>Task_table_03_2_26!$J$2:$J$596)*(A11<Task_table_03_2_26!$K$2:$K$596))} -> 2 | C11: {=SUMPRODUCT((Task_table_03_2_26!$C$2:$C$596=$C$1)*(A11>Task_table_03_2_26!$J$2:$J$596)*(A11<Task_table_03_2_26!$K$2:$K$596))} -> 1 | D11: {=SUMPRODUCT((Task_table_03_2_26!$C$2:$C$596=$D$1)*(A11>Task_table_03_2_26!$J$2:$J$596)*(A11<Task_table_03_2_26!$K$2:$K$596))} -> 0 | E11: {=SUMPRODUCT((Task_table_03_2_26!$C$2:$C$596=$E$1)*(A11>Task_table_03_2_26!$J$2:$J$596)*(A11<Task_table_03_2_26!$K$2:$K$596))} -> 0
A12: 45880 | B12: {=SUMPRODUCT((Task_table_03_2_26!$C$2:$C$596=$B$1)*(A12>Task_table_03_2_26!$J$2:$J$596)*(A12<Task_table_03_2_26!$K$2:$K$596))} -> 2 | C12: {=SUMPRODUCT((Task_table_03_2_26!$C$2:$C$596=$C$1)*(A12>Task_table_03_2_26!$J$2:$J$596)*(A12<Task_table_03_2_26!$K$2:$K$596))} -> 1 | D12: {=SUMPRODUCT((Task_table_03_2_26!$C$2:$C$596=$D$1)*(A12>Task_table_03_2_26!$J$2:$J$596)*(A12<Task_table_03_2_26!$K$2:$K$596))} -> 0 | E12: {=SUMPRODUCT((Task_table_03_2_26!$C$2:$C$596=$E$1)*(A12>Task_table_03_2_26!$J$2:$J$596)*(A12<Task_table_03_2_26!$K$2:$K$596))} -> 0
A13: 45881 | B13: {=SUMPRODUCT((Task_table_03_2_26!$C$2:$C$596=$B$1)*(A13>Task_table_03_2_26!$J$2:$J$596)*(A13<Task_table_03_2_26!$K$2:$K$596))} -> 2 | C13: {=SUMPRODUCT((Task_table_03_2_26!$C$2:$C$596=$C$1)*(A13>Task_table_03_2_26!$J$2:$J$596)*(A13<Task_table_03_2_26!$K$2:$K$596))} -> 1 | D13: {=SUMPRODUCT((Task_table_03_2_26!$C$2:$C$596=$D$1)*(A13>Task_table_03_2_26!$J$2:$J$596)*(A13<Task_table_03_2_26!$K$2:$K$596))} -> 0 | E13: {=SUMPRODUCT((Task_table_03_2_26!$C$2:$C$596=$E$1)*(A13>Task_table_03_2_26!$J$2:$J$596)*(A13<Task_table_03_2_26!$K$2:$K$596))} -> 0
... A520: 46388 | B520: {=SUMPRODUCT((Task_table_03_2_26!$C$2:$C$596=$B$1)*(A520>Task_table_03_2_26!$J$2:$J$596)*(A520<Task_table_03_2_26!$K$2:$K$596))} -> 22 | C520: {=SUMPRODUCT((Task_table_03_2_26!$C$2:$C$596=$C$1)*(A520>Task_table_03_2_26!$J$2:$J$596)*(A520<Task_table_03_2_26!$K$2:$K$596))} -> 0 | D520: {=SUMPRODUCT((Task_table_03_2_26!$C$2:$C$596=$D$1)*(A520>Task_table_03_2_26!$J$2:$J$596)*(A520<Task_table_03_2_26!$K$2:$K$596))} -> 0 | E520: {=SUMPRODUCT((Task_table_03_2_26!$C$2:$C$596=$E$1)*(A520>Task_table_03_2_26!$J$2:$J$596)*(A520<Task_table_03_2_26!$K$2:$K$596))} -> 1

Sheet Task_table_03_2_26
A1: Initiative | B1: Process | C1: Phase | D1: Process level | E1: Process Group | F1: % Arbeit abgeschlossen | G1: IT Process Consultant | H1: IT Process Initiative Lead | I1: IT Process Manager | J1: Anfang | K1: Ende | L1: Dauer2 | M1: Process Approval Date | N1: Actual Phase | O1: Planned phase | P1: Associated Process on L1 | R1: 📌 Analyse
A2: Corporate IT body | B2: Manage IT strategy | C2: Total | D2: L1 | E2: MP | F2: 0.5 | J2: 46055 | K2: 46232 | L2: 128 | M2: Mit 06.05.26 | O2: 1 | P2: Manage IT strategy | R2: Prozesse in Elaboration | S2: 39
A3: Corporate IT body | B3: Manage IT strategy | C3: Elaboration | D3: L1 | E3: MP | F3: 0.5 | G3: Kreis Andreas (LLI) | H3: Felder Max (LLI) | I3: Mielenz Thomas (LMT) | J3: 46055 | K3: 46142 | L3: 64 | M3: NV | N3: Elaboration in progress | O3: Elaboration in progress | P3: Manage IT strategy
A4: Corporate IT body | B4: Manage IT strategy | C4: Implementation LIS | D4: L1 | E4: MP | F4: 0 | J4: 46156 | K4: 46232 | L4: 55 | M4: NV | O4: Scheduled | P4: Manage IT strategy
A5: Corporate IT body | B5: Manage IT strategy | C5: Implementation COT | D5: L1 | E5: MP | F5: 0 | J5: ? | K5: ? | L5: 0 | M5: NV | P5: Manage IT strategy
A6: Corporate IT body | B6: Manage IT strategy | C6: Implementation LUS | D6: L1 | E6: MP | F6: 0 | J6: ? | K6: ? | L6: 0 | M6: NV | P6: Manage IT strategy
A7: Corporate IT body | B7: Manage IT governance framework | C7: Total | D7: L1 | E7: MP | F7: 0.5 | J7: 46029 | K7: 46265 | L7: 169 | M7: NV | P7: Manage IT governance framework
A8: Corporate IT body | B8: Manage IT governance framework | C8: Elaboration | D8: L1 | E8: MP | F8: 0.5 | G8: Kunz Christina (LIS-MHP Management- und IT Beratung GmbH);Kreis Andreas (LLI) | H8: Felder Max (LLI) | I8: Mielenz Thomas (LMT) | J8: 46097 | K8: 46163 | L8: 49 | M8: NV | N8: Elaboration in progress | O8: Elaboration in progress | P8: Manage IT governance framework
A9: Corporate IT body | B9: Manage IT governance framework | C9: Implementation LIS | D9: L1 | E9: MP | F9: 0 | J9: 46167 | K9: 46265 | L9: 71 | M9: NV | O9: Scheduled | P9: Manage IT governance framework
A10: Corporate IT body | B10: Manage IT governance framework | C10: Implementation COT | D10: L1 | E10: MP | F10: 0 | J10: ? | K10: ? | L10: 0 | M10: NV | P10: Manage IT governance framework
A11: Corporate IT body | B11: Manage IT governance framework | C11: Implementation LUS | D11: L1 | E11: MP | F11: 0 | J11: ? | K11: ? | L11: 0 | M11: NV | P11: Manage IT governance framework
A12: Corporate IT body | B12: Maintain IT glossary | C12: Total | D12: L2 | E12: MP | F12: 0.25 | J12: 46029 | K12: 46039 | L12: 8 | M12: NV | P12: Manage IT governance framework
A13: Corporate IT body | B13: Maintain IT glossary | C13: Elaboration | D13: L2 | E13: MP | F13: 0.25 | G13: Kunz Christina (LIS-MHP Management- und IT Beratung GmbH) | H13: Felder Max (LLI) | I13: Mielenz Thomas (LMT) | J13: 46029 | K13: ? | L13: 0 | M13: NV | P13: Manage IT governance framework
A14: Corporate IT body | B14: Maintain IT glossary | C14: Implementation LIS | D14: L2 | E14: MP | F14: 0 | J14: 46029 | K14: 46039 | L14: 7 | M14: NV | N14: Delayed | O14: Implementation LIS Done | P14: Manage IT governance framework
A15: Corporate IT body | B15: Maintain IT glossary | C15: Implementation COT | D15: L2 | E15: MP | F15: 0 | J15: 46029 | K15: ? | L15: 0 | M15: NV | P15: Manage IT governance framework
A16: Corporate IT body | B16: Maintain IT glossary | C16: Implementation LUS | D16: L2 | E16: MP | F16: 0 | J16: ? | K16: ? | L16: 0 | M16: NV | P16: Manage IT governance framework
A17: Corporate IT body | B17: Manage enterprise architecture | C17: Total | D17: L1 | E17: MP | F17: 0.24 | J17: 45946 | K17: 46219 | L17: 195.85 | M17: NV | P17: Manage enterprise architecture
A18: Corporate IT body | B18: Manage enterprise architecture | C18: Elaboration | D18: L1 | E18: MP | F18: 0 | G18: Hoermann Patrick (LLI) | H18: Gujral Parth (COB-COT-IT) | I18: Nussbaumer Florian (LBC) | J18: 46076 | K18: 46150 | L18: 54.85 | M18: NV | N18: Delayed | O18: Elaboration in progress | P18: Manage enterprise architecture
A19: Corporate IT body | B19: Manage enterprise architecture | C19: Implementation LIS | D19: L1 | E19: MP | F19: 0 | J19: 46150 | K19: 46219 | L19: 49 | M19: NV | O19: Scheduled | P19: Manage enterprise architecture
A20: Corporate IT body | B20: Manage enterprise architecture | C20: Implementation COT | D20: L1 | E20: MP | F20: 0 | J20: 46150 | K20: 46153 | L20: 1 | M20: NV | O20: Scheduled | P20: Manage enterprise architecture
A21: Corporate IT body | B21: Manage enterprise architecture | C21: Implementation LUS | D21: L1 | E21: MP | F21: 0 | J21: 46150 | K21: 46153 | L21: 1 | M21: NV | O21: Scheduled | P21: Manage enterprise architecture
A22: Corporate IT body | B22: Strategic architecture process | C22: Total | D22: L2 | E22: MP | F22: 0.5 | J22: 45946 | K22: 46142 | L22: 141 | M22: NV | P22: Manage enterprise architecture
A23: Corporate IT body | B23: Strategic architecture process | C23: Elaboration | D23: L2 | E23: MP | F23: 0.5 | G23: Hoermann Patrick (LLI) | H23: Gujral Parth (COB-COT-IT) | I23: Nussbaumer Florian (LBC) | J23: 46076 | K23: 46142 | L23: 49 | M23: NV | N23: Elaboration in progress | O23: Elaboration in progress | P23: Manage enterprise architecture
A24: Corporate IT body | B24: Strategic architecture process | C24: Implementation LIS | D24: L2 | E24: MP | F24: 0 | J24: ? | K24: ? | L24: 0 | M24: NV | P24: Manage enterprise architecture
A25: Corporate IT body | B25: Strategic architecture process | C25: Implementation COT | D25: L2 | E25: MP | F25: 0 | J25: ? | K25: ? | L25: 0 | M25: NV | P25: Manage enterprise architecture
A26: Corporate IT body | B26: Strategic architecture process | C26: Implementation LUS | D26: L2 | E26: MP | F26: 0 | J26: ? | K26: ? | L26: 0 | M26: NV | P26: Manage enterprise architecture
A27: ITSM | B27: Manage IT portfolio | C27: Total | D27: L1 | E27: MP | F27: 0.69 | J27: 45971 | K27: 46157 | L27: 135 | M27: NV | P27: Manage IT portfolio
A28: ITSM | B28: Manage IT portfolio | C28: Elaboration | D28: L1 | E28: MP | F28: 1 | G28: Frank Maren (LIS);Kunz Christina (LIS-MHP Management- und IT Beratung GmbH) | J28: 45972 | K28: 46051 | L28: 58 | M28: NV | N28: Elaboration Done | O28: Elaboration Done | P28: Manage IT portfolio
A29: ITSM | B29: Manage IT portfolio | C29: Implementation LIS | D29: L1 | E29: MP | F29: 0 | J29: ? | K29: ? | L29: 0 | M29: NV | P29: Manage IT portfolio
A30: ITSM | B30: Manage IT portfolio | C30: Implementation COT | D30: L1 | E30: MP | F30: 0 | J30: ? | K30: ? | L30: 0 | M30: NV | P30: Manage IT portfolio
A31: ITSM | B31: Manage IT portfolio | C31: Implementation LUS | D31: L1 | E31: MP | F31: 0 | J31: ? | K31: ? | L31: 0 | M31: NV | P31: Manage IT portfolio
A32: IT project management | B32: Manage IT project portfolio | C32: Total | D32: L2 | E32: MP | F32: 1 | J32: 45971 | K32: 46173 | L32: 145 | M32: NV | P32: Manage IT portfolio
A33: IT project management | B33: Manage IT project portfolio | C33: Elaboration | D33: L2 | E33: MP | F33: 1 | G33: Frank Maren (LIS) | H33: Mühlbacher Christian (LIS) | I33: Rollinger Alexander (LIS) | J33: 45971 | K33: 46001 | L33: 23 | M33: Mit 28.01.26 | N33: Elaboration Done | O33: Elaboration Done | P33: Manage IT portfolio
A34: IT project management | B34: Manage IT project portfolio | C34: Implementation LIS | D34: L2 | E34: MP | F34: 0 | J34: 46054 | K34: 46173 | L34: 85 | M34: NV | N34: Delayed | O34: Implementation LIS | P34: Manage IT portfolio
A35: IT project management | B35: Manage IT project portfolio | C35: Implementation COT | D35: L2 | E35: MP | F35: 0 | J35: ? | K35: ? | L35: 0 | M35: NV | P35: Manage IT portfolio
A36: IT project management | B36: Manage IT project portfolio | C36: Implementation LUS | D36: L2 | E36: MP | F36: 0 | J36: ? | K36: ? | L36: 0 | M36: NV | P36: Manage IT portfolio
A37: ITSM | B37: Manage IT service portfolio | C37: Total | D37: L2 | E37: MP | F37: 0 | J37: 46113 | K37: 46273 | L37: 115 | M37: NV | P37: Manage IT portfolio
A38: ITSM | B38: Manage IT service portfolio | C38: Elaboration | D38: L2 | E38: MP | F38: 0 | G38: Frank Maren (LIS);Kunz Christina (LIS-MHP Management- und IT Beratung GmbH) | H38: Ceilia Roser (LIS) | I38: Reiner Heiko (HAU-ITSA) | J38: 46113 | K38: 46155 | L38: 31 | M38: NV | O38: Scheduled | P38: Manage IT portfolio
A39: ITSM | B39: Manage IT service portfolio | C39: Implementation LIS | D39: L2 | E39: MP | F39: 0 | J39: 46188 | K39: 46273 | L39: 62 | M39: NV | O39: Scheduled | P39: Manage IT portfolio
A40: ITSM | B40: Manage IT service portfolio | C40: Implementation COT | D40: L2 | E40: MP | F40: 0 | J40: ? | K40: ? | L40: 0 | M40: NV | P40: Manage IT portfolio
A41: ITSM | B41: Manage IT service portfolio | C41: Implementation LUS | D41: L2 | E41: MP | F41: 0 | J41: ? | K41: ? | L41: 0 | M41: NV | P41: Manage IT portfolio
A42: IT planning and steering | B42: Manage and control IT financials | C42: Total | D42: L1 | E42: MP | F42: 0.5 | I42: Moser Mario (LIS-LAH) | J42: 45945 | K42: 46234 | L42: 208 | M42: NV | P42: Manage and control IT financials
A43: IT planning and steering | B43: Manage and control IT financials | C43: Elaboration | D43: L1 | E43: MP | F43: 0.5 | G43: Hynek Tobias (LIS);Kreis Andreas (LLI) | H43: Frank Nicole (LIS) | I43: Moser Mario (LIS-LAH) | J43: 45945 | K43: 46142 | L43: 142 | M43: NV | N43: Elaboration in progress | O43: Elaboration in progress | P43: Manage and control IT financials
A44: IT planning and steering | B44: Manage and control IT financials | C44: Implementation LIS | D44: L1 | E44: MP | F44: 0 | J44: 46143 | K44: 46234 | L44: 66 | M44: NV | O44: Scheduled | P44: Manage and control IT financials
A45: IT planning and steering | B45: Manage and control IT financials | C45: Implementation COT | D45: L2 | E45: MP | F45: 0 | J45: ? | K45: ? | L45: 0 | M45: NV | P45: Manage and control IT financials
A46: IT planning and steering | B46: Manage and control IT financials | C46: Implementation LUS | D46: L1 | E46: MP | F46: 0 | J46: ? | K46: ? | L46: 0 | M46: NV | P46: Manage and control IT financials
A47: IT planning and steering | B47: Create and maintain IT budgets | C47: Total | D47: L2 | E47: MP | F47: 0.5 | J47: 45945 | K47: ? | L47: 0 | M47: NV | P47: Manage and control IT financials
A48: IT planning and steering | B48: Create and maintain IT budgets | C48: Elaboration | D48: L2 | E48: MP | F48: 0.5 | G48: Hynek Tobias (LIS);Kreis Andreas (LLI) | H48: Frank Nicole (LIS) | I48: Mielenz Thomas (LMT) | J48: 45945 | K48: ? | L48: 0 | M48: NV | P48: Manage and control IT financials
A49: IT planning and steering | B49: Create and maintain IT budgets | C49: Implementation LIS | D49: L2 | E49: MP | F49: 0 | J49: ? | K49: ? | L49: 0 | M49: NV | P49: Manage and control IT financials
A50: IT planning and steering | B50: Create and maintain IT budgets | C50: Implementation COT | D50: L2 | E50: MP | F50: 0 | J50: ? | K50: ? | L50: 0 | M50: NV | P50: Manage and control IT financials
A51: IT planning and steering | B51: Create and maintain IT budgets | C51: Implementation LUS | D51: L2 | E51: MP | F51: 0 | J51: ? | K51: ? | L51: 0 | M51: NV | P51: Manage and control IT financials
A52: IT planning and steering | B52: Approve and communicate budget plan | C52: Total | D52: L3 | E52: MP | F52: 0.5 | J52: 45945 | K52: ? | L52: 0 | M52: NV | P52: Manage and control IT financials
A53: IT planning and steering | B53: Approve and communicate budget plan | C53: Elaboration | D53: L3 | E53: MP | F53: 0.5 | G53: Hynek Tobias (LIS);Kreis Andreas (LLI) | H53: Frank Nicole (LIS) | I53: Mielenz Thomas (LMT) | J53: 45945 | K53: ? | L53: 0 | M53: NV | P53: Manage and control IT financials
A54: IT planning and steering | B54: Approve and communicate budget plan | C54: Implementation LIS | D54: L3 | E54: MP | F54: 0 | J54: ? | K54: ? | L54: 0 | M54: NV | P54: Manage and control IT financials
A55: IT planning and steering | B55: Approve and communicate budget plan | C55: Implementation COT | D55: L3 | E55: MP | F55: 0 | J55: ? | K55: ? | L55: 0 | M55: NV | P55: Manage and control IT financials
A56: IT planning and steering | B56: Approve and communicate budget plan | C56: Implementation LUS | D56: L3 | E56: MP | F56: 0 | J56: ? | K56: ? | L56: 0 | M56: NV | P56: Manage and control IT financials
A57: IT planning and steering | B57: Collect and consolidate budget from stakeholders | C57: Total | D57: L3 | E57: MP | F57: 0.5 | J57: 45945 | K57: ? | L57: 0 | M57: NV | P57: Manage and control IT financials
A58: IT planning and steering | B58: Collect and consolidate budget from stakeholders | C58: Elaboration | D58: L3 | E58: MP | F58: 0.5 | G58: Hynek Tobias (LIS);Kreis Andreas (LLI) | H58: Frank Nicole (LIS) | I58: Mielenz Thomas (LMT) | J58: 45945 | K58: ? | L58: 0 | M58: NV | P58: Manage and control IT financials
A59: IT planning and steering | B59: Collect and consolidate budget from stakeholders | C59: Implementation LIS | D59: L3 | E59: MP | F59: 0 | J59: ? | K59: ? | L59: 0 | M59: NV | P59: Manage and control IT financials
A60: IT planning and steering | B60: Collect and consolidate budget from stakeholders | C60: Implementation COT | D60: L3 | E60: MP | F60: 0 | J60: ? | K60: ? | L60: 0 | M60: NV | P60: Manage and control IT financials
A61: IT planning and steering | B61: Collect and consolidate budget from stakeholders | C61: Implementation LUS | D61: L3 | E61: MP | F61: 0 | J61: ? | K61: ? | L61: 0 | M61: NV | P61: Manage and control IT financials
A62: IT planning and steering | B62: Develop preliminary budget plan | C62: Total | D62: L3 | E62: MP | F62: 0.5 | J62: 45945 | K62: ? | L62: 0 | M62: NV | P62: Manage and control IT financials
A63: IT planning and steering | B63: Develop preliminary budget plan | C63: Elaboration | D63: L3 | E63: MP | F63: 0.5 | G63: Hynek Tobias (LIS);Kreis Andreas (LLI) | H63: Frank Nicole (LIS) | I63: Mielenz Thomas (LMT) | J63: 45945 | K63: ? | L63: 0 | M63: NV | P63: Manage and control IT financials
A64: IT planning and steering | B64: Develop preliminary budget plan | C64: Implementation LIS | D64: L3 | E64: MP | F64: 0 | J64: ? | K64: ? | L64: 0 | M64: NV | P64: Manage and control IT financials
A65: IT planning and steering | B65: Develop preliminary budget plan | C65: Implementation COT | D65: L3 | E65: MP | F65: 0 | J65: ? | K65: ? | L65: 0 | M65: NV | P65: Manage and control IT financials
A66: IT planning and steering | B66: Develop preliminary budget plan | C66: Implementation LUS | D66: L3 | E66: MP | F66: 0 | J66: ? | K66: ? | L66: 0 | M66: NV | P66: Manage and control IT financials
A67: IT planning and steering | B67: Maintan and adjust budget | C67: Total | D67: L3 | E67: MP | F67: 0.5 | J67: 45945 | K67: ? | L67: 0 | M67: NV | P67: Manage and control IT financials
A68: IT planning and steering | B68: Maintan and adjust budget | C68: Elaboration | D68: L3 | E68: MP | F68: 0.5 | G68: Hynek Tobias (LIS);Kreis Andreas (LLI) | H68: Frank Nicole (LIS) | I68: Mielenz Thomas (LMT) | J68: 45945 | K68: ? | L68: 0 | M68: NV | P68: Manage and control IT financials
A69: IT planning and steering | B69: Maintan and adjust budget | C69: Implementation LIS | D69: L3 | E69: MP | F69: 0 | J69: ? | K69: ? | L69: 0 | M69: NV | P69: Manage and control IT financials
A70: IT planning and steering | B70: Maintan and adjust budget | C70: Implementation COT | D70: L3 | E70: MP | F70: 0 | J70: ? | K70: ? | L70: 0 | M70: NV | P70: Manage and control IT financials
A71: IT planning and steering | B71: Maintan and adjust budget | C71: Implementation LUS | D71: L3 | E71: MP | F71: 0 | J71: ? | K71: ? | L71: 0 | M71: NV | P71: Manage and control IT financials
A72: IT planning and steering | B72: Review budget plan | C72: Total | D72: L3 | E72: MP | F72: 0.5 | J72: 45945 | K72: ? | L72: 0 | M72: NV | O72: 18 | P72: Manage and control IT financials
A73: IT planning and steering | B73: Review budget plan | C73: Elaboration | D73: L3 | E73: MP | F73: 0.5 | G73: Hynek Tobias (LIS);Kreis Andreas (LLI) | H73: Frank Nicole (LIS) | I73: Mielenz Thomas (LMT) | J73: 45945 | K73: ? | L73: 0 | M73: NV | P73: Manage and control IT financials
A74: IT planning and steering | B74: Review budget plan | C74: Implementation LIS | D74: L3 | E74: MP | F74: 0 | J74: ? | K74: ? | L74: 0 | M74: NV | P74: Manage and control IT financials
A75: IT planning and steering | B75: Review budget plan | C75: Implementation COT | D75: L3 | E75: MP | F75: 0 | J75: ? | K75: ? | L75: 0 | M75: NV | P75: Manage and control IT financials
A76: IT planning and steering | B76: Review budget plan | C76: Implementation LUS | D76: L3 | E76: MP | F76: 0 | J76: ? | K76: ? | L76: 0 | M76: NV | P76: Manage and control IT financials
A77: IT planning and steering | B77: Revise and optimize budget plan | C77: Total | D77: L3 | E77: MP | F77: 0.5 | J77: 45945 | K77: ? | L77: 0 | M77: NV | P77: Manage and control IT financials
A78: IT planning and steering | B78: Revise and optimize budget plan | C78: Elaboration | D78: L3 | E78: MP | F78: 0.5 | G78: Hynek Tobias (LIS);Kreis Andreas (LLI) | H78: Frank Nicole (LIS) | I78: Mielenz Thomas (LMT) | J78: 45945 | K78: ? | L78: 0 | M78: NV | P78: Manage and control IT financials
A79: IT planning and steering | B79: Revise and optimize budget plan | C79: Implementation LIS | D79: L3 | E79: MP | F79: 0 | J79: ? | K79: ? | L79: 0 | M79: NV | P79: Manage and control IT financials
A80: IT planning and steering | B80: Revise and optimize budget plan | C80: Implementation COT | D80: L3 | E80: MP | F80: 0 | J80: ? | K80: ? | L80: 0 | M80: NV | P80: Manage and control IT financials
A81: IT planning and steering | B81: Revise and optimize budget plan | C81: Implementation LUS | D81: L3 | E81: MP | F81: 0 | J81: ? | K81: ? | L81: 0 | M81: NV | P81: Manage and control IT financials
A82: IT planning and steering | B82: Manage finance and accounting | C82: Total | D82: L2 | E82: MP | F82: 0.5 | J82: 45945 | K82: ? | L82: 0 | M82: NV | P82: Manage and control IT financials
A83: IT planning and steering | B83: Manage finance and accounting | C83: Elaboration | D83: L2 | E83: MP | F83: 0.5 | G83: Hynek Tobias (LIS);Kreis Andreas (LLI) | H83: Frank Nicole (LIS) | I83: Moser Mario (LIS-LAH) | J83: 45945 | K83: ? | L83: 0 | M83: NV | P83: Manage and control IT financials
A84: IT planning and steering | B84: Manage finance and accounting | C84: Implementation LIS | D84: L2 | E84: MP | F84: 0 | J84: ? | K84: ? | L84: 0 | M84: NV | P84: Manage and control IT financials
A85: IT planning and steering | B85: Manage finance and accounting | C85: Implementation COT | D85: L2 | E85: MP | F85: 0 | J85: ? | K85: ? | L85: 0 | M85: NV | P85: Manage and control IT financials
A86: IT planning and steering | B86: Manage finance and accounting | C86: Implementation LUS | D86: L2 | E86: MP | F86: 0 | J86: ? | K86: ? | L86: 0 | M86: NV | P86: Manage and control IT financials
A87: IT planning and steering | B87: Define financial management framework | C87: Total | D87: L3 | E87: MP | F87: 0.5 | J87: 45945 | K87: ? | L87: 0 | M87: NV | P87: Manage and control IT financials
A88: IT planning and steering | B88: Define financial management framework | C88: Elaboration | D88: L3 | E88: MP | F88: 0.5 | G88: Hynek Tobias (LIS);Kreis Andreas (LLI) | H88: Frank Nicole (LIS) | I88: Moser Mario (LIS-LAH) | J88: 45945 | K88: ? | L88: 0 | M88: NV | P88: Manage and control IT financials
A89: IT planning and steering | B89: Define financial management framework | C89: Implementation LIS | D89: L3 | E89: MP | F89: 0 | J89: ? | K89: ? | L89: 0 | M89: NV | P89: Manage and control IT financials
A90: IT planning and steering | B90: Define financial management framework | C90: Implementation COT | D90: L3 | E90: MP | F90: 0 | J90: ? | K90: ? | L90: 0 | M90: NV | P90: Manage and control IT financials
A91: IT planning and steering | B91: Define financial management framework | C91: Implementation LUS | D91: L3 | E91: MP | F91: 0 | J91: ? | K91: ? | L91: 0 | M91: NV | P91: Manage and control IT financials
A92: IT planning and steering | B92: Establish financial accounting structure | C92: Total | D92: L3 | E92: MP | F92: 0.5 | J92: 45945 | K92: ? | L92: 0 | M92: NV | P92: Manage and control IT financials
A93: IT planning and steering | B93: Establish financial accounting structure | C93: Elaboration | D93: L3 | E93: MP | F93: 0.5 | G93: Hynek Tobias (LIS);Kreis Andreas (LLI) | H93: Frank Nicole (LIS) | I93: Moser Mario (LIS-LAH) | J93: 45945 | K93: ? | L93: 0 | M93: NV | P93: Manage and control IT financials
A94: IT planning and steering | B94: Establish financial accounting structure | C94: Implementation LIS | D94: L3 | E94: MP | F94: 0 | J94: ? | K94: ? | L94: 0 | M94: NV | P94: Manage and control IT financials
A95: IT planning and steering | B95: Establish financial accounting structure | C95: Implementation COT | D95: L3 | E95: MP | F95: 0 | J95: ? | K95: ? | L95: 0 | M95: NV | P95: Manage and control IT financials
A96: IT planning and steering | B96: Establish financial accounting structure | C96: Implementation LUS | D96: L3 | E96: MP | F96: 0 | J96: ? | K96: ? | L96: 0 | M96: NV | P96: Manage and control IT financials
A97: IT planning and steering | B97: Manage IT costs | C97: Total | D97: L2 | E97: MP | F97: 0.5 | J97: 45945 | K97: ? | L97: 0 | M97: NV | P97: Manage and control IT financials
A98: IT planning and steering | B98: Manage IT costs | C98: Elaboration | D98: L2 | E98: MP | F98: 0.5 | G98: Hynek Tobias (LIS);Kreis Andreas (LLI) | H98: Frank Nicole (LIS) | I98: Moser Mario (LIS-LAH) | J98: 45945 | K98: ? | L98: 0 | M98: NV | P98: Manage and control IT financials
A99: IT planning and steering | B99: Manage IT costs | C99: Implementation LIS | D99: L2 | E99: MP | F99: 0 | J99: ? | K99: ? | L99: 0 | M99: NV | P99: Manage and control IT financials
A100: IT planning and steering | B100: Manage IT costs | C100: Implementation COT | E100: MP | F100: 0 | J100: ? | K100: ? | L100: 0 | M100: NV | P100: Manage and control IT financials
...

Sheet Date_table_03_2_26
A1: Datum | B1: Elaboration | C1: Implementation LIS | D1: Implementation LUS | E1: Implementation COT
A2: 45870 | B2: {=SUMPRODUCT((Task_table_03_2_26!$C$2:$C$596=$B$1)*(A2>Task_table_03_2_26!$J$2:$J$596)*(A2<Task_table_03_2_26!$K$2:$K$596))} -> 0 | C2: {=SUMPRODUCT((Task_table_03_2_26!$C$2:$C$596=$C$1)*(A2>Task_table_03_2_26!$J$2:$J$596)*(A2<Task_table_03_2_26!$K$2:$K$596))} -> 1 | D2: {=SUMPRODUCT((Task_table_03_2_26!$C$2:$C$596=$D$1)*(A2>Task_table_03_2_26!$J$2:$J$596)*(A2<Task_table_03_2_26!$K$2:$K$596))} -> 0 | E2: {=SUMPRODUCT((Task_table_03_2_26!$C$2:$C$596=$E$1)*(A2>Task_table_03_2_26!$J$2:$J$596)*(A2<Task_table_03_2_26!$K$2:$K$596))} -> 0
A3: 45871 | B3: {=SUMPRODUCT((Task_table_03_2_26!$C$2:$C$596=$B$1)*(A3>Task_table_03_2_26!$J$2:$J$596)*(A3<Task_table_03_2_26!$K$2:$K$596))} -> 1 | C3: {=SUMPRODUCT((Task_table_03_2_26!$C$2:$C$596=$C$1)*(A3>Task_table_03_2_26!$J$2:$J$596)*(A3<Task_table_03_2_26!$K$2:$K$596))} -> 1 | D3: {=SUMPRODUCT((Task_table_03_2_26!$C$2:$C$596=$D$1)*(A3>Task_table_03_2_26!$J$2:$J$596)*(A3<Task_table_03_2_26!$K$2:$K$596))} -> 0 | E3: {=SUMPRODUCT((Task_table_03_2_26!$C$2:$C$596=$E$1)*(A3>Task_table_03_2_26!$J$2:$J$596)*(A3<Task_table_03_2_26!$K$2:$K$596))} -> 0
A4: 45872 | B4: {=SUMPRODUCT((Task_table_03_2_26!$C$2:$C$596=$B$1)*(A4>Task_table_03_2_26!$J$2:$J$596)*(A4<Task_table_03_2_26!$K$2:$K$596))} -> 1 | C4: {=SUMPRODUCT((Task_table_03_2_26!$C$2:$C$596=$C$1)*(A4>Task_table_03_2_26!$J$2:$J$596)*(A4<Task_table_03_2_26!$K$2:$K$596))} -> 1 | D4: {=SUMPRODUCT((Task_table_03_2_26!$C$2:$C$596=$D$1)*(A4>Task_table_03_2_26!$J$2:$J$596)*(A4<Task_table_03_2_26!$K$2:$K$596))} -> 0 | E4: {=SUMPRODUCT((Task_table_03_2_26!$C$2:$C$596=$E$1)*(A4>Task_table_03_2_26!$J$2:$J$596)*(A4<Task_table_03_2_26!$K$2:$K$596))} -> 0
A5: 45873 | B5: {=SUMPRODUCT((Task_table_03_2_26!$C$2:$C$596=$B$1)*(A5>Task_table_03_2_26!$J$2:$J$596)*(A5<Task_table_03_2_26!$K$2:$K$596))} -> 1 | C5: {=SUMPRODUCT((Task_table_03_2_26!$C$2:$C$596=$C$1)*(A5>Task_table_03_2_26!$J$2:$J$596)*(A5<Task_table_03_2_26!$K$2:$K$596))} -> 1 | D5: {=SUMPRODUCT((Task_table_03_2_26!$C$2:$C$596=$D$1)*(A5>Task_table_03_2_26!$J$2:$J$596)*(A5<Task_table_03_2_26!$K$2:$K$596))} -> 0 | E5: {=SUMPRODUCT((Task_table_03_2_26!$C$2:$C$596=$E$1)*(A5>Task_table_03_2_26!$J$2:$J$596)*(A5<Task_table_03_2_26!$K$2:$K$596))} -> 0
A6: 45874 | B6: {=SUMPRODUCT((Task_table_03_2_26!$C$2:$C$596=$B$1)*(A6>Task_table_03_2_26!$J$2:$J$596)*(A6<Task_table_03_2_26!$K$2:$K$596))} -> 2 | C6: {=SUMPRODUCT((Task_table_03_2_26!$C$2:$C$596=$C$1)*(A6>Task_table_03_2_26!$J$2:$J$596)*(A6<Task_table_03_2_26!$K$2:$K$596))} -> 1 | D6: {=SUMPRODUCT((Task_table_03_2_26!$C$2:$C$596=$D$1)*(A6>Task_table_03_2_26!$J$2:$J$596)*(A6<Task_table_03_2_26!$K$2:$K$596))} -> 0 | E6: {=SUMPRODUCT((Task_table_03_2_26!$C$2:$C$596=$E$1)*(A6>Task_table_03_2_26!$J$2:$J$596)*(A6<Task_table_03_2_26!$K$2:$K$596))} -> 0
A7: 45875 | B7: {=SUMPRODUCT((Task_table_03_2_26!$C$2:$C$596=$B$1)*(A7>Task_table_03_2_26!$J$2:$J$596)*(A7<Task_table_03_2_26!$K$2:$K$596))} -> 2 | C7: {=SUMPRODUCT((Task_table_03_2_26!$C$2:$C$596=$C$1)*(A7>Task_table_03_2_26!$J$2:$J$596)*(A7<Task_table_03_2_26!$K$2:$K$596))} -> 1 | D7: {=SUMPRODUCT((Task_table_03_2_26!$C$2:$C$596=$D$1)*(A7>Task_table_03_2_26!$J$2:$J$596)*(A7<Task_table_03_2_26!$K$2:$K$596))} -> 0 | E7: {=SUMPRODUCT((Task_table_03_2_26!$C$2:$C$596=$E$1)*(A7>Task_table_03_2_26!$J$2:$J$596)*(A7<Task_table_03_2_26!$K$2:$K$596))} -> 0
A8: 45876 | B8: {=SUMPRODUCT((Task_table_03_2_26!$C$2:$C$596=$B$1)*(A8>Task_table_03_2_26!$J$2:$J$596)*(A8<Task_table_03_2_26!$K$2:$K$596))} -> 2 | C8: {=SUMPRODUCT((Task_table_03_2_26!$C$2:$C$596=$C$1)*(A8>Task_table_03_2_26!$J$2:$J$596)*(A8<Task_table_03_2_26!$K$2:$K$596))} -> 1 | D8: {=SUMPRODUCT((Task_table_03_2_26!$C$2:$C$596=$D$1)*(A8>Task_table_03_2_26!$J$2:$J$596)*(A8<Task_table_03_2_26!$K$2:$K$596))} -> 0 | E8: {=SUMPRODUCT((Task_table_03_2_26!$C$2:$C$596=$E$1)*(A8>Task_table_03_2_26!$J$2:$J$596)*(A8<Task_table_03_2_26!$K$2:$K$596))} -> 0
A9: 45877 | B9: {=SUMPRODUCT((Task_table_03_2_26!$C$2:$C$596=$B$1)*(A9>Task_table_03_2_26!$J$2:$J$596)*(A9<Task_table_03_2_26!$K$2:$K$596))} -> 2 | C9: {=SUMPRODUCT((Task_table_03_2_26!$C$2:$C$596=$C$1)*(A9>Task_table_03_2_26!$J$2:$J$596)*(A9<Task_table_03_2_26!$K$2:$K$596))} -> 1 | D9: {=SUMPRODUCT((Task_table_03_2_26!$C$2:$C$596=$D$1)*(A9>Task_table_03_2_26!$J$2:$J$596)*(A9<Task_table_03_2_26!$K$2:$K$596))} -> 0 | E9: {=SUMPRODUCT((Task_table_03_2_26!$C$2:$C$596=$E$1)*(A9>Task_table_03_2_26!$J$2:$J$596)*(A9<Task_table_03_2_26!$K$2:$K$596))} -> 0
A10: 45878 | B10: {=SUMPRODUCT((Task_table_03_2_26!$C$2:$C$596=$B$1)*(A10>Task_table_03_2_26!$J$2:$J$596)*(A10<Task_table_03_2_26!$K$2:$K$596))} -> 2 | C10: {=SUMPRODUCT((Task_table_03_2_26!$C$2:$C$596=$C$1)*(A10>Task_table_03_2_26!$J$2:$J$596)*(A10<Task_table_03_2_26!$K$2:$K$596))} -> 1 | D10: {=SUMPRODUCT((Task_table_03_2_26!$C$2:$C$596=$D$1)*(A10>Task_table_03_2_26!$J$2:$J$596)*(A10<Task_table_03_2_26!$K$2:$K$596))} -> 0 | E10: {=SUMPRODUCT((Task_table_03_2_26!$C$2:$C$596=$E$1)*(A10>Task_table_03_2_26!$J$2:$J$596)*(A10<Task_table_03_2_26!$K$2:$K$596))} -> 0
A11: 45879 | B11: {=SUMPRODUCT((Task_table_03_2_26!$C$2:$C$596=$B$1)*(A11>Task_table_03_2_26!$J$2:$J$596)*(A11<Task_table_03_2_26!$K$2:$K$596))} -> 2 | C11: {=SUMPRODUCT((Task_table_03_2_26!$C$2:$C$596=$C$1)*(A11>Task_table_03_2_26!$J$2:$J$596)*(A11<Task_table_03_2_26!$K$2:$K$596))} -> 1 | D11: {=SUMPRODUCT((Task_table_03_2_26!$C$2:$C$596=$D$1)*(A11>Task_table_03_2_26!$J$2:$J$596)*(A11<Task_table_03_2_26!$K$2:$K$596))} -> 0 | E11: {=SUMPRODUCT((Task_table_03_2_26!$C$2:$C$596=$E$1)*(A11>Task_table_03_2_26!$J$2:$J$596)*(A11<Task_table_03_2_26!$K$2:$K$596))} -> 0
A12: 45880 | B12: {=SUMPRODUCT((Task_table_03_2_26!$C$2:$C$596=$B$1)*(A12>Task_table_03_2_26!$J$2:$J$596)*(A12<Task_table_03_2_26!$K$2:$K$596))} -> 2 | C12: {=SUMPRODUCT((Task_table_03_2_26!$C$2:$C$596=$C$1)*(A12>Task_table_03_2_26!$J$2:$J$596)*(A12<Task_table_03_2_26!$K$2:$K$596))} -> 1 | D12: {=SUMPRODUCT((Task_table_03_2_26!$C$2:$C$596=$D$1)*(A12>Task_table_03_2_26!$J$2:$J$596)*(A12<Task_table_03_2_26!$K$2:$K$596))} -> 0 | E12: {=SUMPRODUCT((Task_table_03_2_26!$C$2:$C$596=$E$1)*(A12>Task_table_03_2_26!$J$2:$J$596)*(A12<Task_table_03_2_26!$K$2:$K$596))} -> 0
A13: 45881 | B13: {=SUMPRODUCT((Task_table_03_2_26!$C$2:$C$596=$B$1)*(A13>Task_table_03_2_26!$J$2:$J$596)*(A13<Task_table_03_2_26!$K$2:$K$596))} -> 2 | C13: {=SUMPRODUCT((Task_table_03_2_26!$C$2:$C$596=$C$1)*(A13>Task_table_03_2_26!$J$2:$J$596)*(A13<Task_table_03_2_26!$K$2:$K$596))} -> 1 | D13: {=SUMPRODUCT((Task_table_03_2_26!$C$2:$C$596=$D$1)*(A13>Task_table_03_2_26!$J$2:$J$596)*(A13<Task_table_03_2_26!$K$2:$K$596))} -> 0 | E13: {=SUMPRODUCT((Task_table_03_2_26!$C$2:$C$596=$E$1)*(A13>Task_table_03_2_26!$J$2:$J$596)*(A13<Task_table_03_2_26!$K$2:$K$596))} -> 0
... A520: 46388 | B520: {=SUMPRODUCT((Task_table_03_2_26!$C$2:$C$596=$B$1)*(A520>Task_table_03_2_26!$J$2:$J$596)*(A520<Task_table_03_2_26!$K$2:$K$596))} -> 22 | C520: {=SUMPRODUCT((Task_table_03_2_26!$C$2:$C$596=$C$1)*(A520>Task_table_03_2_26!$J$2:$J$596)*(A520<Task_table_03_2_26!$K$2:$K$596))} -> 0 | D520: {=SUMPRODUCT((Task_table_03_2_26!$C$2:$C$596=$D$1)*(A520>Task_table_03_2_26!$J$2:$J$596)*(A520<Task_table_03_2_26!$K$2:$K$596))} -> 0 | E520: {=SUMPRODUCT((Task_table_03_2_26!$C$2:$C$596=$E$1)*(A520>Task_table_03_2_26!$J$2:$J$596)*(A520<Task_table_03_2_26!$K$2:$K$596))} -> 1

Sheet task_table_13_4_26
A1: Initiative | B1: Process | C1: Phase | D1: Process level | E1: Process Group | F1: % Arbeit abgeschlossen | G1: IT Process Consultant | H1: IT Process Initiative Lead | I1: IT Process Manager | J1: Start | K1: Finish | L1: Dauer2 | M1: Process Approval Date | N1: Planned phase | O1: Associated Process on L1 | P1: Comment | Q1: Text19 | R1: LookupKey
A2: Corporate IT body | B2: Manage IT strategy | C2: Total | D2: L1 | E2: MP | F2: 0.5 | J2: 46055 | K2: 46232 | L2: 128 | M2: 46148 | O2: Manage IT strategy | R2: =TRIM(A2)&"♦"&TRIM(B2)&"♦"&TRIM(C2)&"♦"&TRIM(D2)&"♦"&TRIM(E2) -> Corporate IT body♦Manage IT strategy♦Total♦L1♦MP
A3: Corporate IT body | B3: Manage IT strategy | C3: Elaboration | D3: L1 | E3: MP | F3: 0.5 | G3: Kreis Andreas (LLI) | H3: Felder Max (LLI) | I3: Mielenz Thomas (LMT) | J3: 46055 | K3: 46142 | L3: 64 | N3: Elaboration in progress | O3: Manage IT strategy | R3: =TRIM(A3)&"♦"&TRIM(B3)&"♦"&TRIM(C3)&"♦"&TRIM(D3)&"♦"&TRIM(E3) -> Corporate IT body♦Manage IT strategy♦Elaboration♦L1♦MP
A4: Corporate IT body | B4: Manage IT strategy | C4: Implementation LIS | D4: L1 | E4: MP | F4: 0 | J4: 46156 | K4: 46232 | L4: 55 | N4: Scheduled | O4: Manage IT strategy | R4: =TRIM(A4)&"♦"&TRIM(B4)&"♦"&TRIM(C4)&"♦"&TRIM(D4)&"♦"&TRIM(E4) -> Corporate IT body♦Manage IT strategy♦Implementation LIS♦L1♦MP
A5: Corporate IT body | B5: Manage IT strategy | C5: Implementation COT | D5: L1 | E5: MP | F5: 0 | L5: 0 | O5: Manage IT strategy | R5: =TRIM(A5)&"♦"&TRIM(B5)&"♦"&TRIM(C5)&"♦"&TRIM(D5)&"♦"&TRIM(E5) -> Corporate IT body♦Manage IT strategy♦Implementation COT♦L1♦MP
A6: Corporate IT body | B6: Manage IT strategy | C6: Implementation LUS | D6: L1 | E6: MP | F6: 0 | L6: 0 | O6: Manage IT strategy | R6: =TRIM(A6)&"♦"&TRIM(B6)&"♦"&TRIM(C6)&"♦"&TRIM(D6)&"♦"&TRIM(E6) -> Corporate IT body♦Manage IT strategy♦Implementation LUS♦L1♦MP
A7: Corporate IT body | B7: Manage IT governance framework | C7: Total | D7: L1 | E7: MP | F7: 0.5 | J7: 46029 | K7: 46265 | L7: 169 | O7: Manage IT governance framework | R7: =TRIM(A7)&"♦"&TRIM(B7)&"♦"&TRIM(C7)&"♦"&TRIM(D7)&"♦"&TRIM(E7) -> Corporate IT body♦Manage IT governance framework♦Total♦L1♦MP
A8: Corporate IT body | B8: Manage IT governance framework | C8: Elaboration | D8: L1 | E8: MP | F8: 0.5 | G8: Kunz Christina (LIS-MHP Management- und IT Beratung GmbH);Kreis Andreas (LLI) | H8: Felder Max (LLI) | I8: Mielenz Thomas (LMT) | J8: 46097 | K8: 46163 | L8: 49 | N8: Elaboration in progress | O8: Manage IT governance framework | R8: =TRIM(A8)&"♦"&TRIM(B8)&"♦"&TRIM(C8)&"♦"&TRIM(D8)&"♦"&TRIM(E8) -> Corporate IT body♦Manage IT governance framework♦Elaboration♦L1♦MP
A9: Corporate IT body | B9: Manage IT governance framework | C9: Implementation LIS | D9: L1 | E9: MP | F9: 0 | J9: 46167 | K9: 46265 | L9: 71 | N9: Scheduled | O9: Manage IT governance framework | R9: =TRIM(A9)&"♦"&TRIM(B9)&"♦"&TRIM(C9)&"♦"&TRIM(D9)&"♦"&TRIM(E9) -> Corporate IT body♦Manage IT governance framework♦Implementation LIS♦L1♦MP
A10: Corporate IT body | B10: Manage IT governance framework | C10: Implementation COT | D10: L1 | E10: MP | F10: 0 | L10: 0 | O10: Manage IT governance framework | R10: =TRIM(A10)&"♦"&TRIM(B10)&"♦"&TRIM(C10)&"♦"&TRIM(D10)&"♦"&TRIM(E10) -> Corporate IT body♦Manage IT governance framework♦Implementation COT♦L1♦MP
A11: Corporate IT body | B11: Manage IT governance framework | C11: Implementation LUS | D11: L1 | E11: MP | F11: 0 | L11: 0 | O11: Manage IT governance framework | R11: =TRIM(A11)&"♦"&TRIM(B11)&"♦"&TRIM(C11)&"♦"&TRIM(D11)&"♦"&TRIM(E11) -> Corporate IT body♦Manage IT governance framework♦Implementation LUS♦L1♦MP
A12: Corporate IT body | B12: Maintain IT glossary | C12: Total | D12: L2 | E12: MP | F12: 0.25 | J12: 46029 | K12: 46039 | L12: 8 | O12: Manage IT governance framework | R12: =TRIM(A12)&"♦"&TRIM(B12)&"♦"&TRIM(C12)&"♦"&TRIM(D12)&"♦"&TRIM(E12) -> Corporate IT body♦Maintain IT glossary♦Total♦L2♦MP
A13: Corporate IT body | B13: Maintain IT glossary | C13: Elaboration | D13: L2 | E13: MP | F13: 0.25 | G13: Kunz Christina (LIS-MHP Management- und IT Beratung GmbH) | H13: Felder Max (LLI) | I13: Mielenz Thomas (LMT) | J13: 46029 | L13: 0 | O13: Manage IT governance framework | R13: =TRIM(A13)&"♦"&TRIM(B13)&"♦"&TRIM(C13)&"♦"&TRIM(D13)&"♦"&TRIM(E13) -> Corporate IT body♦Maintain IT glossary♦Elaboration♦L2♦MP
A14: Corporate IT body | B14: Maintain IT glossary | C14: Implementation LIS | D14: L2 | E14: MP | F14: 0 | J14: 46029 | K14: 46039 | L14: 7 | N14: Implementation LIS Done | O14: Manage IT governance framework | R14: =TRIM(A14)&"♦"&TRIM(B14)&"♦"&TRIM(C14)&"♦"&TRIM(D14)&"♦"&TRIM(E14) -> Corporate IT body♦Maintain IT glossary♦Implementation LIS♦L2♦MP
A15: Corporate IT body | B15: Maintain IT glossary | C15: Implementation COT | D15: L2 | E15: MP | F15: 0 | J15: 46029 | L15: 0 | O15: Manage IT governance framework | R15: =TRIM(A15)&"♦"&TRIM(B15)&"♦"&TRIM(C15)&"♦"&TRIM(D15)&"♦"&TRIM(E15) -> Corporate IT body♦Maintain IT glossary♦Implementation COT♦L2♦MP
A16: Corporate IT body | B16: Maintain IT glossary | C16: Implementation LUS | D16: L2 | E16: MP | F16: 0 | L16: 0 | O16: Manage IT governance framework | R16: =TRIM(A16)&"♦"&TRIM(B16)&"♦"&TRIM(C16)&"♦"&TRIM(D16)&"♦"&TRIM(E16) -> Corporate IT body♦Maintain IT glossary♦Implementation LUS♦L2♦MP
A17: Corporate IT body | B17: Manage enterprise architecture | C17: Total | D17: L1 | E17: MP | F17: 0 | J17: 45946 | K17: 46219 | L17: 195.85 | O17: Manage enterprise architecture | R17: =TRIM(A17)&"♦"&TRIM(B17)&"♦"&TRIM(C17)&"♦"&TRIM(D17)&"♦"&TRIM(E17) -> Corporate IT body♦Manage enterprise architecture♦Total♦L1♦MP
A18: ITSM | B18: Manage IT portfolio | C18: Total | D18: L1 | E18: MP | F18: 0.78 | J18: 45971 | K18: 46157 | L18: 135 | O18: Manage IT portfolio | R18: =TRIM(A18)&"♦"&TRIM(B18)&"♦"&TRIM(C18)&"♦"&TRIM(D18)&"♦"&TRIM(E18) -> ITSM♦Manage IT portfolio♦Total♦L1♦MP
A19: ITSM | B19: Manage IT portfolio | C19: Elaboration | D19: L1 | E19: MP | F19: 1 | G19: Frank Maren (LIS);Kunz Christina (LIS-MHP Management- und IT Beratung GmbH) | J19: 45972 | K19: 46051 | L19: 58 | N19: Elaboration Done | O19: Manage IT portfolio | R19: =TRIM(A19)&"♦"&TRIM(B19)&"♦"&TRIM(C19)&"♦"&TRIM(D19)&"♦"&TRIM(E19) -> ITSM♦Manage IT portfolio♦Elaboration♦L1♦MP
A20: ITSM | B20: Manage IT portfolio | C20: Implementation LIS | D20: L1 | E20: MP | F20: 0 | L20: 0 | O20: Manage IT portfolio | R20: =TRIM(A20)&"♦"&TRIM(B20)&"♦"&TRIM(C20)&"♦"&TRIM(D20)&"♦"&TRIM(E20) -> ITSM♦Manage IT portfolio♦Implementation LIS♦L1♦MP
A21: ITSM | B21: Manage IT portfolio | C21: Implementation COT | D21: L1 | E21: MP | F21: 0 | L21: 0 | O21: Manage IT portfolio | R21: =TRIM(A21)&"♦"&TRIM(B21)&"♦"&TRIM(C21)&"♦"&TRIM(D21)&"♦"&TRIM(E21) -> ITSM♦Manage IT portfolio♦Implementation COT♦L1♦MP
A22: ITSM | B22: Manage IT portfolio | C22: Implementation LUS | D22: L1 | E22: MP | F22: 0 | L22: 0 | O22: Manage IT portfolio | R22: =TRIM(A22)&"♦"&TRIM(B22)&"♦"&TRIM(C22)&"♦"&TRIM(D22)&"♦"&TRIM(E22) -> ITSM♦Manage IT portfolio♦Implementation LUS♦L1♦MP
A23: IT project management | B23: Manage IT project portfolio | C23: Total | D23: L2 | E23: MP | F23: 1 | J23: 45971 | K23: 46173 | L23: 145 | O23: Manage IT portfolio | R23: =TRIM(A23)&"♦"&TRIM(B23)&"♦"&TRIM(C23)&"♦"&TRIM(D23)&"♦"&TRIM(E23) -> IT project management♦Manage IT project portfolio♦Total♦L2♦MP
A24: IT project management | B24: Manage IT project portfolio | C24: Elaboration | D24: L2 | E24: MP | F24: 1 | G24: Frank Maren (LIS) | H24: Mühlbacher Christian (LIS) | I24: Rollinger Alexander (LIS) | J24: 45971 | K24: 46001 | L24: 23 | M24: 46050 | N24: Elaboration Done | O24: Manage IT portfolio | R24: =TRIM(A24)&"♦"&TRIM(B24)&"♦"&TRIM(C24)&"♦"&TRIM(D24)&"♦"&TRIM(E24) -> IT project management♦Manage IT project portfolio♦Elaboration♦L2♦MP
A25: IT project management | B25: Manage IT project portfolio | C25: Implementation LIS | D25: L2 | E25: MP | F25: 0 | J25: 46054 | K25: 46173 | L25: 85 | N25: Implementation LIS | O25: Manage IT portfolio | R25: =TRIM(A25)&"♦"&TRIM(B25)&"♦"&TRIM(C25)&"♦"&TRIM(D25)&"♦"&TRIM(E25) -> IT project management♦Manage IT project portfolio♦Implementation LIS♦L2♦MP
A26: IT project management | B26: Manage IT project portfolio | C26: Implementation COT | D26: L2 | E26: MP | F26: 0 | L26: 0 | O26: Manage IT portfolio | R26: =TRIM(A26)&"♦"&TRIM(B26)&"♦"&TRIM(C26)&"♦"&TRIM(D26)&"♦"&TRIM(E26) -> IT project management♦Manage IT project portfolio♦Implementation COT♦L2♦MP
A27: IT project management | B27: Manage IT project portfolio | C27: Implementation LUS | D27: L2 | E27: MP | F27: 0 | L27: 0 | O27: Manage IT portfolio | R27: =TRIM(A27)&"♦"&TRIM(B27)&"♦"&TRIM(C27)&"♦"&TRIM(D27)&"♦"&TRIM(E27) -> IT project management♦Manage IT project portfolio♦Implementation LUS♦L2♦MP
A28: ITSM | B28: Manage IT service portfolio | C28: Total | D28: L2 | E28: MP | F28: 0.5 | J28: 46113 | K28: 46273 | L28: 115 | O28: Manage IT portfolio | R28: =TRIM(A28)&"♦"&TRIM(B28)&"♦"&TRIM(C28)&"♦"&TRIM(D28)&"♦"&TRIM(E28) -> ITSM♦Manage IT service portfolio♦Total♦L2♦MP
A29: ITSM | B29: Manage IT service portfolio | C29: Elaboration | D29: L2 | E29: MP | F29: 0.5 | G29: Frank Maren (LIS);Kunz Christina (LIS-MHP Management- und IT Beratung GmbH) | H29: Ceilia Roser (LIS) | I29: Reiner Heiko (HAU-ITSA) | J29: 46113 | K29: 46188 | L29: 54 | N29: Elaboration in progress | O29: Manage IT portfolio | P29: Uwe Kranich is second responsible; 16.06. Vorstellung Comittee | R29: =TRIM(A29)&"♦"&TRIM(B29)&"♦"&TRIM(C29)&"♦"&TRIM(D29)&"♦"&TRIM(E29) -> ITSM♦Manage IT service portfolio♦Elaboration♦L2♦MP
A30: ITSM | B30: Manage IT service portfolio | C30: Implementation LIS | D30: L2 | E30: MP | F30: 0 | J30: 46188 | K30: 46273 | L30: 62 | N30: Scheduled | O30: Manage IT portfolio | R30: =TRIM(A30)&"♦"&TRIM(B30)&"♦"&TRIM(C30)&"♦"&TRIM(D30)&"♦"&TRIM(E30) -> ITSM♦Manage IT service portfolio♦Implementation LIS♦L2♦MP
A31: ITSM | B31: Manage IT service portfolio | C31: Implementation COT | D31: L2 | E31: MP | F31: 0 | L31: 0 | O31: Manage IT portfolio | R31: =TRIM(A31)&"♦"&TRIM(B31)&"♦"&TRIM(C31)&"♦"&TRIM(D31)&"♦"&TRIM(E31) -> ITSM♦Manage IT service portfolio♦Implementation COT♦L2♦MP
A32: ITSM | B32: Manage IT service portfolio | C32: Implementation LUS | D32: L2 | E32: MP | F32: 0 | L32: 0 | O32: Manage IT portfolio | R32: =TRIM(A32)&"♦"&TRIM(B32)&"♦"&TRIM(C32)&"♦"&TRIM(D32)&"♦"&TRIM(E32) -> ITSM♦Manage IT service portfolio♦Implementation LUS♦L2♦MP
A33: IT planning and steering | B33: Manage and control IT financials | C33: Total | D33: L1 | E33: MP | F33: 0.5 | I33: Moser Mario (LIS-LAH) | J33: 45945 | K33: 46234 | L33: 208 | O33: Manage and control IT financials | R33: =TRIM(A33)&"♦"&TRIM(B33)&"♦"&TRIM(C33)&"♦"&TRIM(D33)&"♦"&TRIM(E33) -> IT planning and steering♦Manage and control IT financials♦Total♦L1♦MP
A34: IT planning and steering | B34: Manage and control IT financials | C34: Elaboration | D34: L1 | E34: MP | F34: 0.5 | G34: Hynek Tobias (LIS);Kreis Andreas (LLI) | H34: Frank Nicole (LIS) | I34: Moser Mario (LIS-LAH) | J34: 45945 | K34: 46142 | L34: 142 | N34: Elaboration in progress | O34: Manage and control IT financials | R34: =TRIM(A34)&"♦"&TRIM(B34)&"♦"&TRIM(C34)&"♦"&TRIM(D34)&"♦"&TRIM(E34) -> IT planning and steering♦Manage and control IT financials♦Elaboration♦L1♦MP
A35: IT planning and steering | B35: Manage and control IT financials | C35: Implementation LIS | D35: L1 | E35: MP | F35: 0 | J35: 46143 | K35: 46234 | L35: 66 | N35: Scheduled | O35: Manage and control IT financials | R35: =TRIM(A35)&"♦"&TRIM(B35)&"♦"&TRIM(C35)&"♦"&TRIM(D35)&"♦"&TRIM(E35) -> IT planning and steering♦Manage and control IT financials♦Implementation LIS♦L1♦MP
A36: IT planning and steering | B36: Manage and control IT financials | C36: Implementation COT | D36: L2 | E36: MP | F36: 0 | L36: 0 | O36: Manage and control IT financials | R36: =TRIM(A36)&"♦"&TRIM(B36)&"♦"&TRIM(C36)&"♦"&TRIM(D36)&"♦"&TRIM(E36) -> IT planning and steering♦Manage and control IT financials♦Implementation COT♦L2♦MP
A37: IT planning and steering | B37: Manage and control IT financials | C37: Implementation LUS | D37: L1 | E37: MP | F37: 0 | L37: 0 | O37: Manage and control IT financials | R37: =TRIM(A37)&"♦"&TRIM(B37)&"♦"&TRIM(C37)&"♦"&TRIM(D37)&"♦"&TRIM(E37) -> IT planning and steering♦Manage and control IT financials♦Implementation LUS♦L1♦MP
A38: IT planning and steering | B38: Create and maintain IT budgets | C38: Total | D38: L2 | E38: MP | F38: 0.5 | J38: 45945 | L38: 0 | O38: Manage and control IT financials | R38: =TRIM(A38)&"♦"&TRIM(B38)&"♦"&TRIM(C38)&"♦"&TRIM(D38)&"♦"&TRIM(E38) -> IT planning and steering♦Create and maintain IT budgets♦Total♦L2♦MP
A39: IT planning and steering | B39: Create and maintain IT budgets | C39: Elaboration | D39: L2 | E39: MP | F39: 0.5 | G39: Hynek Tobias (LIS);Kreis Andreas (LLI) | H39: Frank Nicole (LIS) | I39: Mielenz Thomas (LMT) | J39: 45945 | L39: 0 | O39: Manage and control IT financials | R39: =TRIM(A39)&"♦"&TRIM(B39)&"♦"&TRIM(C39)&"♦"&TRIM(D39)&"♦"&TRIM(E39) -> IT planning and steering♦Create and maintain IT budgets♦Elaboration♦L2♦MP
A40: IT planning and steering | B40: Create and maintain IT budgets | C40: Implementation LIS | D40: L2 | E40: MP | F40: 0 | L40: 0 | O40: Manage and control IT financials | R40: =TRIM(A40)&"♦"&TRIM(B40)&"♦"&TRIM(C40)&"♦"&TRIM(D40)&"♦"&TRIM(E40) -> IT planning and steering♦Create and maintain IT budgets♦Implementation LIS♦L2♦MP
A41: IT planning and steering | B41: Create and maintain IT budgets | C41: Implementation COT | D41: L2 | E41: MP | F41: 0 | L41: 0 | O41: Manage and control IT financials | R41: =TRIM(A41)&"♦"&TRIM(B41)&"♦"&TRIM(C41)&"♦"&TRIM(D41)&"♦"&TRIM(E41) -> IT planning and steering♦Create and maintain IT budgets♦Implementation COT♦L2♦MP
A42: IT planning and steering | B42: Create and maintain IT budgets | C42: Implementation LUS | D42: L2 | E42: MP | F42: 0 | L42: 0 | O42: Manage and control IT financials | R42: =TRIM(A42)&"♦"&TRIM(B42)&"♦"&TRIM(C42)&"♦"&TRIM(D42)&"♦"&TRIM(E42) -> IT planning and steering♦Create and maintain IT budgets♦Implementation LUS♦L2♦MP
A43: IT planning and steering | B43: Approve and communicate budget plan | C43: Total | D43: L3 | E43: MP | F43: 0.5 | J43: 45945 | L43: 0 | O43: Manage and control IT financials | R43: =TRIM(A43)&"♦"&TRIM(B43)&"♦"&TRIM(C43)&"♦"&TRIM(D43)&"♦"&TRIM(E43) -> IT planning and steering♦Approve and communicate budget plan♦Total♦L3♦MP
A44: IT planning and steering | B44: Approve and communicate budget plan | C44: Elaboration | D44: L3 | E44: MP | F44: 0.5 | G44: Hynek Tobias (LIS);Kreis Andreas (LLI) | H44: Frank Nicole (LIS) | I44: Mielenz Thomas (LMT) | J44: 45945 | L44: 0 | O44: Manage and control IT financials | R44: =TRIM(A44)&"♦"&TRIM(B44)&"♦"&TRIM(C44)&"♦"&TRIM(D44)&"♦"&TRIM(E44) -> IT planning and steering♦Approve and communicate budget plan♦Elaboration♦L3♦MP
A45: IT planning and steering | B45: Approve and communicate budget plan | C45: Implementation LIS | D45: L3 | E45: MP | F45: 0 | L45: 0 | O45: Manage and control IT financials | R45: =TRIM(A45)&"♦"&TRIM(B45)&"♦"&TRIM(C45)&"♦"&TRIM(D45)&"♦"&TRIM(E45) -> IT planning and steering♦Approve and communicate budget plan♦Implementation LIS♦L3♦MP
A46: IT planning and steering | B46: Approve and communicate budget plan | C46: Implementation COT | D46: L3 | E46: MP | F46: 0 | L46: 0 | O46: Manage and control IT financials | R46: =TRIM(A46)&"♦"&TRIM(B46)&"♦"&TRIM(C46)&"♦"&TRIM(D46)&"♦"&TRIM(E46) -> IT planning and steering♦Approve and communicate budget plan♦Implementation COT♦L3♦MP
A47: IT planning and steering | B47: Approve and communicate budget plan | C47: Implementation LUS | D47: L3 | E47: MP | F47: 0 | L47: 0 | O47: Manage and control IT financials | R47: =TRIM(A47)&"♦"&TRIM(B47)&"♦"&TRIM(C47)&"♦"&TRIM(D47)&"♦"&TRIM(E47) -> IT planning and steering♦Approve and communicate budget plan♦Implementation LUS♦L3♦MP
A48: IT planning and steering | B48: Collect and consolidate budget from stakeholders | C48: Total | D48: L3 | E48: MP | F48: 0.5 | J48: 45945 | L48: 0 | O48: Manage and control IT financials | R48: =TRIM(A48)&"♦"&TRIM(B48)&"♦"&TRIM(C48)&"♦"&TRIM(D48)&"♦"&TRIM(E48) -> IT planning and steering♦Collect and consolidate budget from stakeholders♦Total♦L3♦MP
A49: IT planning and steering | B49: Collect and consolidate budget from stakeholders | C49: Elaboration | D49: L3 | E49: MP | F49: 0.5 | G49: Hynek Tobias (LIS);Kreis Andreas (LLI) | H49: Frank Nicole (LIS) | I49: Mielenz Thomas (LMT) | J49: 45945 | L49: 0 | O49: Manage and control IT financials | R49: =TRIM(A49)&"♦"&TRIM(B49)&"♦"&TRIM(C49)&"♦"&TRIM(D49)&"♦"&TRIM(E49) -> IT planning and steering♦Collect and consolidate budget from stakeholders♦Elaboration♦L3♦MP
A50: IT planning and steering | B50: Collect and consolidate budget from stakeholders | C50: Implementation LIS | D50: L3 | E50: MP | F50: 0 | L50: 0 | O50: Manage and control IT financials | R50: =TRIM(A50)&"♦"&TRIM(B50)&"♦"&TRIM(C50)&"♦"&TRIM(D50)&"♦"&TRIM(E50) -> IT planning and steering♦Collect and consolidate budget from stakeholders♦Implementation LIS♦L3♦MP
A51: IT planning and steering | B51: Collect and consolidate budget from stakeholders | C51: Implementation COT | D51: L3 | E51: MP | F51: 0 | L51: 0 | O51: Manage and control IT financials | R51: =TRIM(A51)&"♦"&TRIM(B51)&"♦"&TRIM(C51)&"♦"&TRIM(D51)&"♦"&TRIM(E51) -> IT planning and steering♦Collect and consolidate budget from stakeholders♦Implementation COT♦L3♦MP
A52: IT planning and steering | B52: Collect and consolidate budget from stakeholders | C52: Implementation LUS | D52: L3 | E52: MP | F52: 0 | L52: 0 | O52: Manage and control IT financials | R52: =TRIM(A52)&"♦"&TRIM(B52)&"♦"&TRIM(C52)&"♦"&TRIM(D52)&"♦"&TRIM(E52) -> IT planning and steering♦Collect and consolidate budget from stakeholders♦Implementation LUS♦L3♦MP
A53: IT planning and steering | B53: Develop preliminary budget plan | C53: Total | D53: L3 | E53: MP | F53: 0.5 | J53: 45945 | L53: 0 | O53: Manage and control IT financials | R53: =TRIM(A53)&"♦"&TRIM(B53)&"♦"&TRIM(C53)&"♦"&TRIM(D53)&"♦"&TRIM(E53) -> IT planning and steering♦Develop preliminary budget plan♦Total♦L3♦MP
A54: IT planning and steering | B54: Develop preliminary budget plan | C54: Elaboration | D54: L3 | E54: MP | F54: 0.5 | G54: Hynek Tobias (LIS);Kreis Andreas (LLI) | H54: Frank Nicole (LIS) | I54: Mielenz Thomas (LMT) | J54: 45945 | L54: 0 | O54: Manage and control IT financials | R54: =TRIM(A54)&"♦"&TRIM(B54)&"♦"&TRIM(C54)&"♦"&TRIM(D54)&"♦"&TRIM(E54) -> IT planning and steering♦Develop preliminary budget plan♦Elaboration♦L3♦MP
A55: IT planning and steering | B55: Develop preliminary budget plan | C55: Implementation LIS | D55: L3 | E55: MP | F55: 0 | L55: 0 | O55: Manage and control IT financials | R55: =TRIM(A55)&"♦"&TRIM(B55)&"♦"&TRIM(C55)&"♦"&TRIM(D55)&"♦"&TRIM(E55) -> IT planning and steering♦Develop preliminary budget plan♦Implementation LIS♦L3♦MP
A56: IT planning and steering | B56: Develop preliminary budget plan | C56: Implementation COT | D56: L3 | E56: MP | F56: 0 | L56: 0 | O56: Manage and control IT financials | R56: =TRIM(A56)&"♦"&TRIM(B56)&"♦"&TRIM(C56)&"♦"&TRIM(D56)&"♦"&TRIM(E56) -> IT planning and steering♦Develop preliminary budget plan♦Implementation COT♦L3♦MP
A57: IT planning and steering | B57: Develop preliminary budget plan | C57: Implementation LUS | D57: L3 | E57: MP | F57: 0 | L57: 0 | O57: Manage and control IT financials | R57: =TRIM(A57)&"♦"&TRIM(B57)&"♦"&TRIM(C57)&"♦"&TRIM(D57)&"♦"&TRIM(E57) -> IT planning and steering♦Develop preliminary budget plan♦Implementation LUS♦L3♦MP
A58: IT planning and steering | B58: Maintan and adjust budget | C58: Total | D58: L3 | E58: MP | F58: 0.5 | J58: 45945 | L58: 0 | O58: Manage and control IT financials | R58: =TRIM(A58)&"♦"&TRIM(B58)&"♦"&TRIM(C58)&"♦"&TRIM(D58)&"♦"&TRIM(E58) -> IT planning and steering♦Maintan and adjust budget♦Total♦L3♦MP
A59: IT planning and steering | B59: Maintan and adjust budget | C59: Elaboration | D59: L3 | E59: MP | F59: 0.5 | G59: Hynek Tobias (LIS);Kreis Andreas (LLI) | H59: Frank Nicole (LIS) | I59: Mielenz Thomas (LMT) | J59: 45945 | L59: 0 | O59: Manage and control IT financials | R59: =TRIM(A59)&"♦"&TRIM(B59)&"♦"&TRIM(C59)&"♦"&TRIM(D59)&"♦"&TRIM(E59) -> IT planning and steering♦Maintan and adjust budget♦Elaboration♦L3♦MP
A60: IT planning and steering | B60: Maintan and adjust budget | C60: Implementation LIS | D60: L3 | E60: MP | F60: 0 | L60: 0 | O60: Manage and control IT financials | R60: =TRIM(A60)&"♦"&TRIM(B60)&"♦"&TRIM(C60)&"♦"&TRIM(D60)&"♦"&TRIM(E60) -> IT planning and steering♦Maintan and adjust budget♦Implementation LIS♦L3♦MP
A61: IT planning and steering | B61: Maintan and adjust budget | C61: Implementation COT | D61: L3 | E61: MP | F61: 0 | L61: 0 | O61: Manage and control IT financials | R61: =TRIM(A61)&"♦"&TRIM(B61)&"♦"&TRIM(C61)&"♦"&TRIM(D61)&"♦"&TRIM(E61) -> IT planning and steering♦Maintan and adjust budget♦Implementation COT♦L3♦MP
A62: IT planning and steering | B62: Maintan and adjust budget | C62: Implementation LUS | D62: L3 | E62: MP | F62: 0 | L62: 0 | O62: Manage and control IT financials | R62: =TRIM(A62)&"♦"&TRIM(B62)&"♦"&TRIM(C62)&"♦"&TRIM(D62)&"♦"&TRIM(E62) -> IT planning and steering♦Maintan and adjust budget♦Implementation LUS♦L3♦MP
A63: IT planning and steering | B63: Review budget plan | C63: Total | D63: L3 | E63: MP | F63: 0.5 | J63: 45945 | L63: 0 | N63: 18 | O63: Manage and control IT financials | R63: =TRIM(A63)&"♦"&TRIM(B63)&"♦"&TRIM(C63)&"♦"&TRIM(D63)&"♦"&TRIM(E63) -> IT planning and steering♦Review budget plan♦Total♦L3♦MP
A64: IT planning and steering | B64: Review budget plan | C64: Elaboration | D64: L3 | E64: MP | F64: 0.5 | G64: Hynek Tobias (LIS);Kreis Andreas (LLI) | H64: Frank Nicole (LIS) | I64: Mielenz Thomas (LMT) | J64: 45945 | L64: 0 | O64: Manage and control IT financials | R64: =TRIM(A64)&"♦"&TRIM(B64)&"♦"&TRIM(C64)&"♦"&TRIM(D64)&"♦"&TRIM(E64) -> IT planning and steering♦Review budget plan♦Elaboration♦L3♦MP
A65: IT planning and steering | B65: Review budget plan | C65: Implementation LIS | D65: L3 | E65: MP | F65: 0 | L65: 0 | O65: Manage and control IT financials | R65: =TRIM(A65)&"♦"&TRIM(B65)&"♦"&TRIM(C65)&"♦"&TRIM(D65)&"♦"&TRIM(E65) -> IT planning and steering♦Review budget plan♦Implementation LIS♦L3♦MP
A66: IT planning and steering | B66: Review budget plan | C66: Implementation COT | D66: L3 | E66: MP | F66: 0 | L66: 0 | O66: Manage and control IT financials | R66: =TRIM(A66)&"♦"&TRIM(B66)&"♦"&TRIM(C66)&"♦"&TRIM(D66)&"♦"&TRIM(E66) -> IT planning and steering♦Review budget plan♦Implementation COT♦L3♦MP
A67: IT planning and steering | B67: Review budget plan | C67: Implementation LUS | D67: L3 | E67: MP | F67: 0 | L67: 0 | O67: Manage and control IT financials | R67: =TRIM(A67)&"♦"&TRIM(B67)&"♦"&TRIM(C67)&"♦"&TRIM(D67)&"♦"&TRIM(E67) -> IT planning and steering♦Review budget plan♦Implementation LUS♦L3♦MP
A68: IT planning and steering | B68: Revise and optimize budget plan | C68: Total | D68: L3 | E68: MP | F68: 0.5 | J68: 45945 | L68: 0 | O68: Manage and control IT financials | R68: =TRIM(A68)&"♦"&TRIM(B68)&"♦"&TRIM(C68)&"♦"&TRIM(D68)&"♦"&TRIM(E68) -> IT planning and steering♦Revise and optimize budget plan♦Total♦L3♦MP
A69: IT planning and steering | B69: Revise and optimize budget plan | C69: Elaboration | D69: L3 | E69: MP | F69: 0.5 | G69: Hynek Tobias (LIS);Kreis Andreas (LLI) | H69: Frank Nicole (LIS) | I69: Mielenz Thomas (LMT) | J69: 45945 | L69: 0 | O69: Manage and control IT financials | R69: =TRIM(A69)&"♦"&TRIM(B69)&"♦"&TRIM(C69)&"♦"&TRIM(D69)&"♦"&TRIM(E69) -> IT planning and steering♦Revise and optimize budget plan♦Elaboration♦L3♦MP
A70: IT planning and steering | B70: Revise and optimize budget plan | C70: Implementation LIS | D70: L3 | E70: MP | F70: 0 | L70: 0 | O70: Manage and control IT financials | R70: =TRIM(A70)&"♦"&TRIM(B70)&"♦"&TRIM(C70)&"♦"&TRIM(D70)&"♦"&TRIM(E70) -> IT planning and steering♦Revise and optimize budget plan♦Implementation LIS♦L3♦MP
A71: IT planning and steering | B71: Revise and optimize budget plan | C71: Implementation COT | D71: L3 | E71: MP | F71: 0 | L71: 0 | O71: Manage and control IT financials | R71: =TRIM(A71)&"♦"&TRIM(B71)&"♦"&TRIM(C71)&"♦"&TRIM(D71)&"♦"&TRIM(E71) -> IT planning and steering♦Revise and optimize budget plan♦Implementation COT♦L3♦MP
A72: IT planning and steering | B72: Revise and optimize budget plan | C72: Implementation LUS | D72: L3 | E72: MP | F72: 0 | L72: 0 | O72: Manage and control IT financials | R72: =TRIM(A72)&"♦"&TRIM(B72)&"♦"&TRIM(C72)&"♦"&TRIM(D72)&"♦"&TRIM(E72) -> IT planning and steering♦Revise and optimize budget plan♦Implementation LUS♦L3♦MP
A73: IT planning and steering | B73: Manage finance and accounting | C73: Total | D73: L2 | E73: MP | F73: 0.5 | J73: 45945 | L73: 0 | O73: Manage and control IT financials | R73: =TRIM(A73)&"♦"&TRIM(B73)&"♦"&TRIM(C73)&"♦"&TRIM(D73)&"♦"&TRIM(E73) -> IT planning and steering♦Manage finance and accounting♦Total♦L2♦MP
A74: IT planning and steering | B74: Manage finance and accounting | C74: Elaboration | D74: L2 | E74: MP | F74: 0.5 | G74: Hynek Tobias (LIS);Kreis Andreas (LLI) | H74: Frank Nicole (LIS) | I74: Moser Mario (LIS-LAH) | J74: 45945 | L74: 0 | O74: Manage and control IT financials | R74: =TRIM(A74)&"♦"&TRIM(B74)&"♦"&TRIM(C74)&"♦"&TRIM(D74)&"♦"&TRIM(E74) -> IT planning and steering♦Manage finance and accounting♦Elaboration♦L2♦MP
A75: IT planning and steering | B75: Manage finance and accounting | C75: Implementation LIS | D75: L2 | E75: MP | F75: 0 | L75: 0 | O75: Manage and control IT financials | R75: =TRIM(A75)&"♦"&TRIM(B75)&"♦"&TRIM(C75)&"♦"&TRIM(D75)&"♦"&TRIM(E75) -> IT planning and steering♦Manage finance and accounting♦Implementation LIS♦L2♦MP
A76: IT planning and steering | B76: Manage finance and accounting | C76: Implementation COT | D76: L2 | E76: MP | F76: 0 | L76: 0 | O76: Manage and control IT financials | R76: =TRIM(A76)&"♦"&TRIM(B76)&"♦"&TRIM(C76)&"♦"&TRIM(D76)&"♦"&TRIM(E76) -> IT planning and steering♦Manage finance and accounting♦Implementation COT♦L2♦MP
A77: IT planning and steering | B77: Manage finance and accounting | C77: Implementation LUS | D77: L2 | E77: MP | F77: 0 | L77: 0 | O77: Manage and control IT financials | R77: =TRIM(A77)&"♦"&TRIM(B77)&"♦"&TRIM(C77)&"♦"&TRIM(D77)&"♦"&TRIM(E77) -> IT planning and steering♦Manage finance and accounting♦Implementation LUS♦L2♦MP
A78: IT planning and steering | B78: Define financial management framework | C78: Total | D78: L3 | E78: MP | F78: 0.5 | J78: 45945 | L78: 0 | O78: Manage and control IT financials | R78: =TRIM(A78)&"♦"&TRIM(B78)&"♦"&TRIM(C78)&"♦"&TRIM(D78)&"♦"&TRIM(E78) -> IT planning and steering♦Define financial management framework♦Total♦L3♦MP
A79: IT planning and steering | B79: Define financial management framework | C79: Elaboration | D79: L3 | E79: MP | F79: 0.5 | G79: Hynek Tobias (LIS);Kreis Andreas (LLI) | H79: Frank Nicole (LIS) | I79: Moser Mario (LIS-LAH) | J79: 45945 | L79: 0 | O79: Manage and control IT financials | R79: =TRIM(A79)&"♦"&TRIM(B79)&"♦"&TRIM(C79)&"♦"&TRIM(D79)&"♦"&TRIM(E79) -> IT planning and steering♦Define financial management framework♦Elaboration♦L3♦MP
A80: IT planning and steering | B80: Define financial management framework | C80: Implementation LIS | D80: L3 | E80: MP | F80: 0 | L80: 0 | O80: Manage and control IT financials | R80: =TRIM(A80)&"♦"&TRIM(B80)&"♦"&TRIM(C80)&"♦"&TRIM(D80)&"♦"&TRIM(E80) -> IT planning and steering♦Define financial management framework♦Implementation LIS♦L3♦MP
A81: IT planning and steering | B81: Define financial management framework | C81: Implementation COT | D81: L3 | E81: MP | F81: 0 | L81: 0 | O81: Manage and control IT financials | R81: =TRIM(A81)&"♦"&TRIM(B81)&"♦"&TRIM(C81)&"♦"&TRIM(D81)&"♦"&TRIM(E81) -> IT planning and steering♦Define financial management framework♦Implementation COT♦L3♦MP
A82: IT planning and steering | B82: Define financial management framework | C82: Implementation LUS | D82: L3 | E82: MP | F82: 0 | L82: 0 | O82: Manage and control IT financials | R82: =TRIM(A82)&"♦"&TRIM(B82)&"♦"&TRIM(C82)&"♦"&TRIM(D82)&"♦"&TRIM(E82) -> IT planning and steering♦Define financial management framework♦Implementation LUS♦L3♦MP
A83: IT planning and steering | B83: Establish financial accounting structure | C83: Total | D83: L3 | E83: MP | F83: 0.5 | J83: 45945 | L83: 0 | O83: Manage and control IT financials | R83: =TRIM(A83)&"♦"&TRIM(B83)&"♦"&TRIM(C83)&"♦"&TRIM(D83)&"♦"&TRIM(E83) -> IT planning and steering♦Establish financial accounting structure♦Total♦L3♦MP
A84: IT planning and steering | B84: Establish financial accounting structure | C84: Elaboration | D84: L3 | E84: MP | F84: 0.5 | G84: Hynek Tobias (LIS);Kreis Andreas (LLI) | H84: Frank Nicole (LIS) | I84: Moser Mario (LIS-LAH) | J84: 45945 | L84: 0 | O84: Manage and control IT financials | R84: =TRIM(A84)&"♦"&TRIM(B84)&"♦"&TRIM(C84)&"♦"&TRIM(D84)&"♦"&TRIM(E84) -> IT planning and steering♦Establish financial accounting structure♦Elaboration♦L3♦MP
A85: IT planning and steering | B85: Establish financial accounting structure | C85: Implementation LIS | D85: L3 | E85: MP | F85: 0 | L85: 0 | O85: Manage and control IT financials | R85: =TRIM(A85)&"♦"&TRIM(B85)&"♦"&TRIM(C85)&"♦"&TRIM(D85)&"♦"&TRIM(E85) -> IT planning and steering♦Establish financial accounting structure♦Implementation LIS♦L3♦MP
A86: IT planning and steering | B86: Establish financial accounting structure | C86: Implementation COT | D86: L3 | E86: MP | F86: 0 | L86: 0 | O86: Manage and control IT financials | R86: =TRIM(A86)&"♦"&TRIM(B86)&"♦"&TRIM(C86)&"♦"&TRIM(D86)&"♦"&TRIM(E86) -> IT planning and steering♦Establish financial accounting structure♦Implementation COT♦L3♦MP
A87: IT planning and steering | B87: Establish financial accounting structure | C87: Implementation LUS | D87: L3 | E87: MP | F87: 0 | L87: 0 | O87: Manage and control IT financials | R87: =TRIM(A87)&"♦"&TRIM(B87)&"♦"&TRIM(C87)&"♦"&TRIM(D87)&"♦"&TRIM(E87) -> IT planning and steering♦Establish financial accounting structure♦Implementation LUS♦L3♦MP
A88: IT planning and steering | B88: Manage IT costs | C88: Total | D88: L2 | E88: MP | F88: 0.5 | J88: 45945 | L88: 0 | O88: Manage and control IT financials | R88: =TRIM(A88)&"♦"&TRIM(B88)&"♦"&TRIM(C88)&"♦"&TRIM(D88)&"♦"&TRIM(E88) -> IT planning and steering♦Manage IT costs♦Total♦L2♦MP
A89: IT planning and steering | B89: Manage IT costs | C89: Elaboration | D89: L2 | E89: MP | F89: 0.5 | G89: Hynek Tobias (LIS);Kreis Andreas (LLI) | H89: Frank Nicole (LIS) | I89: Moser Mario (LIS-LAH) | J89: 45945 | L89: 0 | O89: Manage and control IT financials | R89: =TRIM(A89)&"♦"&TRIM(B89)&"♦"&TRIM(C89)&"♦"&TRIM(D89)&"♦"&TRIM(E89) -> IT planning and steering♦Manage IT costs♦Elaboration♦L2♦MP
A90: IT planning and steering | B90: Manage IT costs | C90: Implementation LIS | D90: L2 | E90: MP | F90: 0 | L90: 0 | O90: Manage and control IT financials | R90: =TRIM(A90)&"♦"&TRIM(B90)&"♦"&TRIM(C90)&"♦"&TRIM(D90)&"♦"&TRIM(E90) -> IT planning and steering♦Manage IT costs♦Implementation LIS♦L2♦MP
A91: IT planning and steering | B91: Manage IT costs | C91: Implementation COT | E91: MP | F91: 0 | L91: 0 | O91: Manage and control IT financials | R91: =TRIM(A91)&"♦"&TRIM(B91)&"♦"&TRIM(C91)&"♦"&TRIM(D91)&"♦"&TRIM(E91) -> IT planning and steering♦Manage IT costs♦Implementation COT♦♦MP
A92: IT planning and steering | B92: Manage IT costs | C92: Implementation LUS | D92: L2 | E92: MP | F92: 0 | L92: 0 | O92: Manage and control IT financials | R92: =TRIM(A92)&"♦"&TRIM(B92)&"♦"&TRIM(C92)&"♦"&TRIM(D92)&"♦"&TRIM(E92) -> IT planning and steering♦Manage IT costs♦Implementation LUS♦L2♦MP
A93: IT planning and steering | B93: Compare actual cost to budget forecast | C93: Total | D93: L3 | E93: MP | F93: 0.5 | J93: 45945 | L93: 0 | O93: Manage and control IT financials | R93: =TRIM(A93)&"♦"&TRIM(B93)&"♦"&TRIM(C93)&"♦"&TRIM(D93)&"♦"&TRIM(E93) -> IT planning and steering♦Compare actual cost to budget forecast♦Total♦L3♦MP
A94: IT planning and steering | B94: Compare actual cost to budget forecast | C94: Elaboration | D94: L3 | E94: MP | F94: 0.5 | G94: Hynek Tobias (LIS);Kreis Andreas (LLI) | H94: Frank Nicole (LIS) | I94: Moser Mario (LIS-LAH) | J94: 45945 | L94: 0 | O94: Manage and control IT financials | R94: =TRIM(A94)&"♦"&TRIM(B94)&"♦"&TRIM(C94)&"♦"&TRIM(D94)&"♦"&TRIM(E94) -> IT planning and steering♦Compare actual cost to budget forecast♦Elaboration♦L3♦MP
A95: IT planning and steering | B95: Compare actual cost to budget forecast | C95: Implementation LIS | D95: L3 | E95: MP | F95: 0 | L95: 0 | O95: Manage and control IT financials | R95: =TRIM(A95)&"♦"&TRIM(B95)&"♦"&TRIM(C95)&"♦"&TRIM(D95)&"♦"&TRIM(E95) -> IT planning and steering♦Compare actual cost to budget forecast♦Implementation LIS♦L3♦MP
A96: IT planning and steering | B96: Compare actual cost to budget forecast | C96: Implementation COT | D96: L3 | E96: MP | F96: 0 | L96: 0 | O96: Manage and control IT financials | R96: =TRIM(A96)&"♦"&TRIM(B96)&"♦"&TRIM(C96)&"♦"&TRIM(D96)&"♦"&TRIM(E96) -> IT planning and steering♦Compare actual cost to budget forecast♦Implementation COT♦L3♦MP
A97: IT planning and steering | B97: Compare actual cost to budget forecast | C97: Implementation LUS | D97: L3 | E97: MP | F97: 0 | L97: 0 | O97: Manage and control IT financials | R97: =TRIM(A97)&"♦"&TRIM(B97)&"♦"&TRIM(C97)&"♦"&TRIM(D97)&"♦"&TRIM(E97) -> IT planning and steering♦Compare actual cost to budget forecast♦Implementation LUS♦L3♦MP
A98: IT planning and steering | B98: Initiate corrective or preventive actions | C98: Total | D98: L3 | E98: MP | F98: 0.5 | J98: 45945 | L98: 0 | O98: Manage and control IT financials | R98: =TRIM(A98)&"♦"&TRIM(B98)&"♦"&TRIM(C98)&"♦"&TRIM(D98)&"♦"&TRIM(E98) -> IT planning and steering♦Initiate corrective or preventive actions♦Total♦L3♦MP
A99: IT planning and steering | B99: Initiate corrective or preventive actions | C99: Elaboration | D99: L3 | E99: MP | F99: 0.5 | G99: Hynek Tobias (LIS);Kreis Andreas (LLI) | H99: Frank Nicole (LIS) | I99: Moser Mario (LIS-LAH) | J99: 45945 | L99: 0 | O99: Manage and control IT financials | R99: =TRIM(A99)&"♦"&TRIM(B99)&"♦"&TRIM(C99)&"♦"&TRIM(D99)&"♦"&TRIM(E99) -> IT planning and steering♦Initiate corrective or preventive actions♦Elaboration♦L3♦MP
A100: IT planning and steering | B100: Initiate corrective or preventive actions | C100: Implementation LIS | D100: L3 | E100: MP | F100: 0 | L100: 0 | O100: Manage and control IT financials | R100: =TRIM(A100)&"♦"&TRIM(B100)&"♦"&TRIM(C100)&"♦"&TRIM(D100)&"♦"&TRIM(E100) -> IT planning and steering♦Initiate corrective or preventive actions♦Implementation LIS♦L3♦MP
...

Sheet Date_table_13_4_26
A1: Datum | B1: Elaboration | C1: Implementation LIS | D1: Implementation LUS | E1: Implementation COT
A2: 45870 | B2: {=SUMPRODUCT((task_table_13_4_26!$C$2:$C$596=$B$1)*(A2>task_table_13_4_26!$J$2:$J$596)*(A2<task_table_13_4_26!$K$2:$K$596))} -> 0 | C2: {=SUMPRODUCT((task_table_13_4_26!$C$2:$C$596=$C$1)*(A2>task_table_13_4_26!$J$2:$J$596)*(A2<task_table_13_4_26!$K$2:$K$596))} -> 1 | D2: {=SUMPRODUCT((task_table_13_4_26!$C$2:$C$596=$D$1)*(A2>task_table_13_4_26!$J$2:$J$596)*(A2<task_table_13_4_26!$K$2:$K$596))} -> 0 | E2: {=SUMPRODUCT((task_table_13_4_26!$C$2:$C$596=$E$1)*(A2>task_table_13_4_26!$J$2:$J$596)*(A2<task_table_13_4_26!$K$2:$K$596))} -> 0
A3: 45871 | B3: {=SUMPRODUCT((task_table_13_4_26!$C$2:$C$596=$B$1)*(A3>task_table_13_4_26!$J$2:$J$596)*(A3<task_table_13_4_26!$K$2:$K$596))} -> 1 | C3: {=SUMPRODUCT((task_table_13_4_26!$C$2:$C$596=$C$1)*(A3>task_table_13_4_26!$J$2:$J$596)*(A3<task_table_13_4_26!$K$2:$K$596))} -> 1 | D3: {=SUMPRODUCT((task_table_13_4_26!$C$2:$C$596=$D$1)*(A3>task_table_13_4_26!$J$2:$J$596)*(A3<task_table_13_4_26!$K$2:$K$596))} -> 0 | E3: {=SUMPRODUCT((task_table_13_4_26!$C$2:$C$596=$E$1)*(A3>task_table_13_4_26!$J$2:$J$596)*(A3<task_table_13_4_26!$K$2:$K$596))} -> 0
A4: 45872 | B4: {=SUMPRODUCT((task_table_13_4_26!$C$2:$C$596=$B$1)*(A4>task_table_13_4_26!$J$2:$J$596)*(A4<task_table_13_4_26!$K$2:$K$596))} -> 1 | C4: {=SUMPRODUCT((task_table_13_4_26!$C$2:$C$596=$C$1)*(A4>task_table_13_4_26!$J$2:$J$596)*(A4<task_table_13_4_26!$K$2:$K$596))} -> 1 | D4: {=SUMPRODUCT((task_table_13_4_26!$C$2:$C$596=$D$1)*(A4>task_table_13_4_26!$J$2:$J$596)*(A4<task_table_13_4_26!$K$2:$K$596))} -> 0 | E4: {=SUMPRODUCT((task_table_13_4_26!$C$2:$C$596=$E$1)*(A4>task_table_13_4_26!$J$2:$J$596)*(A4<task_table_13_4_26!$K$2:$K$596))} -> 0
A5: 45873 | B5: {=SUMPRODUCT((task_table_13_4_26!$C$2:$C$596=$B$1)*(A5>task_table_13_4_26!$J$2:$J$596)*(A5<task_table_13_4_26!$K$2:$K$596))} -> 1 | C5: {=SUMPRODUCT((task_table_13_4_26!$C$2:$C$596=$C$1)*(A5>task_table_13_4_26!$J$2:$J$596)*(A5<task_table_13_4_26!$K$2:$K$596))} -> 1 | D5: {=SUMPRODUCT((task_table_13_4_26!$C$2:$C$596=$D$1)*(A5>task_table_13_4_26!$J$2:$J$596)*(A5<task_table_13_4_26!$K$2:$K$596))} -> 0 | E5: {=SUMPRODUCT((task_table_13_4_26!$C$2:$C$596=$E$1)*(A5>task_table_13_4_26!$J$2:$J$596)*(A5<task_table_13_4_26!$K$2:$K$596))} -> 0
A6: 45874 | B6: {=SUMPRODUCT((task_table_13_4_26!$C$2:$C$596=$B$1)*(A6>task_table_13_4_26!$J$2:$J$596)*(A6<task_table_13_4_26!$K$2:$K$596))} -> 2 | C6: {=SUMPRODUCT((task_table_13_4_26!$C$2:$C$596=$C$1)*(A6>task_table_13_4_26!$J$2:$J$596)*(A6<task_table_13_4_26!$K$2:$K$596))} -> 1 | D6: {=SUMPRODUCT((task_table_13_4_26!$C$2:$C$596=$D$1)*(A6>task_table_13_4_26!$J$2:$J$596)*(A6<task_table_13_4_26!$K$2:$K$596))} -> 0 | E6: {=SUMPRODUCT((task_table_13_4_26!$C$2:$C$596=$E$1)*(A6>task_table_13_4_26!$J$2:$J$596)*(A6<task_table_13_4_26!$K$2:$K$596))} -> 0
A7: 45875 | B7: {=SUMPRODUCT((task_table_13_4_26!$C$2:$C$596=$B$1)*(A7>task_table_13_4_26!$J$2:$J$596)*(A7<task_table_13_4_26!$K$2:$K$596))} -> 2 | C7: {=SUMPRODUCT((task_table_13_4_26!$C$2:$C$596=$C$1)*(A7>task_table_13_4_26!$J$2:$J$596)*(A7<task_table_13_4_26!$K$2:$K$596))} -> 1 | D7: {=SUMPRODUCT((task_table_13_4_26!$C$2:$C$596=$D$1)*(A7>task_table_13_4_26!$J$2:$J$596)*(A7<task_table_13_4_26!$K$2:$K$596))} -> 0 | E7: {=SUMPRODUCT((task_table_13_4_26!$C$2:$C$596=$E$1)*(A7>task_table_13_4_26!$J$2:$J$596)*(A7<task_table_13_4_26!$K$2:$K$596))} -> 0
A8: 45876 | B8: {=SUMPRODUCT((task_table_13_4_26!$C$2:$C$596=$B$1)*(A8>task_table_13_4_26!$J$2:$J$596)*(A8<task_table_13_4_26!$K$2:$K$596))} -> 2 | C8: {=SUMPRODUCT((task_table_13_4_26!$C$2:$C$596=$C$1)*(A8>task_table_13_4_26!$J$2:$J$596)*(A8<task_table_13_4_26!$K$2:$K$596))} -> 1 | D8: {=SUMPRODUCT((task_table_13_4_26!$C$2:$C$596=$D$1)*(A8>task_table_13_4_26!$J$2:$J$596)*(A8<task_table_13_4_26!$K$2:$K$596))} -> 0 | E8: {=SUMPRODUCT((task_table_13_4_26!$C$2:$C$596=$E$1)*(A8>task_table_13_4_26!$J$2:$J$596)*(A8<task_table_13_4_26!$K$2:$K$596))} -> 0
A9: 45877 | B9: {=SUMPRODUCT((task_table_13_4_26!$C$2:$C$596=$B$1)*(A9>task_table_13_4_26!$J$2:$J$596)*(A9<task_table_13_4_26!$K$2:$K$596))} -> 2 | C9: {=SUMPRODUCT((task_table_13_4_26!$C$2:$C$596=$C$1)*(A9>task_table_13_4_26!$J$2:$J$596)*(A9<task_table_13_4_26!$K$2:$K$596))} -> 1 | D9: {=SUMPRODUCT((task_table_13_4_26!$C$2:$C$596=$D$1)*(A9>task_table_13_4_26!$J$2:$J$596)*(A9<task_table_13_4_26!$K$2:$K$596))} -> 0 | E9: {=SUMPRODUCT((task_table_13_4_26!$C$2:$C$596=$E$1)*(A9>task_table_13_4_26!$J$2:$J$596)*(A9<task_table_13_4_26!$K$2:$K$596))} -> 0
A10: 45878 | B10: {=SUMPRODUCT((task_table_13_4_26!$C$2:$C$596=$B$1)*(A10>task_table_13_4_26!$J$2:$J$596)*(A10<task_table_13_4_26!$K$2:$K$596))} -> 2 | C10: {=SUMPRODUCT((task_table_13_4_26!$C$2:$C$596=$C$1)*(A10>task_table_13_4_26!$J$2:$J$596)*(A10<task_table_13_4_26!$K$2:$K$596))} -> 1 | D10: {=SUMPRODUCT((task_table_13_4_26!$C$2:$C$596=$D$1)*(A10>task_table_13_4_26!$J$2:$J$596)*(A10<task_table_13_4_26!$K$2:$K$596))} -> 0 | E10: {=SUMPRODUCT((task_table_13_4_26!$C$2:$C$596=$E$1)*(A10>task_table_13_4_26!$J$2:$J$596)*(A10<task_table_13_4_26!$K$2:$K$596))} -> 0
A11: 45879 | B11: {=SUMPRODUCT((task_table_13_4_26!$C$2:$C$596=$B$1)*(A11>task_table_13_4_26!$J$2:$J$596)*(A11<task_table_13_4_26!$K$2:$K$596))} -> 2 | C11: {=SUMPRODUCT((task_table_13_4_26!$C$2:$C$596=$C$1)*(A11>task_table_13_4_26!$J$2:$J$596)*(A11<task_table_13_4_26!$K$2:$K$596))} -> 1 | D11: {=SUMPRODUCT((task_table_13_4_26!$C$2:$C$596=$D$1)*(A11>task_table_13_4_26!$J$2:$J$596)*(A11<task_table_13_4_26!$K$2:$K$596))} -> 0 | E11: {=SUMPRODUCT((task_table_13_4_26!$C$2:$C$596=$E$1)*(A11>task_table_13_4_26!$J$2:$J$596)*(A11<task_table_13_4_26!$K$2:$K$596))} -> 0
A12: 45880 | B12: {=SUMPRODUCT((task_table_13_4_26!$C$2:$C$596=$B$1)*(A12>task_table_13_4_26!$J$2:$J$596)*(A12<task_table_13_4_26!$K$2:$K$596))} -> 2 | C12: {=SUMPRODUCT((task_table_13_4_26!$C$2:$C$596=$C$1)*(A12>task_table_13_4_26!$J$2:$J$596)*(A12<task_table_13_4_26!$K$2:$K$596))} -> 1 | D12: {=SUMPRODUCT((task_table_13_4_26!$C$2:$C$596=$D$1)*(A12>task_table_13_4_26!$J$2:$J$596)*(A12<task_table_13_4_26!$K$2:$K$596))} -> 0 | E12: {=SUMPRODUCT((task_table_13_4_26!$C$2:$C$596=$E$1)*(A12>task_table_13_4_26!$J$2:$J$596)*(A12<task_table_13_4_26!$K$2:$K$596))} -> 0
A13: 45881 | B13: {=SUMPRODUCT((task_table_13_4_26!$C$2:$C$596=$B$1)*(A13>task_table_13_4_26!$J$2:$J$596)*(A13<task_table_13_4_26!$K$2:$K$596))} -> 2 | C13: {=SUMPRODUCT((task_table_13_4_26!$C$2:$C$596=$C$1)*(A13>task_table_13_4_26!$J$2:$J$596)*(A13<task_table_13_4_26!$K$2:$K$596))} -> 1 | D13: {=SUMPRODUCT((task_table_13_4_26!$C$2:$C$596=$D$1)*(A13>task_table_13_4_26!$J$2:$J$596)*(A13<task_table_13_4_26!$K$2:$K$596))} -> 0 | E13: {=SUMPRODUCT((task_table_13_4_26!$C$2:$C$596=$E$1)*(A13>task_table_13_4_26!$J$2:$J$596)*(A13<task_table_13_4_26!$K$2:$K$596))} -> 0
... A520: 46388 | B520: {=SUMPRODUCT((task_table_13_4_26!$C$2:$C$596=$B$1)*(A520>task_table_13_4_26!$J$2:$J$596)*(A520<task_table_13_4_26!$K$2:$K$596))} -> 0 | C520: {=SUMPRODUCT((task_table_13_4_26!$C$2:$C$596=$C$1)*(A520>task_table_13_4_26!$J$2:$J$596)*(A520<task_table_13_4_26!$K$2:$K$596))} -> 0 | D520: {=SUMPRODUCT((task_table_13_4_26!$C$2:$C$596=$D$1)*(A520>task_table_13_4_26!$J$2:$J$596)*(A520<task_table_13_4_26!$K$2:$K$596))} -> 0 | E520: {=SUMPRODUCT((task_table_13_4_26!$C$2:$C$596=$E$1)*(A520>task_table_13_4_26!$J$2:$J$596)*(A520<task_table_13_4_26!$K$2:$K$596))} -> 0

Sheet data Draft-april26
A1: Vorgangsmodus | B1: Initiative | C1: Process | D1: Phase | E1: Process level | F1: Process Group | G1: % Work done | H1: IT Process Consultant | I1: IT Process Initiative Lead | J1: IT Process Manager | K1: Start | L1: End | M1: Duration in days | N1: Process Approval Date | O1: Actual Phase | P1: Planned phase | Q1: Associated Process on L1 | R1: Comment | S1: Parent Process
A2: Manuell geplant | C2: Management Processes | E2: L1 | F2: MP | G2: 0.31 | K2: 45931 | M2: =_xlfn.LET(_xlpm.k,TRIM(tbl_DataDraftApril26[[#This Row],[Initiative]])&"♦"&TRIM(tbl_DataDraftApril26[[#This Row],[Process]])&"♦"&TRIM(tbl_DataDraftApril26[[#This Row],[Phase]])&"♦"&TRIM(tbl_DataDraftApril26[[#This Row],[Process level]])&"♦"&TRIM(tbl_DataDraftApril26[[#This Row],[Process Group]]),_xlpm.s,tbl_DataDraftApril26[[#This Row],[Start]],_xlpm.e,tbl_DataDraftApril26[[#This Row],[End]],IF(OR(_xlpm.s="",_xlpm.e=""),"",_xlfn.XLOOKUP(_xlpm.k,task_table_13_4_26!$R$2:$R$612,task_table_13_4_26!$L$2:$L$612,""))) | Q2: Management Processes
A3: Automatisch geplant | B3: Corporate IT body | C3: Manage IT strategy | D3: Total | E3: L1 | F3: MP | G3: 0.5 | H3: Kreis Andreas (LLI) | I3: Felder Max (LLI) | J3: Mielenz Thomas (LMT) | K3: 46055 | L3: 46232 | M3: =_xlfn.LET(_xlpm.k,TRIM(tbl_DataDraftApril26[[#This Row],[Initiative]])&"♦"&TRIM(tbl_DataDraftApril26[[#This Row],[Process]])&"♦"&TRIM(tbl_DataDraftApril26[[#This Row],[Phase]])&"♦"&TRIM(tbl_DataDraftApril26[[#This Row],[Process level]])&"♦"&TRIM(tbl_DataDraftApril26[[#This Row],[Process Group]]),_xlpm.s,tbl_DataDraftApril26[[#This Row],[Start]],_xlpm.e,tbl_DataDraftApril26[[#This Row],[End]],IF(OR(_xlpm.s="",_xlpm.e=""),"",_xlfn.XLOOKUP(_xlpm.k,task_table_13_4_26!$R$2:$R$612,task_table_13_4_26!$L$2:$L$612,""))) -> 128 | N3: 46148 | P3: 1 | Q3: Manage IT strategy
A4: Manuell geplant | B4: Corporate IT body | C4: Manage IT strategy | D4: Elaboration | E4: L1 | F4: MP | G4: 0.5 | H4: Kreis Andreas (LLI) | I4: Felder Max (LLI) | J4: Mielenz Thomas (LMT) | K4: 46055 | L4: 46142 | M4: =_xlfn.LET(_xlpm.k,TRIM(tbl_DataDraftApril26[[#This Row],[Initiative]])&"♦"&TRIM(tbl_DataDraftApril26[[#This Row],[Process]])&"♦"&TRIM(tbl_DataDraftApril26[[#This Row],[Phase]])&"♦"&TRIM(tbl_DataDraftApril26[[#This Row],[Process level]])&"♦"&TRIM(tbl_DataDraftApril26[[#This Row],[Process Group]]),_xlpm.s,tbl_DataDraftApril26[[#This Row],[Start]],_xlpm.e,tbl_DataDraftApril26[[#This Row],[End]],IF(OR(_xlpm.s="",_xlpm.e=""),"",_xlfn.XLOOKUP(_xlpm.k,task_table_13_4_26!$R$2:$R$612,task_table_13_4_26!$L$2:$L$612,""))) -> 64 | O4: Elaboration in progress | P4: Elaboration in progress | Q4: Manage IT strategy
A5: Manuell geplant | B5: Corporate IT body | C5: Manage IT strategy | D5: Implementation LIS | E5: L1 | F5: MP | G5: 0 | H5: Kreis Andreas (LLI) | I5: Felder Max (LLI) | J5: Mielenz Thomas (LMT) | K5: 46156 | L5: 46232 | M5: =_xlfn.LET(_xlpm.k,TRIM(tbl_DataDraftApril26[[#This Row],[Initiative]])&"♦"&TRIM(tbl_DataDraftApril26[[#This Row],[Process]])&"♦"&TRIM(tbl_DataDraftApril26[[#This Row],[Phase]])&"♦"&TRIM(tbl_DataDraftApril26[[#This Row],[Process level]])&"♦"&TRIM(tbl_DataDraftApril26[[#This Row],[Process Group]]),_xlpm.s,tbl_DataDraftApril26[[#This Row],[Start]],_xlpm.e,tbl_DataDraftApril26[[#This Row],[End]],IF(OR(_xlpm.s="",_xlpm.e=""),"",_xlfn.XLOOKUP(_xlpm.k,task_table_13_4_26!$R$2:$R$612,task_table_13_4_26!$L$2:$L$612,""))) -> 55 | P5: Scheduled | Q5: Manage IT strategy
A6: Manuell geplant | B6: Corporate IT body | C6: Manage IT strategy | D6: Implementation COT | E6: L1 | F6: MP | G6: 0 | H6: Kreis Andreas (LLI) | I6: Felder Max (LLI) | J6: Mielenz Thomas (LMT) | M6: =_xlfn.LET(_xlpm.k,TRIM(tbl_DataDraftApril26[[#This Row],[Initiative]])&"♦"&TRIM(tbl_DataDraftApril26[[#This Row],[Process]])&"♦"&TRIM(tbl_DataDraftApril26[[#This Row],[Phase]])&"♦"&TRIM(tbl_DataDraftApril26[[#This Row],[Process level]])&"♦"&TRIM(tbl_DataDraftApril26[[#This Row],[Process Group]]),_xlpm.s,tbl_DataDraftApril26[[#This Row],[Start]],_xlpm.e,tbl_DataDraftApril26[[#This Row],[End]],IF(OR(_xlpm.s="",_xlpm.e=""),"",_xlfn.XLOOKUP(_xlpm.k,task_table_13_4_26!$R$2:$R$612,task_table_13_4_26!$L$2:$L$612,""))) | Q6: Manage IT strategy
A7: Manuell geplant | B7: Corporate IT body | C7: Manage IT strategy | D7: Implementation LUS | E7: L1 | F7: MP | G7: 0 | H7: Kreis Andreas (LLI) | I7: Felder Max (LLI) | J7: Mielenz Thomas (LMT) | M7: =_xlfn.LET(_xlpm.k,TRIM(tbl_DataDraftApril26[[#This Row],[Initiative]])&"♦"&TRIM(tbl_DataDraftApril26[[#This Row],[Process]])&"♦"&TRIM(tbl_DataDraftApril26[[#This Row],[Phase]])&"♦"&TRIM(tbl_DataDraftApril26[[#This Row],[Process level]])&"♦"&TRIM(tbl_DataDraftApril26[[#This Row],[Process Group]]),_xlpm.s,tbl_DataDraftApril26[[#This Row],[Start]],_xlpm.e,tbl_DataDraftApril26[[#This Row],[End]],IF(OR(_xlpm.s="",_xlpm.e=""),"",_xlfn.XLOOKUP(_xlpm.k,task_table_13_4_26!$R$2:$R$612,task_table_13_4_26!$L$2:$L$612,""))) | Q7: Manage IT strategy
A8: Automatisch geplant | B8: Corporate IT body | C8: Manage IT governance framework | D8: Total | E8: L1 | F8: MP | G8: 0.5 | H8: Kunz Christina (LIS-MHP Management- und IT Beratung GmbH);Kreis Andreas (LLI) | I8: Felder Max (LLI) | J8: Mielenz Thomas (LMT) | K8: 46029 | L8: 46265 | M8: =_xlfn.LET(_xlpm.k,TRIM(tbl_DataDraftApril26[[#This Row],[Initiative]])&"♦"&TRIM(tbl_DataDraftApril26[[#This Row],[Process]])&"♦"&TRIM(tbl_DataDraftApril26[[#This Row],[Phase]])&"♦"&TRIM(tbl_DataDraftApril26[[#This Row],[Process level]])&"♦"&TRIM(tbl_DataDraftApril26[[#This Row],[Process Group]]),_xlpm.s,tbl_DataDraftApril26[[#This Row],[Start]],_xlpm.e,tbl_DataDraftApril26[[#This Row],[End]],IF(OR(_xlpm.s="",_xlpm.e=""),"",_xlfn.XLOOKUP(_xlpm.k,task_table_13_4_26!$R$2:$R$612,task_table_13_4_26!$L$2:$L$612,""))) -> 169 | Q8: Manage IT governance framework
A9: Manuell geplant | B9: Corporate IT body | C9: Manage IT governance framework | D9: Elaboration | E9: L1 | F9: MP | G9: 0.5 | H9: Kunz Christina (LIS-MHP Management- und IT Beratung GmbH);Kreis Andreas (LLI) | I9: Felder Max (LLI) | J9: Mielenz Thomas (LMT) | K9: 46097 | L9: 46163 | M9: =_xlfn.LET(_xlpm.k,TRIM(tbl_DataDraftApril26[[#This Row],[Initiative]])&"♦"&TRIM(tbl_DataDraftApril26[[#This Row],[Process]])&"♦"&TRIM(tbl_DataDraftApril26[[#This Row],[Phase]])&"♦"&TRIM(tbl_DataDraftApril26[[#This Row],[Process level]])&"♦"&TRIM(tbl_DataDraftApril26[[#This Row],[Process Group]]),_xlpm.s,tbl_DataDraftApril26[[#This Row],[Start]],_xlpm.e,tbl_DataDraftApril26[[#This Row],[End]],IF(OR(_xlpm.s="",_xlpm.e=""),"",_xlfn.XLOOKUP(_xlpm.k,task_table_13_4_26!$R$2:$R$612,task_table_13_4_26!$L$2:$L$612,""))) -> 49 | O9: Elaboration in progress | P9: Elaboration in progress | Q9: Manage IT governance framework
A10: Manuell geplant | B10: Corporate IT body | C10: Manage IT governance framework | D10: Implementation LIS | E10: L1 | F10: MP | G10: 0 | H10: Kunz Christina (LIS-MHP Management- und IT Beratung GmbH);Kreis Andreas (LLI) | I10: Felder Max (LLI) | J10: Mielenz Thomas (LMT) | K10: 46167 | L10: 46265 | M10: =_xlfn.LET(_xlpm.k,TRIM(tbl_DataDraftApril26[[#This Row],[Initiative]])&"♦"&TRIM(tbl_DataDraftApril26[[#This Row],[Process]])&"♦"&TRIM(tbl_DataDraftApril26[[#This Row],[Phase]])&"♦"&TRIM(tbl_DataDraftApril26[[#This Row],[Process level]])&"♦"&TRIM(tbl_DataDraftApril26[[#This Row],[Process Group]]),_xlpm.s,tbl_DataDraftApril26[[#This Row],[Start]],_xlpm.e,tbl_DataDraftApril26[[#This Row],[End]],IF(OR(_xlpm.s="",_xlpm.e=""),"",_xlfn.XLOOKUP(_xlpm.k,task_table_13_4_26!$R$2:$R$612,task_table_13_4_26!$L$2:$L$612,""))) -> 71 | P10: Scheduled | Q10: Manage IT governance framework
A11: Manuell geplant | B11: Corporate IT body | C11: Manage IT governance framework | D11: Implementation COT | E11: L1 | F11: MP | G11: 0 | H11: Kunz Christina (LIS-MHP Management- und IT Beratung GmbH);Kreis Andreas (LLI) | I11: Felder Max (LLI) | J11: Mielenz Thomas (LMT) | M11: =_xlfn.LET(_xlpm.k,TRIM(tbl_DataDraftApril26[[#This Row],[Initiative]])&"♦"&TRIM(tbl_DataDraftApril26[[#This Row],[Process]])&"♦"&TRIM(tbl_DataDraftApril26[[#This Row],[Phase]])&"♦"&TRIM(tbl_DataDraftApril26[[#This Row],[Process level]])&"♦"&TRIM(tbl_DataDraftApril26[[#This Row],[Process Group]]),_xlpm.s,tbl_DataDraftApril26[[#This Row],[Start]],_xlpm.e,tbl_DataDraftApril26[[#This Row],[End]],IF(OR(_xlpm.s="",_xlpm.e=""),"",_xlfn.XLOOKUP(_xlpm.k,task_table_13_4_26!$R$2:$R$612,task_table_13_4_26!$L$2:$L$612,""))) | Q11: Manage IT governance framework
A12: Manuell geplant | B12: Corporate IT body | C12: Manage IT governance framework | D12: Implementation LUS | E12: L1 | F12: MP | G12: 0 | H12: Kunz Christina (LIS-MHP Management- und IT Beratung GmbH);Kreis Andreas (LLI) | I12: Felder Max (LLI) | J12: Mielenz Thomas (LMT) | M12: =_xlfn.LET(_xlpm.k,TRIM(tbl_DataDraftApril26[[#This Row],[Initiative]])&"♦"&TRIM(tbl_DataDraftApril26[[#This Row],[Process]])&"♦"&TRIM(tbl_DataDraftApril26[[#This Row],[Phase]])&"♦"&TRIM(tbl_DataDraftApril26[[#This Row],[Process level]])&"♦"&TRIM(tbl_DataDraftApril26[[#This Row],[Process Group]]),_xlpm.s,tbl_DataDraftApril26[[#This Row],[Start]],_xlpm.e,tbl_DataDraftApril26[[#This Row],[End]],IF(OR(_xlpm.s="",_xlpm.e=""),"",_xlfn.XLOOKUP(_xlpm.k,task_table_13_4_26!$R$2:$R$612,task_table_13_4_26!$L$2:$L$612,""))) | Q12: Manage IT governance framework
A13: Automatisch geplant | B13: Corporate IT body | C13: Maintain IT glossary | D13: Total | E13: L2 | F13: MP | G13: 0.25 | H13: Kunz Christina (LIS-MHP Management- und IT Beratung GmbH) | I13: Felder Max (LLI) | J13: Mielenz Thomas (LMT) | K13: 46029 | L13: 46039 | M13: =_xlfn.LET(_xlpm.k,TRIM(tbl_DataDraftApril26[[#This Row],[Initiative]])&"♦"&TRIM(tbl_DataDraftApril26[[#This Row],[Process]])&"♦"&TRIM(tbl_DataDraftApril26[[#This Row],[Phase]])&"♦"&TRIM(tbl_DataDraftApril26[[#This Row],[Process level]])&"♦"&TRIM(tbl_DataDraftApril26[[#This Row],[Process Group]]),_xlpm.s,tbl_DataDraftApril26[[#This Row],[Start]],_xlpm.e,tbl_DataDraftApril26[[#This Row],[End]],IF(OR(_xlpm.s="",_xlpm.e=""),"",_xlfn.XLOOKUP(_xlpm.k,task_table_13_4_26!$R$2:$R$612,task_table_13_4_26!$L$2:$L$612,""))) -> 8 | Q13: Manage IT governance framework | S13: =C8 -> Manage IT governance framework
A14: Manuell geplant | B14: Corporate IT body | C14: Maintain IT glossary | D14: Elaboration | E14: L2 | F14: MP | G14: 0.25 | H14: Kunz Christina (LIS-MHP Management- und IT Beratung GmbH) | I14: Felder Max (LLI) | J14: Mielenz Thomas (LMT) | K14: 46029 | M14: =_xlfn.LET(_xlpm.k,TRIM(tbl_DataDraftApril26[[#This Row],[Initiative]])&"♦"&TRIM(tbl_DataDraftApril26[[#This Row],[Process]])&"♦"&TRIM(tbl_DataDraftApril26[[#This Row],[Phase]])&"♦"&TRIM(tbl_DataDraftApril26[[#This Row],[Process level]])&"♦"&TRIM(tbl_DataDraftApril26[[#This Row],[Process Group]]),_xlpm.s,tbl_DataDraftApril26[[#This Row],[Start]],_xlpm.e,tbl_DataDraftApril26[[#This Row],[End]],IF(OR(_xlpm.s="",_xlpm.e=""),"",_xlfn.XLOOKUP(_xlpm.k,task_table_13_4_26!$R$2:$R$612,task_table_13_4_26!$L$2:$L$612,""))) | Q14: Manage IT governance framework | S14: =C9 -> Manage IT governance framework
A15: Manuell geplant | B15: Corporate IT body | C15: Maintain IT glossary | D15: Implementation LIS | E15: L2 | F15: MP | G15: 0 | H15: Kunz Christina (LIS-MHP Management- und IT Beratung GmbH) | I15: Felder Max (LLI) | J15: Mielenz Thomas (LMT) | K15: 46029 | L15: 46039 | M15: =_xlfn.LET(_xlpm.k,TRIM(tbl_DataDraftApril26[[#This Row],[Initiative]])&"♦"&TRIM(tbl_DataDraftApril26[[#This Row],[Process]])&"♦"&TRIM(tbl_DataDraftApril26[[#This Row],[Phase]])&"♦"&TRIM(tbl_DataDraftApril26[[#This Row],[Process level]])&"♦"&TRIM(tbl_DataDraftApril26[[#This Row],[Process Group]]),_xlpm.s,tbl_DataDraftApril26[[#This Row],[Start]],_xlpm.e,tbl_DataDraftApril26[[#This Row],[End]],IF(OR(_xlpm.s="",_xlpm.e=""),"",_xlfn.XLOOKUP(_xlpm.k,task_table_13_4_26!$R$2:$R$612,task_table_13_4_26!$L$2:$L$612,""))) -> 7 | O15: Delayed | P15: Implementation LIS Done | Q15: Manage IT governance framework | S15: =C10 -> Manage IT governance framework
A16: Manuell geplant | B16: Corporate IT body | C16: Maintain IT glossary | D16: Implementation COT | E16: L2 | F16: MP | G16: 0 | H16: Kunz Christina (LIS-MHP Management- und IT Beratung GmbH) | I16: Felder Max (LLI) | J16: Mielenz Thomas (LMT) | K16: 46029 | M16: =_xlfn.LET(_xlpm.k,TRIM(tbl_DataDraftApril26[[#This Row],[Initiative]])&"♦"&TRIM(tbl_DataDraftApril26[[#This Row],[Process]])&"♦"&TRIM(tbl_DataDraftApril26[[#This Row],[Phase]])&"♦"&TRIM(tbl_DataDraftApril26[[#This Row],[Process level]])&"♦"&TRIM(tbl_DataDraftApril26[[#This Row],[Process Group]]),_xlpm.s,tbl_DataDraftApril26[[#This Row],[Start]],_xlpm.e,tbl_DataDraftApril26[[#This Row],[End]],IF(OR(_xlpm.s="",_xlpm.e=""),"",_xlfn.XLOOKUP(_xlpm.k,task_table_13_4_26!$R$2:$R$612,task_table_13_4_26!$L$2:$L$612,""))) | Q16: Manage IT governance framework | S16: =C11 -> Manage IT governance framework
A17: Manuell geplant | B17: Corporate IT body | C17: Maintain IT glossary | D17: Implementation LUS | E17: L2 | F17: MP | G17: 0 | H17: Kunz Christina (LIS-MHP Management- und IT Beratung GmbH) | I17: Felder Max (LLI) | J17: Mielenz Thomas (LMT) | M17: =_xlfn.LET(_xlpm.k,TRIM(tbl_DataDraftApril26[[#This Row],[Initiative]])&"♦"&TRIM(tbl_DataDraftApril26[[#This Row],[Process]])&"♦"&TRIM(tbl_DataDraftApril26[[#This Row],[Phase]])&"♦"&TRIM(tbl_DataDraftApril26[[#This Row],[Process level]])&"♦"&TRIM(tbl_DataDraftApril26[[#This Row],[Process Group]]),_xlpm.s,tbl_DataDraftApril26[[#This Row],[Start]],_xlpm.e,tbl_DataDraftApril26[[#This Row],[End]],IF(OR(_xlpm.s="",_xlpm.e=""),"",_xlfn.XLOOKUP(_xlpm.k,task_table_13_4_26!$R$2:$R$612,task_table_13_4_26!$L$2:$L$612,""))) | Q17: Manage IT governance framework | S17: =C12 -> Manage IT governance framework
A18: Automatisch geplant | B18: Corporate IT body | C18: Manage enterprise architecture | D18: Total | E18: L1 | F18: MP | G18: 0 | K18: 45946 | L18: 46219 | M18: =_xlfn.LET(_xlpm.k,TRIM(tbl_DataDraftApril26[[#This Row],[Initiative]])&"♦"&TRIM(tbl_DataDraftApril26[[#This Row],[Process]])&"♦"&TRIM(tbl_DataDraftApril26[[#This Row],[Phase]])&"♦"&TRIM(tbl_DataDraftApril26[[#This Row],[Process level]])&"♦"&TRIM(tbl_DataDraftApril26[[#This Row],[Process Group]]),_xlpm.s,tbl_DataDraftApril26[[#This Row],[Start]],_xlpm.e,tbl_DataDraftApril26[[#This Row],[End]],IF(OR(_xlpm.s="",_xlpm.e=""),"",_xlfn.XLOOKUP(_xlpm.k,task_table_13_4_26!$R$2:$R$612,task_table_13_4_26!$L$2:$L$612,""))) -> 195.85 | Q18: Manage enterprise architecture
A19: Manuell geplant | B19: Corporate IT body | C19: Manage enterprise architecture | D19: Elaboration | E19: L1 | F19: MP | G19: 0 | H19: Hoermann Patrick (LLI) | I19: Gujral Parth (COB-COT-IT) | J19: Nussbaumer Florian (LBC) | K19: 46076 | L19: 46150 | M19: =_xlfn.LET(_xlpm.k,TRIM(tbl_DataDraftApril26[[#This Row],[Initiative]])&"♦"&TRIM(tbl_DataDraftApril26[[#This Row],[Process]])&"♦"&TRIM(tbl_DataDraftApril26[[#This Row],[Phase]])&"♦"&TRIM(tbl_DataDraftApril26[[#This Row],[Process level]])&"♦"&TRIM(tbl_DataDraftApril26[[#This Row],[Process Group]]),_xlpm.s,tbl_DataDraftApril26[[#This Row],[Start]],_xlpm.e,tbl_DataDraftApril26[[#This Row],[End]],IF(OR(_xlpm.s="",_xlpm.e=""),"",_xlfn.XLOOKUP(_xlpm.k,task_table_13_4_26!$R$2:$R$612,task_table_13_4_26!$L$2:$L$612,""))) | O19: Delayed | P19: Elaboration in progress | Q19: Manage enterprise architecture
A20: Automatisch geplant | B20: Corporate IT body | C20: Manage enterprise architecture | D20: Implementation LIS | E20: L1 | F20: MP | G20: 0 | K20: 46150 | L20: 46219 | M20: =_xlfn.LET(_xlpm.k,TRIM(tbl_DataDraftApril26[[#This Row],[Initiative]])&"♦"&TRIM(tbl_DataDraftApril26[[#This Row],[Process]])&"♦"&TRIM(tbl_DataDraftApril26[[#This Row],[Phase]])&"♦"&TRIM(tbl_DataDraftApril26[[#This Row],[Process level]])&"♦"&TRIM(tbl_DataDraftApril26[[#This Row],[Process Group]]),_xlpm.s,tbl_DataDraftApril26[[#This Row],[Start]],_xlpm.e,tbl_DataDraftApril26[[#This Row],[End]],IF(OR(_xlpm.s="",_xlpm.e=""),"",_xlfn.XLOOKUP(_xlpm.k,task_table_13_4_26!$R$2:$R$612,task_table_13_4_26!$L$2:$L$612,""))) | P20: Scheduled | Q20: Manage enterprise architecture
A21: Manuell geplant | B21: Corporate IT body | C21: Manage enterprise architecture | D21: Implementation COT | E21: L1 | F21: MP | G21: 0 | K21: 46150 | L21: 46153 | M21: =_xlfn.LET(_xlpm.k,TRIM(tbl_DataDraftApril26[[#This Row],[Initiative]])&"♦"&TRIM(tbl_DataDraftApril26[[#This Row],[Process]])&"♦"&TRIM(tbl_DataDraftApril26[[#This Row],[Phase]])&"♦"&TRIM(tbl_DataDraftApril26[[#This Row],[Process level]])&"♦"&TRIM(tbl_DataDraftApril26[[#This Row],[Process Group]]),_xlpm.s,tbl_DataDraftApril26[[#This Row],[Start]],_xlpm.e,tbl_DataDraftApril26[[#This Row],[End]],IF(OR(_xlpm.s="",_xlpm.e=""),"",_xlfn.XLOOKUP(_xlpm.k,task_table_13_4_26!$R$2:$R$612,task_table_13_4_26!$L$2:$L$612,""))) | P21: Scheduled | Q21: Manage enterprise architecture
A22: Manuell geplant | B22: Corporate IT body | C22: Manage enterprise architecture | D22: Implementation LUS | E22: L1 | F22: MP | G22: 0 | K22: 46150 | L22: 46153 | M22: =_xlfn.LET(_xlpm.k,TRIM(tbl_DataDraftApril26[[#This Row],[Initiative]])&"♦"&TRIM(tbl_DataDraftApril26[[#This Row],[Process]])&"♦"&TRIM(tbl_DataDraftApril26[[#This Row],[Phase]])&"♦"&TRIM(tbl_DataDraftApril26[[#This Row],[Process level]])&"♦"&TRIM(tbl_DataDraftApril26[[#This Row],[Process Group]]),_xlpm.s,tbl_DataDraftApril26[[#This Row],[Start]],_xlpm.e,tbl_DataDraftApril26[[#This Row],[End]],IF(OR(_xlpm.s="",_xlpm.e=""),"",_xlfn.XLOOKUP(_xlpm.k,task_table_13_4_26!$R$2:$R$612,task_table_13_4_26!$L$2:$L$612,""))) | P22: Scheduled | Q22: Manage enterprise architecture
A23: Automatisch geplant | B23: Corporate IT body | C23: Strategic architecture process | D23: Total | E23: L2 | F23: MP | G23: 0 | K23: 45946 | L23: 46142 | M23: =_xlfn.LET(_xlpm.k,TRIM(tbl_DataDraftApril26[[#This Row],[Initiative]])&"♦"&TRIM(tbl_DataDraftApril26[[#This Row],[Process]])&"♦"&TRIM(tbl_DataDraftApril26[[#This Row],[Phase]])&"♦"&TRIM(tbl_DataDraftApril26[[#This Row],[Process level]])&"♦"&TRIM(tbl_DataDraftApril26[[#This Row],[Process Group]]),_xlpm.s,tbl_DataDraftApril26[[#This Row],[Start]],_xlpm.e,tbl_DataDraftApril26[[#This Row],[End]],IF(OR(_xlpm.s="",_xlpm.e=""),"",_xlfn.XLOOKUP(_xlpm.k,task_table_13_4_26!$R$2:$R$612,task_table_13_4_26!$L$2:$L$612,""))) | Q23: Manage enterprise architecture
A24: Manuell geplant | B24: Corporate IT body | C24: Strategic architecture process | D24: Elaboration | E24: L2 | F24: MP | G24: 0 | H24: Hoermann Patrick (LLI) | I24: Gujral Parth (COB-COT-IT) | J24: Nussbaumer Florian (LBC) | K24: 46076 | L24: 46142 | M24: =_xlfn.LET(_xlpm.k,TRIM(tbl_DataDraftApril26[[#This Row],[Initiative]])&"♦"&TRIM(tbl_DataDraftApril26[[#This Row],[Process]])&"♦"&TRIM(tbl_DataDraftApril26[[#This Row],[Phase]])&"♦"&TRIM(tbl_DataDraftApril26[[#This Row],[Process level]])&"♦"&TRIM(tbl_DataDraftApril26[[#This Row],[Process Group]]),_xlpm.s,tbl_DataDraftApril26[[#This Row],[Start]],_xlpm.e,tbl_DataDraftApril26[[#This Row],[End]],IF(OR(_xlpm.s="",_xlpm.e=""),"",_xlfn.XLOOKUP(_xlpm.k,task_table_13_4_26!$R$2:$R$612,task_table_13_4_26!$L$2:$L$612,""))) | O24: Delayed | P24: Elaboration in progress | Q24: Manage enterprise architecture
A25: Manuell geplant | B25: Corporate IT body | C25: Strategic architecture process | D25: Implementation LIS | E25: L2 | F25: MP | G25: 0 | M25: =_xlfn.LET(_xlpm.k,TRIM(tbl_DataDraftApril26[[#This Row],[Initiative]])&"♦"&TRIM(tbl_DataDraftApril26[[#This Row],[Process]])&"♦"&TRIM(tbl_DataDraftApril26[[#This Row],[Phase]])&"♦"&TRIM(tbl_DataDraftApril26[[#This Row],[Process level]])&"♦"&TRIM(tbl_DataDraftApril26[[#This Row],[Process Group]]),_xlpm.s,tbl_DataDraftApril26[[#This Row],[Start]],_xlpm.e,tbl_DataDraftApril26[[#This Row],[End]],IF(OR(_xlpm.s="",_xlpm.e=""),"",_xlfn.XLOOKUP(_xlpm.k,task_table_13_4_26!$R$2:$R$612,task_table_13_4_26!$L$2:$L$612,""))) | Q25: Manage enterprise architecture
A26: Manuell geplant | B26: Corporate IT body | C26: Strategic architecture process | D26: Implementation COT | E26: L2 | F26: MP | G26: 0 | M26: =_xlfn.LET(_xlpm.k,TRIM(tbl_DataDraftApril26[[#This Row],[Initiative]])&"♦"&TRIM(tbl_DataDraftApril26[[#This Row],[Process]])&"♦"&TRIM(tbl_DataDraftApril26[[#This Row],[Phase]])&"♦"&TRIM(tbl_DataDraftApril26[[#This Row],[Process level]])&"♦"&TRIM(tbl_DataDraftApril26[[#This Row],[Process Group]]),_xlpm.s,tbl_DataDraftApril26[[#This Row],[Start]],_xlpm.e,tbl_DataDraftApril26[[#This Row],[End]],IF(OR(_xlpm.s="",_xlpm.e=""),"",_xlfn.XLOOKUP(_xlpm.k,task_table_13_4_26!$R$2:$R$612,task_table_13_4_26!$L$2:$L$612,""))) | Q26: Manage enterprise architecture
A27: Manuell geplant | B27: Corporate IT body | C27: Strategic architecture process | D27: Implementation LUS | E27: L2 | F27: MP | G27: 0 | M27: =_xlfn.LET(_xlpm.k,TRIM(tbl_DataDraftApril26[[#This Row],[Initiative]])&"♦"&TRIM(tbl_DataDraftApril26[[#This Row],[Process]])&"♦"&TRIM(tbl_DataDraftApril26[[#This Row],[Phase]])&"♦"&TRIM(tbl_DataDraftApril26[[#This Row],[Process level]])&"♦"&TRIM(tbl_DataDraftApril26[[#This Row],[Process Group]]),_xlpm.s,tbl_DataDraftApril26[[#This Row],[Start]],_xlpm.e,tbl_DataDraftApril26[[#This Row],[End]],IF(OR(_xlpm.s="",_xlpm.e=""),"",_xlfn.XLOOKUP(_xlpm.k,task_table_13_4_26!$R$2:$R$612,task_table_13_4_26!$L$2:$L$612,""))) | Q27: Manage enterprise architecture
A28: Manuell geplant | B28: ITSM | C28: Manage IT portfolio | D28: Total | E28: L1 | F28: MP | G28: 0.78 | H28: Frank Maren (LIS);Kunz Christina (LIS-MHP Management- und IT Beratung GmbH) | I28: ? | K28: 45971 | L28: 46157 | M28: =_xlfn.LET(_xlpm.k,TRIM(tbl_DataDraftApril26[[#This Row],[Initiative]])&"♦"&TRIM(tbl_DataDraftApril26[[#This Row],[Process]])&"♦"&TRIM(tbl_DataDraftApril26[[#This Row],[Phase]])&"♦"&TRIM(tbl_DataDraftApril26[[#This Row],[Process level]])&"♦"&TRIM(tbl_DataDraftApril26[[#This Row],[Process Group]]),_xlpm.s,tbl_DataDraftApril26[[#This Row],[Start]],_xlpm.e,tbl_DataDraftApril26[[#This Row],[End]],IF(OR(_xlpm.s="",_xlpm.e=""),"",_xlfn.XLOOKUP(_xlpm.k,task_table_13_4_26!$R$2:$R$612,task_table_13_4_26!$L$2:$L$612,""))) -> 135 | Q28: Manage IT portfolio
A29: Manuell geplant | B29: ITSM | C29: Manage IT portfolio | D29: Elaboration | E29: L1 | F29: MP | G29: 1 | H29: Frank Maren (LIS);Kunz Christina (LIS-MHP Management- und IT Beratung GmbH) | I29: ? | K29: 45972 | L29: 46051 | M29: =_xlfn.LET(_xlpm.k,TRIM(tbl_DataDraftApril26[[#This Row],[Initiative]])&"♦"&TRIM(tbl_DataDraftApril26[[#This Row],[Process]])&"♦"&TRIM(tbl_DataDraftApril26[[#This Row],[Phase]])&"♦"&TRIM(tbl_DataDraftApril26[[#This Row],[Process level]])&"♦"&TRIM(tbl_DataDraftApril26[[#This Row],[Process Group]]),_xlpm.s,tbl_DataDraftApril26[[#This Row],[Start]],_xlpm.e,tbl_DataDraftApril26[[#This Row],[End]],IF(OR(_xlpm.s="",_xlpm.e=""),"",_xlfn.XLOOKUP(_xlpm.k,task_table_13_4_26!$R$2:$R$612,task_table_13_4_26!$L$2:$L$612,""))) -> 58 | O29: Elaboration Done | P29: Elaboration Done | Q29: Manage IT portfolio
A30: Manuell geplant | B30: ITSM | C30: Manage IT portfolio | D30: Implementation LIS | E30: L1 | F30: MP | G30: 0 | H30: Frank Maren (LIS);Kunz Christina (LIS-MHP Management- und IT Beratung GmbH) | I30: ? | M30: =_xlfn.LET(_xlpm.k,TRIM(tbl_DataDraftApril26[[#This Row],[Initiative]])&"♦"&TRIM(tbl_DataDraftApril26[[#This Row],[Process]])&"♦"&TRIM(tbl_DataDraftApril26[[#This Row],[Phase]])&"♦"&TRIM(tbl_DataDraftApril26[[#This Row],[Process level]])&"♦"&TRIM(tbl_DataDraftApril26[[#This Row],[Process Group]]),_xlpm.s,tbl_DataDraftApril26[[#This Row],[Start]],_xlpm.e,tbl_DataDraftApril26[[#This Row],[End]],IF(OR(_xlpm.s="",_xlpm.e=""),"",_xlfn.XLOOKUP(_xlpm.k,task_table_13_4_26!$R$2:$R$612,task_table_13_4_26!$L$2:$L$612,""))) | Q30: Manage IT portfolio
A31: Manuell geplant | B31: ITSM | C31: Manage IT portfolio | D31: Implementation COT | E31: L1 | F31: MP | G31: 0 | H31: Frank Maren (LIS);Kunz Christina (LIS-MHP Management- und IT Beratung GmbH) | I31: ? | M31: =_xlfn.LET(_xlpm.k,TRIM(tbl_DataDraftApril26[[#This Row],[Initiative]])&"♦"&TRIM(tbl_DataDraftApril26[[#This Row],[Process]])&"♦"&TRIM(tbl_DataDraftApril26[[#This Row],[Phase]])&"♦"&TRIM(tbl_DataDraftApril26[[#This Row],[Process level]])&"♦"&TRIM(tbl_DataDraftApril26[[#This Row],[Process Group]]),_xlpm.s,tbl_DataDraftApril26[[#This Row],[Start]],_xlpm.e,tbl_DataDraftApril26[[#This Row],[End]],IF(OR(_xlpm.s="",_xlpm.e=""),"",_xlfn.XLOOKUP(_xlpm.k,task_table_13_4_26!$R$2:$R$612,task_table_13_4_26!$L$2:$L$612,""))) | Q31: Manage IT portfolio
A32: Manuell geplant | B32: ITSM | C32: Manage IT portfolio | D32: Implementation LUS | E32: L1 | F32: MP | G32: 0 | H32: Frank Maren (LIS);Kunz Christina (LIS-MHP Management- und IT Beratung GmbH) | I32: ? | M32: =_xlfn.LET(_xlpm.k,TRIM(tbl_DataDraftApril26[[#This Row],[Initiative]])&"♦"&TRIM(tbl_DataDraftApril26[[#This Row],[Process]])&"♦"&TRIM(tbl_DataDraftApril26[[#This Row],[Phase]])&"♦"&TRIM(tbl_DataDraftApril26[[#This Row],[Process level]])&"♦"&TRIM(tbl_DataDraftApril26[[#This Row],[Process Group]]),_xlpm.s,tbl_DataDraftApril26[[#This Row],[Start]],_xlpm.e,tbl_DataDraftApril26[[#This Row],[End]],IF(OR(_xlpm.s="",_xlpm.e=""),"",_xlfn.XLOOKUP(_xlpm.k,task_table_13_4_26!$R$2:$R$612,task_table_13_4_26!$L$2:$L$612,""))) | Q32: Manage IT portfolio
A33: Automatisch geplant | B33: IT project management | C33: Manage IT project portfolio | D33: Total | E33: L2 | F33: MP | G33: 1 | H33: Frank Maren (LIS) | I33: Mühlbacher Christian (LIS) | J33: Rollinger Alexander (LIS) | K33: 45971 | L33: 46173 | M33: =_xlfn.LET(_xlpm.k,TRIM(tbl_DataDraftApril26[[#This Row],[Initiative]])&"♦"&TRIM(tbl_DataDraftApril26[[#This Row],[Process]])&"♦"&TRIM(tbl_DataDraftApril26[[#This Row],[Phase]])&"♦"&TRIM(tbl_DataDraftApril26[[#This Row],[Process level]])&"♦"&TRIM(tbl_DataDraftApril26[[#This Row],[Process Group]]),_xlpm.s,tbl_DataDraftApril26[[#This Row],[Start]],_xlpm.e,tbl_DataDraftApril26[[#This Row],[End]],IF(OR(_xlpm.s="",_xlpm.e=""),"",_xlfn.XLOOKUP(_xlpm.k,task_table_13_4_26!$R$2:$R$612,task_table_13_4_26!$L$2:$L$612,""))) -> 145 | Q33: Manage IT portfolio | S33: =C28 -> Manage IT portfolio
A34: Manuell geplant | B34: IT project management | C34: Manage IT project portfolio | D34: Elaboration | E34: L2 | F34: MP | G34: 1 | H34: Frank Maren (LIS) | I34: Mühlbacher Christian (LIS) | J34: Rollinger Alexander (LIS) | K34: 45971 | L34: 46001 | M34: =_xlfn.LET(_xlpm.k,TRIM(tbl_DataDraftApril26[[#This Row],[Initiative]])&"♦"&TRIM(tbl_DataDraftApril26[[#This Row],[Process]])&"♦"&TRIM(tbl_DataDraftApril26[[#This Row],[Phase]])&"♦"&TRIM(tbl_DataDraftApril26[[#This Row],[Process level]])&"♦"&TRIM(tbl_DataDraftApril26[[#This Row],[Process Group]]),_xlpm.s,tbl_DataDraftApril26[[#This Row],[Start]],_xlpm.e,tbl_DataDraftApril26[[#This Row],[End]],IF(OR(_xlpm.s="",_xlpm.e=""),"",_xlfn.XLOOKUP(_xlpm.k,task_table_13_4_26!$R$2:$R$612,task_table_13_4_26!$L$2:$L$612,""))) -> 23 | N34: 46050 | O34: Elaboration Done | P34: Elaboration Done | Q34: Manage IT portfolio | S34: Manage IT portfolio
A35: Manuell geplant | B35: IT project management | C35: Manage IT project portfolio | D35: Implementation LIS | E35: L2 | F35: MP | G35: 0 | H35: Frank Maren (LIS) | I35: Mühlbacher Christian (LIS) | J35: Rollinger Alexander (LIS) | K35: 46054 | L35: 46173 | M35: =_xlfn.LET(_xlpm.k,TRIM(tbl_DataDraftApril26[[#This Row],[Initiative]])&"♦"&TRIM(tbl_DataDraftApril26[[#This Row],[Process]])&"♦"&TRIM(tbl_DataDraftApril26[[#This Row],[Phase]])&"♦"&TRIM(tbl_DataDraftApril26[[#This Row],[Process level]])&"♦"&TRIM(tbl_DataDraftApril26[[#This Row],[Process Group]]),_xlpm.s,tbl_DataDraftApril26[[#This Row],[Start]],_xlpm.e,tbl_DataDraftApril26[[#This Row],[End]],IF(OR(_xlpm.s="",_xlpm.e=""),"",_xlfn.XLOOKUP(_xlpm.k,task_table_13_4_26!$R$2:$R$612,task_table_13_4_26!$L$2:$L$612,""))) -> 85 | O35: Delayed | P35: Implementation LIS | Q35: Manage IT portfolio | R35: No actual status | S35: Manage IT portfolio
A36: Manuell geplant | B36: IT project management | C36: Manage IT project portfolio | D36: Implementation COT | E36: L2 | F36: MP | G36: 0 | H36: Frank Maren (LIS) | I36: Mühlbacher Christian (LIS) | J36: Rollinger Alexander (LIS) | M36: =_xlfn.LET(_xlpm.k,TRIM(tbl_DataDraftApril26[[#This Row],[Initiative]])&"♦"&TRIM(tbl_DataDraftApril26[[#This Row],[Process]])&"♦"&TRIM(tbl_DataDraftApril26[[#This Row],[Phase]])&"♦"&TRIM(tbl_DataDraftApril26[[#This Row],[Process level]])&"♦"&TRIM(tbl_DataDraftApril26[[#This Row],[Process Group]]),_xlpm.s,tbl_DataDraftApril26[[#This Row],[Start]],_xlpm.e,tbl_DataDraftApril26[[#This Row],[End]],IF(OR(_xlpm.s="",_xlpm.e=""),"",_xlfn.XLOOKUP(_xlpm.k,task_table_13_4_26!$R$2:$R$612,task_table_13_4_26!$L$2:$L$612,""))) | Q36: Manage IT portfolio | S36: Manage IT portfolio
A37: Manuell geplant | B37: IT project management | C37: Manage IT project portfolio | D37: Implementation LUS | E37: L2 | F37: MP | G37: 0 | H37: Frank Maren (LIS) | I37: Mühlbacher Christian (LIS) | J37: Rollinger Alexander (LIS) | M37: =_xlfn.LET(_xlpm.k,TRIM(tbl_DataDraftApril26[[#This Row],[Initiative]])&"♦"&TRIM(tbl_DataDraftApril26[[#This Row],[Process]])&"♦"&TRIM(tbl_DataDraftApril26[[#This Row],[Phase]])&"♦"&TRIM(tbl_DataDraftApril26[[#This Row],[Process level]])&"♦"&TRIM(tbl_DataDraftApril26[[#This Row],[Process Group]]),_xlpm.s,tbl_DataDraftApril26[[#This Row],[Start]],_xlpm.e,tbl_DataDraftApril26[[#This Row],[End]],IF(OR(_xlpm.s="",_xlpm.e=""),"",_xlfn.XLOOKUP(_xlpm.k,task_table_13_4_26!$R$2:$R$612,task_table_13_4_26!$L$2:$L$612,""))) | Q37: Manage IT portfolio | S37: Manage IT portfolio
A38: Automatisch geplant | B38: ITSM | C38: Manage IT service portfolio | D38: Total | E38: L2 | F38: MP | G38: 0.5 | H38: Frank Maren (LIS);Kunz Christina (LIS-MHP Management- und IT Beratung GmbH) | I38: Birgit Gerathewohl (LIS) | J38: Reiner Heiko (HAU-ITSA) | K38: 46113 | L38: 46273 | M38: =_xlfn.LET(_xlpm.k,TRIM(tbl_DataDraftApril26[[#This Row],[Initiative]])&"♦"&TRIM(tbl_DataDraftApril26[[#This Row],[Process]])&"♦"&TRIM(tbl_DataDraftApril26[[#This Row],[Phase]])&"♦"&TRIM(tbl_DataDraftApril26[[#This Row],[Process level]])&"♦"&TRIM(tbl_DataDraftApril26[[#This Row],[Process Group]]),_xlpm.s,tbl_DataDraftApril26[[#This Row],[Start]],_xlpm.e,tbl_DataDraftApril26[[#This Row],[End]],IF(OR(_xlpm.s="",_xlpm.e=""),"",_xlfn.XLOOKUP(_xlpm.k,task_table_13_4_26!$R$2:$R$612,task_table_13_4_26!$L$2:$L$612,""))) -> 115 | Q38: Manage IT portfolio | S38: Manage IT portfolio
A39: Manuell geplant | B39: ITSM | C39: Manage IT service portfolio | D39: Elaboration | E39: L2 | F39: MP | G39: 0.5 | H39: Frank Maren (LIS);Kunz Christina (LIS-MHP Management- und IT Beratung GmbH) | I39: Birgit Gerathewohl (LIS) | J39: Reiner Heiko (HAU-ITSA) | K39: 46113 | L39: 46218 | M39: =_xlfn.LET(_xlpm.k,TRIM(tbl_DataDraftApril26[[#This Row],[Initiative]])&"♦"&TRIM(tbl_DataDraftApril26[[#This Row],[Process]])&"♦"&TRIM(tbl_DataDraftApril26[[#This Row],[Phase]])&"♦"&TRIM(tbl_DataDraftApril26[[#This Row],[Process level]])&"♦"&TRIM(tbl_DataDraftApril26[[#This Row],[Process Group]]),_xlpm.s,tbl_DataDraftApril26[[#This Row],[Start]],_xlpm.e,tbl_DataDraftApril26[[#This Row],[End]],IF(OR(_xlpm.s="",_xlpm.e=""),"",_xlfn.XLOOKUP(_xlpm.k,task_table_13_4_26!$R$2:$R$612,task_table_13_4_26!$L$2:$L$612,""))) -> 54 | O39: Elaboration in progress | P39: Elaboration in progress | Q39: Manage IT portfolio | S39: Manage IT portfolio
A40: Manuell geplant | B40: ITSM | C40: Manage IT service portfolio | D40: Implementation LIS | E40: L2 | F40: MP | G40: 0 | H40: Frank Maren (LIS);Kunz Christina (LIS-MHP Management- und IT Beratung GmbH) | I40: Birgit Gerathewohl (LIS) | J40: Reiner Heiko (HAU-ITSA) | M40: =_xlfn.LET(_xlpm.k,TRIM(tbl_DataDraftApril26[[#This Row],[Initiative]])&"♦"&TRIM(tbl_DataDraftApril26[[#This Row],[Process]])&"♦"&TRIM(tbl_DataDraftApril26[[#This Row],[Phase]])&"♦"&TRIM(tbl_DataDraftApril26[[#This Row],[Process level]])&"♦"&TRIM(tbl_DataDraftApril26[[#This Row],[Process Group]]),_xlpm.s,tbl_DataDraftApril26[[#This Row],[Start]],_xlpm.e,tbl_DataDraftApril26[[#This Row],[End]],IF(OR(_xlpm.s="",_xlpm.e=""),"",_xlfn.XLOOKUP(_xlpm.k,task_table_13_4_26!$R$2:$R$612,task_table_13_4_26!$L$2:$L$612,""))) | O40: Not planned yet | Q40: Manage IT portfolio | S40: Manage IT portfolio
A41: Manuell geplant | B41: ITSM | C41: Manage IT service portfolio | D41: Implementation COT | E41: L2 | F41: MP | G41: 0 | H41: Frank Maren (LIS);Kunz Christina (LIS-MHP Management- und IT Beratung GmbH) | I41: Birgit Gerathewohl (LIS) | J41: Reiner Heiko (HAU-ITSA) | M41: =_xlfn.LET(_xlpm.k,TRIM(tbl_DataDraftApril26[[#This Row],[Initiative]])&"♦"&TRIM(tbl_DataDraftApril26[[#This Row],[Process]])&"♦"&TRIM(tbl_DataDraftApril26[[#This Row],[Phase]])&"♦"&TRIM(tbl_DataDraftApril26[[#This Row],[Process level]])&"♦"&TRIM(tbl_DataDraftApril26[[#This Row],[Process Group]]),_xlpm.s,tbl_DataDraftApril26[[#This Row],[Start]],_xlpm.e,tbl_DataDraftApril26[[#This Row],[End]],IF(OR(_xlpm.s="",_xlpm.e=""),"",_xlfn.XLOOKUP(_xlpm.k,task_table_13_4_26!$R$2:$R$612,task_table_13_4_26!$L$2:$L$612,""))) | O41: Not planned yet | Q41: Manage IT portfolio | S41: Manage IT portfolio
A42: Manuell geplant | B42: ITSM | C42: Manage IT service portfolio | D42: Implementation LUS | E42: L2 | F42: MP | G42: 0 | H42: Frank Maren (LIS);Kunz Christina (LIS-MHP Management- und IT Beratung GmbH) | I42: Birgit Gerathewohl (LIS) | J42: Reiner Heiko (HAU-ITSA) | M42: =_xlfn.LET(_xlpm.k,TRIM(tbl_DataDraftApril26[[#This Row],[Initiative]])&"♦"&TRIM(tbl_DataDraftApril26[[#This Row],[Process]])&"♦"&TRIM(tbl_DataDraftApril26[[#This Row],[Phase]])&"♦"&TRIM(tbl_DataDraftApril26[[#This Row],[Process level]])&"♦"&TRIM(tbl_DataDraftApril26[[#This Row],[Process Group]]),_xlpm.s,tbl_DataDraftApril26[[#This Row],[Start]],_xlpm.e,tbl_DataDraftApril26[[#This Row],[End]],IF(OR(_xlpm.s="",_xlpm.e=""),"",_xlfn.XLOOKUP(_xlpm.k,task_table_13_4_26!$R$2:$R$612,task_table_13_4_26!$L$2:$L$612,""))) | O42: Not planned yet | Q42: Manage IT portfolio | S42: Manage IT portfolio
A43: Automatisch geplant | B43: IT planning and steering | C43: Manage and control IT financials | D43: Total | E43: L1 | F43: MP | G43: 0.5 | H43: Hynek Tobias (LIS);Kreis Andreas (LLI) | I43: Frank Nicole (LIS) | J43: Moser Mario (LIS-LAH) | K43: 45945 | L43: 46234 | M43: =_xlfn.LET(_xlpm.k,TRIM(tbl_DataDraftApril26[[#This Row],[Initiative]])&"♦"&TRIM(tbl_DataDraftApril26[[#This Row],[Process]])&"♦"&TRIM(tbl_DataDraftApril26[[#This Row],[Phase]])&"♦"&TRIM(tbl_DataDraftApril26[[#This Row],[Process level]])&"♦"&TRIM(tbl_DataDraftApril26[[#This Row],[Process Group]]),_xlpm.s,tbl_DataDraftApril26[[#This Row],[Start]],_xlpm.e,tbl_DataDraftApril26[[#This Row],[End]],IF(OR(_xlpm.s="",_xlpm.e=""),"",_xlfn.XLOOKUP(_xlpm.k,task_table_13_4_26!$R$2:$R$612,task_table_13_4_26!$L$2:$L$612,""))) -> 208 | Q43: Manage and control IT financials
A44: Manuell geplant | B44: IT planning and steering | C44: Manage and control IT financials | D44: Elaboration | E44: L1 | F44: MP | G44: 0.5 | H44: Hynek Tobias (LIS);Kreis Andreas (LLI) | I44: Frank Nicole (LIS) | J44: Moser Mario (LIS-LAH) | K44: 45945 | L44: 46142 | M44: =_xlfn.LET(_xlpm.k,TRIM(tbl_DataDraftApril26[[#This Row],[Initiative]])&"♦"&TRIM(tbl_DataDraftApril26[[#This Row],[Process]])&"♦"&TRIM(tbl_DataDraftApril26[[#This Row],[Phase]])&"♦"&TRIM(tbl_DataDraftApril26[[#This Row],[Process level]])&"♦"&TRIM(tbl_DataDraftApril26[[#This Row],[Process Group]]),_xlpm.s,tbl_DataDraftApril26[[#This Row],[Start]],_xlpm.e,tbl_DataDraftApril26[[#This Row],[End]],IF(OR(_xlpm.s="",_xlpm.e=""),"",_xlfn.XLOOKUP(_xlpm.k,task_table_13_4_26!$R$2:$R$612,task_table_13_4_26!$L$2:$L$612,""))) -> 142 | O44: Elaboration in progress | P44: Elaboration in progress | Q44: Manage and control IT financials
A45: Manuell geplant | B45: IT planning and steering | C45: Manage and control IT financials | D45: Implementation LIS | E45: L1 | F45: MP | G45: 0 | H45: Hynek Tobias (LIS);Kreis Andreas (LLI) | I45: Frank Nicole (LIS) | J45: Moser Mario (LIS-LAH) | K45: 46143 | L45: 46234 | M45: =_xlfn.LET(_xlpm.k,TRIM(tbl_DataDraftApril26[[#This Row],[Initiative]])&"♦"&TRIM(tbl_DataDraftApril26[[#This Row],[Process]])&"♦"&TRIM(tbl_DataDraftApril26[[#This Row],[Phase]])&"♦"&TRIM(tbl_DataDraftApril26[[#This Row],[Process level]])&"♦"&TRIM(tbl_DataDraftApril26[[#This Row],[Process Group]]),_xlpm.s,tbl_DataDraftApril26[[#This Row],[Start]],_xlpm.e,tbl_DataDraftApril26[[#This Row],[End]],IF(OR(_xlpm.s="",_xlpm.e=""),"",_xlfn.XLOOKUP(_xlpm.k,task_table_13_4_26!$R$2:$R$612,task_table_13_4_26!$L$2:$L$612,""))) -> 66 | P45: Scheduled | Q45: Manage and control IT financials
A46: Manuell geplant | B46: IT planning and steering | C46: Manage and control IT financials | D46: Implementation COT | E46: L2 | F46: MP | G46: 0 | H46: Hynek Tobias (LIS);Kreis Andreas (LLI) | I46: Frank Nicole (LIS) | J46: Moser Mario (LIS-LAH) | M46: =_xlfn.LET(_xlpm.k,TRIM(tbl_DataDraftApril26[[#This Row],[Initiative]])&"♦"&TRIM(tbl_DataDraftApril26[[#This Row],[Process]])&"♦"&TRIM(tbl_DataDraftApril26[[#This Row],[Phase]])&"♦"&TRIM(tbl_DataDraftApril26[[#This Row],[Process level]])&"♦"&TRIM(tbl_DataDraftApril26[[#This Row],[Process Group]]),_xlpm.s,tbl_DataDraftApril26[[#This Row],[Start]],_xlpm.e,tbl_DataDraftApril26[[#This Row],[End]],IF(OR(_xlpm.s="",_xlpm.e=""),"",_xlfn.XLOOKUP(_xlpm.k,task_table_13_4_26!$R$2:$R$612,task_table_13_4_26!$L$2:$L$612,""))) | Q46: Manage and control IT financials
A47: Manuell geplant | B47: IT planning and steering | C47: Manage and control IT financials | D47: Implementation LUS | E47: L1 | F47: MP | G47: 0 | H47: Hynek Tobias (LIS);Kreis Andreas (LLI) | I47: Frank Nicole (LIS) | J47: Moser Mario (LIS-LAH) | M47: =_xlfn.LET(_xlpm.k,TRIM(tbl_DataDraftApril26[[#This Row],[Initiative]])&"♦"&TRIM(tbl_DataDraftApril26[[#This Row],[Process]])&"♦"&TRIM(tbl_DataDraftApril26[[#This Row],[Phase]])&"♦"&TRIM(tbl_DataDraftApril26[[#This Row],[Process level]])&"♦"&TRIM(tbl_DataDraftApril26[[#This Row],[Process Group]]),_xlpm.s,tbl_DataDraftApril26[[#This Row],[Start]],_xlpm.e,tbl_DataDraftApril26[[#This Row],[End]],IF(OR(_xlpm.s="",_xlpm.e=""),"",_xlfn.XLOOKUP(_xlpm.k,task_table_13_4_26!$R$2:$R$612,task_table_13_4_26!$L$2:$L$612,""))) | Q47: Manage and control IT financials
A48: Manuell geplant | B48: IT planning and steering | C48: Create and maintain IT budgets | D48: Total | E48: L2 | F48: MP | G48: 0.5 | H48: Hynek Tobias (LIS);Kreis Andreas (LLI) | I48: Frank Nicole (LIS) | J48: Mielenz Thomas (LMT) | K48: 45945 | M48: =_xlfn.LET(_xlpm.k,TRIM(tbl_DataDraftApril26[[#This Row],[Initiative]])&"♦"&TRIM(tbl_DataDraftApril26[[#This Row],[Process]])&"♦"&TRIM(tbl_DataDraftApril26[[#This Row],[Phase]])&"♦"&TRIM(tbl_DataDraftApril26[[#This Row],[Process level]])&"♦"&TRIM(tbl_DataDraftApril26[[#This Row],[Process Group]]),_xlpm.s,tbl_DataDraftApril26[[#This Row],[Start]],_xlpm.e,tbl_DataDraftApril26[[#This Row],[End]],IF(OR(_xlpm.s="",_xlpm.e=""),"",_xlfn.XLOOKUP(_xlpm.k,task_table_13_4_26!$R$2:$R$612,task_table_13_4_26!$L$2:$L$612,""))) | Q48: Manage and control IT financials | S48: Manage and control IT financials
A49: Manuell geplant | B49: IT planning and steering | C49: Create and maintain IT budgets | D49: Elaboration | E49: L2 | F49: MP | G49: 0.5 | H49: Hynek Tobias (LIS);Kreis Andreas (LLI) | I49: Frank Nicole (LIS) | J49: Mielenz Thomas (LMT) | K49: 45945 | M49: =_xlfn.LET(_xlpm.k,TRIM(tbl_DataDraftApril26[[#This Row],[Initiative]])&"♦"&TRIM(tbl_DataDraftApril26[[#This Row],[Process]])&"♦"&TRIM(tbl_DataDraftApril26[[#This Row],[Phase]])&"♦"&TRIM(tbl_DataDraftApril26[[#This Row],[Process level]])&"♦"&TRIM(tbl_DataDraftApril26[[#This Row],[Process Group]]),_xlpm.s,tbl_DataDraftApril26[[#This Row],[Start]],_xlpm.e,tbl_DataDraftApril26[[#This Row],[End]],IF(OR(_xlpm.s="",_xlpm.e=""),"",_xlfn.XLOOKUP(_xlpm.k,task_table_13_4_26!$R$2:$R$612,task_table_13_4_26!$L$2:$L$612,""))) | Q49: Manage and control IT financials | S49: Manage and control IT financials
A50: Manuell geplant | B50: IT planning and steering | C50: Create and maintain IT budgets | D50: Implementation LIS | E50: L2 | F50: MP | G50: 0 | H50: Hynek Tobias (LIS);Kreis Andreas (LLI) | I50: Frank Nicole (LIS) | J50: Mielenz Thomas (LMT) | M50: =_xlfn.LET(_xlpm.k,TRIM(tbl_DataDraftApril26[[#This Row],[Initiative]])&"♦"&TRIM(tbl_DataDraftApril26[[#This Row],[Process]])&"♦"&TRIM(tbl_DataDraftApril26[[#This Row],[Phase]])&"♦"&TRIM(tbl_DataDraftApril26[[#This Row],[Process level]])&"♦"&TRIM(tbl_DataDraftApril26[[#This Row],[Process Group]]),_xlpm.s,tbl_DataDraftApril26[[#This Row],[Start]],_xlpm.e,tbl_DataDraftApril26[[#This Row],[End]],IF(OR(_xlpm.s="",_xlpm.e=""),"",_xlfn.XLOOKUP(_xlpm.k,task_table_13_4_26!$R$2:$R$612,task_table_13_4_26!$L$2:$L$612,""))) | Q50: Manage and control IT financials | S50: Manage and control IT financials
A51: Manuell geplant | B51: IT planning and steering | C51: Create and maintain IT budgets | D51: Implementation COT | E51: L2 | F51: MP | G51: 0 | H51: Hynek Tobias (LIS);Kreis Andreas (LLI) | I51: Frank Nicole (LIS) | J51: Mielenz Thomas (LMT) | M51: =_xlfn.LET(_xlpm.k,TRIM(tbl_DataDraftApril26[[#This Row],[Initiative]])&"♦"&TRIM(tbl_DataDraftApril26[[#This Row],[Process]])&"♦"&TRIM(tbl_DataDraftApril26[[#This Row],[Phase]])&"♦"&TRIM(tbl_DataDraftApril26[[#This Row],[Process level]])&"♦"&TRIM(tbl_DataDraftApril26[[#This Row],[Process Group]]),_xlpm.s,tbl_DataDraftApril26[[#This Row],[Start]],_xlpm.e,tbl_DataDraftApril26[[#This Row],[End]],IF(OR(_xlpm.s="",_xlpm.e=""),"",_xlfn.XLOOKUP(_xlpm.k,task_table_13_4_26!$R$2:$R$612,task_table_13_4_26!$L$2:$L$612,""))) | Q51: Manage and control IT financials | S51: Manage and control IT financials
